Workbook

Sheet README
B1: LifeMap calculators
B2: Version 2.8 · 9 Oct 2026 · built from LifeMap-Customer-Journey prototype (CALCS and Settings). Since 2.7: date of birth replaces age (calendar-year cashflow), the over-80 State Pension increase only when a State Pension counts, and the Report spec sheet. Since 2.4: the main plan in Make my plan (eight sheets starting "Plan ..." and the Calculation register), audit fixes to the calculators (see "Audit fixes applied"), an example column on every calculator input block, law figures on the Plan sheets read from Assumptions, up to 20 saved-for goals, data validation on the Plan sheets and Settings, and the same "Choose your ... to see this" words and order as the app on every calculator. Since 2.6 (journey spec section 27): only retirement age, plan-until age, inflation and a working partner's retirement age block the plan (the gate card says "we need N things"); every LifeMap standard is used automatically and is labelled "Set by LifeMap"; a market rate you do not give uses the suggested or planning rate ("Assumed: add yours"); any retirement age from your age + 1 is allowed, with the pension from the access age (60, or 50 for some occupational schemes) and the years before it paid from savings; a goal dated before today reads "Date has passed". The four UI sheets (UI Guide, UI Calculators, UI Screens, UI Make my plan) are added by tools/build_ui_sheets.py.
B3: Fill example values? (Yes/No) | C3: No | D3: Example only: Yes fills every blank input with its grey figure, so testers see numbers. Default No (blank template).
B4: How to use
B5: • Open a calculator from the list below. Fill the yellow cells (blue text): everything else updates on its own.
B6: • Every number is one of three types (journey spec §14, §18, §27). Type 1, set by Government (tax, USC, PRSI, relief %, lump-sum bands, DIRT, exit tax, Central Bank limits, full State Pension and benefit rates): on the Assumptions sheet, not an input. Type 2, a market rate or a figure you enter yourself (mortgage rate, card APR, fund charges, the State Pension you will get …): a yellow input with a suggested figure and its source, or "Usually between X and Y (source)" where an official range exists; on a calculator it stays blank until you add it, in the plan a blank one uses the suggested published rate (mortgage and loans) or the planning rate (cards 20%) and is labelled "Assumed: add yours". Type 3, a LifeMap standard (growth rates, pay rises, emergency months, drawdown timing, retirement multiple, pension access age …): the calculator and the plan start from the standard ("Set by LifeMap"); type your own and it is "Your choice". Only four things are never filled in for you: retirement age, plan-until age, inflation, and a working partner's retirement age.
B7: • Your own figures stay blank: a calculator result that needs one (a market rate, the State Pension, Illness Benefit, your age, the retirement age) shows "Choose your … to see this" or "Add your … to see this". A LifeMap standard never blocks a result. Set "Fill example values?" (above) to Yes to fill every blank input with its grey "Example only" figure (the standard, or the sample customer's figure).
B8: • Each input cell shows its unit and allowed range when you click it, and refuses values outside it. The default is in the cell note and at the far right.
B9: • Market rates (mortgage, loans, cards, deposits, buying fees, fund charges) are never pre-filled on a calculator. Beside each is a suggested rate with its source, from the Settings sheet: by default Central Bank of Ireland averages with their month (journey spec §18, §19). In the plan, a rate you do not give uses that suggestion (mortgage and loans) or the planning rate (cards 20%) and says "Assumed: add yours". A partner can put its own rates and name there ("Suggested by …"). Law values cannot be changed.
B10: • Facts and law (tax bands, State rates, Central Bank rules, stamp duty, lump-sum bands …) are on the Assumptions sheet, the Irish rules register (Irish rules 2026 · checked 2 Oct 2026). Take-home pay is worked out on the Tax engine sheet, which C25 and C26 use.
B11: • Results are in the green box, each with its formula written out beside it. Formulas use names (e.g. =Amount*(1+Inflation)^Years) so they read like the maths.
B12: • Inflation is the client's own choice: the yellow "Inflation you expect" cell on each calculator that uses it starts blank. While it is blank, results that need it say "Choose your inflation rate to see this"; 0% is a real choice (no adjustment for prices).
B13: • Statements: grey-blue cells under "FROM YOUR STATEMENT" are filled by the document reader. The FIGURE USED box uses the statement figure if there is one, otherwise your typed figure, and says which. See the "Document reader spec" sheet.
B14: • The workbook recalculates automatically, including when it is opened. No sheet or workbook protection is applied: this is an engineering template, so formulas and inputs can be edited. Keep the yellow cells for typing and leave formulas alone.
B15: • Settings sheet: every standard, its wording and source, and the partner name in one block (defined names Set_*). "Your lists": loans, cards, pensions and policies, one row each; the calculators use the totals when their own cell is left blank.
... B30: Calculators
B31: No. | C31: Calculator (click to open) | D31: Question it answers | E31: Category
B32: C01 | C32: =HYPERLINK("#'C01 Borrowing'!A1","How much could I borrow?") -> How much could I borrow? | D32: What home price could be within reach? | E32: Home & Mortgage
B33: C02 | C33: =HYPERLINK("#'C02 Mortgage repayment'!A1","Monthly mortgage repayment") -> Monthly mortgage repayment | D33: What would my monthly repayment be? | E33: Home & Mortgage
B34: C03 | C34: =HYPERLINK("#'C03 Deposit'!A1","Deposit calculator") -> Deposit calculator | D34: How long until I have my deposit? | E34: Home & Mortgage
B35: C04 | C35: =HYPERLINK("#'C04 Mortgage overpayment'!A1","Mortgage overpayment") -> Mortgage overpayment | D35: What if I paid a little extra each month? | E35: Home & Mortgage
B36: C05 | C36: =HYPERLINK("#'C05 Interest rate impact'!A1","Interest-rate impact") -> Interest-rate impact | D36: What if my mortgage rate changed? | E36: Home & Mortgage
B37: C06 | C37: =HYPERLINK("#'C06 Term comparison'!A1","Mortgage term comparison") -> Mortgage term comparison | D37: Shorter or longer term: what is the trade-off? | E37: Home & Mortgage
B38: C07 | C38: =HYPERLINK("#'C07 Rent vs buy'!A1","Rent vs buy") -> Rent vs buy | D38: How do renting and buying compare over time? | E38: Home & Mortgage
B39: C08 | C39: =HYPERLINK("#'C08 Goal planner'!A1","Goal planner") -> Goal planner | D39: How much a month to reach my goal? | E39: Savings & Goals
B40: C09 | C40: =HYPERLINK("#'C09 Compound growth'!A1","Compound growth") -> Compound growth | D40: What could regular saving grow into? | E40: Savings & Goals
B41: C10 | C41: =HYPERLINK("#'C10 Lump sum growth'!A1","Lump-sum growth") -> Lump-sum growth | D41: What could a one-off amount become? | E41: Investments
B42: C11 | C42: =HYPERLINK("#'C11 Emergency fund'!A1","Emergency fund") -> Emergency fund | D42: How strong is my emergency fund? | E42: Savings & Goals
B43: C12 | C43: =HYPERLINK("#'C12 Retirement projection'!A1","Retirement projection") -> Retirement projection | D43: Could your current path fund the retirement you want? | E43: Pensions & Retirement
B44: C13 | C44: =HYPERLINK("#'C13 Contribution impact'!A1","Contribution impact") -> Contribution impact | D44: What difference would a small increase make? | E44: Pensions & Retirement
B45: C14 | C45: =HYPERLINK("#'C14 AVC impact'!A1","AVC impact") -> AVC impact | D45: What could extra voluntary contributions add? | E45: Pensions & Retirement
B46: C15 | C46: =HYPERLINK("#'C15 Will my money last'!A1","Will my money last?") -> Will my money last? | D46: How long could my retirement savings last? | E46: Pensions & Retirement
B47: C16 | C47: =HYPERLINK("#'C16 Drawdown scenarios'!A1","Retirement drawdown scenarios") -> Retirement drawdown scenarios | D47: How do different growth rates change things? | E47: Pensions & Retirement
B48: C17 | C48: =HYPERLINK("#'C17 Inflation adjusted return'!A1","Inflation-adjusted return") -> Inflation-adjusted return | D48: What is my money really worth in future? | E48: Investments
B49: C18 | C49: =HYPERLINK("#'C18 Regular investing'!A1","Regular investing") -> Regular investing | D49: What could investing monthly build? | E49: Investments
B50: C19 | C50: =HYPERLINK("#'C19 Fees impact'!A1","Fees impact") -> Fees impact | D50: How much do fees really cost over time? | E50: Investments
B51: C20 | C51: =HYPERLINK("#'C20 Risk and return'!A1","Risk & return simulator") -> Risk & return simulator | D51: What range of outcomes might each style have? | E51: Investments
B52: C21 | C52: =HYPERLINK("#'C21 Life cover'!A1","Life cover estimator") -> Life cover estimator | D52: How much cover might my family need? | E52: Protection
B53: C22 | C53: =HYPERLINK("#'C22 Income protection gap'!A1","Income protection gap") -> Income protection gap | D53: How long could I cope if I couldn't work? | E53: Protection
B54: C23 | C54: =HYPERLINK("#'C23 Mortgage protection'!A1","Mortgage protection") -> Mortgage protection | D54: What cover would clear my mortgage? | E54: Protection
B55: C24 | C55: =HYPERLINK("#'C24 Net worth'!A1","Net worth") -> Net worth | D55: What am I worth, all in? | E55: Everyday Money
B56: C25 | C56: =HYPERLINK("#'C25 Monthly surplus'!A1","Monthly surplus") -> Monthly surplus | D56: What is left at the end of the month? | E56: Everyday Money
B57: C26 | C57: =HYPERLINK("#'C26 Budget 50 30 20'!A1","Budget (50/30/20)") -> Budget (50/30/20) | D57: A simple way to split your pay | E57: Everyday Money
B58: C27 | C58: =HYPERLINK("#'C27 Debt repayment'!A1","Debt repayment") -> Debt repayment | D58: How fast can I clear my debt? | E58: Everyday Money
B59: C28 | C59: =HYPERLINK("#'C28 Loan repayment'!A1","Loan repayment") -> Loan repayment | D59: What would a loan cost me? | E59: Everyday Money
C60: =HYPERLINK("#'Assumptions'!A1","Assumptions") -> Assumptions
C61: =HYPERLINK("#'Tax engine'!A1","Tax engine") -> Tax engine
C62: =HYPERLINK("#'Document reader spec'!A1","Document reader spec") -> Document reader spec
B64: BUDGET 2027 (announced 6 Oct 2026): not applied yet
B65: Budget 2027 changes (announced 6 Oct 2026) aren't included yet. We'll update LifeMap once they're final. Nothing from Budget 2027 is used in any calculation. The values below stay at their 2026 figures until the changes are final and official (Revenue, the Finance Act, the Department of Social Protection). Then update each named constant with its effective date and re-run the Tax engine checks. No Budget 2027 amount is written here on purpose.
B66: Constant (2026 value, unchanged) | C66: Name(s) to update | D66: Status
B67: Income-tax bands (€44,000 / €48,000 / €53,000; €35,000 second-earner uplift) | C67: Band_Single, Band_Single_Parent, Band_Married, Band_Second_Earner_Max | D67: 2026 value kept until final and official
B68: Personal and PAYE credits (€2,000 + €2,000; €4,000 married) | C68: Credit_Personal_Single, Credit_Personal_Married, Credit_PAYE | D68: 2026 value kept until final and official
B69: Rent, Home Carer and SPCCC credits (€1,000 / €1,950 / €1,900) | C69: Credit_Rent_Single, Credit_Rent_Joint, Credit_Home_Carer, Credit_SPCCC | D69: 2026 value kept until final and official
B70: USC bands (€12,012 / €28,700 / €70,044) and exemption €13,000 | C70: USC_Band_1–3, USC_Exempt | D70: 2026 value kept until final and official
B71: PRSI path (4.35% now; 4.5% from 1 Oct 2027; 4.7% from 1 Oct 2028) | C71: PRSI_Rate, PRSI credit | D71: 2026 value kept until final and official
B72: State Pension €299.30 a week (€15,563.60) | C72: State_Pension_Week | D72: 2026 value kept until final and official
B73: Illness Benefit €254; survivor's pension €259.50 (<66) / €299.30 (66+) | C73: Illness_Benefit_Week, Survivor_Pension_Week, Survivor_Pension_Week_66 | D73: 2026 value kept until final and official
B74: Exit tax 38%, deemed disposal 8 years, DIRT 33% | C74: Exit_Tax, Deemed_Disposal_Years, DIRT | D74: 2026 value kept until final and official
B75: Pension relief bands, €115,000 cap, lump-sum bands, SFT (€2.4m in 2027) | C75: Relief_Age_From/Relief_Age_Pct, Relief_Earnings_Cap, Lump_Sum_* | D75: 2026 value kept until final and official
B76: Stamp duty 1% / 2% / 6%; Help to Buy €30,000; CBI 4× / 3.5× / 90% | C76: SD_*, LTI_FTB, LTI_SSB, LTV_Max | D76: 2026 value kept until final and official
B77: ="Inflation ""Ireland now"" "&TEXT(Set_inflNow,"0.0%")&" (CSO HICP flash Sep 2026)" -> Inflation "Ireland now" 3.9% (CSO HICP flash Sep 2026) | C77: Guidance text on each inflation input and on this sheet | D77: Guidance text shows the latest CSO figure
B79: Audit fixes applied
B80: Where | C80: Audit class | D80: Item
B81: C12 | C81: Must | D81: Gap is like-for-like: target (today's money) − fund ÷ (1 + inflation)^years.
B82: C12 | C82: Must | D82: Hand-off updates the existing retirement goal (income, age) instead of a 25× lump-sum spend.
B83: C02 | C83: Must | D83: Hand-off is the deposit (loan × 10% ÷ 90%), not the mortgage amount.
B84: C04 | C84: Must | D84: Hand-off is a mortgage-free (mfree) goal, not today's balance as a spend; none if it never clears.
B85: C04 | C85: Must | D85: No "Infinity yrs" and no negative interest saved: "Not at this repayment" / "—".
B86: C04, C27 | C86: Must | D86: Exact months by NPER (no 1,200-month loop cap); over 1,200 months shows "Over 100 years" / "Payment too low…".
B87: C09, C10 | C87: Must | D87: Hand-off always in today's money (value ÷ (1 + inflation)^years), kind pot.
B88: C13, C14 | C88: Must | D88: No spend goal: raise the plan's pension contribution instead.
B89: C18 | C89: Must | D89: Hand-off in today's money, kind pot (was nominal, inflated twice).
B90: C20 | C90: Must | D90: Style is a 1/2/3 list (no decimals, no €NaN).
B91: C21 | C91: Must | D91: No spend goal: a protection need for the adviser.
... B110: Assumptions | C110: Nice | D110: Constants added for the fixes (DIRT, exit tax, Illness Benefit, survivor's pension); inflation reference refreshed (3.4% Aug 2026).
B112: Not applied (for Pooja to decide)
B113: Where | C113: Audit class | D113: Item
B114: All calculators | C114: Journey spec §14 | D114: Every input typed: 1 = set by Government (Assumptions only, grey, not an input); 2 = range ("Usually between X and Y (source)"); 3 = personal, blank until chosen ("Generally the standard is X (source). Choose what you want to use."). Blank inputs give "Choose your … to see this"; README switch "Fill example values?" (default No) fills them from the grey "Example only" column.
B115: C11, C15, C22, C13 | C115: UI/UX Appendix B | D115: Singular "1 month"; C15 at the 60-year cap reads "Beyond [plan-until age] (your plan-until age)", as the prototype (not "age 126"); C13/C14 show the relief room left after what you already pay in.
B116: C01 | C116: Should | D116: Remove the placeholder "[confirm current Central Bank rules]" from the customer line (prototype copy; the workbook uses the audit's replacement wording).
B117: C01, C03 | C117: Nice | D117: Help to Buy as an optional deposit input (rules audit #62).
B118: C02 | C118: Nice | D118: Use "−" (not "-") in the rate text (prototype copy).
B119: C03 | C119: Should | D119: House prices rising while saving (stamp duty and fees are now included).
B120: C07 | C120: Nice | D120: Local Property Tax and insurance in the cost of owning (rules audit #63).
B121: C08–C10, C18 | C121: Should | D121: An after-tax result row (DIRT 33% / exit tax 38% with deemed disposal). Only the "before tax" note is applied.
B122: C10 | C122: Nice | D122: Hide "start later" when the term is no longer than the wait.
B123: C11 | C123: Nice | D123: Tip copy: "Often 3 to 6 months" instead of "Ideal: 6 months" (prototype copy).
B124: C12 | C124: Should | D124: Gross up the desired income for tax (a "before tax" note is applied instead).
... B132: Copy | C132: Nice | D132: Fix the "29 calculators" note (there are 28).
B135: Plan sheets and the Calculation register
C136: =HYPERLINK("#'Plan inputs'!A1","Plan inputs") -> Plan inputs | D136: Everything you type for the plan: about you, goals, finances, assumptions, what-if.
C137: =HYPERLINK("#'Plan pay & tax'!A1","Plan pay & tax") -> Plan pay & tax | D137: Law figures (read from Assumptions), the figures the plan uses, and each year's pay, pension and tax.
C138: =HYPERLINK("#'Plan debt months'!A1","Plan debt months") -> Plan debt months | D138: Mortgage, cards and loans month by month.
C139: =HYPERLINK("#'Plan cashflow'!A1","Plan cashflow") -> Plan cashflow | D139: One row per year: money in, spending, goals, saving, savings left.
C140: =HYPERLINK("#'Plan goals'!A1","Plan goals") -> Plan goals | D140: Goals in funding order, each goal's % covered, band and goal line.
C141: =HYPERLINK("#'Plan results'!A1","Plan results") -> Plan results | D141: What the Results, Home and Plan screens show: saving, gate, findings, foundations, retirement at a glance, road and chart numbers.
C142: =HYPERLINK("#'Plan profile'!A1","Plan profile") -> Plan profile | D142: Money personality, risk profile and money terms from the Discover and Understand Me answers.
C143: =HYPERLINK("#'Plan how it works'!A1","Plan how it works") -> Plan how it works | D143: One paragraph per sheet, and which prototype value each Plan input is.
C144: =HYPERLINK("#'Calculation register'!A1","Calculation register") -> Calculation register | D144: Every place the prototype calculates, scores or shows a number, where it is in the workbook, and whether it was matched in a test.
...

Sheet C01 Borrowing
B1: C01 · How much could I borrow? | E1: Category: Home & Mortgage · prototype id: borrow
B2: Question it answers: What home price could be within reach? | E2: =IF(Fill_Example="Yes","Example values are ON (README): grey Example only figures fill blank inputs.","Blank template: fill the yellow inputs (or switch on example values on the README).") -> Blank template: fill the yellow inputs (or switch on example values on the README).
B3: ="Applies the Central Bank limits ("&LTI_FTB&"× or "&LTI_SSB&"×"&" income, "&TEXT(LTV_Max,"0%")&" loan-to-value) to show the most you could borrow and the home price that gives, after stamp duty and fees." -> Applies the Central Bank limits (4× or 3.5× income, 90% loan-to-value) to show the most you could borrow and the home price that gives, after stamp duty and fees.
B5: INPUTS | C5: Your figure | D5: Unit | E5: Allowed | F5: Example only (grey; used only when "Fill example values" is Yes)
B6: Your gross yearly income | D6: € | E6: Type 3 · your figure · Your own figure. In the app it is pre-filled from Your finances: income. Allowed: €15,000 to €2,500,000 · steps of €1,000 | F6: 60000 | G6: =IF(ISBLANK(C6),IF(Fill_Example="Yes",F6,""),C6)
B7: Partner's gross yearly income | D7: € | E7: Type 3 · your figure · Your own figure. In the app it is pre-filled from Your finances: partner's income. Allowed: €0 to €2,500,000 · steps of €1,000 | F7: 0 | G7: =IF(ISBLANK(C7),IF(Fill_Example="Yes",F7,""),C7)
B8: Deposit saved | D8: € | E8: Type 3 · your figure · Your own figure. In the app it is pre-filled from Plan: home goal's amount saved. Allowed: €0 to €2,000,000 · steps of €1,000 | F8: 25000 | G8: =IF(ISBLANK(C8),IF(Fill_Example="Yes",F8,""),C8)
B9: First-time buyer? | D9: Yes / No | E9: Type 3 · your figure · Your own figure. In the app it is pre-filled from Your finances: home status (owner = No). Allowed: Yes or No | F9: Yes | G9: =IF(ISBLANK(C9),IF(Fill_Example="Yes",F9,""),C9)
B10: Mortgage interest rate | D10: % | E10: ="Type 2 · your figure · Your own rate (your statement shows it; typing it is fine, no upload needed). "&IF(ISNUMBER(Suggest_Mortgage_Rate),"Suggested: "&TEXT(Suggest_Mortgage_Rate,"0.00%")&" · "&Suggest_Mortgage_Rate_Label&". ","No suggestion. ")&"Enter your own figure."&" Allowed: 1% to 8% · steps of 0.05%" -> Type 2 · your figure · Your own rate (your statement shows it; typing it is fine, no upload needed). Suggested: 3.48% · Central Bank of Ireland: average rate on new mortgages, Jul 2026. Enter your own figure. Allowed: 1% to 8% · steps of 0.05% | F10: =IF(ISNUMBER(Suggest_Mortgage_Rate),Suggest_Mortgage_Rate,"") -> 0.0348 | G10: =IF(ISBLANK(C10),IF(Fill_Example="Yes",F10,""),C10)
B11: Mortgage term | D11: years | E11: Type 3 · your figure · Your own figure. Allowed: 10 to 35 · steps of 1 | F11: 30 | G11: =IF(AND(ISNUMBER(C11),N(C11)<10),"",IF(ISBLANK(C11),IF(Fill_Example="Yes",F11,""),C11))
B12: Legal and other buying fees | D12: € | E12: ="Type 2 · optional · Legal and survey fees (stamp duty is added for you). "&IF(ISNUMBER(Suggest_Buying_Fees),"Suggested: "&TEXT(Suggest_Buying_Fees,"€#,##0")&" · "&Suggest_Buying_Fees_Label&". ","No suggestion. ")&"Leave blank to count €0."&" Allowed: €0 to €10,000 · steps of €100" -> Type 2 · optional · Legal and survey fees (stamp duty is added for you). No suggestion. Leave blank to count €0. Allowed: €0 to €10,000 · steps of €100 | F12: =IF(ISNUMBER(Suggest_Buying_Fees),Suggest_Buying_Fees,"") | G12: =IF(ISBLANK(C12),IF(AND(Fill_Example="Yes",ISNUMBER(F12)),F12,0),C12) -> 0
B13: Years until you buy (for the plan) | D13: years | E13: Type 3 · your figure · Your own figure. Allowed: 1 to 30 · steps of 1 | F13: 3 | G13: =IF(ISBLANK(C13),IF(Fill_Example="Yes",F13,""),C13)
B14: What if: save extra towards the deposit | D14: € | E14: Type 3 · optional · Optional: leave blank for none. Allowed: €0 to €500,000 · steps of €1,000 | F14: 0 | G14: =IF(ISBLANK(C14),F14,C14) -> 0
B16: RESULTS | C16: Result | D16: Shown as | E16: Formula
B17: Homes up to about | C17: =IF(Need_1<>"",Need_1,MIN(Price_By_Deposit,Price_By_Income)) -> Choose your gross yearly income to see this | D17: € | E17: ƒx =MIN(Price_By_Deposit,Price_By_Income)
B18: Most you could borrow | C18: =IF(Need_1<>"",Need_1,MIN(Borrow_By_Income,LTV_Max*Home_Price)) -> Choose your gross yearly income to see this | D18: € | E18: ƒx =MIN(Borrow_By_Income,LTV_Max*Home_Price)
B19: Monthly repayment (illustrative) | C19: =IF(Need_2<>"",Need_2,PMT(Interest_Rate/12,Term_Years*12,-Max_Loan)) -> Choose your gross yearly income to see this | D19: € | E19: ƒx =PMT(Interest_Rate/12,Term_Years*12,-Max_Loan)
B20: Stamp duty on that price (paid from your deposit) | C20: =IF(Need_1<>"",Need_1,SD_Rate_1*MIN(Home_Price,SD_Band_1)+SD_Rate_2*MAX(0,MIN(Home_Price,SD_Band_2)-SD_Band_1)+SD_Rate_3*MAX(0,Home_Price-SD_Band_2)) -> Choose your gross yearly income to see this | D20: € | E20: ƒx =SD_Rate_1*MIN(Home_Price,SD_Band_1)+SD_Rate_2*MAX(0,MIN(Home_Price,SD_Band_2)-SD_Band_1)+SD_Rate_3*MAX(0,Home_Price-SD_Band_2)
B21: Borrowing allowed by income | C21: =IF(Need_3<>"",Need_3,(Income+Partner_Income)*Income_Multiple) -> Choose your gross yearly income to see this | D21: € | E21: ƒx =(Income+Partner_Income)*Income_Multiple
B22: Income multiple used | C22: =IF(Need_4<>"",Need_4,IF(First_Time_Buyer="Yes",LTI_FTB,LTI_SSB)) -> Choose your first-time buyer answer to see this | D22: × income | E22: ƒx =IF(First_Time_Buyer="Yes",LTI_FTB,LTI_SSB)
B23: Your deposit (incl. what-if extra) | C23: =IF(Need_5<>"",Need_5,Deposit+Extra_Deposit) -> Choose your deposit saved to see this | D23: € | E23: ƒx =Deposit+Extra_Deposit
B24: Deposit left for the price after fees | C24: =IF(Need_6<>"",Need_6,MAX(0,Total_Deposit-Buying_Fees)) -> Choose your deposit saved to see this | D24: € | E24: ƒx =MAX(0,Total_Deposit-Buying_Fees)
B25: Deposit + stamp duty needed for a €1m home | C25: =(1-LTV_Max+SD_Rate_1)*SD_Band_1 -> 110000 | D25: € | E25: ƒx =(1-LTV_Max+SD_Rate_1)*SD_Band_1
B26: Deposit + stamp duty needed for a €1.5m home | C26: =Cash_At_Band_1+(1-LTV_Max+SD_Rate_2)*(SD_Band_2-SD_Band_1) -> 170000 | D26: € | E26: ƒx =Cash_At_Band_1+(1-LTV_Max+SD_Rate_2)*(SD_Band_2-SD_Band_1)
B27: Price your deposit allows (10% deposit + stamp duty) | C27: =IF(Need_6<>"",Need_6,IF(Cash_For_Price<=Cash_At_Band_1,Cash_For_Price/(1-LTV_Max+SD_Rate_1),IF(Cash_For_Price<=Cash_At_Band_2,SD_Band_1+(Cash_For_Price-Cash_At_Band_1)/(1-LTV_Max+SD_Rate_2),SD_Band_2+(Cash_For_Price-Cash_At_Band_2)/(1-LTV_Max+SD_Rate_3)))) -> Choose your deposit saved to see this | D27: € | E27: ƒx =IF(Cash_For_Price<=Cash_At_Band_1,Cash_For_Price/(1-LTV_Max+SD_Rate_1),IF(Cash_For_Price<=Cash_At_Band_2,SD_Band_1+(Cash_For_Price-Cash_At_Band_1)/(1-LTV_Max+SD_Rate_2),SD_Band_2+(Cash_For_Price-Cash_At_Band_2)/(1-LTV_Max+SD_Rate_3)))
B28: Income limit + deposit left after fees | C28: =IF(Need_1<>"",Need_1,Borrow_By_Income+Cash_For_Price) -> Choose your gross yearly income to see this | D28: € | E28: ƒx =Borrow_By_Income+Cash_For_Price
B29: Price your income allows (loan + deposit, after stamp duty) | C29: =IF(Need_1<>"",Need_1,IF(Income_Cash<=(1+SD_Rate_1)*SD_Band_1,Income_Cash/(1+SD_Rate_1),IF(Income_Cash<=(1+SD_Rate_1)*SD_Band_1+(1+SD_Rate_2)*(SD_Band_2-SD_Band_1),SD_Band_1+(Income_Cash-(1+SD_Rate_1)*SD_Band_1)/(1+SD_Rate_2),SD_Band_2+(Income_Cash-(1+SD_Rate_1)*SD_Band_1-(1+SD_Rate_2)*(SD_Band_2-SD_Band_1))/(1+SD_Rate_3)))) -> Choose your gross yearly income to see this | D29: € | E29: ƒx =IF(Income_Cash<=(1+SD_Rate_1)*SD_Band_1,Income_Cash/(1+SD_Rate_1),IF(Income_Cash<=(1+SD_Rate_1)*SD_Band_1+(1+SD_Rate_2)*(SD_Band_2-SD_Band_1),SD_Band_1+(Income_Cash-(1+SD_Rate_1)*SD_Band_1)/(1+SD_Rate_2),SD_Band_2+(Income_Cash-(1+SD_Rate_1)*SD_Band_1-(1+SD_Rate_2)*(SD_Band_2-SD_Band_1))/(1+SD_Rate_3)))
B30: What sets the limit | C30: =IF(Need_1<>"",Need_1,IF(Price_By_Deposit<Price_By_Income,"Your deposit","Your income")) -> Choose your gross yearly income to see this | E30: ƒx =IF(Price_By_Deposit<Price_By_Income,"Your deposit","Your income")
B32: HOW IT WORKS
B33: ="• Income limit = combined gross income "&"× "&LTI_FTB&" (first-time buyer)"&" or "&"× "&LTI_SSB&" (everyone else)"&". The loan can also be at most "&TEXT(LTV_Max,"0%")&" of the price." -> • Income limit = combined gross income × 4 (first-time buyer) or × 3.5 (everyone else). The loan can also be at most 90% of the price.
B34: • Your deposit must pay 10% of the price, the stamp duty (1% up to €1m, 2% on €1m–€1.5m, 6% above) and the buying fees. So the price is the lower of: what the deposit allows (10% + stamp duty) and what income + deposit allow (price + stamp duty). Both are solved exactly, band by band.
B35: • Repayment = standard annuity PMT at rate ÷ 12 over the term.
B36: Edge rules and validation:
B37: • First-time buyer is a Yes/No choice.
B38: • When both limits are equal the text says the income sets the limit.
B39: • Lenders can lend above these limits for a small share of loans each year, so some buyers get an exception. Your lender decides.
B40: • At 0% interest Excel's PMT/NPER/FV give amount ÷ months, so no special case is needed in Excel; in code use payment = amount / months.
B42: ADD TO MY PLAN (what this calculator sends to the plan)
B43: Goal | C43: ="Buy a home (deposit goal)" -> Buy a home (deposit goal) | E43: ƒx ="Buy a home (deposit goal)"
B44: Amount (today's money): 10% deposit + stamp duty + fees | C44: =IF(Need_1<>"",Need_1,ROUND(Home_Price*Min_Deposit_Pct+Stamp_Duty+Buying_Fees,0)) -> Choose your gross yearly income to see this | E44: ƒx =ROUND(Home_Price*Min_Deposit_Pct+Stamp_Duty+Buying_Fees,0)
B45: Already saved | C45: =IF(Need_5<>"",Need_5,Total_Deposit) -> Choose your deposit saved to see this | E45: ƒx =Total_Deposit
B46: In (years) | C46: =IF(Need_7<>"",Need_7,Home_Goal_Years) -> Choose your years until you buy to see this | E46: ƒx =Home_Goal_Years
B48: CHOICES STILL NEEDED (helper rows: blank = all inputs a result needs are filled)
B49: Needs: buying fees, deposit saved, first-time buyer answer, gross yearly income, partner's gross yearly income | C49: =IF(Income="","Choose your gross yearly income to see this",IF(Partner_Income="","Choose your partner's gross yearly income to see this",IF(Deposit="","Choose your deposit saved to see this",IF(First_Time_Buyer="","Choose your first-time buyer answer to see this",IF(Buying_Fees="","Choose your buying fees to see this",IF(Interest_Rate="","Choose your mortgage rate to see this","")))))) -> Choose your gross yearly income to see this
B50: Needs: buying fees, deposit saved, first-time buyer answer, gross yearly income, interest rate, partner's gross yearly income, mortgage term | C50: =IF(Income="","Choose your gross yearly income to see this",IF(Partner_Income="","Choose your partner's gross yearly income to see this",IF(Deposit="","Choose your deposit saved to see this",IF(First_Time_Buyer="","Choose your first-time buyer answer to see this",IF(Term_Years="","Choose your mortgage term to see this",IF(Buying_Fees="","Choose your buying fees to see this",IF(Interest_Rate="","Choose your mortgage rate to see this",""))))))) -> Choose your gross yearly income to see this
B51: Needs: first-time buyer answer, gross yearly income, partner's gross yearly income | C51: =IF(Income="","Choose your gross yearly income to see this",IF(Partner_Income="","Choose your partner's gross yearly income to see this",IF(First_Time_Buyer="","Choose your first-time buyer answer to see this",IF(Interest_Rate="","Choose your mortgage rate to see this","")))) -> Choose your gross yearly income to see this
B52: Needs: first-time buyer answer | C52: =IF(First_Time_Buyer="","Choose your first-time buyer answer to see this",IF(Interest_Rate="","Choose your mortgage rate to see this","")) -> Choose your first-time buyer answer to see this
B53: Needs: deposit saved | C53: =IF(Deposit="","Choose your deposit saved to see this",IF(Interest_Rate="","Choose your mortgage rate to see this","")) -> Choose your deposit saved to see this
B54: Needs: buying fees, deposit saved | C54: =IF(Deposit="","Choose your deposit saved to see this",IF(Buying_Fees="","Choose your buying fees to see this",IF(Interest_Rate="","Choose your mortgage rate to see this",""))) -> Choose your deposit saved to see this
B55: Needs: years until you buy | C55: =IF(Home_Goal_Years="","Choose your years until you buy to see this",IF(Interest_Rate="","Choose your mortgage rate to see this","")) -> Choose your years until you buy to see this
B57: Note: stamp duty is worked out on the price shown; for a new home it is charged on the price excluding VAT, and Help to Buy is not included.

Sheet C02 Mortgage repayment
B1: C02 · Monthly mortgage repayment | E1: Category: Home & Mortgage · prototype id: repayment
B2: Question it answers: What would my monthly repayment be? | E2: =IF(Fill_Example="Yes","Example values are ON (README): grey Example only figures fill blank inputs.","Blank template: fill the yellow inputs (or switch on example values on the README).") -> Blank template: fill the yellow inputs (or switch on example values on the README).
B3: Works out the monthly repayment, how long until the mortgage is paid off and the total interest; and what a rate change would do.
B5: FROM YOUR STATEMENT (filled automatically by the document reader)
B6: Document: Mortgage statement (annual statement of account) or offer letter. Blank = no statement uploaded, or the figure is not on it. Grey-blue cells are filled by the reader (you can type here to test).
B7: Outstanding balance | D7: € | E7: Allowed: €0 to €10,000,000 | G7: Reader field: see note
B8: Interest rate | D8: % | E8: Allowed: 0% to 15% | G8: Reader field: see note
B9: Term remaining | D9: years | E9: Allowed: 0 to 40 | G9: Reader field: see note
B10: Monthly repayment | D10: € | E10: Allowed: €0 to €100,000 | G10: Reader field: see note
B11: Statement date | D11: date | E11: Allowed: a date (dd/mm/yyyy) | G11: Reader field: see note
B13: OR TYPE IT YOURSELF | C13: Your figure | D13: Unit | E13: Allowed | F13: Example only (grey; used only when "Fill example values" is Yes)
B14: Mortgage amount | D14: € | E14: Type 3 · your figure · Your own figure. In the app it is pre-filled from Your finances / mortgage statement: balance. Allowed: €50,000 to €10,000,000 · steps of €1,000 | F14: 300000 | G14: =IF(ISBLANK(C14),IF(Fill_Example="Yes",F14,""),C14)
B15: Interest rate | D15: % | E15: ="Type 2 · your figure · Your own rate (your statement shows it; typing it is fine, no upload needed). "&IF(ISNUMBER(Suggest_Mortgage_Rate),"Suggested: "&TEXT(Suggest_Mortgage_Rate,"0.00%")&" · "&Suggest_Mortgage_Rate_Label&". ","No suggestion. ")&"Enter your own figure."&" In the app it is pre-filled from Your finances / mortgage statement: rate. Enter your own figure. Allowed: 1% to 8% · steps of 0.05%" -> Type 2 · your figure · Your own rate (your statement shows it; typing it is fine, no upload needed). Suggested: 3.48% · Central Bank of Ireland: average rate on new mortgages, Jul 2026. Enter your own figure. In the app it is pre-filled from Your finances / mortgage statement: rate. Enter your own figure. Allowed: 1% to 8% · steps of 0.05% | F15: =IF(ISNUMBER(Suggest_Mortgage_Rate),Suggest_Mortgage_Rate,"") -> 0.0348 | G15: =IF(ISBLANK(C15),IF(Fill_Example="Yes",F15,""),C15)
B16: Term | D16: years | E16: Type 3 · your figure · Your own figure. In the app it is pre-filled from Years left (25 if not given). Allowed: 5 to 35 · steps of 1 | F16: 30 | G16: =IF(AND(ISNUMBER(C16),N(C16)<5),"",IF(ISBLANK(C16),IF(Fill_Example="Yes",F16,""),C16))
B17: Your actual monthly repayment (optional, 0 = work it out) | D17: € | E17: Type 3 · optional · Optional: leave blank for none. Allowed: €0 to €100,000 · steps of €1 | F17: 0 | G17: =IF(ISBLANK(C17),F17,C17) -> 0
B18: Years until you buy (for the plan) | D18: years | E18: Type 3 · your figure · Your own figure. Allowed: 1 to 30 · steps of 1 | F18: 3 | G18: =IF(ISBLANK(C18),IF(Fill_Example="Yes",F18,""),C18)
B19: What if: rates change by | D19: % | E19: Type 3 · optional · Optional: leave blank for none. Allowed: -2% to 3% · steps of 0.25% | F19: 0 | G19: =IF(ISBLANK(C19),F19,C19) -> 0
B21: FIGURE USED (statement figure if present, else your figure)
B22: Mortgage amount | C22: =IF(ISBLANK(Stmt_Balance),Loan_Amount,Stmt_Balance) | D22: =IF(ISBLANK(Stmt_Balance),"Your figure","From your statement") -> Your figure | E22: ƒx =IF(ISBLANK(Stmt_Balance),Loan_Amount,Stmt_Balance)
B23: Interest rate | C23: =IF(ISBLANK(Stmt_Rate),Interest_Rate,Stmt_Rate) | D23: =IF(ISBLANK(Stmt_Rate),"Your figure","From your statement") -> Your figure | E23: ƒx =IF(ISBLANK(Stmt_Rate),Interest_Rate,Stmt_Rate)
B24: Term | C24: =IF(ISBLANK(Stmt_Term),Term_Years,Stmt_Term) | D24: =IF(ISBLANK(Stmt_Term),"Your figure","From your statement") -> Your figure | E24: ƒx =IF(ISBLANK(Stmt_Term),Term_Years,Stmt_Term)
B25: Actual monthly repayment (0 = work it out) | C25: =IF(ISBLANK(Stmt_Repayment),Actual_Repayment,Stmt_Repayment) -> 0 | D25: =IF(ISBLANK(Stmt_Repayment),"Your figure","From your statement") -> Your figure | E25: ƒx =IF(ISBLANK(Stmt_Repayment),Actual_Repayment,Stmt_Repayment)
B26: Statement date check | C26: =IF(ISBLANK(Stmt_Statement_Date),"",IF(TODAY()-Stmt_Statement_Date>Statement_Max_Age_Days,"Needs a look: statement is more than 12 months old","Up to date")) | E26: ƒx =IF(ISBLANK(Stmt_Statement_Date),"",IF(TODAY()-Stmt_Statement_Date>Statement_Max_Age_Days,"Needs a look: statement is more than 12 months old","Up to date"))
B28: RESULTS | C28: Result | D28: Shown as | E28: Formula
B29: Monthly repayment | C29: =IF(Need_1<>"",Need_1,IF(Used_Actual_Repayment>0,Used_Actual_Repayment,Formula_Repayment)) -> Choose your mortgage amount to see this | D29: € | E29: ƒx =IF(Used_Actual_Repayment>0,Used_Actual_Repayment,Formula_Repayment)
B30: Mortgage free in (months) | C30: =IF(Need_1<>"",Need_1,IF(Monthly_Repayment<=Used_Loan_Amount*Monthly_Rate,"Never",ROUNDUP(ROUND(NPER(Monthly_Rate,-Monthly_Repayment,Used_Loan_Amount),6),0))) -> Choose your mortgage amount to see this | D30: =IF(Need_1<>"",Need_1,IF(Months_To_Pay="Never","Never at this repayment",IF(Months_To_Pay>Cap_Months,"Over 100 years",IF(INT(Months_To_Pay/12)=0,MOD(Months_To_Pay,12)&IF(MOD(Months_To_Pay,12)=1," month"," months"),INT(Months_To_Pay/12)&IF(INT(Months_To_Pay/12)=1," year"," years")&IF(MOD(Months_To_Pay,12)=0,""," "&MOD(Months_To_Pay,12)&IF(MOD(Months_To_Pay,12)=1," month"," months")))))) -> Choose your mortgage amount to see this | E30: ƒx =IF(Monthly_Repayment<=Used_Loan_Amount*Monthly_Rate,"Never",ROUNDUP(ROUND(NPER(Monthly_Rate,-Monthly_Repayment,Used_Loan_Amount),6),0))
B31: Total interest | C31: =IF(Need_1<>"",Need_1,IF(Months_To_Pay="Never","—",Monthly_Repayment*(Months_To_Pay-1)+Final_Payment-Used_Loan_Amount)) -> Choose your mortgage amount to see this | D31: € | E31: ƒx =IF(Months_To_Pay="Never","—",Monthly_Repayment*(Months_To_Pay-1)+Final_Payment-Used_Loan_Amount)
B32: Total repaid | C32: =IF(Need_1<>"",Need_1,IF(Months_To_Pay="Never","—",Used_Loan_Amount+Total_Interest)) -> Choose your mortgage amount to see this | D32: € | E32: ƒx =IF(Months_To_Pay="Never","—",Used_Loan_Amount+Total_Interest)
B33: Monthly interest rate | C33: =IF(Need_2<>"",Need_2,Used_Interest_Rate/12) -> Choose your mortgage rate to see this | E33: ƒx =Used_Interest_Rate/12
B34: Repayment by formula (standard annuity) | C34: =IF(Need_3<>"",Need_3,PMT(Monthly_Rate,Used_Term_Years*12,-Used_Loan_Amount)) -> Choose your mortgage amount to see this | D34: € | E34: ƒx =PMT(Monthly_Rate,Used_Term_Years*12,-Used_Loan_Amount)
B35: Last (part) payment | C35: =IF(Need_1<>"",Need_1,IF(Months_To_Pay="Never","—",-FV(Monthly_Rate,Months_To_Pay-1,-Monthly_Repayment,Used_Loan_Amount)*(1+Monthly_Rate))) -> Choose your mortgage amount to see this | D35: € | E35: ƒx =IF(Months_To_Pay="Never","—",-FV(Monthly_Rate,Months_To_Pay-1,-Monthly_Repayment,Used_Loan_Amount)*(1+Monthly_Rate)) (balance left before the last month, plus that month's interest)
B36: What if: new rate (never below 0%) | C36: =IF(Need_2<>"",Need_2,MAX(0,Used_Interest_Rate+Rate_Change)) -> Choose your mortgage rate to see this | D36: % | E36: ƒx =MAX(0,Used_Interest_Rate+Rate_Change)
B37: What if: monthly repayment | C37: =IF(Need_1<>"",Need_1,Monthly_Repayment+PMT(New_Rate/12,Used_Term_Years*12,-Used_Loan_Amount)-Formula_Repayment) -> Choose your mortgage amount to see this | D37: € | E37: ƒx =Monthly_Repayment+PMT(New_Rate/12,Used_Term_Years*12,-Used_Loan_Amount)-Formula_Repayment
B38: What if: change over a year | C38: =IF(Need_1<>"",Need_1,(Repayment_If_Changed-Monthly_Repayment)*12) -> Choose your mortgage amount to see this | D38: € | E38: ƒx =(Repayment_If_Changed-Monthly_Repayment)*12
B40: HOW IT WORKS
B41: • Repayment = PMT(rate ÷ 12, years × 12, −amount), the standard repayment-mortgage formula; your stated repayment replaces it if you give one.
B42: • Months to pay off = NPER(rate ÷ 12, −repayment, amount), rounded up. Total interest = all full payments + the last part payment − the amount (exact, as a lender's schedule).
B43: • What if: the stated repayment moves by the same amount as the formula repayment would: repayment + PMT(new rate) − PMT(current rate). The new rate is floored at 0%.
B44: Edge rules and validation:
B45: • If the payment is at or below the first month's interest the balance never falls: show "Never at this repayment" and leave total interest blank ("—").
B46: • More than 1,200 months (100 years) is shown as "Over 100 years"; the exact month count is still calculated (no loop cap).
B47: • NPER is rounded to 6 decimals before rounding up, so a repayment that exactly fits the term ends on the term (floating-point noise would otherwise add a month).
B48: • At 0% interest Excel's PMT/NPER/FV give amount ÷ months, so no special case is needed in Excel; in code use payment = amount / months.
B50: ADD TO MY PLAN (what this calculator sends to the plan)
B51: Goal | C51: ="Buy a home (deposit goal)" -> Buy a home (deposit goal) | E51: ƒx ="Buy a home (deposit goal)"
B52: Amount (today's money): the deposit for this loan | C52: =IF(Need_4<>"",Need_4,ROUND(Used_Loan_Amount*(1-LTV_Max)/LTV_Max,0)) -> Choose your mortgage amount to see this | E52: ƒx =ROUND(Used_Loan_Amount*(1-LTV_Max)/LTV_Max,0)
B53: In (years) | C53: =IF(Need_5<>"",Need_5,Home_Goal_Years) -> Choose your years until you buy to see this | E53: ƒx =Home_Goal_Years
B54: ="Audit fix: the mortgage amount itself is borrowing, not a savings goal, so only the deposit ("&"loan × "&TEXT(Min_Deposit_Pct,"0%")&" ÷ "&TEXT(LTV_Max,"0%")&" at "&TEXT(LTV_Max,"0%")&" LTV"&") is sent." -> Audit fix: the mortgage amount itself is borrowing, not a savings goal, so only the deposit (loan × 10% ÷ 90% at 90% LTV) is sent.
B56: CHOICES STILL NEEDED (helper rows: blank = all inputs a result needs are filled)
B57: Needs: Used_Actual_Repayment, Used_Interest_Rate, Used_Loan_Amount, Used_Term_Years | C57: =IF(NOT(ISNUMBER(Used_Loan_Amount)),IF(Used_Loan_Amount="",IF(Loan_Amount="","Choose your mortgage amount to see this",""),Used_Loan_Amount),IF(NOT(ISNUMBER(Used_Term_Years)),IF(Used_Term_Years="",IF(Term_Years="","Choose your mortgage term to see this",""),Used_Term_Years),IF(NOT(ISNUMBER(Used_Actual_Repayment)),IF(Used_Actual_Repayment="","Choose your actual monthly repayment to see this",Used_Actual_Repayment),IF(NOT(ISNUMBER(Used_Interest_Rate)),IF(Used_Interest_Rate="",IF(Interest_Rate="","Choose your mortgage rate to see this",""),Used_Interest_Rate),"")))) -> Choose your mortgage amount to see this
B58: Needs: Used_Interest_Rate | C58: =IF(NOT(ISNUMBER(Used_Interest_Rate)),IF(Used_Interest_Rate="",IF(Interest_Rate="","Choose your mortgage rate to see this",""),Used_Interest_Rate),"") -> Choose your mortgage rate to see this
B59: Needs: Used_Interest_Rate, Used_Loan_Amount, Used_Term_Years | C59: =IF(NOT(ISNUMBER(Used_Loan_Amount)),IF(Used_Loan_Amount="",IF(Loan_Amount="","Choose your mortgage amount to see this",""),Used_Loan_Amount),IF(NOT(ISNUMBER(Used_Term_Years)),IF(Used_Term_Years="",IF(Term_Years="","Choose your mortgage term to see this",""),Used_Term_Years),IF(NOT(ISNUMBER(Used_Interest_Rate)),IF(Used_Interest_Rate="",IF(Interest_Rate="","Choose your mortgage rate to see this",""),Used_Interest_Rate),""))) -> Choose your mortgage amount to see this
B60: Needs: Used_Loan_Amount | C60: =IF(NOT(ISNUMBER(Used_Loan_Amount)),IF(Used_Loan_Amount="",IF(Loan_Amount="","Choose your mortgage amount to see this",""),Used_Loan_Amount),IF(NOT(ISNUMBER(Used_Interest_Rate)),IF(Used_Interest_Rate="",IF(Interest_Rate="","Choose your mortgage rate to see this",""),Used_Interest_Rate),"")) -> Choose your mortgage amount to see this
B61: Needs: years until you buy | C61: =IF(Home_Goal_Years="","Choose your years until you buy to see this",IF(NOT(ISNUMBER(Used_Interest_Rate)),IF(Used_Interest_Rate="",IF(Interest_Rate="","Choose your mortgage rate to see this",""),Used_Interest_Rate),"")) -> Choose your years until you buy to see this
B63: Note: the rate is a yearly rate, compounded monthly (nominal rate ÷ 12), the way lenders quote mortgage rates.

Sheet C03 Deposit
B1: C03 · Deposit calculator | E1: Category: Home & Mortgage · prototype id: deposit
B2: Question it answers: How long until I have my deposit? | E2: =IF(Fill_Example="Yes","Example values are ON (README): grey Example only figures fill blank inputs.","Blank template: fill the yellow inputs (or switch on example values on the README).") -> Blank template: fill the yellow inputs (or switch on example values on the README).
B3: Works out the deposit, stamp duty and fees you need and how many months of saving it takes.
B5: INPUTS | C5: Your figure | D5: Unit | E5: Allowed | F5: Example only (grey; used only when "Fill example values" is Yes)
B6: Home price | D6: € | E6: Type 3 · your figure · Your own figure. Allowed: €100,000 to €10,000,000 · steps of €5,000 | F6: 350000 | G6: =IF(ISBLANK(C6),IF(Fill_Example="Yes",F6,""),C6)
B7: Deposit needed | D7: % | E7: ="Type 3 · your figure · Your own figure. Allowed: 10% to 30% · steps of 1% · the Central Bank "&"minimum is "&TEXT(Min_Deposit_Pct,"0%")&" ("&TEXT(LTV_Max,"0%")&" LTV)" -> Type 3 · your figure · Your own figure. Allowed: 10% to 30% · steps of 1% · the Central Bank minimum is 10% (90% LTV) | F7: 0.1 | G7: =IF(ISBLANK(C7),IF(Fill_Example="Yes",F7,""),C7)
B8: Legal and other buying fees | D8: € | E8: ="Type 2 · optional · Legal and survey fees (stamp duty is added for you). "&IF(ISNUMBER(Suggest_Buying_Fees),"Suggested: "&TEXT(Suggest_Buying_Fees,"€#,##0")&" · "&Suggest_Buying_Fees_Label&". ","No suggestion. ")&"Leave blank to count €0."&" Allowed: €0 to €10,000 · steps of €100" -> Type 2 · optional · Legal and survey fees (stamp duty is added for you). No suggestion. Leave blank to count €0. Allowed: €0 to €10,000 · steps of €100 | F8: =IF(ISNUMBER(Suggest_Buying_Fees),Suggest_Buying_Fees,"") | G8: =IF(ISBLANK(C8),IF(AND(Fill_Example="Yes",ISNUMBER(F8)),F8,0),C8) -> 0
B9: Saved so far | D9: € | E9: Type 3 · your figure · Your own figure. In the app it is pre-filled from Plan: home goal's amount saved. Allowed: €0 to €2,000,000 · steps of €500 | F9: 12000 | G9: =IF(ISBLANK(C9),IF(Fill_Example="Yes",F9,""),C9)
B10: Monthly saving | D10: € | E10: Type 3 · your figure · Your own figure. Allowed: €50 to €50,000 · steps of €50 | F10: 800 | G10: =IF(AND(ISNUMBER(C10),N(C10)<50),"",IF(ISBLANK(C10),IF(Fill_Example="Yes",F10,""),C10))
B11: What if: save extra each month | D11: € | E11: Type 3 · optional · Optional: leave blank for none. Allowed: €0 to €15,000 · steps of €50 | F11: 0 | G11: =IF(ISBLANK(C11),F11,C11) -> 0
B13: RESULTS | C13: Result | D13: Shown as | E13: Formula
B14: Time to your deposit (months) | C14: =IF(Need_1<>"",Need_1,IF(Still_To_Save=0,0,ROUNDUP(Still_To_Save/(Monthly_Saving+Extra_Saving),0))) -> Choose your home price to see this | D14: =IF(Need_1<>"",Need_1,IF(Months_To_Deposit=0,"You have your deposit",IF(INT(Months_To_Deposit/12)=0,MOD(Months_To_Deposit,12)&IF(MOD(Months_To_Deposit,12)=1," month"," months"),INT(Months_To_Deposit/12)&IF(INT(Months_To_Deposit/12)=1," year"," years")&IF(MOD(Months_To_Deposit,12)=0,""," "&MOD(Months_To_Deposit,12)&IF(MOD(Months_To_Deposit,12)=1," month"," months"))))) -> Choose your home price to see this | E14: ƒx =IF(Still_To_Save=0,0,ROUNDUP(Still_To_Save/(Monthly_Saving+Extra_Saving),0))
B15: Total you need (deposit + stamp duty + fees) | C15: =IF(Need_2<>"",Need_2,Deposit_Needed+Stamp_Duty+Buying_Fees) -> Choose your home price to see this | D15: € | E15: ƒx =Deposit_Needed+Stamp_Duty+Buying_Fees
B16: Still to save | C16: =IF(Need_3<>"",Need_3,MAX(0,Total_Needed-Saved)) -> Choose your home price to see this | D16: € | E16: ƒx =MAX(0,Total_Needed-Saved)
B17: Deposit | C17: =IF(Need_4<>"",Need_4,Home_Price*Deposit_Pct) -> Choose your home price to see this | D17: € | E17: ƒx =Home_Price*Deposit_Pct
B18: Stamp duty | C18: =IF(Need_5<>"",Need_5,SD_Rate_1*MIN(Home_Price,SD_Band_1)+SD_Rate_2*MAX(0,MIN(Home_Price,SD_Band_2)-SD_Band_1)+SD_Rate_3*MAX(0,Home_Price-SD_Band_2)) -> Choose your home price to see this | D18: € | E18: ƒx =SD_Rate_1*MIN(Home_Price,SD_Band_1)+SD_Rate_2*MAX(0,MIN(Home_Price,SD_Band_2)-SD_Band_1)+SD_Rate_3*MAX(0,Home_Price-SD_Band_2)
B20: HOW IT WORKS
B21: • Deposit = price × deposit %. Stamp duty = 1% up to €1m, 2% on €1m–€1.5m, 6% above. Total = deposit + stamp duty + fees.
B22: • Months = still to save ÷ monthly saving (incl. the what-if extra), rounded up. No interest and no house-price growth are assumed.
B23: Edge rules and validation:
B24: ="• Deposit % "&"starts at "&TEXT(Min_Deposit_Pct,"0%")&", the Central Bank minimum ("&TEXT(LTV_Max,"0%")&" loan-to-value)." -> • Deposit % starts at 10%, the Central Bank minimum (90% loan-to-value).
B25: • Nothing left to save shows "You have your deposit".
B26: • Monthly saving must be at least €50, so there is no divide by zero.
B28: ADD TO MY PLAN (what this calculator sends to the plan)
B29: Goal | C29: ="Home deposit" -> Home deposit | E29: ƒx ="Home deposit"
B30: Amount (today's money): deposit + stamp duty + fees | C30: =IF(Need_2<>"",Need_2,ROUND(Total_Needed,0)) -> Choose your home price to see this | E30: ƒx =ROUND(Total_Needed,0)
B31: Already saved | C31: =IF(Need_6<>"",Need_6,Saved) -> Choose your saved so far to see this | E31: ƒx =Saved
B32: In (years) | C32: =IF(Need_1<>"",Need_1,MAX(1,ROUNDUP(Months_To_Deposit/12,0))) -> Choose your home price to see this | E32: ƒx =MAX(1,ROUNDUP(Months_To_Deposit/12,0))
B34: CHOICES STILL NEEDED (helper rows: blank = all inputs a result needs are filled)
B35: Needs: buying fees, deposit %, home price, monthly saving, saved so far | C35: =IF(Home_Price="","Choose your home price to see this",IF(Deposit_Pct="","Choose your deposit % to see this",IF(Buying_Fees="","Choose your buying fees to see this",IF(Saved="","Choose your saved so far to see this",IF(Monthly_Saving="","Choose your monthly saving to see this",""))))) -> Choose your home price to see this
B36: Needs: buying fees, deposit %, home price | C36: =IF(Home_Price="","Choose your home price to see this",IF(Deposit_Pct="","Choose your deposit % to see this",IF(Buying_Fees="","Choose your buying fees to see this",""))) -> Choose your home price to see this
B37: Needs: buying fees, deposit %, home price, saved so far | C37: =IF(Home_Price="","Choose your home price to see this",IF(Deposit_Pct="","Choose your deposit % to see this",IF(Buying_Fees="","Choose your buying fees to see this",IF(Saved="","Choose your saved so far to see this","")))) -> Choose your home price to see this
B38: Needs: deposit %, home price | C38: =IF(Home_Price="","Choose your home price to see this",IF(Deposit_Pct="","Choose your deposit % to see this","")) -> Choose your home price to see this
B39: Needs: home price | C39: =IF(Home_Price="","Choose your home price to see this","") -> Choose your home price to see this
B40: Needs: saved so far | C40: =IF(Saved="","Choose your saved so far to see this","") -> Choose your saved so far to see this
B42: Note: stamp duty is worked out on the price shown; for a new home it is charged on the price excluding VAT, and Help to Buy is not included.

Sheet C04 Mortgage overpayment
B1: C04 · Mortgage overpayment | E1: Category: Home & Mortgage · prototype id: overpay
B2: Question it answers: What if I paid a little extra each month? | E2: =IF(Fill_Example="Yes","Example values are ON (README): grey Example only figures fill blank inputs.","Blank template: fill the yellow inputs (or switch on example values on the README).") -> Blank template: fill the yellow inputs (or switch on example values on the README).
B3: Compares paying off the mortgage at your repayment with paying a little extra each month: time and interest saved.
B5: FROM YOUR STATEMENT (filled automatically by the document reader)
B6: Document: Mortgage statement (annual statement of account) or offer letter. Blank = no statement uploaded, or the figure is not on it. Grey-blue cells are filled by the reader (you can type here to test).
B7: Outstanding balance | D7: € | E7: Allowed: €0 to €10,000,000 | G7: Reader field: see note
B8: Interest rate | D8: % | E8: Allowed: 0% to 15% | G8: Reader field: see note
B9: Term remaining | D9: years | E9: Allowed: 0 to 40 | G9: Reader field: see note
B10: Monthly repayment | D10: € | E10: Allowed: €0 to €100,000 | G10: Reader field: see note
B11: Statement date | D11: date | E11: Allowed: a date (dd/mm/yyyy) | G11: Reader field: see note
B13: OR TYPE IT YOURSELF | C13: Your figure | D13: Unit | E13: Allowed | F13: Example only (grey; used only when "Fill example values" is Yes)
B14: Mortgage balance | D14: € | E14: Type 3 · your figure · Your own figure. In the app it is pre-filled from Your finances / statement: balance. Allowed: €20,000 to €10,000,000 · steps of €1,000 | F14: 250000 | G14: =IF(ISBLANK(C14),IF(Fill_Example="Yes",F14,""),C14)
B15: Interest rate | D15: % | E15: ="Type 2 · your figure · Your own rate (your statement shows it; typing it is fine, no upload needed). "&IF(ISNUMBER(Suggest_Mortgage_Rate),"Suggested: "&TEXT(Suggest_Mortgage_Rate,"0.00%")&" · "&Suggest_Mortgage_Rate_Label&". ","No suggestion. ")&"Enter your own figure."&" In the app it is pre-filled from Your finances / statement: rate. Enter your own figure. Allowed: 1% to 8% · steps of 0.05%" -> Type 2 · your figure · Your own rate (your statement shows it; typing it is fine, no upload needed). Suggested: 3.48% · Central Bank of Ireland: average rate on new mortgages, Jul 2026. Enter your own figure. In the app it is pre-filled from Your finances / statement: rate. Enter your own figure. Allowed: 1% to 8% · steps of 0.05% | F15: =IF(ISNUMBER(Suggest_Mortgage_Rate),Suggest_Mortgage_Rate,"") -> 0.0348 | G15: =IF(ISBLANK(C15),IF(Fill_Example="Yes",F15,""),C15)
B16: Years left | D16: years | E16: Type 3 · your figure · Your own figure. In the app it is pre-filled from Years left (25 if not given). Allowed: 3 to 35 · steps of 1 | F16: 25 | G16: =IF(AND(ISNUMBER(C16),N(C16)<3),"",IF(ISBLANK(C16),IF(Fill_Example="Yes",F16,""),C16))
B17: Extra each month | D17: € | E17: Type 3 · your figure · Your own figure. Allowed: €0 to €20,000 · steps of €25 | F17: 200 | G17: =IF(ISBLANK(C17),IF(Fill_Example="Yes",F17,""),C17)
B18: Your actual monthly repayment (optional, 0 = work it out) | D18: € | E18: Type 3 · optional · Optional: leave blank for none. Allowed: €0 to €100,000 · steps of €1 | F18: 0 | G18: =IF(ISBLANK(C18),F18,C18) -> 0
B20: FIGURE USED (statement figure if present, else your figure)
B21: Mortgage balance | C21: =IF(ISBLANK(Stmt_Balance),Mortgage_Balance,Stmt_Balance) | D21: =IF(ISBLANK(Stmt_Balance),"Your figure","From your statement") -> Your figure | E21: ƒx =IF(ISBLANK(Stmt_Balance),Mortgage_Balance,Stmt_Balance)
B22: Interest rate | C22: =IF(ISBLANK(Stmt_Rate),Interest_Rate,Stmt_Rate) | D22: =IF(ISBLANK(Stmt_Rate),"Your figure","From your statement") -> Your figure | E22: ƒx =IF(ISBLANK(Stmt_Rate),Interest_Rate,Stmt_Rate)
B23: Years left | C23: =IF(ISBLANK(Stmt_Term),Years_Left,Stmt_Term) | D23: =IF(ISBLANK(Stmt_Term),"Your figure","From your statement") -> Your figure | E23: ƒx =IF(ISBLANK(Stmt_Term),Years_Left,Stmt_Term)
B24: Actual monthly repayment (0 = work it out) | C24: =IF(ISBLANK(Stmt_Repayment),Actual_Repayment,Stmt_Repayment) -> 0 | D24: =IF(ISBLANK(Stmt_Repayment),"Your figure","From your statement") -> Your figure | E24: ƒx =IF(ISBLANK(Stmt_Repayment),Actual_Repayment,Stmt_Repayment)
B25: Statement date check | C25: =IF(ISBLANK(Stmt_Statement_Date),"",IF(TODAY()-Stmt_Statement_Date>Statement_Max_Age_Days,"Needs a look: statement is more than 12 months old","Up to date")) | E25: ƒx =IF(ISBLANK(Stmt_Statement_Date),"",IF(TODAY()-Stmt_Statement_Date>Statement_Max_Age_Days,"Needs a look: statement is more than 12 months old","Up to date"))
B27: RESULTS | C27: Result | D27: Shown as | E27: Formula
B28: Mortgage free sooner by (months) | C28: =IF(Need_1<>"",Need_1,IF(OR(Months_Now="Never",Months_With_Extra="Never"),"—",Months_Now-Months_With_Extra)) -> Choose your extra each month to see this | D28: =IF(Need_1<>"",Need_1,IF(Months_Sooner="—","—",IF(Months_Sooner=0,"No change",IF(INT(Months_Sooner/12)=0,MOD(Months_Sooner,12)&IF(MOD(Months_Sooner,12)=1," month"," months"),INT(Months_Sooner/12)&IF(INT(Months_Sooner/12)=1," year"," years")&IF(MOD(Months_Sooner,12)=0,""," "&MOD(Months_Sooner,12)&IF(MOD(Months_Sooner,12)=1," month"," months")))))) -> Choose your extra each month to see this | E28: ƒx =IF(OR(Months_Now="Never",Months_With_Extra="Never"),"—",Months_Now-Months_With_Extra)
B29: Interest saved | C29: =IF(Need_1<>"",Need_1,IF(OR(Months_Now="Never",Months_With_Extra="Never"),"—",Interest_Now-Interest_With_Extra)) -> Choose your extra each month to see this | D29: € | E29: ƒx =IF(OR(Months_Now="Never",Months_With_Extra="Never"),"—",Interest_Now-Interest_With_Extra)
B30: Mortgage free now in (months) | C30: =IF(Need_2<>"",Need_2,IF(Repayment_Now<=Used_Mortgage_Balance*Monthly_Rate,"Never",ROUNDUP(ROUND(NPER(Monthly_Rate,-Repayment_Now,Used_Mortgage_Balance),6),0))) -> Choose your mortgage balance to see this | D30: =IF(Need_2<>"",Need_2,IF(Months_Now="Never","Not at this repayment",IF(Months_Now>Cap_Months,"Over 100 years",IF(INT(Months_Now/12)=0,MOD(Months_Now,12)&IF(MOD(Months_Now,12)=1," month"," months"),INT(Months_Now/12)&IF(INT(Months_Now/12)=1," year"," years")&IF(MOD(Months_Now,12)=0,""," "&MOD(Months_Now,12)&IF(MOD(Months_Now,12)=1," month"," months")))))) -> Choose your mortgage balance to see this | E30: ƒx =IF(Repayment_Now<=Used_Mortgage_Balance*Monthly_Rate,"Never",ROUNDUP(ROUND(NPER(Monthly_Rate,-Repayment_Now,Used_Mortgage_Balance),6),0))
B31: With the extra (months) | C31: =IF(Need_1<>"",Need_1,IF(Repayment_With_Extra<=Used_Mortgage_Balance*Monthly_Rate,"Never",ROUNDUP(ROUND(NPER(Monthly_Rate,-Repayment_With_Extra,Used_Mortgage_Balance),6),0))) -> Choose your extra each month to see this | D31: =IF(Need_1<>"",Need_1,IF(Months_With_Extra="Never","—",IF(Months_With_Extra>Cap_Months,"Over 100 years",IF(INT(Months_With_Extra/12)=0,MOD(Months_With_Extra,12)&IF(MOD(Months_With_Extra,12)=1," month"," months"),INT(Months_With_Extra/12)&IF(INT(Months_With_Extra/12)=1," year"," years")&IF(MOD(Months_With_Extra,12)=0,""," "&MOD(Months_With_Extra,12)&IF(MOD(Months_With_Extra,12)=1," month"," months")))))) -> Choose your extra each month to see this | E31: ƒx =IF(Repayment_With_Extra<=Used_Mortgage_Balance*Monthly_Rate,"Never",ROUNDUP(ROUND(NPER(Monthly_Rate,-Repayment_With_Extra,Used_Mortgage_Balance),6),0))
B32: Monthly interest rate | C32: =IF(Need_3<>"",Need_3,Used_Interest_Rate/12) -> Choose your mortgage rate to see this | E32: ƒx =Used_Interest_Rate/12
B33: Repayment now | C33: =IF(Need_2<>"",Need_2,IF(Used_Actual_Repayment>0,Used_Actual_Repayment,PMT(Monthly_Rate,Used_Years_Left*12,-Used_Mortgage_Balance))) -> Choose your mortgage balance to see this | D33: € | E33: ƒx =IF(Used_Actual_Repayment>0,Used_Actual_Repayment,PMT(Monthly_Rate,Used_Years_Left*12,-Used_Mortgage_Balance))
B34: Repayment with the extra | C34: =IF(Need_1<>"",Need_1,Repayment_Now+Extra_Payment) -> Choose your extra each month to see this | D34: € | E34: ƒx =Repayment_Now+Extra_Payment
B35: Last (part) payment now | C35: =IF(Need_2<>"",Need_2,IF(Months_Now="Never","—",-FV(Monthly_Rate,Months_Now-1,-Repayment_Now,Used_Mortgage_Balance)*(1+Monthly_Rate))) -> Choose your mortgage balance to see this | D35: € | E35: ƒx =IF(Months_Now="Never","—",-FV(Monthly_Rate,Months_Now-1,-Repayment_Now,Used_Mortgage_Balance)*(1+Monthly_Rate))
B36: Last (part) payment with the extra | C36: =IF(Need_1<>"",Need_1,IF(Months_With_Extra="Never","—",-FV(Monthly_Rate,Months_With_Extra-1,-Repayment_With_Extra,Used_Mortgage_Balance)*(1+Monthly_Rate))) -> Choose your extra each month to see this | D36: € | E36: ƒx =IF(Months_With_Extra="Never","—",-FV(Monthly_Rate,Months_With_Extra-1,-Repayment_With_Extra,Used_Mortgage_Balance)*(1+Monthly_Rate))
B37: Total interest now | C37: =IF(Need_2<>"",Need_2,IF(Months_Now="Never","—",Repayment_Now*(Months_Now-1)+Last_Payment_Now-Used_Mortgage_Balance)) -> Choose your mortgage balance to see this | D37: € | E37: ƒx =IF(Months_Now="Never","—",Repayment_Now*(Months_Now-1)+Last_Payment_Now-Used_Mortgage_Balance)
B38: Total interest with the extra | C38: =IF(Need_1<>"",Need_1,IF(Months_With_Extra="Never","—",Repayment_With_Extra*(Months_With_Extra-1)+Last_Payment_With_Extra-Used_Mortgage_Balance)) -> Choose your extra each month to see this | D38: € | E38: ƒx =IF(Months_With_Extra="Never","—",Repayment_With_Extra*(Months_With_Extra-1)+Last_Payment_With_Extra-Used_Mortgage_Balance)
B40: HOW IT WORKS
B41: • Months to pay off = NPER(rate ÷ 12, −repayment, balance), rounded up, worked out twice: at your repayment and at repayment + extra.
B42: • Total interest = full payments + last part payment − balance. Interest saved = interest now − interest with the extra. Sooner by = the difference in months.
B43: Edge rules and validation:
B44: • If your repayment never clears the mortgage: "Not at this repayment", and "—" for sooner by and interest saved (no negative saving).
B45: • If even the extra does not clear it: "—" for "With the extra" and no goal is sent.
B46: • More than 1,200 months (100 years) is shown as "Over 100 years"; the exact month count is still calculated (no loop cap).
B47: • NPER is rounded to 6 decimals before rounding up, so a repayment that exactly fits the term ends on the term (floating-point noise would otherwise add a month).
B48: • A difference of 0 months reads "No change".
B50: ADD TO MY PLAN (what this calculator sends to the plan)
B51: Goal | C51: =IF(Need_1<>"",Need_1,IF(Months_With_Extra="Never","No goal","Mortgage free (plan kind mfree, priced from your mortgage; no cash amount)")) -> Choose your extra each month to see this | E51: ƒx =IF(Months_With_Extra="Never","No goal","Mortgage free (plan kind mfree, priced from your mortgage; no cash amount)")
B52: In (years) | C52: =IF(Need_1<>"",Need_1,IF(Months_With_Extra="Never","—",ROUNDUP(Months_With_Extra/12,0))) -> Choose your extra each month to see this | E52: ƒx =IF(Months_With_Extra="Never","—",ROUNDUP(Months_With_Extra/12,0))
B53: Audit fix: the old goal sent today's balance as a cash spend at the payoff year (a double count). The plan should also raise its mortgage repayment by the extra.
B55: CHOICES STILL NEEDED (helper rows: blank = all inputs a result needs are filled)
B56: Needs: extra each month, Used_Actual_Repayment, Used_Interest_Rate, Used_Mortgage_Balance, Used_Years_Left | C56: =IF(Extra_Payment="","Choose your extra each month to see this",IF(NOT(ISNUMBER(Used_Mortgage_Balance)),IF(Used_Mortgage_Balance="",IF(Mortgage_Balance="","Choose your mortgage balance to see this",""),Used_Mortgage_Balance),IF(NOT(ISNUMBER(Used_Years_Left)),IF(Used_Years_Left="",IF(Years_Left="","Choose your years left to see this",""),Used_Years_Left),IF(NOT(ISNUMBER(Used_Actual_Repayment)),IF(Used_Actual_Repayment="","Choose your actual monthly repayment to see this",Used_Actual_Repayment),IF(NOT(ISNUMBER(Used_Interest_Rate)),IF(Used_Interest_Rate="",IF(Interest_Rate="","Choose your mortgage rate to see this",""),Used_Interest_Rate),""))))) -> Choose your extra each month to see this
B57: Needs: Used_Actual_Repayment, Used_Interest_Rate, Used_Mortgage_Balance, Used_Years_Left | C57: =IF(NOT(ISNUMBER(Used_Mortgage_Balance)),IF(Used_Mortgage_Balance="",IF(Mortgage_Balance="","Choose your mortgage balance to see this",""),Used_Mortgage_Balance),IF(NOT(ISNUMBER(Used_Years_Left)),IF(Used_Years_Left="",IF(Years_Left="","Choose your years left to see this",""),Used_Years_Left),IF(NOT(ISNUMBER(Used_Actual_Repayment)),IF(Used_Actual_Repayment="","Choose your actual monthly repayment to see this",Used_Actual_Repayment),IF(NOT(ISNUMBER(Used_Interest_Rate)),IF(Used_Interest_Rate="",IF(Interest_Rate="","Choose your mortgage rate to see this",""),Used_Interest_Rate),"")))) -> Choose your mortgage balance to see this
B58: Needs: Used_Interest_Rate | C58: =IF(NOT(ISNUMBER(Used_Interest_Rate)),IF(Used_Interest_Rate="",IF(Interest_Rate="","Choose your mortgage rate to see this",""),Used_Interest_Rate),"") -> Choose your mortgage rate to see this

Sheet C05 Interest rate impact
B1: C05 · Interest-rate impact | E1: Category: Home & Mortgage · prototype id: ratechange
B2: Question it answers: What if my mortgage rate changed? | E2: =IF(Fill_Example="Yes","Example values are ON (README): grey Example only figures fill blank inputs.","Blank template: fill the yellow inputs (or switch on example values on the README).") -> Blank template: fill the yellow inputs (or switch on example values on the README).
B3: Shows how much your monthly repayment changes if your mortgage rate goes up or down.
B5: FROM YOUR STATEMENT (filled automatically by the document reader)
B6: Document: Mortgage statement (annual statement of account) or offer letter. Blank = no statement uploaded, or the figure is not on it. Grey-blue cells are filled by the reader (you can type here to test).
B7: Outstanding balance | D7: € | E7: Allowed: €0 to €10,000,000 | G7: Reader field: see note
B8: Interest rate | D8: % | E8: Allowed: 0% to 15% | G8: Reader field: see note
B9: Term remaining | D9: years | E9: Allowed: 0 to 40 | G9: Reader field: see note
B10: Monthly repayment | D10: € | E10: Allowed: €0 to €100,000 | G10: Reader field: see note
B11: Statement date | D11: date | E11: Allowed: a date (dd/mm/yyyy) | G11: Reader field: see note
B13: OR TYPE IT YOURSELF | C13: Your figure | D13: Unit | E13: Allowed | F13: Example only (grey; used only when "Fill example values" is Yes)
B14: Mortgage balance | D14: € | E14: Type 3 · your figure · Your own figure. In the app it is pre-filled from Your finances / statement: balance. Allowed: €50,000 to €10,000,000 · steps of €1,000 | F14: 300000 | G14: =IF(ISBLANK(C14),IF(Fill_Example="Yes",F14,""),C14)
B15: Current rate | D15: % | E15: ="Type 2 · your figure · Your own rate (your statement shows it; typing it is fine, no upload needed). "&IF(ISNUMBER(Suggest_Mortgage_Rate),"Suggested: "&TEXT(Suggest_Mortgage_Rate,"0.00%")&" · "&Suggest_Mortgage_Rate_Label&". ","No suggestion. ")&"Enter your own figure."&" In the app it is pre-filled from Your finances / statement: rate. Enter your own figure. Allowed: 1% to 8% · steps of 0.05%" -> Type 2 · your figure · Your own rate (your statement shows it; typing it is fine, no upload needed). Suggested: 3.48% · Central Bank of Ireland: average rate on new mortgages, Jul 2026. Enter your own figure. In the app it is pre-filled from Your finances / statement: rate. Enter your own figure. Allowed: 1% to 8% · steps of 0.05% | F15: =IF(ISNUMBER(Suggest_Mortgage_Rate),Suggest_Mortgage_Rate,"") -> 0.0348 | G15: =IF(ISBLANK(C15),IF(Fill_Example="Yes",F15,""),C15)
B16: Years left | D16: years | E16: Type 3 · your figure · Your own figure. In the app it is pre-filled from Years left (25 if not given). Allowed: 5 to 35 · steps of 1 | F16: 25 | G16: =IF(AND(ISNUMBER(C16),N(C16)<5),"",IF(ISBLANK(C16),IF(Fill_Example="Yes",F16,""),C16))
B17: Rate change | D17: % | E17: Type 3 · your figure · Your own figure. Allowed: -2% to 3% · steps of 0.25% | F17: 0.01 | G17: =IF(ISBLANK(C17),IF(Fill_Example="Yes",F17,""),C17)
B18: Your actual monthly repayment (optional, 0 = work it out) | D18: € | E18: Type 3 · optional · Optional: leave blank for none. Allowed: €0 to €100,000 · steps of €1 | F18: 0 | G18: =IF(ISBLANK(C18),F18,C18) -> 0
B20: FIGURE USED (statement figure if present, else your figure)
B21: Mortgage balance | C21: =IF(ISBLANK(Stmt_Balance),Mortgage_Balance,Stmt_Balance) | D21: =IF(ISBLANK(Stmt_Balance),"Your figure","From your statement") -> Your figure | E21: ƒx =IF(ISBLANK(Stmt_Balance),Mortgage_Balance,Stmt_Balance)
B22: Current rate | C22: =IF(ISBLANK(Stmt_Rate),Current_Rate,Stmt_Rate) | D22: =IF(ISBLANK(Stmt_Rate),"Your figure","From your statement") -> Your figure | E22: ƒx =IF(ISBLANK(Stmt_Rate),Current_Rate,Stmt_Rate)
B23: Years left | C23: =IF(ISBLANK(Stmt_Term),Years_Left,Stmt_Term) | D23: =IF(ISBLANK(Stmt_Term),"Your figure","From your statement") -> Your figure | E23: ƒx =IF(ISBLANK(Stmt_Term),Years_Left,Stmt_Term)
B24: Actual monthly repayment (0 = work it out) | C24: =IF(ISBLANK(Stmt_Repayment),Actual_Repayment,Stmt_Repayment) -> 0 | D24: =IF(ISBLANK(Stmt_Repayment),"Your figure","From your statement") -> Your figure | E24: ƒx =IF(ISBLANK(Stmt_Repayment),Actual_Repayment,Stmt_Repayment)
B25: Statement date check | C25: =IF(ISBLANK(Stmt_Statement_Date),"",IF(TODAY()-Stmt_Statement_Date>Statement_Max_Age_Days,"Needs a look: statement is more than 12 months old","Up to date")) | E25: ƒx =IF(ISBLANK(Stmt_Statement_Date),"",IF(TODAY()-Stmt_Statement_Date>Statement_Max_Age_Days,"Needs a look: statement is more than 12 months old","Up to date"))
B27: RESULTS | C27: Result | D27: Shown as | E27: Formula
B28: Monthly change | C28: =IF(Need_1<>"",Need_1,Repayment_After-Repayment_Now) -> Choose your rate change to see this | D28: =IF(Need_1<>"",Need_1,IF(Monthly_Change>=0,"+","−")&TEXT(ABS(Monthly_Change),"€#,##0")) -> Choose your rate change to see this | E28: ƒx =Repayment_After-Repayment_Now
B29: Repayment now | C29: =IF(Need_2<>"",Need_2,IF(Used_Actual_Repayment>0,Used_Actual_Repayment,Formula_Now)) -> Choose your mortgage balance to see this | D29: € | E29: ƒx =IF(Used_Actual_Repayment>0,Used_Actual_Repayment,Formula_Now)
B30: Repayment after the change | C30: =IF(Need_1<>"",Need_1,Repayment_Now+PMT(New_Rate/12,Used_Years_Left*12,-Used_Mortgage_Balance)-Formula_Now) -> Choose your rate change to see this | D30: € | E30: ƒx =Repayment_Now+PMT(New_Rate/12,Used_Years_Left*12,-Used_Mortgage_Balance)-Formula_Now
B31: Change over a year | C31: =IF(Need_1<>"",Need_1,Monthly_Change*12) -> Choose your rate change to see this | D31: € | E31: ƒx =Monthly_Change*12
B32: Repayment now by formula | C32: =IF(Need_3<>"",Need_3,PMT(Used_Current_Rate/12,Used_Years_Left*12,-Used_Mortgage_Balance)) -> Choose your mortgage balance to see this | D32: € | E32: ƒx =PMT(Used_Current_Rate/12,Used_Years_Left*12,-Used_Mortgage_Balance)
B33: New rate (never below 0%) | C33: =IF(Need_4<>"",Need_4,MAX(0,Used_Current_Rate+Rate_Change)) -> Choose your rate change to see this | D33: % | E33: ƒx =MAX(0,Used_Current_Rate+Rate_Change)
B35: HOW IT WORKS
B36: • Repayment = PMT(rate ÷ 12, years left × 12, −balance) at the current and the new rate.
B37: • The change is the difference between the two; a stated repayment moves by the same amount.
B38: Edge rules and validation:
B39: • The new rate is floored at 0% (Irish mortgages have not had negative rates).
B40: • At 0% interest Excel's PMT/NPER/FV give amount ÷ months, so no special case is needed in Excel; in code use payment = amount / months.
B42: ADD TO MY PLAN (what this calculator sends to the plan)
B43: Goal | C43: ="No goal" -> No goal | E43: ƒx ="No goal"
B45: CHOICES STILL NEEDED (helper rows: blank = all inputs a result needs are filled)
B46: Needs: rate change, Used_Actual_Repayment, Used_Current_Rate, Used_Mortgage_Balance, Used_Years_Left | C46: =IF(Rate_Change="","Choose your rate change to see this",IF(NOT(ISNUMBER(Used_Mortgage_Balance)),IF(Used_Mortgage_Balance="",IF(Mortgage_Balance="","Choose your mortgage balance to see this",""),Used_Mortgage_Balance),IF(NOT(ISNUMBER(Used_Years_Left)),IF(Used_Years_Left="",IF(Years_Left="","Choose your years left to see this",""),Used_Years_Left),IF(NOT(ISNUMBER(Used_Actual_Repayment)),IF(Used_Actual_Repayment="","Choose your actual monthly repayment to see this",Used_Actual_Repayment),IF(NOT(ISNUMBER(Used_Current_Rate)),IF(Used_Current_Rate="",IF(Current_Rate="","Choose your mortgage rate to see this",""),Used_Current_Rate),""))))) -> Choose your rate change to see this
B47: Needs: Used_Actual_Repayment, Used_Current_Rate, Used_Mortgage_Balance, Used_Years_Left | C47: =IF(NOT(ISNUMBER(Used_Mortgage_Balance)),IF(Used_Mortgage_Balance="",IF(Mortgage_Balance="","Choose your mortgage balance to see this",""),Used_Mortgage_Balance),IF(NOT(ISNUMBER(Used_Years_Left)),IF(Used_Years_Left="",IF(Years_Left="","Choose your years left to see this",""),Used_Years_Left),IF(NOT(ISNUMBER(Used_Actual_Repayment)),IF(Used_Actual_Repayment="","Choose your actual monthly repayment to see this",Used_Actual_Repayment),IF(NOT(ISNUMBER(Used_Current_Rate)),IF(Used_Current_Rate="",IF(Current_Rate="","Choose your mortgage rate to see this",""),Used_Current_Rate),"")))) -> Choose your mortgage balance to see this
B48: Needs: Used_Current_Rate, Used_Mortgage_Balance, Used_Years_Left | C48: =IF(NOT(ISNUMBER(Used_Mortgage_Balance)),IF(Used_Mortgage_Balance="",IF(Mortgage_Balance="","Choose your mortgage balance to see this",""),Used_Mortgage_Balance),IF(NOT(ISNUMBER(Used_Years_Left)),IF(Used_Years_Left="",IF(Years_Left="","Choose your years left to see this",""),Used_Years_Left),IF(NOT(ISNUMBER(Used_Current_Rate)),IF(Used_Current_Rate="",IF(Current_Rate="","Choose your mortgage rate to see this",""),Used_Current_Rate),""))) -> Choose your mortgage balance to see this
B49: Needs: rate change, Used_Current_Rate | C49: =IF(Rate_Change="","Choose your rate change to see this",IF(NOT(ISNUMBER(Used_Current_Rate)),IF(Used_Current_Rate="",IF(Current_Rate="","Choose your mortgage rate to see this",""),Used_Current_Rate),"")) -> Choose your rate change to see this

Sheet C06 Term comparison
B1: C06 · Mortgage term comparison | E1: Category: Home & Mortgage · prototype id: term
B2: Question it answers: Shorter or longer term: what is the trade-off? | E2: =IF(Fill_Example="Yes","Example values are ON (README): grey Example only figures fill blank inputs.","Blank template: fill the yellow inputs (or switch on example values on the README).") -> Blank template: fill the yellow inputs (or switch on example values on the README).
B3: Compares two mortgage terms: the monthly repayment and the total interest of each.
B5: FROM YOUR STATEMENT (filled automatically by the document reader)
B6: Document: Mortgage statement (annual statement of account) or offer letter. Blank = no statement uploaded, or the figure is not on it. Grey-blue cells are filled by the reader (you can type here to test).
B7: Outstanding balance | D7: € | E7: Allowed: €0 to €10,000,000 | G7: Reader field: see note
B8: Interest rate | D8: % | E8: Allowed: 0% to 15% | G8: Reader field: see note
B9: Term remaining | D9: years | E9: Allowed: 0 to 40 | G9: Reader field: see note
B10: Statement date | D10: date | E10: Allowed: a date (dd/mm/yyyy) | G10: Reader field: see note
B12: OR TYPE IT YOURSELF | C12: Your figure | D12: Unit | E12: Allowed | F12: Example only (grey; used only when "Fill example values" is Yes)
B13: Mortgage amount | D13: € | E13: Type 3 · your figure · Your own figure. In the app it is pre-filled from Your finances / statement: balance. Allowed: €50,000 to €10,000,000 · steps of €1,000 | F13: 300000 | G13: =IF(ISBLANK(C13),IF(Fill_Example="Yes",F13,""),C13)
B14: Interest rate | D14: % | E14: ="Type 2 · your figure · Your own rate (your statement shows it; typing it is fine, no upload needed). "&IF(ISNUMBER(Suggest_Mortgage_Rate),"Suggested: "&TEXT(Suggest_Mortgage_Rate,"0.00%")&" · "&Suggest_Mortgage_Rate_Label&". ","No suggestion. ")&"Enter your own figure."&" In the app it is pre-filled from Your finances / statement: rate. Enter your own figure. Allowed: 1% to 8% · steps of 0.05%" -> Type 2 · your figure · Your own rate (your statement shows it; typing it is fine, no upload needed). Suggested: 3.48% · Central Bank of Ireland: average rate on new mortgages, Jul 2026. Enter your own figure. In the app it is pre-filled from Your finances / statement: rate. Enter your own figure. Allowed: 1% to 8% · steps of 0.05% | F14: =IF(ISNUMBER(Suggest_Mortgage_Rate),Suggest_Mortgage_Rate,"") -> 0.0348 | G14: =IF(ISBLANK(C14),IF(Fill_Example="Yes",F14,""),C14)
B15: Term A | D15: years | E15: Type 3 · your figure · Your own figure. In the app it is pre-filled from Years left (25 if not given). Allowed: 5 to 35 · steps of 1 | F15: 25 | G15: =IF(AND(ISNUMBER(C15),N(C15)<5),"",IF(ISBLANK(C15),IF(Fill_Example="Yes",F15,""),C15))
B16: Term B | D16: years | E16: Type 3 · your figure · Your own figure. Allowed: 5 to 35 · steps of 1 | F16: 35 | G16: =IF(AND(ISNUMBER(C16),N(C16)<5),"",IF(ISBLANK(C16),IF(Fill_Example="Yes",F16,""),C16))
B18: FIGURE USED (statement figure if present, else your figure)
B19: Mortgage amount | C19: =IF(ISBLANK(Stmt_Balance),Loan_Amount,Stmt_Balance) | D19: =IF(ISBLANK(Stmt_Balance),"Your figure","From your statement") -> Your figure | E19: ƒx =IF(ISBLANK(Stmt_Balance),Loan_Amount,Stmt_Balance)
B20: Interest rate | C20: =IF(ISBLANK(Stmt_Rate),Interest_Rate,Stmt_Rate) | D20: =IF(ISBLANK(Stmt_Rate),"Your figure","From your statement") -> Your figure | E20: ƒx =IF(ISBLANK(Stmt_Rate),Interest_Rate,Stmt_Rate)
B21: Term A | C21: =IF(ISBLANK(Stmt_Term),Term_A,Stmt_Term) | D21: =IF(ISBLANK(Stmt_Term),"Your figure","From your statement") -> Your figure | E21: ƒx =IF(ISBLANK(Stmt_Term),Term_A,Stmt_Term)
B22: Statement date check | C22: =IF(ISBLANK(Stmt_Statement_Date),"",IF(TODAY()-Stmt_Statement_Date>Statement_Max_Age_Days,"Needs a look: statement is more than 12 months old","Up to date")) | E22: ƒx =IF(ISBLANK(Stmt_Statement_Date),"",IF(TODAY()-Stmt_Statement_Date>Statement_Max_Age_Days,"Needs a look: statement is more than 12 months old","Up to date"))
B24: RESULTS | C24: Result | D24: Shown as | E24: Formula
B25: Interest difference | C25: =IF(Need_1<>"",Need_1,ABS(Interest_B-Interest_A)) -> Choose your term B to see this | D25: =IF(Need_1<>"",Need_1,IF(Used_Term_A=Term_B,"Both terms are the same.","The "&MIN(Used_Term_A,Term_B)&"-year term costs more each month but less interest overall.")) -> Choose your term B to see this | E25: ƒx =ABS(Interest_B-Interest_A)
B26: Term A: monthly repayment | C26: =IF(Need_2<>"",Need_2,PMT(Used_Interest_Rate/12,Used_Term_A*12,-Used_Loan_Amount)) -> Choose your mortgage amount to see this | D26: € | E26: ƒx =PMT(Used_Interest_Rate/12,Used_Term_A*12,-Used_Loan_Amount)
B27: Term B: monthly repayment | C27: =IF(Need_3<>"",Need_3,PMT(Used_Interest_Rate/12,Term_B*12,-Used_Loan_Amount)) -> Choose your term B to see this | D27: € | E27: ƒx =PMT(Used_Interest_Rate/12,Term_B*12,-Used_Loan_Amount)
B28: Term A: total interest | C28: =IF(Need_2<>"",Need_2,Monthly_A*Used_Term_A*12-Used_Loan_Amount) -> Choose your mortgage amount to see this | D28: € | E28: ƒx =Monthly_A*Used_Term_A*12-Used_Loan_Amount
B29: Term B: total interest | C29: =IF(Need_3<>"",Need_3,Monthly_B*Term_B*12-Used_Loan_Amount) -> Choose your term B to see this | D29: € | E29: ƒx =Monthly_B*Term_B*12-Used_Loan_Amount
B31: HOW IT WORKS
B32: • Monthly = PMT(rate ÷ 12, term × 12, −amount) for each term.
B33: • Total interest = monthly × months − amount.
B34: Edge rules and validation:
B35: • Equal terms show "Both terms are the same."
B36: • At 0% interest Excel's PMT/NPER/FV give amount ÷ months, so no special case is needed in Excel; in code use payment = amount / months.
B38: ADD TO MY PLAN (what this calculator sends to the plan)
B39: Goal | C39: ="No goal" -> No goal | E39: ƒx ="No goal"
B41: CHOICES STILL NEEDED (helper rows: blank = all inputs a result needs are filled)
B42: Needs: term B, Used_Interest_Rate, Used_Loan_Amount, Used_Term_A | C42: =IF(Term_B="","Choose your term B to see this",IF(NOT(ISNUMBER(Used_Loan_Amount)),IF(Used_Loan_Amount="",IF(Loan_Amount="","Choose your mortgage amount to see this",""),Used_Loan_Amount),IF(NOT(ISNUMBER(Used_Term_A)),IF(Used_Term_A="",IF(Term_A="","Choose your term A to see this",""),Used_Term_A),IF(NOT(ISNUMBER(Used_Interest_Rate)),IF(Used_Interest_Rate="",IF(Interest_Rate="","Choose your mortgage rate to see this",""),Used_Interest_Rate),"")))) -> Choose your term B to see this
B43: Needs: Used_Interest_Rate, Used_Loan_Amount, Used_Term_A | C43: =IF(NOT(ISNUMBER(Used_Loan_Amount)),IF(Used_Loan_Amount="",IF(Loan_Amount="","Choose your mortgage amount to see this",""),Used_Loan_Amount),IF(NOT(ISNUMBER(Used_Term_A)),IF(Used_Term_A="",IF(Term_A="","Choose your term A to see this",""),Used_Term_A),IF(NOT(ISNUMBER(Used_Interest_Rate)),IF(Used_Interest_Rate="",IF(Interest_Rate="","Choose your mortgage rate to see this",""),Used_Interest_Rate),""))) -> Choose your mortgage amount to see this
B44: Needs: term B, Used_Interest_Rate, Used_Loan_Amount | C44: =IF(Term_B="","Choose your term B to see this",IF(NOT(ISNUMBER(Used_Loan_Amount)),IF(Used_Loan_Amount="",IF(Loan_Amount="","Choose your mortgage amount to see this",""),Used_Loan_Amount),IF(NOT(ISNUMBER(Used_Interest_Rate)),IF(Used_Interest_Rate="",IF(Interest_Rate="","Choose your mortgage rate to see this",""),Used_Interest_Rate),""))) -> Choose your term B to see this

Sheet C07 Rent vs buy
B1: C07 · Rent vs buy | E1: Category: Home & Mortgage · prototype id: rentbuy
B2: Question it answers: How do renting and buying compare over time? | E2: =IF(Fill_Example="Yes","Example values are ON (README): grey Example only figures fill blank inputs.","Blank template: fill the yellow inputs (or switch on example values on the README).") -> Blank template: fill the yellow inputs (or switch on example values on the README).
B3: Compares rent paid with the costs of buying that do not build equity (interest, upkeep, stamp duty, fees and what the deposit could have earned), and the equity you would build.
B5: INPUTS | C5: Your figure | D5: Unit | E5: Allowed | F5: Example only (grey; used only when "Fill example values" is Yes)
B6: Monthly rent | D6: € | E6: Type 3 · your figure · Your own figure. Allowed: €500 to €50,000 · steps of €50 | F6: 1800 | G6: =IF(ISBLANK(C6),IF(Fill_Example="Yes",F6,""),C6)
B7: Home price | D7: € | E7: Type 3 · your figure · Your own figure. Allowed: €100,000 to €10,000,000 · steps of €5,000 | F7: 350000 | G7: =IF(ISBLANK(C7),IF(Fill_Example="Yes",F7,""),C7)
B8: Deposit | D8: € | E8: Type 3 · your figure · Your own figure. Allowed: at least 10% of the price and no more than the price | F8: 35000 | G8: =IF(ISBLANK(C8),IF(Fill_Example="Yes",F8,""),C8)
B9: Mortgage rate | D9: % | E9: ="Type 2 · your figure · Your own rate (your statement shows it; typing it is fine, no upload needed). "&IF(ISNUMBER(Suggest_Mortgage_Rate),"Suggested: "&TEXT(Suggest_Mortgage_Rate,"0.00%")&" · "&Suggest_Mortgage_Rate_Label&". ","No suggestion. ")&"Enter your own figure."&" Allowed: 1% to 8% · steps of 0.05%" -> Type 2 · your figure · Your own rate (your statement shows it; typing it is fine, no upload needed). Suggested: 3.48% · Central Bank of Ireland: average rate on new mortgages, Jul 2026. Enter your own figure. Allowed: 1% to 8% · steps of 0.05% | F9: =IF(ISNUMBER(Suggest_Mortgage_Rate),Suggest_Mortgage_Rate,"") -> 0.0348 | G9: =IF(ISBLANK(C9),IF(Fill_Example="Yes",F9,""),C9)
B10: Mortgage term | D10: years | E10: Type 3 · your figure · Your own figure. Allowed: 5 to 35 · steps of 1 | F10: 30 | G10: =IF(AND(ISNUMBER(C10),N(C10)<5),"",IF(ISBLANK(C10),IF(Fill_Example="Yes",F10,""),C10))
B11: Years to compare | D11: years | E11: Type 3 · your figure · Your own figure. Allowed: 1 to 30 · steps of 1 | F11: 10 | G11: =IF(ISBLANK(C11),IF(Fill_Example="Yes",F11,""),C11)
B12: House prices rise a year | D12: % | E12: Type 3 · LifeMap standard · LifeMap uses 2% a year, in line with long-run inflation (house prices can fall as well as rise). Change it if you want to use your own. Allowed: 0% to 6% · steps of 0.5% | F12: =Set_houseGrow -> 0.02 | G12: =IF(ISBLANK(C12),F12,C12) -> 0.02
B13: Rent rises a year | D13: % | E13: Type 3 · LifeMap standard · LifeMap uses 3% a year (Irish rents have risen faster than prices in recent years). Change it if you want to use your own. Allowed: 0% to 8% · steps of 0.5% | F13: =Set_rentRise -> 0.03 | G13: =IF(ISBLANK(C13),F13,C13) -> 0.03
B14: Upkeep a year, % of the home's value | D14: % | E14: Type 3 · LifeMap standard · LifeMap uses 1% of the home's value a year for repairs, insurance and maintenance. Change it if you want to use your own. Allowed: 0% to 3% · steps of 0.1% | F14: =Set_upkeep -> 0.01 | G14: =IF(ISBLANK(C14),F14,C14) -> 0.01
B15: Legal and other buying fees | D15: € | E15: ="Type 2 · optional · Legal and survey fees (stamp duty is added for you). "&IF(ISNUMBER(Suggest_Buying_Fees),"Suggested: "&TEXT(Suggest_Buying_Fees,"€#,##0")&" · "&Suggest_Buying_Fees_Label&". ","No suggestion. ")&"Leave blank to count €0."&" Allowed: €0 to €10,000 · steps of €100" -> Type 2 · optional · Legal and survey fees (stamp duty is added for you). No suggestion. Leave blank to count €0. Allowed: €0 to €10,000 · steps of €100 | F15: =IF(ISNUMBER(Suggest_Buying_Fees),Suggest_Buying_Fees,"") | G15: =IF(ISBLANK(C15),IF(AND(Fill_Example="Yes",ISNUMBER(F15)),F15,0),C15) -> 0
B16: What the deposit could earn a year (after tax) | D16: % | E16: ="Type 2 · optional · What your deposit could earn after 33% DIRT if you rent instead. "&IF(ISNUMBER(Suggest_Deposit_Rate),"Suggested: "&TEXT(ROUND(Suggest_Deposit_Rate*(1-DIRT),4),"0.00%")&" after DIRT · "&Suggest_Deposit_Rate_Label&" ("&TEXT(Suggest_Deposit_Rate,"0.00%")&" before DIRT). ","No suggestion. ")&"Leave blank and we use the suggested rate (Assumed: add yours)."&" Allowed: 0% to 6% · steps of 0.5%" -> Type 2 · optional · What your deposit could earn after 33% DIRT if you rent instead. Suggested: 1.29% after DIRT · Central Bank of Ireland: average rate on new fixed-term household deposits, Jul 2026 (1.92% before DIRT). Leave blank and we use the suggested rate (Assumed: add yours). Allowed: 0% to 6% · steps of 0.5% | F16: =IF(ISNUMBER(Suggest_Deposit_Rate),ROUND(Suggest_Deposit_Rate*(1-DIRT),4),"") -> 0.0129 | G16: =IF(ISBLANK(C16),IF(ISNUMBER(F16),F16,0),C16) -> 0.0129
B17: Years until you buy (for the plan) | D17: years | E17: Type 3 · your figure · Your own figure. Allowed: 1 to 30 · steps of 1 | F17: 3 | G17: =IF(ISBLANK(C17),IF(Fill_Example="Yes",F17,""),C17)
B18: Deposit used (at least 10% of the price, at most the price) | C18: =IF(OR(Home_Price="",Deposit=""),"",MIN(MAX(Deposit,Home_Price*(1-LTV_Max)),Home_Price)) | D18: €
B19: RESULTS | C19: Result | D19: Shown as | E19: Formula
B20: Home equity after the years | C20: =IF(Need_1<>"",Need_1,Home_Value-Balance_After) -> Choose your home price to see this | D20: € | E20: ƒx =Home_Value-Balance_After
B21: Rent paid (rising each year) | C21: =IF(Need_2<>"",Need_2,IF(Rent_Growth=0,Monthly_Rent*12*Years,Monthly_Rent*12*((1+Rent_Growth)^Years-1)/Rent_Growth)) -> Choose your monthly rent to see this | D21: € | E21: ƒx =IF(Rent_Growth=0,Monthly_Rent*12*Years,Monthly_Rent*12*((1+Rent_Growth)^Years-1)/Rent_Growth)
B22: Buying costs that don't build equity | C22: =IF(Need_3<>"",Need_3,Interest_Paid+Upkeep+Stamp_Duty+Buying_Fees+Opportunity_Cost) -> Choose your home price to see this | D22: € | E22: ƒx =Interest_Paid+Upkeep+Stamp_Duty+Buying_Fees+Opportunity_Cost
B23: Home value | C23: =IF(Need_4<>"",Need_4,Home_Price*(1+House_Growth)^Years) -> Choose your home price to see this | D23: € | E23: ƒx =Home_Price*(1+House_Growth)^Years
B24: Mortgage | C24: =IF(Need_5<>"",Need_5,MAX(0,Home_Price-Deposit_Used)) -> Choose your home price to see this | D24: € | E24: ƒx =MAX(0,Home_Price-Deposit)
B25: Monthly repayment | C25: =IF(Need_6<>"",Need_6,PMT(Mortgage_Rate/12,RentBuy_Term*12,-Loan)) -> Choose your home price to see this | D25: € | E25: ƒx =PMT(Mortgage_Rate/12,RentBuy_Term*12,-Loan)
B26: Mortgage left after the years | C26: =IF(Need_7<>"",Need_7,MAX(0,-FV(Mortgage_Rate/12,MIN(Years,RentBuy_Term)*12,-Monthly_Repayment,Loan))) -> Choose your home price to see this | D26: € | E26: ƒx =MAX(0,-FV(Mortgage_Rate/12,MIN(Years,RentBuy_Term)*12,-Monthly_Repayment,Loan))
B27: Interest paid over the years | C27: =IF(Need_7<>"",Need_7,Monthly_Repayment*MIN(Years,RentBuy_Term)*12-(Loan-Balance_After)) -> Choose your home price to see this | D27: € | E27: ƒx =Monthly_Repayment*MIN(Years,RentBuy_Term)*12-(Loan-Balance_After)
B28: Upkeep (on the home's value each year) | C28: =IF(Need_8<>"",Need_8,IF(House_Growth=0,Home_Price*Upkeep_Rate*Years,Home_Price*Upkeep_Rate*((1+House_Growth)^Years-1)/House_Growth)) -> Choose your home price to see this | D28: € | E28: ƒx =IF(House_Growth=0,Home_Price*Upkeep_Rate*Years,Home_Price*Upkeep_Rate*((1+House_Growth)^Years-1)/House_Growth)
B29: Stamp duty | C29: =IF(Need_9<>"",Need_9,SD_Rate_1*MIN(Home_Price,SD_Band_1)+SD_Rate_2*MAX(0,MIN(Home_Price,SD_Band_2)-SD_Band_1)+SD_Rate_3*MAX(0,Home_Price-SD_Band_2)) -> Choose your home price to see this | D29: € | E29: ƒx =SD_Rate_1*MIN(Home_Price,SD_Band_1)+SD_Rate_2*MAX(0,MIN(Home_Price,SD_Band_2)-SD_Band_1)+SD_Rate_3*MAX(0,Home_Price-SD_Band_2)
B30: What the deposit could have earned | C30: =IF(Need_10<>"",Need_10,Deposit_Used*((1+Opp_Rate)^Years-1)) -> Choose your deposit to see this | D30: € | E30: ƒx =Deposit*((1+Opp_Rate)^Years-1)
B32: HOW IT WORKS
B33: • Mortgage = price − deposit: repayment = PMT(rate ÷ 12, term × 12, −mortgage). Balance after the years = −FV(rate ÷ 12, months, −repayment, mortgage). Interest = repayments − capital repaid.
B34: • Rent rises each year: rent paid = monthly rent × 12 × ((1 + rise)^years − 1) ÷ rise. Upkeep is a % of the home's value each year, which rises with house prices.
B35: • Buying costs that don't build equity = interest + upkeep + stamp duty + fees + what the deposit could have earned. Home value = price × (1 + growth)^years; equity = value − balance.
B36: Edge rules and validation:
B37: • The deposit must be between 10% of the price (Central Bank LTV) and the price itself; the mortgage is never negative.
B38: • Comparing for longer than the term: the balance is 0 after the term and no further interest is paid. Local Property Tax and insurance are not included.
B40: ADD TO MY PLAN (what this calculator sends to the plan)
B41: Goal | C41: ="Buy a home (deposit goal)" -> Buy a home (deposit goal) | E41: ƒx ="Buy a home (deposit goal)"
B42: Amount (today's money): deposit + stamp duty + fees | C42: =IF(Need_11<>"",Need_11,ROUND(Deposit_Used+Stamp_Duty+Buying_Fees,0)) -> Choose your home price to see this | E42: ƒx =ROUND(Deposit+Stamp_Duty+Buying_Fees,0)
B43: In (years) | C43: =IF(Need_12<>"",Need_12,Home_Goal_Years) -> Choose your years until you buy to see this | E43: ƒx =Home_Goal_Years
B45: CHOICES STILL NEEDED (helper rows: blank = all inputs a result needs are filled)
B46: Needs: deposit, home price, house price growth, mortgage rate, mortgage term, years to compare | C46: =IF(Home_Price="","Choose your home price to see this",IF(Deposit="","Choose your deposit to see this",IF(RentBuy_Term="","Choose your mortgage term to see this",IF(Years="","Choose your years to compare to see this",IF(Mortgage_Rate="","Choose your mortgage rate to see this",""))))) -> Choose your home price to see this
B47: Needs: monthly rent, rent rise, years to compare | C47: =IF(Monthly_Rent="","Choose your monthly rent to see this",IF(Years="","Choose your years to compare to see this",IF(Mortgage_Rate="","Choose your mortgage rate to see this",""))) -> Choose your monthly rent to see this
B48: Needs: buying fees, deposit, home price, house price growth, mortgage rate, deposit earnings rate, mortgage term, upkeep rate, years to compare | C48: =IF(Home_Price="","Choose your home price to see this",IF(Deposit="","Choose your deposit to see this",IF(RentBuy_Term="","Choose your mortgage term to see this",IF(Years="","Choose your years to compare to see this",IF(Buying_Fees="","Choose your buying fees to see this",IF(Opp_Rate="","Choose your deposit earnings rate to see this",IF(Mortgage_Rate="","Choose your mortgage rate to see this",""))))))) -> Choose your home price to see this
B49: Needs: home price, house price growth, years to compare | C49: =IF(Home_Price="","Choose your home price to see this",IF(Years="","Choose your years to compare to see this",IF(Mortgage_Rate="","Choose your mortgage rate to see this",""))) -> Choose your home price to see this
B50: Needs: deposit, home price | C50: =IF(Home_Price="","Choose your home price to see this",IF(Deposit="","Choose your deposit to see this",IF(Mortgage_Rate="","Choose your mortgage rate to see this",""))) -> Choose your home price to see this
B51: Needs: deposit, home price, mortgage rate, mortgage term | C51: =IF(Home_Price="","Choose your home price to see this",IF(Deposit="","Choose your deposit to see this",IF(RentBuy_Term="","Choose your mortgage term to see this",IF(Mortgage_Rate="","Choose your mortgage rate to see this","")))) -> Choose your home price to see this
B52: Needs: deposit, home price, mortgage rate, mortgage term, years to compare | C52: =IF(Home_Price="","Choose your home price to see this",IF(Deposit="","Choose your deposit to see this",IF(RentBuy_Term="","Choose your mortgage term to see this",IF(Years="","Choose your years to compare to see this",IF(Mortgage_Rate="","Choose your mortgage rate to see this",""))))) -> Choose your home price to see this
B53: Needs: home price, house price growth, upkeep rate, years to compare | C53: =IF(Home_Price="","Choose your home price to see this",IF(Years="","Choose your years to compare to see this",IF(Mortgage_Rate="","Choose your mortgage rate to see this",""))) -> Choose your home price to see this
B54: Needs: home price | C54: =IF(Home_Price="","Choose your home price to see this",IF(Mortgage_Rate="","Choose your mortgage rate to see this","")) -> Choose your home price to see this
B55: Needs: deposit, deposit earnings rate, years to compare | C55: =IF(Deposit="","Choose your deposit to see this",IF(Years="","Choose your years to compare to see this",IF(Opp_Rate="","Choose your deposit earnings rate to see this",IF(Mortgage_Rate="","Choose your mortgage rate to see this","")))) -> Choose your deposit to see this
B56: Needs: buying fees, deposit, home price | C56: =IF(Home_Price="","Choose your home price to see this",IF(Deposit="","Choose your deposit to see this",IF(Buying_Fees="","Choose your buying fees to see this",IF(Mortgage_Rate="","Choose your mortgage rate to see this","")))) -> Choose your home price to see this
B57: Needs: years until you buy | C57: =IF(Home_Goal_Years="","Choose your years until you buy to see this",IF(Mortgage_Rate="","Choose your mortgage rate to see this","")) -> Choose your years until you buy to see this
B59: Note: stamp duty is worked out on the price shown; for a new home it is charged on the price excluding VAT, and Help to Buy is not included. Home equity is before selling costs.

Sheet C08 Goal planner
B1: C08 · Goal planner | E1: Category: Savings & Goals · prototype id: goalplanner
B2: Question it answers: How much a month to reach my goal? | E2: =IF(Fill_Example="Yes","Example values are ON (README): grey Example only figures fill blank inputs.","Blank template: fill the yellow inputs (or switch on example values on the README).") -> Blank template: fill the yellow inputs (or switch on example values on the README).
B3: Works out how much to save each month to reach a goal, allowing for prices rising and growth on your savings.
B5: YOUR INFLATION CHOICE | C5: Your figure | D5: Unit | E5: Allowed | F5: Example only (grey; used only when "Fill example values" is Yes)
B6: Inflation you expect (your choice) | D6: % | E6: ="Type 3 · your choice · Generally the standard is 2% a year (ECB target); Ireland's prices are rising "&TEXT(Set_inflNow,"0.0%")&" now (CSO HICP flash, Sep 2026). Choose what you want to use. Allowed: 0% to 10% · steps of 0.25%" -> Type 3 · your choice · Generally the standard is 2% a year (ECB target); Ireland's prices are rising 3.9% now (CSO HICP flash, Sep 2026). Choose what you want to use. Allowed: 0% to 10% · steps of 0.25% | F6: 0.02 | G6: =IF(ISBLANK(C6),IF(Fill_Example="Yes",F6,""),C6)
B7: ="Everyone sees this differently. Ireland's prices are rising "&TEXT(Set_inflNow,"0.0%")&" now (CSO HICP flash, Sep 2026), mostly because of energy. Over decades, 2%–2.5% is the usual planning range (ECB target 2%). Enter 0% if you don't want to adjust for prices." -> Everyone sees this differently. Ireland's prices are rising 3.9% now (CSO HICP flash, Sep 2026), mostly because of energy. Over decades, 2%–2.5% is the usual planning range (ECB target 2%). Enter 0% if you don't want to adjust for prices.
B9: INPUTS | C9: Your figure | D9: Unit | E9: Allowed | F9: Example only (grey; used only when "Fill example values" is Yes)
B10: Goal amount (today's prices) | D10: € | E10: Type 3 · your figure · Your own figure. Allowed: €500 to €5,000,000 · steps of €500 | F10: 15000 | G10: =IF(ISBLANK(C10),IF(Fill_Example="Yes",F10,""),C10)
B11: Years until the goal | D11: years | E11: Type 3 · your figure · Your own figure. Allowed: 1 to 30 · steps of 1 | F11: 3 | G11: =IF(AND(ISNUMBER(C11),N(C11)<1),"",IF(ISBLANK(C11),IF(Fill_Example="Yes",F11,""),C11))
B12: Already saved | D12: € | E12: Type 3 · your figure · Your own figure. Allowed: €0 to €2,000,000 · steps of €500 | F12: 2000 | G12: =IF(ISBLANK(C12),IF(Fill_Example="Yes",F12,""),C12)
B13: Growth / interest a year (after tax) | D13: % | E13: Type 3 · LifeMap standard · LifeMap uses 1% a year after DIRT for cash savings (Irish fixed-term deposits about 2% before tax in mid-2026). Change it if you want to use your own. Allowed: 0% to 7% · steps of 0.5% | F13: =AS_Cash -> 0.01 | G13: =IF(ISBLANK(C13),F13,C13) -> 0.01
B15: RESULTS | C15: Result | D15: Shown as | E15: Formula
B16: Monthly amount to save | C16: =IF(Need_1<>"",Need_1,IF(Inflation_Choice="","Choose your inflation rate to see this",PMT(Monthly_Growth,Years*12,0,-Still_Needed))) -> Choose your goal amount to see this | D16: € | E16: ƒx =IF(Inflation_Choice="","Choose your inflation rate to see this",PMT(Monthly_Growth,Years*12,0,-Still_Needed))
B17: Goal will cost about (in the goal year) | C17: =IF(Need_2<>"",Need_2,IF(Inflation_Choice="","Choose your inflation rate to see this",Goal_Amount*(1+Inflation_Choice)^Years)) -> Choose your goal amount to see this | D17: € | E17: ƒx =IF(Inflation_Choice="","Choose your inflation rate to see this",Goal_Amount*(1+Inflation_Choice)^Years)
B18: Your savings grow to | C18: =IF(Need_3<>"",Need_3,Saved*(1+Growth_Rate)^Years) -> Choose your years until the goal to see this | D18: € | E18: ƒx =Saved*(1+Growth_Rate)^Years
B19: Still needed at the goal year | C19: =IF(Need_1<>"",Need_1,IF(Inflation_Choice="","Choose your inflation rate to see this",MAX(0,Future_Cost-Saved_Grows_To))) -> Choose your goal amount to see this | D19: € | E19: ƒx =IF(Inflation_Choice="","Choose your inflation rate to see this",MAX(0,Future_Cost-Saved_Grows_To))
B20: Monthly growth rate | C20: =IF(Need_4<>"",Need_4,(1+Growth_Rate)^(1/12)-1) -> 0.00082953811 | E20: ƒx =(1+Growth_Rate)^(1/12)-1
B21: ="Before tax: deposit interest is taxed at "&TEXT(DIRT,"0%")&" DIRT; investment funds and life policies pay "&TEXT(Exit_Tax,"0%")&" exit tax on gains, also charged every "&Deemed_Disposal_Years&" years (deemed disposal). Pension funds grow tax-free. No tax is taken off here." -> Before tax: deposit interest is taxed at 33% DIRT; investment funds and life policies pay 38% exit tax on gains, also charged every 8 years (deemed disposal). Pension funds grow tax-free. No tax is taken off here.
B23: HOW IT WORKS
B24: • Future cost = goal × (1 + inflation)^years. Savings already put aside grow at the growth rate.
B25: • Monthly saving = PMT(monthly growth, months, 0, −still needed): the level end-of-month saving that grows to what is still needed.
B26: • Monthly growth = (1 + yearly growth)^(1/12) − 1, the monthly rate equal to the yearly rate.
B27: Edge rules and validation:
B28: • If savings already cover the goal the monthly amount is €0.
B29: • Inflation is always applied (Assumptions). With 0% growth PMT gives still needed ÷ months.
B31: ADD TO MY PLAN (what this calculator sends to the plan)
B32: Goal | C32: ="My goal (spend goal)" -> My goal (spend goal) | E32: ƒx ="My goal (spend goal)"
B33: Amount (today's prices) | C33: =IF(Need_5<>"",Need_5,Goal_Amount) -> Choose your goal amount to see this | E33: ƒx =Goal_Amount
B34: Already saved | C34: =IF(Need_6<>"",Need_6,Saved) -> Choose your already saved to see this | E34: ƒx =Saved
B35: In (years) | C35: =IF(Need_7<>"",Need_7,Years) -> Choose your years until the goal to see this | E35: ƒx =Years
B36: Inflation for the plan (your choice) | C36: =IF(Inflation_Choice="","Choose an inflation rate first",Inflation_Choice) -> Choose an inflation rate first | E36: ƒx =IF(Inflation_Choice="","Choose an inflation rate first",Inflation_Choice)
B38: CHOICES STILL NEEDED (helper rows: blank = all inputs a result needs are filled)
B39: Needs: goal amount, growth rate, inflation rate, already saved, years until the goal | C39: =IF(Goal_Amount="","Choose your goal amount to see this",IF(Years="","Choose your years until the goal to see this",IF(Saved="","Choose your already saved to see this",IF(Inflation_Choice="","Choose your inflation rate to see this","")))) -> Choose your goal amount to see this
B40: Needs: goal amount, inflation rate, years until the goal | C40: =IF(Goal_Amount="","Choose your goal amount to see this",IF(Years="","Choose your years until the goal to see this",IF(Inflation_Choice="","Choose your inflation rate to see this",""))) -> Choose your goal amount to see this
B41: Needs: growth rate, already saved, years until the goal | C41: =IF(Years="","Choose your years until the goal to see this",IF(Saved="","Choose your already saved to see this","")) -> Choose your years until the goal to see this
B42: Needs: growth rate | C42: =""
B43: Needs: goal amount | C43: =IF(Goal_Amount="","Choose your goal amount to see this","") -> Choose your goal amount to see this
B44: Needs: already saved | C44: =IF(Saved="","Choose your already saved to see this","") -> Choose your already saved to see this
B45: Needs: years until the goal | C45: =IF(Years="","Choose your years until the goal to see this","") -> Choose your years until the goal to see this

Sheet C09 Compound growth
B1: C09 · Compound growth | E1: Category: Savings & Goals · prototype id: compound
B2: Question it answers: What could regular saving grow into? | E2: =IF(Fill_Example="Yes","Example values are ON (README): grey Example only figures fill blank inputs.","Blank template: fill the yellow inputs (or switch on example values on the README).") -> Blank template: fill the yellow inputs (or switch on example values on the README).
B3: Shows what a starting amount plus regular monthly saving could grow to, and what that is worth in today's money.
B5: YOUR INFLATION CHOICE | C5: Your figure | D5: Unit | E5: Allowed | F5: Example only (grey; used only when "Fill example values" is Yes)
B6: Inflation you expect (your choice) | D6: % | E6: ="Type 3 · your choice · Generally the standard is 2% a year (ECB target); Ireland's prices are rising "&TEXT(Set_inflNow,"0.0%")&" now (CSO HICP flash, Sep 2026). Choose what you want to use. Allowed: 0% to 10% · steps of 0.25%" -> Type 3 · your choice · Generally the standard is 2% a year (ECB target); Ireland's prices are rising 3.9% now (CSO HICP flash, Sep 2026). Choose what you want to use. Allowed: 0% to 10% · steps of 0.25% | F6: 0.02 | G6: =IF(ISBLANK(C6),IF(Fill_Example="Yes",F6,""),C6)
B7: ="Everyone sees this differently. Ireland's prices are rising "&TEXT(Set_inflNow,"0.0%")&" now (CSO HICP flash, Sep 2026), mostly because of energy. Over decades, 2%–2.5% is the usual planning range (ECB target 2%). Enter 0% if you don't want to adjust for prices." -> Everyone sees this differently. Ireland's prices are rising 3.9% now (CSO HICP flash, Sep 2026), mostly because of energy. Over decades, 2%–2.5% is the usual planning range (ECB target 2%). Enter 0% if you don't want to adjust for prices.
B9: INPUTS | C9: Your figure | D9: Unit | E9: Allowed | F9: Example only (grey; used only when "Fill example values" is Yes)
B10: Starting amount | D10: € | E10: Type 3 · your figure · Your own figure. Allowed: €0 to €2,000,000 · steps of €500 | F10: 5000 | G10: =IF(ISBLANK(C10),IF(Fill_Example="Yes",F10,""),C10)
B11: Monthly addition | D11: € | E11: Type 3 · your figure · Your own figure. Allowed: €0 to €30,000 · steps of €25 | F11: 200 | G11: =IF(ISBLANK(C11),IF(Fill_Example="Yes",F11,""),C11)
B12: Growth rate a year | D12: % | E12: Type 3 · LifeMap standard · LifeMap uses 5% a year before charges and tax for a mixed fund (LifeMap standard, not a forecast). Change it if you want to use your own. Allowed: 0% to 8% · steps of 0.5% | F12: =Set_invGross -> 0.05 | G12: =IF(ISBLANK(C12),F12,C12) -> 0.05
B13: Years | D13: years | E13: Type 3 · your figure · Your own figure. Allowed: 1 to 40 · steps of 1 | F13: 20 | G13: =IF(ISBLANK(C13),IF(Fill_Example="Yes",F13,""),C13)
B15: RESULTS | C15: Result | D15: Shown as | E15: Formula
B16: Could grow to | C16: =IF(Need_1<>"",Need_1,FV(Monthly_Growth,Years*12,-Monthly_Addition,-Starting_Amount)) -> Choose your starting amount to see this | D16: € | E16: ƒx =FV(Monthly_Growth,Years*12,-Monthly_Addition,-Starting_Amount)
B17: Worth in today's money | C17: =IF(Need_2<>"",Need_2,IF(Inflation_Choice="","Choose your inflation rate to see this",Grows_To/(1+Inflation_Choice)^Years)) -> Choose your starting amount to see this | D17: € | E17: ƒx =IF(Inflation_Choice="","Choose your inflation rate to see this",Grows_To/(1+Inflation_Choice)^Years)
B18: Paid in | C18: =IF(Need_3<>"",Need_3,Starting_Amount+Monthly_Addition*12*Years) -> Choose your starting amount to see this | D18: € | E18: ƒx =Starting_Amount+Monthly_Addition*12*Years
B19: Illustrative growth | C19: =IF(Need_1<>"",Need_1,Grows_To-Paid_In) -> Choose your starting amount to see this | D19: € | E19: ƒx =Grows_To-Paid_In
B20: Monthly growth rate | C20: =IF(Need_4<>"",Need_4,(1+Growth_Rate)^(1/12)-1) -> 0.0040741238 | E20: ƒx =(1+Growth_Rate)^(1/12)-1
B21: ="Before tax: deposit interest is taxed at "&TEXT(DIRT,"0%")&" DIRT; investment funds and life policies pay "&TEXT(Exit_Tax,"0%")&" exit tax on gains, also charged every "&Deemed_Disposal_Years&" years (deemed disposal). Pension funds grow tax-free. No tax is taken off here." -> Before tax: deposit interest is taxed at 33% DIRT; investment funds and life policies pay 38% exit tax on gains, also charged every 8 years (deemed disposal). Pension funds grow tax-free. No tax is taken off here.
B23: HOW IT WORKS
B24: • Value = FV(monthly growth, months, −monthly addition, −starting amount): the starting amount compounds and each addition is made at the end of the month.
B25: • Today's money = value ÷ (1 + inflation)^years.
B26: Edge rules and validation:
B27: • 0% growth gives starting amount + additions.
B28: • Results are before tax and are not guaranteed.
B30: ADD TO MY PLAN (what this calculator sends to the plan)
B31: Goal | C31: ="Grow my wealth (plan kind pot)" -> Grow my wealth (plan kind pot) | E31: ƒx ="Grow my wealth (plan kind pot)"
B32: Amount (today's money) | C32: =IF(Need_1<>"",Need_1,IF(Inflation_Choice="","Choose an inflation rate first",ROUND(Value_Today,0))) -> Choose your starting amount to see this | E32: ƒx =IF(Inflation_Choice="","Choose an inflation rate first",ROUND(Value_Today,0))
B33: In (years) | C33: =IF(Need_5<>"",Need_5,Years) -> Choose your years to see this | E33: ƒx =Years
B34: Inflation for the plan (your choice) | C34: =IF(Inflation_Choice="","Choose an inflation rate first",Inflation_Choice) -> Choose an inflation rate first | E34: ƒx =IF(Inflation_Choice="","Choose an inflation rate first",Inflation_Choice)
B35: Audit fix: the amount is always in today's money (the plan adds inflation itself).
B37: CHOICES STILL NEEDED (helper rows: blank = all inputs a result needs are filled)
B38: Needs: growth rate, monthly addition, starting amount, years | C38: =IF(Starting_Amount="","Choose your starting amount to see this",IF(Monthly_Addition="","Choose your monthly addition to see this",IF(Years="","Choose your years to see this",""))) -> Choose your starting amount to see this
B39: Needs: growth rate, inflation rate, monthly addition, starting amount, years | C39: =IF(Starting_Amount="","Choose your starting amount to see this",IF(Monthly_Addition="","Choose your monthly addition to see this",IF(Years="","Choose your years to see this",IF(Inflation_Choice="","Choose your inflation rate to see this","")))) -> Choose your starting amount to see this
B40: Needs: monthly addition, starting amount, years | C40: =IF(Starting_Amount="","Choose your starting amount to see this",IF(Monthly_Addition="","Choose your monthly addition to see this",IF(Years="","Choose your years to see this",""))) -> Choose your starting amount to see this
B41: Needs: growth rate | C41: =""
B42: Needs: years | C42: =IF(Years="","Choose your years to see this","") -> Choose your years to see this

Sheet C10 Lump sum growth
B1: C10 · Lump-sum growth | E1: Category: Investments · prototype id: lumpsum
B2: Question it answers: What could a one-off amount become? | E2: =IF(Fill_Example="Yes","Example values are ON (README): grey Example only figures fill blank inputs.","Blank template: fill the yellow inputs (or switch on example values on the README).") -> Blank template: fill the yellow inputs (or switch on example values on the README).
B3: Shows what a one-off amount could become after fees, the cost of waiting 5 years, and the value in today's money.
B5: YOUR INFLATION CHOICE | C5: Your figure | D5: Unit | E5: Allowed | F5: Example only (grey; used only when "Fill example values" is Yes)
B6: Inflation you expect (your choice) | D6: % | E6: ="Type 3 · your choice · Generally the standard is 2% a year (ECB target); Ireland's prices are rising "&TEXT(Set_inflNow,"0.0%")&" now (CSO HICP flash, Sep 2026). Choose what you want to use. Allowed: 0% to 10% · steps of 0.25%" -> Type 3 · your choice · Generally the standard is 2% a year (ECB target); Ireland's prices are rising 3.9% now (CSO HICP flash, Sep 2026). Choose what you want to use. Allowed: 0% to 10% · steps of 0.25% | F6: 0.02 | G6: =IF(ISBLANK(C6),IF(Fill_Example="Yes",F6,""),C6)
B7: ="Everyone sees this differently. Ireland's prices are rising "&TEXT(Set_inflNow,"0.0%")&" now (CSO HICP flash, Sep 2026), mostly because of energy. Over decades, 2%–2.5% is the usual planning range (ECB target 2%). Enter 0% if you don't want to adjust for prices." -> Everyone sees this differently. Ireland's prices are rising 3.9% now (CSO HICP flash, Sep 2026), mostly because of energy. Over decades, 2%–2.5% is the usual planning range (ECB target 2%). Enter 0% if you don't want to adjust for prices.
B9: FROM YOUR STATEMENT (filled automatically by the document reader)
B10: Document: Investment / fund statement. Blank = no statement uploaded, or the figure is not on it. Grey-blue cells are filled by the reader (you can type here to test).
B11: Total value | D11: € | E11: Allowed: €0 to €100,000,000 | G11: Reader field: see note
B12: Annual charges % (if shown) | D12: % | E12: Allowed: 0% to 5% | G12: Reader field: see note
B13: Statement date | D13: date | E13: Allowed: a date (dd/mm/yyyy) | G13: Reader field: see note
B15: OR TYPE IT YOURSELF | C15: Your figure | D15: Unit | E15: Allowed | F15: Example only (grey; used only when "Fill example values" is Yes)
B16: Amount | D16: € | E16: Type 3 · your figure · Your own figure. In the app it is pre-filled from Your finances / statement: investments. Allowed: €500 to €5,000,000 · steps of €100 | F16: 10000 | G16: =IF(ISBLANK(C16),IF(Fill_Example="Yes",F16,""),C16)
B17: Growth rate a year (before fees) | D17: % | E17: Type 3 · LifeMap standard · LifeMap uses 5% a year before charges and tax for a mixed fund (LifeMap standard, not a forecast). Change it if you want to use your own. Allowed: 0% to 8% · steps of 0.5% | F17: =Set_invGross -> 0.05 | G17: =IF(ISBLANK(C17),F17,C17) -> 0.05
B18: Years | D18: years | E18: Type 3 · your figure · Your own figure. Allowed: 1 to 40 · steps of 1 | F18: 15 | G18: =IF(ISBLANK(C18),IF(Fill_Example="Yes",F18,""),C18)
B19: Yearly fees | D19: % | E19: ="Type 2 · your figure · Fund charges a year (your statement shows yours). "&IF(ISNUMBER(Suggest_Fund_Charges),"Suggested: "&TEXT(Suggest_Fund_Charges,"0.00%")&" · "&Suggest_Fund_Charges_Label&". ","No suggestion. ")&"Enter your own figure."&" Allowed: 0% to 3% · steps of 0.05%" -> Type 2 · your figure · Fund charges a year (your statement shows yours). Suggested: 1.00% · Pensions Authority pension calculator assumption. Enter your own figure. Allowed: 0% to 3% · steps of 0.05% | F19: =IF(ISNUMBER(Suggest_Fund_Charges),Suggest_Fund_Charges,"") -> 0.01 | G19: =IF(ISBLANK(C19),IF(Fill_Example="Yes",F19,""),C19)
B20: Years you might wait before investing | D20: years | E20: Type 3 · LifeMap standard · LifeMap uses 5 years (an illustration of the cost of waiting). Change it if you want to use your own. Allowed: 1 to 20 · steps of 1 | F20: =Set_waitYears -> 5 | G20: =IF(ISBLANK(C20),F20,C20) -> 5
B21: Show in today's money? | D21: Yes / No | E21: Type 3 · optional · Optional: leave blank for none. Allowed: Yes or No | F21: No | G21: =IF(ISBLANK(C21),F21,C21) -> No
B23: FIGURE USED (statement figure if present, else your figure)
B24: Statement uploaded? | C24: =IF(COUNTA(Stmt_Total_Value,Stmt_Charges,Stmt_Statement_Date)>0,"Yes","No") -> No | E24: ƒx =IF(COUNTA(Stmt_Total_Value,Stmt_Charges,Stmt_Statement_Date)>0,"Yes","No")
B25: Amount | C25: =IF(ISBLANK(Stmt_Total_Value),Amount,Stmt_Total_Value) | D25: =IF(ISBLANK(Stmt_Total_Value),"Your figure","From your statement") -> Your figure | E25: ƒx =IF(ISBLANK(Stmt_Total_Value),Amount,Stmt_Total_Value)
B26: Yearly fees | C26: =IF(NOT(ISBLANK(Stmt_Charges)),Stmt_Charges,IF(Statement_Uploaded="Yes",0,Yearly_Fees)) | D26: =IF(NOT(ISBLANK(Stmt_Charges)),"From your statement",IF(Statement_Uploaded="Yes","None shown on your statement","Your figure")) -> Your figure | E26: ƒx =IF(NOT(ISBLANK(Stmt_Charges)),Stmt_Charges,IF(Statement_Uploaded="Yes",0,Yearly_Fees))
B27: Statement date check | C27: =IF(ISBLANK(Stmt_Statement_Date),"",IF(TODAY()-Stmt_Statement_Date>Statement_Max_Age_Days,"Needs a look: statement is more than 12 months old","Up to date")) | E27: ƒx =IF(ISBLANK(Stmt_Statement_Date),"",IF(TODAY()-Stmt_Statement_Date>Statement_Max_Age_Days,"Needs a look: statement is more than 12 months old","Up to date"))
B29: RESULTS | C29: Result | D29: Shown as | E29: Formula
B30: Could grow to (today's money if you chose Yes) | C30: =IF(Need_1<>"",Need_1,IF(Adjust_For_Inflation="Yes",Value_Today,Grows_To)) -> Choose your years to see this | D30: € | E30: ƒx =IF(Adjust_For_Inflation="Yes",Value_Today,Grows_To)
B31: If you start today (after fees) | C31: =IF(Need_1<>"",Need_1,Used_Amount*(1+Growth_After_Fees)^Years) -> Choose your years to see this | D31: € | E31: ƒx =Used_Amount*(1+Growth_After_Fees)^Years
B32: Worth in today's money | C32: =IF(Need_2<>"",Need_2,IF(Inflation_Choice="","Choose your inflation rate to see this",Grows_To/(1+Inflation_Choice)^Years)) -> Choose your years to see this | D32: € | E32: ƒx =IF(Inflation_Choice="","Choose your inflation rate to see this",Grows_To/(1+Inflation_Choice)^Years)
B33: If you start after waiting | C33: =IF(Need_3<>"",Need_3,Used_Amount*(1+Growth_After_Fees)^MAX(0,Years-Wait_Years)) -> Choose your years to see this | D33: € | E33: ƒx =Used_Amount*(1+Growth_After_Fees)^MAX(0,Years-Wait_Years)
B34: Cost of waiting | C34: =IF(Need_3<>"",Need_3,IF(Adjust_For_Inflation="Yes",IF(Inflation_Choice="","Choose your inflation rate to see this",(Grows_To-Value_Start_Later)/(1+Inflation_Choice)^Years),Grows_To-Value_Start_Later)) -> Choose your years to see this | D34: € | E34: ƒx =IF(Adjust_For_Inflation="Yes",IF(Inflation_Choice="","Choose your inflation rate to see this",(Grows_To-Value_Start_Later)/(1+Inflation_Choice)^Years),Grows_To-Value_Start_Later)
B35: Fees cost | C35: =IF(Need_1<>"",Need_1,Used_Amount*(1+Growth_Rate)^Years-Grows_To) -> Choose your years to see this | D35: € | E35: ƒx =Used_Amount*(1+Growth_Rate)^Years-Grows_To
B36: Growth after fees a year | C36: =IF(Need_4<>"",Need_4,(1+Growth_Rate)*(1-Used_Yearly_Fees)-1) -> Choose your yearly fees to see this | E36: ƒx =(1+Growth_Rate)*(1-Used_Yearly_Fees)-1
B37: Real return a year (after fees and inflation) | C37: =IF(Need_5<>"",Need_5,IF(Inflation_Choice="","Choose your inflation rate to see this",(1+Growth_After_Fees)/(1+Inflation_Choice)-1)) -> Choose your yearly fees to see this | E37: ƒx =IF(Inflation_Choice="","Choose your inflation rate to see this",(1+Growth_After_Fees)/(1+Inflation_Choice)-1)
B38: ="Before tax: deposit interest is taxed at "&TEXT(DIRT,"0%")&" DIRT; investment funds and life policies pay "&TEXT(Exit_Tax,"0%")&" exit tax on gains, also charged every "&Deemed_Disposal_Years&" years (deemed disposal). Pension funds grow tax-free. No tax is taken off here." -> Before tax: deposit interest is taxed at 33% DIRT; investment funds and life policies pay 38% exit tax on gains, also charged every 8 years (deemed disposal). Pension funds grow tax-free. No tax is taken off here.
B40: HOW IT WORKS
B41: • Growth after fees = (1 + growth) × (1 − fees) − 1 (fees taken from the fund each year).
B42: • Value = amount × (1 + growth after fees)^years. Starting in 5 years means 5 fewer years of growth to the same end date.
B43: • Today's money = value ÷ (1 + inflation)^years; real return = (1 + growth after fees) ÷ (1 + inflation) − 1 (exact, not growth − inflation).
B44: Edge rules and validation:
B45: • With 5 years or fewer, "start in 5 years" equals the amount itself.
B46: • Results are before tax.
B48: ADD TO MY PLAN (what this calculator sends to the plan)
B49: Goal | C49: ="Grow my wealth (plan kind pot)" -> Grow my wealth (plan kind pot) | E49: ƒx ="Grow my wealth (plan kind pot)"
B50: Amount (today's money) | C50: =IF(Need_1<>"",Need_1,IF(Inflation_Choice="","Choose an inflation rate first",ROUND(Value_Today,0))) -> Choose your years to see this | E50: ƒx =IF(Inflation_Choice="","Choose an inflation rate first",ROUND(Value_Today,0))
B51: In (years) | C51: =IF(Need_6<>"",Need_6,Years) -> Choose your years to see this | E51: ƒx =Years
B52: Inflation for the plan (your choice) | C52: =IF(Inflation_Choice="","Choose an inflation rate first",Inflation_Choice) -> Choose an inflation rate first | E52: ƒx =IF(Inflation_Choice="","Choose an inflation rate first",Inflation_Choice)
B53: Always in today's money, whatever the 'Show in today's money' choice.
B55: CHOICES STILL NEEDED (helper rows: blank = all inputs a result needs are filled)
B56: Needs: growth rate, Used_Amount, Used_Yearly_Fees, years | C56: =IF(Years="","Choose your years to see this",IF(NOT(ISNUMBER(Used_Amount)),IF(Used_Amount="",IF(Amount="","Choose your amount to see this",""),Used_Amount),IF(NOT(ISNUMBER(Used_Yearly_Fees)),IF(Used_Yearly_Fees="",IF(Yearly_Fees="","Choose your yearly fees to see this",""),Used_Yearly_Fees),""))) -> Choose your years to see this
B57: Needs: growth rate, inflation rate, Used_Amount, Used_Yearly_Fees, years | C57: =IF(Years="","Choose your years to see this",IF(NOT(ISNUMBER(Used_Amount)),IF(Used_Amount="",IF(Amount="","Choose your amount to see this",""),Used_Amount),IF(NOT(ISNUMBER(Used_Yearly_Fees)),IF(Used_Yearly_Fees="",IF(Yearly_Fees="","Choose your yearly fees to see this",""),Used_Yearly_Fees),IF(Inflation_Choice="","Choose your inflation rate to see this","")))) -> Choose your years to see this
B58: Needs: growth rate, Used_Amount, Used_Yearly_Fees, years of waiting, years | C58: =IF(Years="","Choose your years to see this",IF(NOT(ISNUMBER(Used_Amount)),IF(Used_Amount="",IF(Amount="","Choose your amount to see this",""),Used_Amount),IF(NOT(ISNUMBER(Used_Yearly_Fees)),IF(Used_Yearly_Fees="",IF(Yearly_Fees="","Choose your yearly fees to see this",""),Used_Yearly_Fees),""))) -> Choose your years to see this
B59: Needs: growth rate, Used_Yearly_Fees | C59: =IF(NOT(ISNUMBER(Used_Yearly_Fees)),IF(Used_Yearly_Fees="",IF(Yearly_Fees="","Choose your yearly fees to see this",""),Used_Yearly_Fees),"") -> Choose your yearly fees to see this
B60: Needs: growth rate, inflation rate, Used_Yearly_Fees | C60: =IF(NOT(ISNUMBER(Used_Yearly_Fees)),IF(Used_Yearly_Fees="",IF(Yearly_Fees="","Choose your yearly fees to see this",""),Used_Yearly_Fees),IF(Inflation_Choice="","Choose your inflation rate to see this","")) -> Choose your yearly fees to see this
B61: Needs: years | C61: =IF(Years="","Choose your years to see this",IF(NOT(ISNUMBER(Used_Yearly_Fees)),IF(Used_Yearly_Fees="",IF(Yearly_Fees="","Choose your yearly fees to see this",""),Used_Yearly_Fees),"")) -> Choose your years to see this
B63: Note: the money is assumed to earn nothing while it waits. If growth after fees is zero or negative there is no cost of waiting to show.

Sheet C11 Emergency fund
B1: C11 · Emergency fund | E1: Category: Savings & Goals · prototype id: emergency
B2: Question it answers: How strong is my emergency fund? | E2: =IF(Fill_Example="Yes","Example values are ON (README): grey Example only figures fill blank inputs.","Blank template: fill the yellow inputs (or switch on example values on the README).") -> Blank template: fill the yellow inputs (or switch on example values on the README).
B3: Shows how many months of essential spending your easy-access savings cover, against your target.
B5: INPUTS | C5: Your figure | D5: Unit | E5: Allowed | F5: Example only (grey; used only when "Fill example values" is Yes)
B6: Essential monthly spending | D6: € | E6: Type 3 · your figure · Your own figure. In the app it is pre-filled from Your finances: costs + mortgage + debt repayments. Allowed: €500 to €100,000 · steps of €100 | F6: 2500 | G6: =IF(AND(ISNUMBER(C6),N(C6)<500),"",IF(ISBLANK(C6),IF(Fill_Example="Yes",F6,""),C6))
B7: Emergency fund: months of essential spending | D7: months | E7: Type 3 · LifeMap standard · LifeMap uses 6 months of essential spending (3 if you have two secure incomes). Change it if you want to use your own. Allowed: 1 to 12 · steps of 1 | F7: =AS_Months -> 6 | G7: =IF(ISBLANK(C7),F7,C7) -> 6
B8: Build the emergency fund within (years, for the plan) | D8: years | E8: Type 3 · your figure · Your own figure. Allowed: 1 to 10 · steps of 1 | F8: 2 | G8: =IF(ISBLANK(C8),IF(Fill_Example="Yes",F8,""),C8)
B9: Easy-access savings | D9: € | E9: Type 3 · your figure · Your own figure. In the app it is pre-filled from Your finances: cash. Allowed: €0 to €1,000,000 · steps of €250 | F9: 6250 | G9: =IF(ISBLANK(C9),IF(Fill_Example="Yes",F9,""),C9)
B11: RESULTS | C11: Result | D11: Shown as | E11: Formula
B12: You currently have (months) | C12: =IF(Need_1<>"",Need_1,Savings/Essential_Spending) -> Choose your essential monthly spending to see this | D12: =IF(Need_1<>"",Need_1,IF(ROUND(Months_Covered,1)=1,"1 month",FIXED(Months_Covered,1)&" months")) -> Choose your essential monthly spending to see this | E12: ƒx =Savings/Essential_Spending
B13: Target emergency fund | C13: =IF(Need_2<>"",Need_2,Essential_Spending*Months_Wanted) -> Choose your essential monthly spending to see this | D13: € | E13: ƒx =Essential_Spending*Months_Wanted
B14: Still to build | C14: =IF(Need_3<>"",Need_3,MAX(0,Target-Savings)) -> Choose your essential monthly spending to see this | D14: € | E14: ƒx =MAX(0,Target-Savings)
B16: HOW IT WORKS
B17: • Months covered = savings ÷ essential monthly spending. Target = spending × months wanted. Still to build = target − savings (never below 0).
B18: Edge rules and validation:
B19: • Spending must be at least €500, so there is no divide by zero.
B21: ADD TO MY PLAN (what this calculator sends to the plan)
B22: Goal | C22: =IF(Need_3<>"",Need_3,IF(Still_To_Build>0,"Emergency fund (plan kind safety: a reserve, not a spend)","No goal (emergency fund already in place)")) -> Choose your essential monthly spending to see this | E22: ƒx =IF(Still_To_Build>0,"Emergency fund (plan kind safety: a reserve, not a spend)","No goal (emergency fund already in place)")
B23: Amount (today's money) | C23: =IF(Need_3<>"",Need_3,IF(Still_To_Build>0,ROUND(Target,0),"—")) -> Choose your essential monthly spending to see this | E23: ƒx =IF(Still_To_Build>0,ROUND(Target,0),"—")
B24: Already saved | C24: =IF(Need_4<>"",Need_4,Savings) -> Choose your easy-access savings to see this | E24: ƒx =Savings
B25: In (years) | C25: =IF(Need_5<>"",Need_5,Safety_Goal_Years) -> Choose your years to build the emergency fund to see this | E25: ƒx =Safety_Goal_Years
B27: CHOICES STILL NEEDED (helper rows: blank = all inputs a result needs are filled)
B28: Needs: essential monthly spending, easy-access savings | C28: =IF(Essential_Spending="","Choose your essential monthly spending to see this",IF(Savings="","Choose your easy-access savings to see this","")) -> Choose your essential monthly spending to see this
B29: Needs: essential monthly spending, emergency months | C29: =IF(Essential_Spending="","Choose your essential monthly spending to see this","") -> Choose your essential monthly spending to see this
B30: Needs: essential monthly spending, emergency months, easy-access savings | C30: =IF(Essential_Spending="","Choose your essential monthly spending to see this",IF(Savings="","Choose your easy-access savings to see this","")) -> Choose your essential monthly spending to see this
B31: Needs: easy-access savings | C31: =IF(Savings="","Choose your easy-access savings to see this","") -> Choose your easy-access savings to see this
B32: Needs: years to build the emergency fund | C32: =IF(Safety_Goal_Years="","Choose your years to build the emergency fund to see this","") -> Choose your years to build the emergency fund to see this

Sheet C12 Retirement projection
B1: C12 · Retirement projection | E1: Category: Pensions & Retirement · prototype id: retirement
B2: Question it answers: Could your current path fund the retirement you want? | E2: =IF(Fill_Example="Yes","Example values are ON (README): grey Example only figures fill blank inputs.","Blank template: fill the yellow inputs (or switch on example values on the README).") -> Blank template: fill the yellow inputs (or switch on example values on the README).
B3: Projects your pension fund at retirement and compares it, in today's money, with the fund you would need for the income you want.
B5: YOUR INFLATION CHOICE | C5: Your figure | D5: Unit | E5: Allowed | F5: Example only (grey; used only when "Fill example values" is Yes)
B6: Inflation you expect (your choice) | D6: % | E6: ="Type 3 · your choice · Generally the standard is 2% a year (ECB target); Ireland's prices are rising "&TEXT(Set_inflNow,"0.0%")&" now (CSO HICP flash, Sep 2026). Choose what you want to use. Allowed: 0% to 10% · steps of 0.25%" -> Type 3 · your choice · Generally the standard is 2% a year (ECB target); Ireland's prices are rising 3.9% now (CSO HICP flash, Sep 2026). Choose what you want to use. Allowed: 0% to 10% · steps of 0.25% | F6: 0.02 | G6: =IF(ISBLANK(C6),IF(Fill_Example="Yes",F6,""),C6)
B7: ="Everyone sees this differently. Ireland's prices are rising "&TEXT(Set_inflNow,"0.0%")&" now (CSO HICP flash, Sep 2026), mostly because of energy. Over decades, 2%–2.5% is the usual planning range (ECB target 2%). Enter 0% if you don't want to adjust for prices." -> Everyone sees this differently. Ireland's prices are rising 3.9% now (CSO HICP flash, Sep 2026), mostly because of energy. Over decades, 2%–2.5% is the usual planning range (ECB target 2%). Enter 0% if you don't want to adjust for prices.
B9: FROM YOUR STATEMENT (filled automatically by the document reader)
B10: Document: Pension benefit statement / Statement of Reasonable Projection / PRSA statement. Blank = no statement uploaded, or the figure is not on it. Grey-blue cells are filled by the reader (you can type here to test).
B11: Fund value today | D11: € | E11: Allowed: €0 to €50,000,000 | G11: Reader field: see note
B12: Your monthly contribution | D12: € | E12: Allowed: €0 to €100,000 | G12: Reader field: see note
B13: Employer monthly contribution | D13: € | E13: Allowed: €0 to €100,000 | G13: Reader field: see note
B14: Normal retirement age | D14: age | E14: Allowed: 50 to 75 | G14: Reader field: see note
B15: Projected fund at retirement (if shown) | D15: € | E15: Allowed: €0 to €100,000,000 | G15: Reader field: see note
B16: Projection is in today's money? (if shown) | D16: Yes / No | E16: Allowed: Yes or No | G16: Reader field: see note
B17: Annual charges % (if shown) | D17: % | E17: Allowed: 0% to 5% | G17: Reader field: see note
B18: Statement date | D18: date | E18: Allowed: a date (dd/mm/yyyy) | G18: Reader field: see note
B20: OR TYPE IT YOURSELF | C20: Your figure | D20: Unit | E20: Allowed | F20: Example only (grey; used only when "Fill example values" is Yes)
B21: Your age | D21: age | E21: Type 3 · your figure · Your own figure. In the app it is pre-filled from About you: age. Allowed: 20 to 70 · steps of 1 | F21: 40 | G21: =IF(ISBLANK(C21),IF(Fill_Example="Yes",F21,""),C21)
B22: Target retirement age | D22: age | E22: Type 3 · your choice (no standard) · You can usually draw a pension from 60 (some occupational schemes from 50); State Pension is paid from 66. Choose your own: there is no default. Allowed: 21 to 104 · steps of 1 | F22: 65 | G22: =IF(ISBLANK(C22),IF(Fill_Example="Yes",F22,""),C22)
B23: Pension value today | D23: € | E23: Type 3 · your figure · Your own figure. In the app it is pre-filled from Your finances / pension statement. Allowed: €0 to €15,000,000 · steps of €1,000 | F23: 60000 | G23: =IF(ISBLANK(C23),IF(Pens_Value_Total>0,Pens_Value_Total,IF(Fill_Example="Yes",F23,"")),C23)
B24: Monthly contributions (you + employer) | D24: € | E24: Type 3 · your figure · Your own figure. In the app it is pre-filled from Your finances / pension statement. Allowed: €0 to €50,000 · steps of €10 | F24: 500 | G24: =IF(ISBLANK(C24),IF(Pens_Monthly_Total>0,Pens_Monthly_Total,IF(Fill_Example="Yes",F24,"")),C24)
B25: Desired yearly income in retirement (today's money) | D25: € | E25: Type 3 · your figure · Your own figure. In the app it is pre-filled from Plan: retirement goal income. Allowed: €10,000 to €1,500,000 · steps of €1,000 | F25: 40000 | G25: =IF(ISBLANK(C25),IF(Fill_Example="Yes",F25,""),C25)
B26: Other yearly income from 66, e.g. State Pension (today's money) | D26: € | E26: ="Type 2 · range · Usually between €0 and €15,564 a year: the full State Pension is "&"€"&TEXT(State_Pension_Week,"0.00")&" a week (DSP 2026), partial rates are lower and depend on your PRSI record. In the app it is pre-filled from State Pension €15,563.60 × your entitlement (full 1, partly 0.6, not sure 0.8). Enter your own figure. Allowed: €0 to €500,000 · st"&"eps of €500" -> Type 2 · range · Usually between €0 and €15,564 a year: the full State Pension is €299.30 a week (DSP 2026), partial rates are lower and depend on your PRSI record. In the app it is pre-filled from State Pension €15,563.60 × your entitlement (full 1, partly 0.6, not sure 0.8). Enter your own figure. Allowed: €0 to €500,000 · steps of €500 | F26: =ROUND(State_Pension_Year,0) -> 15564 | G26: =IF(ISBLANK(C26),IF(Fill_Example="Yes",F26,""),C26)
B27: Pension growth after charges a year | D27: % | E27: Type 3 · LifeMap standard · LifeMap uses 4.5% a year after charges while you work (LifeMap Standard set; Cautious 4%). Change it if you want to use your own. Allowed: 1% to 7% · steps of 0.25% | F27: =AS_Pen -> 0.045 | G27: =IF(ISBLANK(C27),F27,C27) -> 0.045
B28: Pay rises a year (contributions rise with pay) | D28: % | E28: Type 3 · LifeMap standard · LifeMap uses 3% a year (Irish pay has grown about 3%–4% a year recently; LifeMap Standard set). Change it if you want to use your own. Allowed: 0% to 6% · steps of 0.25% | F28: =AS_Wage -> 0.03 | G28: =IF(ISBLANK(C28),F28,C28) -> 0.03
B29: Retirement savings target: × the yearly income you need | E29: Type 3 · LifeMap standard · LifeMap uses 25 times the yearly income you need (about 4% a year). Change it if you want to use your own. Allowed: 20 to 33 · steps of 1 | F29: =Set_retireMult -> 25 | G29: =IF(ISBLANK(C29),F29,C29) -> 25
B30: Typical pension charges (if your statement doesn't say) | D30: % | E30: ="Type 2 · your figure · Typical pension charges a year (your statement shows yours). "&IF(ISNUMBER(Suggest_Fund_Charges),"Suggested: "&TEXT(Suggest_Fund_Charges,"0.00%")&" · "&Suggest_Fund_Charges_Label&". ","No suggestion. ")&"Enter your own figure."&" Allowed: 0% to 2.5% · steps of 0.05%" -> Type 2 · your figure · Typical pension charges a year (your statement shows yours). Suggested: 1.00% · Pensions Authority pension calculator assumption. Enter your own figure. Allowed: 0% to 2.5% · steps of 0.05% | F30: =IF(ISNUMBER(Suggest_Fund_Charges),Suggest_Fund_Charges,"") -> 0.01 | G30: =IF(ISBLANK(C30),IF(Fill_Example="Yes",F30,""),C30)
B31: Tax-free lump sum you plan to take (% of the fund) | D31: % | E31: ="Type 3 · LifeMap standard · LifeMap uses 25% of the fund, the most allowed (first "&"€"&TEXT(Lump_Sum_Tax_Free,"#,##0")&" tax-free, next €"&TEXT(Lump_Sum_Cap-Lump_Sum_Tax_Free,"#,##0")&" at "&TEXT(Lump_Sum_Rate,"0%")&"). Change it if you want to use your own. Allowed: 0% to 25% · steps of 1%" -> Type 3 · LifeMap standard · LifeMap uses 25% of the fund, the most allowed (first €200,000 tax-free, next €300,000 at 20%). Change it if you want to use your own. Allowed: 0% to 25% · steps of 1% | F31: =AS_LumpPct -> 0.25 | G31: =IF(ISBLANK(C31),F31,C31) -> 0.25
B32: What if: retire later by | D32: years | E32: Type 3 · optional · Optional: leave blank for none. Allowed: 0 to 5 · steps of 1 | F32: 0 | G32: =IF(ISBLANK(C32),F32,C32) -> 0
B33: What if: save more each month | D33: € | E33: Type 3 · optional · Optional: leave blank for none. Allowed: €0 to €15,000 · steps of €50 | F33: 0 | G33: =IF(ISBLANK(C33),F33,C33) -> 0
B34: What if: spend less in retirement (a year) | D34: € | E34: ="Type 3 · optional · Optional: leave blank for none. Allowed: €0 to "&TEXT(Max_Money_Input,"€#,##0")&" · steps of €500" -> Type 3 · optional · Optional: leave blank for none. Allowed: €0 to €200,000 · steps of €500 | F34: 0 | G34: =IF(ISBLANK(C34),F34,C34) -> 0
B35: Pension access age (the earliest age you can draw your pension) | D35: age | E35: Type 3 · LifeMap standard · LifeMap uses 60 (most pensions can be drawn from 60; some occupational schemes allow 50). Change it only if your scheme allows 50. Allowed: 50 or 60 | F35: =AS_AccessAge -> 60 | G35: =IF(ISBLANK(C35),F35,C35) -> 60
B36: FIGURE USED (statement figure if present, else your figure)
B37: Pension value today | C37: =IF(ISBLANK(Stmt_Fund_Value),Pension_Today,Stmt_Fund_Value) | D37: =IF(ISBLANK(Stmt_Fund_Value),"Your figure","From your statement") -> Your figure | E37: ƒx =IF(ISBLANK(Stmt_Fund_Value),Pension_Today,Stmt_Fund_Value)
B38: Monthly contributions (you + employer) | C38: =IF(COUNT(Stmt_You_Monthly,Stmt_Employer_Monthly)=0,Monthly_Contribution,SUM(Stmt_You_Monthly,Stmt_Employer_Monthly)) | D38: =IF(COUNT(Stmt_You_Monthly,Stmt_Employer_Monthly)=0,"Your figure","From your statement") -> Your figure | E38: ƒx =IF(COUNT(Stmt_You_Monthly,Stmt_Employer_Monthly)=0,Monthly_Contribution,SUM(Stmt_You_Monthly,Stmt_Employer_Monthly))
B39: Growth after charges | C39: =IF(ISBLANK(Stmt_Charges),Growth_Rate,IF(OR(Growth_Rate="",Typical_Pension_Charges=""),"",Growth_Rate+Typical_Pension_Charges-Stmt_Charges)) -> 0.045 | D39: =IF(ISBLANK(Stmt_Charges),"Your figure","Adjusted for your statement's charges") -> Your figure | E39: ƒx =IF(ISBLANK(Stmt_Charges),Growth_Rate,IF(OR(Growth_Rate="",Typical_Pension_Charges=""),"",Growth_Rate+Typical_Pension_Charges-Stmt_Charges))
B40: Use the statement's projected fund? | C40: =IF(Need_1<>"",Need_1,IF(AND(NOT(ISBLANK(Stmt_Projected_Fund)),Stmt_NRA=Retirement_Age+Retire_Later,Save_More=0),"Yes","No")) -> Choose your retirement age to see this | E40: ƒx =IF(AND(NOT(ISBLANK(Stmt_Projected_Fund)),Stmt_NRA=Retirement_Age+Retire_Later,Save_More=0),"Yes","No") (projection shown, its retirement age matches yours, and no "save more" what-if)
B41: Statement date check | C41: =IF(ISBLANK(Stmt_Statement_Date),"",IF(TODAY()-Stmt_Statement_Date>Statement_Max_Age_Days,"Needs a look: statement is more than 12 months old","Up to date")) | E41: ƒx =IF(ISBLANK(Stmt_Statement_Date),"",IF(TODAY()-Stmt_Statement_Date>Statement_Max_Age_Days,"Needs a look: statement is more than 12 months old","Up to date"))
B43: RESULTS | C43: Result | D43: Shown as | E43: Formula
B44: Illustrative gap (today's money) | C44: =IF(Need_2<>"",Need_2,IF(ISNUMBER(Fund_Today),Target_Today-Fund_Today,Fund_Today)) -> Choose your age to see this | D44: =IF(Need_2<>"",Need_2,IF(ISNUMBER(Gap_Today),IF(Gap_Today>0,"Gap of "&TEXT(Gap_Today,"€#,##0")&" in today's money","On track: no gap"),Gap_Today)) -> Choose your age to see this | E44: ƒx =IF(ISNUMBER(Fund_Today),Target_Today-Fund_Today,Fund_Today)
B45: Projected fund at retirement | C45: =IF(Need_3<>"",Need_3,IF(Use_Statement_Projection="Yes",Stmt_Projected_Fund,Calculated_Fund)) -> Choose your age to see this | D45: =IF(Need_3<>"",Need_3,IF(Use_Statement_Projection="Yes","From your statement","Calculated")) -> Choose your age to see this | E45: ƒx =IF(Use_Statement_Projection="Yes",Stmt_Projected_Fund,Calculated_Fund)
B46: Projected fund in today's money | C46: =IF(Need_3<>"",Need_3,IF(AND(Use_Statement_Projection="Yes",Stmt_Projection_Today<>"No"),Stmt_Projected_Fund,IF(Inflation_Choice="","Choose your inflation rate to see this",Projected_Fund/(1+Inflation_Choice)^Years_To_Retirement))) -> Choose your age to see this | D46: € | E46: ƒx =IF(AND(Use_Statement_Projection="Yes",Stmt_Projection_Today<>"No"),Stmt_Projected_Fund,IF(Inflation_Choice="","Choose your inflation rate to see this",Projected_Fund/(1+Inflation_Choice)^Years_To_Retirement)) (a statement projection already in today's money is not deflated again)
B47: Calculated fund at retirement (our assumptions) | C47: =IF(Need_3<>"",Need_3,Used_Pension_Today*(1+Used_Growth_Rate)^Years_To_Retirement+Contributions_Grow_To) -> Choose your age to see this | D47: € | E47: ƒx =Used_Pension_Today*(1+Used_Growth_Rate)^Years_To_Retirement+Contributions_Grow_To
B48: Illustrative target (today's money) | C48: =IF(Need_4<>"",Need_4,MAX(0,Desired_Income-Spend_Less-Other_Income)*Retire_Multiple+Bridge_Years*MIN(Other_Income,MAX(0,Desired_Income-Spend_Less))) -> Choose your desired retirement income to see this | D48: € | E48: ƒx =MAX(0,Desired_Income-Spend_Less-Other_Income)*Retire_Multiple+Bridge_Years*MIN(Other_Income,MAX(0,Desired_Income-Spend_Less)) (the years before the State Pension never need more than the income you need)
B49: Years before the State Pension starts at 66 (to fund yourself) | C49: =IF(Need_1<>"",Need_1,MAX(0,State_Pension_Age-(Retirement_Age+Retire_Later))) -> Choose your retirement age to see this | D49: years | E49: ƒx =MAX(0,State_Pension_Age-(Retirement_Age+Retire_Later))
B50: Lump sum you could take at retirement (gross) | C50: =IF(Need_5<>"",Need_5,Projected_Fund*MIN(Lump_Sum_Pct,Lump_Sum_Max_Pct)) -> Choose your age to see this | D50: € | E50: ="ƒx =Projected_Fund*MIN(Lump_Sum_Pct,Lump_Sum_Max_Pct) (25% at most of the fund: no cap; first "&"€"&TEXT(Lump_Sum_Tax_Free,"#,##0")&" tax-free, next €"&TEXT(Lump_Sum_Cap-Lump_Sum_Tax_Free,"#,##0")&" at "&TEXT(Lump_Sum_Rate,"0%")&", the excess at the higher rate)" -> ƒx =Projected_Fund*MIN(Lump_Sum_Pct,Lump_Sum_Max_Pct) (25% at most of the fund: no cap; first €200,000 tax-free, next €300,000 at 20%, the excess at the higher rate)
B51: Tax on the lump sum | C51: =IF(Need_5<>"",Need_5,Lump_Sum_Rate*MAX(0,MIN(Lump_Sum,Lump_Sum_Cap)-Lump_Sum_Tax_Free)+Rate_Higher*MAX(0,Lump_Sum-Lump_Sum_Cap)) -> Choose your age to see this | D51: € | E51: ƒx =Lump_Sum_Rate*MAX(0,MIN(Lump_Sum,Lump_Sum_Cap)-Lump_Sum_Tax_Free)+Rate_Higher*MAX(0,Lump_Sum-Lump_Sum_Cap) (the part above €500,000 is taxed at the higher rate; verify on Revenue)
B52: Lump sum after tax | C52: =IF(Need_5<>"",Need_5,Lump_Sum-Lump_Sum_Tax) -> Choose your age to see this | D52: € | E52: ƒx =Lump_Sum-Lump_Sum_Tax
B53: Message to show | C53: =IF(Need_1<>"","",IF(Retirement_Age+Retire_Later<Access_Age,"Most pensions can't be taken before 60 (PRSA and personal pensions; some occupational schemes allow it from 50). Until then you would live on savings and other income.",""))
B54: Message to show | C54: =IF(Need_3<>"","",IF(AND(ISNUMBER(Fund_Today),IF(ISNUMBER(Fund_Today),Fund_Today,0)>SFT_2026),"Your fund in today's money is above the Standard Fund Threshold (€2.2m in 2026, rising to €2.8m by 2029; later years are not set yet): the excess is taxed at "&TEXT(SFT_Tax,"0%")&".",""))
B55: Years to retirement | C55: =IF(Need_6<>"",Need_6,MAX(1,Retirement_Age+Retire_Later-Age)) -> Choose your age to see this | D55: years | E55: ƒx =MAX(1,Retirement_Age+Retire_Later-Age)
B56: Monthly contribution incl. what-if | C56: =IF(Need_7<>"",Need_7,Used_Monthly_Contribution+Save_More) -> Choose your monthly contributions to see this | D56: € | E56: ƒx =Used_Monthly_Contribution+Save_More
B57: Contributions (rising with pay) grow to | C57: =IF(Need_8<>"",Need_8,IF(Used_Growth_Rate=Wage,12*Contribution*Years_To_Retirement*(1+Used_Growth_Rate)^(Years_To_Retirement-1),12*Contribution*((1+Used_Growth_Rate)^Years_To_Retirement-(1+Wage)^Years_To_Retirement)/(Used_Growth_Rate-Wage))) -> Choose your age to see this | D57: € | E57: ƒx =IF(Used_Growth_Rate=Wage,12*Contribution*Years_To_Retirement*(1+Used_Growth_Rate)^(Years_To_Retirement-1),12*Contribution*((1+Used_Growth_Rate)^Years_To_Retirement-(1+Wage)^Years_To_Retirement)/(Used_Growth_Rate-Wage))
B59: HOW IT WORKS
B60: • Fund = pension today × (1 + growth)^years + each year's contributions (12 × monthly, rising with pay each year, added at the year end), the closed-form growing annuity.
B61: • The fund is future money, the target is today's money, so the fund is turned into today's money first: fund ÷ (1 + inflation)^years (audit Must fix: like-for-like gap).
B62: • Target = (desired income − spend less − other income) × your multiple (suggested 25), plus the State Pension you must fund yourself for each year you retire before 66 (at most the income you need each year). Gap = target − fund in today's money.
B63: ="• Desired income and the State Pension are before tax: the State Pension is taxable (USC-exempt) and drawdown pays income tax and USC. The lump sum is the share you chose "&"("&TEXT(Lump_Sum_Max_Pct,"0%")&" at most)"&": the "&"first "&TEXT(Lump_Sum_Tax_Free,"€#,##0")&" tax-free, the "&"next "&TEXT(Lump_Sum_Cap-Lump_Sum_Tax_Free,"€#,##0")&" at "&TEXT(Lump_Sum_Rate,"0%")&", anything "&"above "&TEXT(Lump_Sum_Cap,"€#,##0")&" at the higher rate. Contributions are counted as paid at the end of each year." -> • Desired income and the State Pension are before tax: the State Pension is taxable (USC-exempt) and drawdown pays income tax and USC. The lump sum is the share you chose (25% at most): the first €200,000 tax-free, the next €300,000 at 20%, anything above €500,000 at the higher rate. Contributions are counted as paid at the end of each year.
B64: Edge rules and validation:
B65: • A retirement age at or before your age gives "Choose a retirement age after your age to see this" (never a silent 1 year).
B66: • If growth equals the pay-rise rate the growing-annuity formula divides by zero, so the equal-rate form 12 × contribution × years × (1+g)^(years−1) is used.
B67: • Gap ≤ 0 shows "On track: no gap".
B69: ADD TO MY PLAN (what this calculator sends to the plan)
B70: Goal | C70: ="Update your retirement goal (no new goal)" -> Update your retirement goal (no new goal) | E70: ƒx ="Update your retirement goal (no new goal)"
B71: Yearly income in retirement (today's money) | C71: =IF(Need_9<>"",Need_9,Desired_Income-Spend_Less) -> Choose your desired retirement income to see this | E71: ƒx =Desired_Income-Spend_Less
B72: Retirement age | C72: =IF(Need_1<>"",Need_1,Retirement_Age+Retire_Later) -> Choose your retirement age to see this | E72: ƒx =Retirement_Age+Retire_Later
B73: Inflation for the plan (your choice) | C73: =IF(Inflation_Choice="","Choose an inflation rate first",Inflation_Choice) -> Choose an inflation rate first | E73: ƒx =IF(Inflation_Choice="","Choose an inflation rate first",Inflation_Choice)
B74: Audit fix: the old 25× lump sum spend goal double-counted the plan's own retirement goal.
B76: CHOICES STILL NEEDED (helper rows: blank = all inputs a result needs are filled)
B77: Needs: retirement age | C77: =IF(AND(ISNUMBER(Age),ISNUMBER(Retirement_Age),N(Retirement_Age)+N(Retire_Later)<=N(Age)),"Choose a retirement age after your age to see this",IF(Retirement_Age="","Choose your retirement age to see this",IF(Other_Income="","Choose your State Pension (other yearly income) to see this",""))) -> Choose your retirement age to see this
B78: Needs: age, desired retirement income, other income (State Pension), retirement multiple, retirement age, Used_Growth_Rate, Used_Monthly_Contribution, Used_Pension_Today, pay rise | C78: =IF(Age="","Choose your age to see this",IF(Desired_Income="","Choose your desired retirement income to see this",IF(NOT(ISNUMBER(Used_Pension_Today)),IF(Used_Pension_Today="",IF(Pension_Today="","Choose your pension value to see this",""),Used_Pension_Today),IF(NOT(ISNUMBER(Used_Monthly_Contribution)),IF(Used_Monthly_Contribution="",IF(Monthly_Contribution="","Choose your monthly contributions to see this",""),Used_Monthly_Contribution),IF(NOT(ISNUMBER(Used_Growth_Rate)),IF(Used_Growth_Rate="",IF(Growth_Rate="","Choose your growth rate to see this",IF(Growth_Rate="","Choose your growth rate to see this",IF(Growth_Rate="","Choose your growth rate to see this",IF(Typical_Pension_Charges="","Choose your typical pension charges to see this",IF(Typical_Pension_Charges="","Choose your typical pension charges to see this",""))))),Used_Growth_Rate),IF(AND(ISNUMBER(Age),ISNUMBER(Retirement_Age),N(Retirement_Age)+N(Retire_Later)<=N(Age)),"Choose a retirement age after your age to see this",IF(Retirement_Age="","Choose your retirement age to see this",IF(Other_Income="","Choose your State Pension (other yearly income) to see this","")))))))) -> Choose your age to see this
B79: Needs: age, retirement age, Used_Growth_Rate, Used_Monthly_Contribution, Used_Pension_Today, pay rise | C79: =IF(Age="","Choose your age to see this",IF(NOT(ISNUMBER(Used_Pension_Today)),IF(Used_Pension_Today="",IF(Pension_Today="","Choose your pension value to see this",""),Used_Pension_Today),IF(NOT(ISNUMBER(Used_Monthly_Contribution)),IF(Used_Monthly_Contribution="",IF(Monthly_Contribution="","Choose your monthly contributions to see this",""),Used_Monthly_Contribution),IF(NOT(ISNUMBER(Used_Growth_Rate)),IF(Used_Growth_Rate="",IF(Growth_Rate="","Choose your growth rate to see this",IF(Growth_Rate="","Choose your growth rate to see this",IF(Growth_Rate="","Choose your growth rate to see this",IF(Typical_Pension_Charges="","Choose your typical pension charges to see this",IF(Typical_Pension_Charges="","Choose your typical pension charges to see this",""))))),Used_Growth_Rate),IF(AND(ISNUMBER(Age),ISNUMBER(Retirement_Age),N(Retirement_Age)+N(Retire_Later)<=N(Age)),"Choose a retirement age after your age to see this",IF(Retirement_Age="","Choose your retirement age to see this",IF(Other_Income="","Choose your State Pension (other yearly income) to see this",""))))))) -> Choose your age to see this
B80: Needs: desired retirement income, other income (State Pension), retirement multiple, retirement age | C80: =IF(Desired_Income="","Choose your desired retirement income to see this",IF(AND(ISNUMBER(Age),ISNUMBER(Retirement_Age),N(Retirement_Age)+N(Retire_Later)<=N(Age)),"Choose a retirement age after your age to see this",IF(Retirement_Age="","Choose your retirement age to see this",IF(Other_Income="","Choose your State Pension (other yearly income) to see this","")))) -> Choose your desired retirement income to see this
B81: Needs: age, lump sum share, retirement age, Used_Growth_Rate, Used_Monthly_Contribution, Used_Pension_Today, pay rise | C81: =IF(Age="","Choose your age to see this",IF(NOT(ISNUMBER(Used_Pension_Today)),IF(Used_Pension_Today="",IF(Pension_Today="","Choose your pension value to see this",""),Used_Pension_Today),IF(NOT(ISNUMBER(Used_Monthly_Contribution)),IF(Used_Monthly_Contribution="",IF(Monthly_Contribution="","Choose your monthly contributions to see this",""),Used_Monthly_Contribution),IF(NOT(ISNUMBER(Used_Growth_Rate)),IF(Used_Growth_Rate="",IF(Growth_Rate="","Choose your growth rate to see this",IF(Growth_Rate="","Choose your growth rate to see this",IF(Growth_Rate="","Choose your growth rate to see this",IF(Typical_Pension_Charges="","Choose your typical pension charges to see this",IF(Typical_Pension_Charges="","Choose your typical pension charges to see this",""))))),Used_Growth_Rate),IF(AND(ISNUMBER(Age),ISNUMBER(Retirement_Age),N(Retirement_Age)+N(Retire_Later)<=N(Age)),"Choose a retirement age after your age to see this",IF(Retirement_Age="","Choose your retirement age to see this",IF(Other_Income="","Choose your State Pension (other yearly income) to see this",""))))))) -> Choose your age to see this
B82: Needs: age, retirement age | C82: =IF(Age="","Choose your age to see this",IF(AND(ISNUMBER(Age),ISNUMBER(Retirement_Age),N(Retirement_Age)+N(Retire_Later)<=N(Age)),"Choose a retirement age after your age to see this",IF(Retirement_Age="","Choose your retirement age to see this",IF(Other_Income="","Choose your State Pension (other yearly income) to see this","")))) -> Choose your age to see this
B83: Needs: Used_Monthly_Contribution | C83: =IF(NOT(ISNUMBER(Used_Monthly_Contribution)),IF(Used_Monthly_Contribution="",IF(Monthly_Contribution="","Choose your monthly contributions to see this",""),Used_Monthly_Contribution),IF(AND(ISNUMBER(Age),ISNUMBER(Retirement_Age),N(Retirement_Age)+N(Retire_Later)<=N(Age)),"Choose a retirement age after your age to see this",IF(Retirement_Age="","Choose your retirement age to see this",IF(Other_Income="","Choose your State Pension (other yearly income) to see this","")))) -> Choose your monthly contributions to see this
B84: Needs: age, retirement age, Used_Growth_Rate, Used_Monthly_Contribution, pay rise | C84: =IF(Age="","Choose your age to see this",IF(NOT(ISNUMBER(Used_Monthly_Contribution)),IF(Used_Monthly_Contribution="",IF(Monthly_Contribution="","Choose your monthly contributions to see this",""),Used_Monthly_Contribution),IF(NOT(ISNUMBER(Used_Growth_Rate)),IF(Used_Growth_Rate="",IF(Growth_Rate="","Choose your growth rate to see this",IF(Growth_Rate="","Choose your growth rate to see this",IF(Growth_Rate="","Choose your growth rate to see this",IF(Typical_Pension_Charges="","Choose your typical pension charges to see this",IF(Typical_Pension_Charges="","Choose your typical pension charges to see this",""))))),Used_Growth_Rate),IF(AND(ISNUMBER(Age),ISNUMBER(Retirement_Age),N(Retirement_Age)+N(Retire_Later)<=N(Age)),"Choose a retirement age after your age to see this",IF(Retirement_Age="","Choose your retirement age to see this",IF(Other_Income="","Choose your State Pension (other yearly income) to see this","")))))) -> Choose your age to see this
B85: Needs: desired retirement income | C85: =IF(Desired_Income="","Choose your desired retirement income to see this",IF(AND(ISNUMBER(Age),ISNUMBER(Retirement_Age),N(Retirement_Age)+N(Retire_Later)<=N(Age)),"Choose a retirement age after your age to see this",IF(Retirement_Age="","Choose your retirement age to see this",IF(Other_Income="","Choose your State Pension (other yearly income) to see this","")))) -> Choose your desired retirement income to see this

Sheet C13 Contribution impact
B1: C13 · Contribution impact | E1: Category: Pensions & Retirement · prototype id: contrib
B2: Question it answers: What difference would a small increase make? | E2: =IF(Fill_Example="Yes","Example values are ON (README): grey Example only figures fill blank inputs.","Blank template: fill the yellow inputs (or switch on example values on the README).") -> Blank template: fill the yellow inputs (or switch on example values on the README).
B3: Shows what raising your pension contributions by a % of salary could add by retirement, and what it costs after tax relief.
B5: YOUR INFLATION CHOICE | C5: Your figure | D5: Unit | E5: Allowed | F5: Example only (grey; used only when "Fill example values" is Yes)
B6: Inflation you expect (your choice) | D6: % | E6: ="Type 3 · your choice · Generally the standard is 2% a year (ECB target); Ireland's prices are rising "&TEXT(Set_inflNow,"0.0%")&" now (CSO HICP flash, Sep 2026). Choose what you want to use. Allowed: 0% to 10% · steps of 0.25%" -> Type 3 · your choice · Generally the standard is 2% a year (ECB target); Ireland's prices are rising 3.9% now (CSO HICP flash, Sep 2026). Choose what you want to use. Allowed: 0% to 10% · steps of 0.25% | F6: 0.02 | G6: =IF(ISBLANK(C6),IF(Fill_Example="Yes",F6,""),C6)
B7: ="Everyone sees this differently. Ireland's prices are rising "&TEXT(Set_inflNow,"0.0%")&" now (CSO HICP flash, Sep 2026), mostly because of energy. Over decades, 2%–2.5% is the usual planning range (ECB target 2%). Enter 0% if you don't want to adjust for prices." -> Everyone sees this differently. Ireland's prices are rising 3.9% now (CSO HICP flash, Sep 2026), mostly because of energy. Over decades, 2%–2.5% is the usual planning range (ECB target 2%). Enter 0% if you don't want to adjust for prices.
B9: FROM YOUR STATEMENT (filled automatically by the document reader)
B10: Document: Pension benefit statement / PRSA statement. Blank = no statement uploaded, or the figure is not on it. Grey-blue cells are filled by the reader (you can type here to test).
B11: Annual charges % (if shown) | D11: % | E11: Allowed: 0% to 5% | G11: Reader field: see note
B12: Statement date | D12: date | E12: Allowed: a date (dd/mm/yyyy) | G12: Reader field: see note
B14: OR TYPE IT YOURSELF | C14: Your figure | D14: Unit | E14: Allowed | F14: Example only (grey; used only when "Fill example values" is Yes)
B15: Salary | D15: € | E15: Type 3 · your figure · Your own figure. In the app it is pre-filled from Your finances: income. Allowed: €15,000 to €2,500,000 · steps of €1,000 | F15: 60000 | G15: =IF(ISBLANK(C15),IF(Fill_Example="Yes",F15,""),C15)
B16: Increase contributions by (% of salary) | D16: % | E16: Type 3 · your figure · Your own figure. Allowed: 0.5% to 10% · steps of 0.5% | F16: 0.02 | G16: =IF(ISBLANK(C16),IF(Fill_Example="Yes",F16,""),C16)
B17: Years to retirement | D17: years | E17: Type 3 · your figure · Your own figure. In the app it is pre-filled from Plan: retirement age − age. Allowed: 1 to 45 · steps of 1 | F17: 25 | G17: =IF(ISBLANK(C17),IF(Fill_Example="Yes",F17,""),C17)
B18: Growth assumption a year | D18: % | E18: Type 3 · LifeMap standard · LifeMap uses 4.5% a year after charges while you work (LifeMap Standard set; Cautious 4%). Change it if you want to use your own. Allowed: 1% to 7% · steps of 0.25% | F18: =AS_Pen -> 0.045 | G18: =IF(ISBLANK(C18),F18,C18) -> 0.045
B19: Typical pension charges (if your statement doesn't say) | D19: % | E19: ="Type 2 · your figure · Typical pension charges a year (your statement shows yours). "&IF(ISNUMBER(Suggest_Fund_Charges),"Suggested: "&TEXT(Suggest_Fund_Charges,"0.00%")&" · "&Suggest_Fund_Charges_Label&". ","No suggestion. ")&"Enter your own figure."&" Allowed: 0% to 2.5% · steps of 0.05%" -> Type 2 · your figure · Typical pension charges a year (your statement shows yours). Suggested: 1.00% · Pensions Authority pension calculator assumption. Enter your own figure. Allowed: 0% to 2.5% · steps of 0.05% | F19: =IF(ISNUMBER(Suggest_Fund_Charges),Suggest_Fund_Charges,"") -> 0.01 | G19: =IF(ISBLANK(C19),IF(Fill_Example="Yes",F19,""),C19)
B20: Your tax rate (0.2 = 20%, 0.4 = 40%) | D20: 20% or 40% | E20: Type 2 · range · Usually between 20% or 40%: your top rate of income tax (the Tax engine works it out). In the app it is pre-filled from Tax engine marginal rate (band by status: €44k single, €48k single parent, €53k married, + up to €35k second earner). Enter your own figure. Allowed: 20% or 40% | F20: =TE_Marginal_Rate -> Choose your tax status to see this | G20: =IF(ISBLANK(C20),IF(Fill_Example="Yes",F20,""),C20)
B21: Your age (for the pension relief limit) | D21: age | E21: Type 3 · your figure · Your own figure. In the app it is pre-filled from About you: age. Allowed: 18 to 75 · steps of 1 | F21: 40 | G21: =IF(ISBLANK(C21),IF(Fill_Example="Yes",F21,""),C21)
B22: What you pay in yourself now, a year (counts towards the relief limit) | D22: € | E22: Type 3 · optional · Optional: leave blank for none. Allowed: €0 to €1,000,000 · steps of €100 | F22: 0 | G22: =IF(ISBLANK(C22),IF(Pens_Own_Total>0,Pens_Own_Total*12,F22),C22) -> 0
B24: FIGURE USED (statement figure if present, else your figure)
B25: Growth assumption | C25: =IF(ISBLANK(Stmt_Charges),Growth_Rate,IF(OR(Growth_Rate="",Typical_Pension_Charges=""),"",Growth_Rate+Typical_Pension_Charges-Stmt_Charges)) -> 0.045 | D25: =IF(ISBLANK(Stmt_Charges),"Your figure","Adjusted for your statement's charges") -> Your figure | E25: ƒx =IF(ISBLANK(Stmt_Charges),Growth_Rate,IF(OR(Growth_Rate="",Typical_Pension_Charges=""),"",Growth_Rate+Typical_Pension_Charges-Stmt_Charges))
B26: Statement date check | C26: =IF(ISBLANK(Stmt_Statement_Date),"",IF(TODAY()-Stmt_Statement_Date>Statement_Max_Age_Days,"Needs a look: statement is more than 12 months old","Up to date")) | E26: ƒx =IF(ISBLANK(Stmt_Statement_Date),"",IF(TODAY()-Stmt_Statement_Date>Statement_Max_Age_Days,"Needs a look: statement is more than 12 months old","Up to date"))
B28: RESULTS | C28: Result | D28: Shown as | E28: Formula
B29: Could add to your pension | C29: =IF(Need_1<>"",Need_1,FV((1+Used_Growth_Rate)^(1/12)-1,Years*12,-Extra_Per_Month)) -> Choose your salary to see this | D29: € | E29: ƒx =FV((1+Used_Growth_Rate)^(1/12)-1,Years*12,-Extra_Per_Month)
B30: Worth in today's money | C30: =IF(Need_2<>"",Need_2,IF(Inflation_Choice="","Choose your inflation rate to see this",Grows_To/(1+Inflation_Choice)^Years)) -> Choose your salary to see this | D30: € | E30: ƒx =IF(Inflation_Choice="","Choose your inflation rate to see this",Grows_To/(1+Inflation_Choice)^Years)
B31: Extra per month | C31: =IF(Need_3<>"",Need_3,Salary*Increase_Pct/12) -> Choose your salary to see this | D31: € | E31: ƒx =Salary*Increase_Pct/12
B32: Cost to you after tax relief, a month | C32: =IF(Need_4<>"",Need_4,Extra_Per_Month-Relief_Per_Month) -> Choose your salary to see this | D32: € | E32: ƒx =Extra_Per_Month-Relief_Per_Month
B33: ="Most you can get relief on in a year (age-band % × earnings up to "&"€"&TEXT(Relief_Earnings_Cap,"#,##0")&")" -> Most you can get relief on in a year (age-band % × earnings up to €115,000) | C33: =IF(Need_5<>"",Need_5,LOOKUP(Age,Relief_Age_From,Relief_Age_Pct)*MIN(Salary,Relief_Earnings_Cap)) -> Choose your salary to see this | D33: € | E33: ƒx =LOOKUP(Age,Relief_Age_From,Relief_Age_Pct)*MIN(Salary,Relief_Earnings_Cap)
B34: Room left for relief after what you already pay in | C34: =IF(Need_5<>"",Need_5,MAX(0,Relief_Limit_Year-Existing_Pension_Year)) -> Choose your salary to see this | D34: € | E34: ƒx =MAX(0,Relief_Limit_Year-Existing_Pension_Year)
B35: Extra that gets relief, a year | C35: =IF(Need_6<>"",Need_6,MIN(Extra_Per_Month*12,Relief_Room_Year)) -> Choose your salary to see this | D35: € | E35: ƒx =MIN(Extra_Per_Month*12,Relief_Room_Year)
B36: Tax relief a month | C36: =IF(Need_4<>"",Need_4,Relieved_Year*Tax_Rate/12) -> Choose your salary to see this | D36: € | E36: ƒx =Relieved_Year*Tax_Rate/12
B38: HOW IT WORKS
B39: • Extra a month = salary × increase ÷ 12. Value = FV(monthly growth, months, −extra): level end-of-month contributions.
B40: • Tax relief = the part of the extra within your relief limit × your tax rate (USC and PRSI still apply). Cost = extra − relief.
B41: Edge rules and validation:
B42: • Tax rate is 20% or 40% only (list); it pre-fills from the Tax engine.
B43: ="• Relief only within the age-related limit (15% under 30 … 40% from 60) of earnings up to "&"€"&TEXT(Relief_Earnings_Cap,"#,##0")&", less what you already pay in (audit #79)." -> • Relief only within the age-related limit (15% under 30 … 40% from 60) of earnings up to €115,000, less what you already pay in (audit #79).
B45: ADD TO MY PLAN (what this calculator sends to the plan)
B46: Goal | C46: ="No goal: raise the plan's pension contribution instead" -> No goal: raise the plan's pension contribution instead | E46: ƒx ="No goal: raise the plan's pension contribution instead"
B47: Extra pension contribution a month | C47: =IF(Need_3<>"",Need_3,Extra_Per_Month) -> Choose your salary to see this | E47: ƒx =Extra_Per_Month
B48: Audit fix: pension money is not a spend goal.
B50: CHOICES STILL NEEDED (helper rows: blank = all inputs a result needs are filled)
B51: Needs: contribution increase, salary, Used_Growth_Rate, years to retirement | C51: =IF(Salary="","Choose your salary to see this",IF(Increase_Pct="","Choose your contribution increase to see this",IF(Years="","Choose your years to retirement to see this",IF(NOT(ISNUMBER(Used_Growth_Rate)),IF(Used_Growth_Rate="",IF(Growth_Rate="","Choose your growth rate to see this",IF(Growth_Rate="","Choose your growth rate to see this",IF(Growth_Rate="","Choose your growth rate to see this",IF(Typical_Pension_Charges="","Choose your typical pension charges to see this",IF(Typical_Pension_Charges="","Choose your typical pension charges to see this",""))))),Used_Growth_Rate),"")))) -> Choose your salary to see this
B52: Needs: contribution increase, inflation rate, salary, Used_Growth_Rate, years to retirement | C52: =IF(Salary="","Choose your salary to see this",IF(Increase_Pct="","Choose your contribution increase to see this",IF(Years="","Choose your years to retirement to see this",IF(NOT(ISNUMBER(Used_Growth_Rate)),IF(Used_Growth_Rate="",IF(Growth_Rate="","Choose your growth rate to see this",IF(Growth_Rate="","Choose your growth rate to see this",IF(Growth_Rate="","Choose your growth rate to see this",IF(Typical_Pension_Charges="","Choose your typical pension charges to see this",IF(Typical_Pension_Charges="","Choose your typical pension charges to see this",""))))),Used_Growth_Rate),IF(Inflation_Choice="","Choose your inflation rate to see this",""))))) -> Choose your salary to see this
B53: Needs: contribution increase, salary | C53: =IF(Salary="","Choose your salary to see this",IF(Increase_Pct="","Choose your contribution increase to see this","")) -> Choose your salary to see this
B54: Needs: age, contribution increase, salary, tax rate | C54: =IF(Salary="","Choose your salary to see this",IF(Increase_Pct="","Choose your contribution increase to see this",IF(Tax_Rate="","Choose your tax rate to see this",IF(Age="","Choose your age to see this","")))) -> Choose your salary to see this
B55: Needs: age, salary | C55: =IF(Salary="","Choose your salary to see this",IF(Age="","Choose your age to see this","")) -> Choose your salary to see this
B56: Needs: age, contribution increase, salary | C56: =IF(Salary="","Choose your salary to see this",IF(Increase_Pct="","Choose your contribution increase to see this",IF(Age="","Choose your age to see this",""))) -> Choose your salary to see this
B58: Note: the extra contribution is the same every year; it does not rise with pay (the Retirement projection and your plan do let contributions rise with pay).

Sheet C14 AVC impact
B1: C14 · AVC impact | E1: Category: Pensions & Retirement · prototype id: avc
B2: Question it answers: What could extra voluntary contributions add? | E2: =IF(Fill_Example="Yes","Example values are ON (README): grey Example only figures fill blank inputs.","Blank template: fill the yellow inputs (or switch on example values on the README).") -> Blank template: fill the yellow inputs (or switch on example values on the README).
B3: Shows what extra voluntary contributions (AVCs) could add by retirement, and their cost after tax relief.
B5: YOUR INFLATION CHOICE | C5: Your figure | D5: Unit | E5: Allowed | F5: Example only (grey; used only when "Fill example values" is Yes)
B6: Inflation you expect (your choice) | D6: % | E6: ="Type 3 · your choice · Generally the standard is 2% a year (ECB target); Ireland's prices are rising "&TEXT(Set_inflNow,"0.0%")&" now (CSO HICP flash, Sep 2026). Choose what you want to use. Allowed: 0% to 10% · steps of 0.25%" -> Type 3 · your choice · Generally the standard is 2% a year (ECB target); Ireland's prices are rising 3.9% now (CSO HICP flash, Sep 2026). Choose what you want to use. Allowed: 0% to 10% · steps of 0.25% | F6: 0.02 | G6: =IF(ISBLANK(C6),IF(Fill_Example="Yes",F6,""),C6)
B7: ="Everyone sees this differently. Ireland's prices are rising "&TEXT(Set_inflNow,"0.0%")&" now (CSO HICP flash, Sep 2026), mostly because of energy. Over decades, 2%–2.5% is the usual planning range (ECB target 2%). Enter 0% if you don't want to adjust for prices." -> Everyone sees this differently. Ireland's prices are rising 3.9% now (CSO HICP flash, Sep 2026), mostly because of energy. Over decades, 2%–2.5% is the usual planning range (ECB target 2%). Enter 0% if you don't want to adjust for prices.
B9: FROM YOUR STATEMENT (filled automatically by the document reader)
B10: Document: Pension benefit statement / PRSA / AVC statement. Blank = no statement uploaded, or the figure is not on it. Grey-blue cells are filled by the reader (you can type here to test).
B11: Annual charges % (if shown) | D11: % | E11: Allowed: 0% to 5% | G11: Reader field: see note
B12: Statement date | D12: date | E12: Allowed: a date (dd/mm/yyyy) | G12: Reader field: see note
B14: OR TYPE IT YOURSELF | C14: Your figure | D14: Unit | E14: Allowed | F14: Example only (grey; used only when "Fill example values" is Yes)
B15: AVC per month | D15: € | E15: Type 3 · your figure · Your own figure. Allowed: €25 to €20,000 · steps of €25 | F15: 200 | G15: =IF(ISBLANK(C15),IF(Fill_Example="Yes",F15,""),C15)
B16: Salary (for the relief limit) | D16: € | E16: Type 3 · your figure · Your own figure. In the app it is pre-filled from Your finances: income. Allowed: €15,000 to €2,500,000 · steps of €1,000 | F16: 60000 | G16: =IF(ISBLANK(C16),IF(Fill_Example="Yes",F16,""),C16)
B17: Years to retirement | D17: years | E17: Type 3 · your figure · Your own figure. In the app it is pre-filled from Plan: retirement age − age. Allowed: 1 to 40 · steps of 1 | F17: 15 | G17: =IF(ISBLANK(C17),IF(Fill_Example="Yes",F17,""),C17)
B18: Growth assumption a year | D18: % | E18: Type 3 · LifeMap standard · LifeMap uses 4.5% a year after charges while you work (LifeMap Standard set; Cautious 4%). Change it if you want to use your own. Allowed: 1% to 7% · steps of 0.25% | F18: =AS_Pen -> 0.045 | G18: =IF(ISBLANK(C18),F18,C18) -> 0.045
B19: Typical pension charges (if your statement doesn't say) | D19: % | E19: ="Type 2 · your figure · Typical pension charges a year (your statement shows yours). "&IF(ISNUMBER(Suggest_Fund_Charges),"Suggested: "&TEXT(Suggest_Fund_Charges,"0.00%")&" · "&Suggest_Fund_Charges_Label&". ","No suggestion. ")&"Enter your own figure."&" Allowed: 0% to 2.5% · steps of 0.05%" -> Type 2 · your figure · Typical pension charges a year (your statement shows yours). Suggested: 1.00% · Pensions Authority pension calculator assumption. Enter your own figure. Allowed: 0% to 2.5% · steps of 0.05% | F19: =IF(ISNUMBER(Suggest_Fund_Charges),Suggest_Fund_Charges,"") -> 0.01 | G19: =IF(ISBLANK(C19),IF(Fill_Example="Yes",F19,""),C19)
B20: Your tax rate (0.2 = 20%, 0.4 = 40%) | D20: 20% or 40% | E20: Type 2 · range · Usually between 20% or 40%: your top rate of income tax (the Tax engine works it out). In the app it is pre-filled from Tax engine marginal rate (band by status: €44k single, €48k single parent, €53k married, + up to €35k second earner). Enter your own figure. Allowed: 20% or 40% | F20: =TE_Marginal_Rate -> Choose your tax status to see this | G20: =IF(ISBLANK(C20),IF(Fill_Example="Yes",F20,""),C20)
B21: Your age (for the pension relief limit) | D21: age | E21: Type 3 · your figure · Your own figure. In the app it is pre-filled from About you: age. Allowed: 18 to 75 · steps of 1 | F21: 40 | G21: =IF(ISBLANK(C21),IF(Fill_Example="Yes",F21,""),C21)
B22: What you pay in yourself now, a year (counts towards the relief limit) | D22: € | E22: Type 3 · optional · Optional: leave blank for none. Allowed: €0 to €1,000,000 · steps of €100 | F22: 0 | G22: =IF(ISBLANK(C22),IF(Pens_Own_Total>0,Pens_Own_Total*12,F22),C22) -> 0
B24: FIGURE USED (statement figure if present, else your figure)
B25: Growth assumption | C25: =IF(ISBLANK(Stmt_Charges),Growth_Rate,IF(OR(Growth_Rate="",Typical_Pension_Charges=""),"",Growth_Rate+Typical_Pension_Charges-Stmt_Charges)) -> 0.045 | D25: =IF(ISBLANK(Stmt_Charges),"Your figure","Adjusted for your statement's charges") -> Your figure | E25: ƒx =IF(ISBLANK(Stmt_Charges),Growth_Rate,IF(OR(Growth_Rate="",Typical_Pension_Charges=""),"",Growth_Rate+Typical_Pension_Charges-Stmt_Charges))
B26: Statement date check | C26: =IF(ISBLANK(Stmt_Statement_Date),"",IF(TODAY()-Stmt_Statement_Date>Statement_Max_Age_Days,"Needs a look: statement is more than 12 months old","Up to date")) | E26: ƒx =IF(ISBLANK(Stmt_Statement_Date),"",IF(TODAY()-Stmt_Statement_Date>Statement_Max_Age_Days,"Needs a look: statement is more than 12 months old","Up to date"))
B28: RESULTS | C28: Result | D28: Shown as | E28: Formula
B29: Could add | C29: =IF(Need_1<>"",Need_1,FV((1+Used_Growth_Rate)^(1/12)-1,Years*12,-AVC_Per_Month)) -> Choose your AVC per month to see this | D29: € | E29: ƒx =FV((1+Used_Growth_Rate)^(1/12)-1,Years*12,-AVC_Per_Month)
B30: Worth in today's money | C30: =IF(Need_2<>"",Need_2,IF(Inflation_Choice="","Choose your inflation rate to see this",Grows_To/(1+Inflation_Choice)^Years)) -> Choose your AVC per month to see this | D30: € | E30: ƒx =IF(Inflation_Choice="","Choose your inflation rate to see this",Grows_To/(1+Inflation_Choice)^Years)
B31: Paid in | C31: =IF(Need_3<>"",Need_3,AVC_Per_Month*12*Years) -> Choose your AVC per month to see this | D31: € | E31: ƒx =AVC_Per_Month*12*Years
B32: Net cost to you | C32: =IF(Need_4<>"",Need_4,Net_Cost_Per_Month*12*Years) -> Choose your AVC per month to see this | D32: € | E32: ƒx =Net_Cost_Per_Month*12*Years
B33: Net cost of each monthly AVC | C33: =IF(Need_5<>"",Need_5,AVC_Per_Month-Relief_Per_Month) -> Choose your AVC per month to see this | D33: € | E33: ƒx =AVC_Per_Month-Relief_Per_Month
B34: ="Most you can get relief on in a year (age-band % × earnings up to "&"€"&TEXT(Relief_Earnings_Cap,"#,##0")&")" -> Most you can get relief on in a year (age-band % × earnings up to €115,000) | C34: =IF(Need_6<>"",Need_6,LOOKUP(Age,Relief_Age_From,Relief_Age_Pct)*MIN(Salary,Relief_Earnings_Cap)) -> Choose your salary to see this | D34: € | E34: ƒx =LOOKUP(Age,Relief_Age_From,Relief_Age_Pct)*MIN(Salary,Relief_Earnings_Cap)
B35: Room left for relief after what you already pay in | C35: =IF(Need_6<>"",Need_6,MAX(0,Relief_Limit_Year-Existing_Pension_Year)) -> Choose your salary to see this | D35: € | E35: ƒx =MAX(0,Relief_Limit_Year-Existing_Pension_Year)
B36: AVC that gets relief, a year | C36: =IF(Need_7<>"",Need_7,MIN(AVC_Per_Month*12,Relief_Room_Year)) -> Choose your AVC per month to see this | D36: € | E36: ƒx =MIN(AVC_Per_Month*12,Relief_Room_Year)
B37: Tax relief a month | C37: =IF(Need_5<>"",Need_5,Relieved_Year*Tax_Rate/12) -> Choose your AVC per month to see this | D37: € | E37: ƒx =Relieved_Year*Tax_Rate/12
B39: HOW IT WORKS
B40: ="• Value = FV(monthly growth, months, −AVC). Tax relief = the part of the AVC within your relief limit (age band × earnings up to "&"€"&TEXT(Relief_Earnings_Cap,"#,##0")&", less what you already pay) × your tax rate. Net cost = AVC − relief." -> • Value = FV(monthly growth, months, −AVC). Tax relief = the part of the AVC within your relief limit (age band × earnings up to €115,000, less what you already pay) × your tax rate. Net cost = AVC − relief.
B41: Edge rules and validation:
B42: • Tax rate is 20% or 40% only (list); it pre-fills from the Tax engine.
B43: • The age-related limit covers your main scheme and AVCs together: enter what you already pay in.
B45: ADD TO MY PLAN (what this calculator sends to the plan)
B46: Goal | C46: ="No goal: raise the plan's pension contribution instead" -> No goal: raise the plan's pension contribution instead | E46: ƒx ="No goal: raise the plan's pension contribution instead"
B47: Extra pension contribution a month | C47: =IF(Need_8<>"",Need_8,AVC_Per_Month) -> Choose your AVC per month to see this | E47: ƒx =AVC_Per_Month
B49: CHOICES STILL NEEDED (helper rows: blank = all inputs a result needs are filled)
B50: Needs: AVC per month, Used_Growth_Rate, years to retirement | C50: =IF(AVC_Per_Month="","Choose your AVC per month to see this",IF(Years="","Choose your years to retirement to see this",IF(NOT(ISNUMBER(Used_Growth_Rate)),IF(Used_Growth_Rate="",IF(Growth_Rate="","Choose your growth rate to see this",IF(Growth_Rate="","Choose your growth rate to see this",IF(Growth_Rate="","Choose your growth rate to see this",IF(Typical_Pension_Charges="","Choose your typical pension charges to see this",IF(Typical_Pension_Charges="","Choose your typical pension charges to see this",""))))),Used_Growth_Rate),""))) -> Choose your AVC per month to see this
B51: Needs: AVC per month, inflation rate, Used_Growth_Rate, years to retirement | C51: =IF(AVC_Per_Month="","Choose your AVC per month to see this",IF(Years="","Choose your years to retirement to see this",IF(NOT(ISNUMBER(Used_Growth_Rate)),IF(Used_Growth_Rate="",IF(Growth_Rate="","Choose your growth rate to see this",IF(Growth_Rate="","Choose your growth rate to see this",IF(Growth_Rate="","Choose your growth rate to see this",IF(Typical_Pension_Charges="","Choose your typical pension charges to see this",IF(Typical_Pension_Charges="","Choose your typical pension charges to see this",""))))),Used_Growth_Rate),IF(Inflation_Choice="","Choose your inflation rate to see this","")))) -> Choose your AVC per month to see this
B52: Needs: AVC per month, years to retirement | C52: =IF(AVC_Per_Month="","Choose your AVC per month to see this",IF(Years="","Choose your years to retirement to see this","")) -> Choose your AVC per month to see this
B53: Needs: AVC per month, age, salary, tax rate, years to retirement | C53: =IF(AVC_Per_Month="","Choose your AVC per month to see this",IF(Salary="","Choose your salary to see this",IF(Years="","Choose your years to retirement to see this",IF(Tax_Rate="","Choose your tax rate to see this",IF(Age="","Choose your age to see this",""))))) -> Choose your AVC per month to see this
B54: Needs: AVC per month, age, salary, tax rate | C54: =IF(AVC_Per_Month="","Choose your AVC per month to see this",IF(Salary="","Choose your salary to see this",IF(Tax_Rate="","Choose your tax rate to see this",IF(Age="","Choose your age to see this","")))) -> Choose your AVC per month to see this
B55: Needs: age, salary | C55: =IF(Salary="","Choose your salary to see this",IF(Age="","Choose your age to see this","")) -> Choose your salary to see this
B56: Needs: AVC per month, age, salary | C56: =IF(AVC_Per_Month="","Choose your AVC per month to see this",IF(Salary="","Choose your salary to see this",IF(Age="","Choose your age to see this",""))) -> Choose your AVC per month to see this
B57: Needs: AVC per month | C57: =IF(AVC_Per_Month="","Choose your AVC per month to see this","") -> Choose your AVC per month to see this

Sheet C15 Will my money last
B1: C15 · Will my money last? | E1: Category: Pensions & Retirement · prototype id: lastmoney
B2: Question it answers: How long could my retirement savings last? | E2: =IF(Fill_Example="Yes","Example values are ON (README): grey Example only figures fill blank inputs.","Blank template: fill the yellow inputs (or switch on example values on the README).") -> Blank template: fill the yellow inputs (or switch on example values on the README).
B3: Shows how many full years your retirement savings could pay a yearly income that rises with prices.
B5: YOUR INFLATION CHOICE | C5: Your figure | D5: Unit | E5: Allowed | F5: Example only (grey; used only when "Fill example values" is Yes)
B6: Inflation you expect (your choice) | D6: % | E6: ="Type 3 · your choice · Generally the standard is 2% a year (ECB target); Ireland's prices are rising "&TEXT(Set_inflNow,"0.0%")&" now (CSO HICP flash, Sep 2026). Choose what you want to use. Allowed: 0% to 10% · steps of 0.25%" -> Type 3 · your choice · Generally the standard is 2% a year (ECB target); Ireland's prices are rising 3.9% now (CSO HICP flash, Sep 2026). Choose what you want to use. Allowed: 0% to 10% · steps of 0.25% | F6: 0.02 | G6: =IF(ISBLANK(C6),IF(Fill_Example="Yes",F6,""),C6)
B7: ="Everyone sees this differently. Ireland's prices are rising "&TEXT(Set_inflNow,"0.0%")&" now (CSO HICP flash, Sep 2026), mostly because of energy. Over decades, 2%–2.5% is the usual planning range (ECB target 2%). Enter 0% if you don't want to adjust for prices." -> Everyone sees this differently. Ireland's prices are rising 3.9% now (CSO HICP flash, Sep 2026), mostly because of energy. Over decades, 2%–2.5% is the usual planning range (ECB target 2%). Enter 0% if you don't want to adjust for prices.
B9: FROM YOUR STATEMENT (filled automatically by the document reader)
B10: Document: Pension benefit statement / Statement of Reasonable Projection. Blank = no statement uploaded, or the figure is not on it. Grey-blue cells are filled by the reader (you can type here to test).
B11: Projected fund at retirement (if shown) | D11: € | E11: Allowed: €0 to €100,000,000 | G11: Reader field: see note
B12: Fund value today | D12: € | E12: Allowed: €0 to €50,000,000 | G12: Reader field: see note
B13: Statement date | D13: date | E13: Allowed: a date (dd/mm/yyyy) | G13: Reader field: see note
B15: OR TYPE IT YOURSELF | C15: Your figure | D15: Unit | E15: Allowed | F15: Example only (grey; used only when "Fill example values" is Yes)
B16: Retirement savings | D16: € | E16: Type 3 · your figure · Your own figure. In the app it is pre-filled from Plan: pension projected to retirement. Allowed: €10,000 to €30,000,000 · steps of €10,000 | F16: 400000 | G16: =IF(AND(ISNUMBER(C16),N(C16)<10000),"",IF(ISBLANK(C16),IF(Fill_Example="Yes",F16,""),C16))
B17: Yearly withdrawal (first year) | D17: € | E17: Type 3 · your figure · Your own figure. Allowed: €1,000 to €2,000,000 · steps of €1,000 | F17: 24000 | G17: =IF(ISBLANK(C17),IF(Fill_Example="Yes",F17,""),C17)
B18: Growth assumption a year (once retired) | D18: % | E18: Type 3 · LifeMap standard · LifeMap uses 3.15% a year after charges once retired (LifeMap Standard set; Cautious 2.8%). Change it if you want to use your own. Allowed: 0% to 7% · steps of 0.05% | F18: =AS_PenRet -> 0.0315 | G18: =IF(ISBLANK(C18),F18,C18) -> 0.0315
B19: Withdrawal taken at the | E19: Type 3 · LifeMap standard · LifeMap uses the start of the year (the prudent choice). Change it if you want to use your own. Allowed: Start of year or End of year | F19: =IF(Set_ddTiming="end","End of year","Start of year") -> Start of year | G19: =IF(ISBLANK(C19),F19,C19) -> Start of year
B20: Your age when withdrawals start | D20: age | E20: Type 3 · your choice (no standard) · You can usually draw a pension from 60 (some occupational schemes from 50); State Pension is paid from 66. Choose your own: there is no default. Allowed: 50 to 90 · steps of 1 | F20: 66 | G20: =IF(ISBLANK(C20),IF(Fill_Example="Yes",F20,""),C20)
B21: Plan to age | D21: age | E21: Type 3 · your choice (no standard) · At 65, average life expectancy in Ireland is about 83 for men and 86 for women (CSO, Irish Life Tables No. 17, 2015–2017). Choose your own: there is no default. Allowed: 85 to 100 · steps of 1 | F21: 90 | G21: =IF(ISBLANK(C21),IF(Fill_Example="Yes",F21,""),C21)
B23: FIGURE USED (statement figure if present, else your figure)
B24: Retirement savings | C24: =IF(NOT(ISBLANK(Stmt_Projected_Fund)),Stmt_Projected_Fund,IF(NOT(ISBLANK(Stmt_Fund_Value)),Stmt_Fund_Value,Retirement_Savings)) | D24: =IF(NOT(ISBLANK(Stmt_Projected_Fund)),"From your statement (projected fund)",IF(NOT(ISBLANK(Stmt_Fund_Value)),"From your statement (fund value today)","Your figure")) -> Your figure | E24: ƒx =IF(NOT(ISBLANK(Stmt_Projected_Fund)),Stmt_Projected_Fund,IF(NOT(ISBLANK(Stmt_Fund_Value)),Stmt_Fund_Value,Retirement_Savings))
B25: Statement date check | C25: =IF(ISBLANK(Stmt_Statement_Date),"",IF(TODAY()-Stmt_Statement_Date>Statement_Max_Age_Days,"Needs a look: statement is more than 12 months old","Up to date")) | E25: ƒx =IF(ISBLANK(Stmt_Statement_Date),"",IF(TODAY()-Stmt_Statement_Date>Statement_Max_Age_Days,"Needs a look: statement is more than 12 months old","Up to date"))
B27: RESULTS | C27: Result | D27: Shown as | E27: Formula
B28: Could last about (full years) | C28: =IF(Need_1<>"",Need_1,IF(Inflation_Choice="","Choose your inflation rate to see this",SUM(W_paid))) -> Choose your yearly withdrawal to see this | D28: =IF(Need_1<>"",Need_1,IF(ISNUMBER(Years_Lasting),IF(Years_Lasting>=Cap_Years,Cap_Years&"+ years",IF(Years_Lasting<1,"Less than a year",Years_Lasting&IF(Years_Lasting=1," year"," years"))),"Choose your inflation rate to see this")) -> Choose your yearly withdrawal to see this | E28: ƒx =IF(Inflation_Choice="","Choose your inflation rate to see this",SUM(W_paid))
B29: Money lasts to about age | C29: =IF(Need_2<>"",Need_2,IF(ISNUMBER(Years_Lasting),IF(Years_Lasting>=Cap_Years,"Beyond "&Plan_To_Age,IF(Years_Lasting<1,"Less than a year",Age_At_Start+Years_Lasting)),"Choose your inflation rate to see this")) -> Choose your yearly withdrawal to see this | D29: =IF(Need_2<>"",Need_2,IF(ISNUMBER(Years_Lasting),IF(Years_Lasting>=Cap_Years,"Beyond "&Plan_To_Age&" (your plan-until age)",IF(Years_Lasting<1,"Less than a year after you start",IF(Age_At_Start+Years_Lasting>=Plan_To_Age,"Lasts to your plan age ("&Plan_To_Age&")","Runs out "&(Plan_To_Age-Age_At_Start-Years_Lasting)&" years before your plan age"))),"Choose your inflation rate to see this")) -> Choose your yearly withdrawal to see this | E29: ƒx =IF(ISNUMBER(Years_Lasting),IF(Years_Lasting>=Cap_Years,"Beyond "&Plan_To_Age&" (your plan-until age)",Age_At_Start+Years_Lasting),"Choose your inflation rate to see this")
B30: Withdrawal rate (first year) | C30: =IF(Need_3<>"",Need_3,Yearly_Withdrawal/Used_Retirement_Savings) -> Choose your yearly withdrawal to see this | D30: % | E30: ƒx =Yearly_Withdrawal/Used_Retirement_Savings
B31: WORKING (one row per year; withdrawal at the start or end of the year, as chosen)
B32: Year | C32: Withdrawal (rises with inflation) | D32: Savings at the start of the year | E32: Paid in full? (1 = yes) | F32: Left at the end of the year
B33: 1 | C33: =IF(Need_1<>"","",Yearly_Withdrawal) | D33: =IF(Need_1<>"","",Used_Retirement_Savings) | E33: =IF(Need_1<>"","",IF(Withdrawal_Timing="Start of year",IF(D33>=C33,1,0),IF(D33*(1+Growth_Rate)>=C33,1,0))) | F33: =IF(Need_1<>"","",IF(E33=1,IF(Withdrawal_Timing="Start of year",(D33-C33)*(1+Growth_Rate),D33*(1+Growth_Rate)-C33),0))
B34: 2 | C34: =IF(Need_1<>"","",C33*(1+Inflation_Choice)) | D34: =IF(Need_1<>"","",F33) | E34: =IF(Need_1<>"","",IF(Withdrawal_Timing="Start of year",IF(D34>=C34,1,0),IF(D34*(1+Growth_Rate)>=C34,1,0))) | F34: =IF(Need_1<>"","",IF(E34=1,IF(Withdrawal_Timing="Start of year",(D34-C34)*(1+Growth_Rate),D34*(1+Growth_Rate)-C34),0))
B35: 3 | C35: =IF(Need_1<>"","",C34*(1+Inflation_Choice)) | D35: =IF(Need_1<>"","",F34) | E35: =IF(Need_1<>"","",IF(Withdrawal_Timing="Start of year",IF(D35>=C35,1,0),IF(D35*(1+Growth_Rate)>=C35,1,0))) | F35: =IF(Need_1<>"","",IF(E35=1,IF(Withdrawal_Timing="Start of year",(D35-C35)*(1+Growth_Rate),D35*(1+Growth_Rate)-C35),0))
B36: 4 | C36: =IF(Need_1<>"","",C35*(1+Inflation_Choice)) | D36: =IF(Need_1<>"","",F35) | E36: =IF(Need_1<>"","",IF(Withdrawal_Timing="Start of year",IF(D36>=C36,1,0),IF(D36*(1+Growth_Rate)>=C36,1,0))) | F36: =IF(Need_1<>"","",IF(E36=1,IF(Withdrawal_Timing="Start of year",(D36-C36)*(1+Growth_Rate),D36*(1+Growth_Rate)-C36),0))
B37: 5 | C37: =IF(Need_1<>"","",C36*(1+Inflation_Choice)) | D37: =IF(Need_1<>"","",F36) | E37: =IF(Need_1<>"","",IF(Withdrawal_Timing="Start of year",IF(D37>=C37,1,0),IF(D37*(1+Growth_Rate)>=C37,1,0))) | F37: =IF(Need_1<>"","",IF(E37=1,IF(Withdrawal_Timing="Start of year",(D37-C37)*(1+Growth_Rate),D37*(1+Growth_Rate)-C37),0))
B38: 6 | C38: =IF(Need_1<>"","",C37*(1+Inflation_Choice)) | D38: =IF(Need_1<>"","",F37) | E38: =IF(Need_1<>"","",IF(Withdrawal_Timing="Start of year",IF(D38>=C38,1,0),IF(D38*(1+Growth_Rate)>=C38,1,0))) | F38: =IF(Need_1<>"","",IF(E38=1,IF(Withdrawal_Timing="Start of year",(D38-C38)*(1+Growth_Rate),D38*(1+Growth_Rate)-C38),0))
B39: 7 | C39: =IF(Need_1<>"","",C38*(1+Inflation_Choice)) | D39: =IF(Need_1<>"","",F38) | E39: =IF(Need_1<>"","",IF(Withdrawal_Timing="Start of year",IF(D39>=C39,1,0),IF(D39*(1+Growth_Rate)>=C39,1,0))) | F39: =IF(Need_1<>"","",IF(E39=1,IF(Withdrawal_Timing="Start of year",(D39-C39)*(1+Growth_Rate),D39*(1+Growth_Rate)-C39),0))
B40: 8 | C40: =IF(Need_1<>"","",C39*(1+Inflation_Choice)) | D40: =IF(Need_1<>"","",F39) | E40: =IF(Need_1<>"","",IF(Withdrawal_Timing="Start of year",IF(D40>=C40,1,0),IF(D40*(1+Growth_Rate)>=C40,1,0))) | F40: =IF(Need_1<>"","",IF(E40=1,IF(Withdrawal_Timing="Start of year",(D40-C40)*(1+Growth_Rate),D40*(1+Growth_Rate)-C40),0))
B41: 9 | C41: =IF(Need_1<>"","",C40*(1+Inflation_Choice)) | D41: =IF(Need_1<>"","",F40) | E41: =IF(Need_1<>"","",IF(Withdrawal_Timing="Start of year",IF(D41>=C41,1,0),IF(D41*(1+Growth_Rate)>=C41,1,0))) | F41: =IF(Need_1<>"","",IF(E41=1,IF(Withdrawal_Timing="Start of year",(D41-C41)*(1+Growth_Rate),D41*(1+Growth_Rate)-C41),0))
B42: 10 | C42: =IF(Need_1<>"","",C41*(1+Inflation_Choice)) | D42: =IF(Need_1<>"","",F41) | E42: =IF(Need_1<>"","",IF(Withdrawal_Timing="Start of year",IF(D42>=C42,1,0),IF(D42*(1+Growth_Rate)>=C42,1,0))) | F42: =IF(Need_1<>"","",IF(E42=1,IF(Withdrawal_Timing="Start of year",(D42-C42)*(1+Growth_Rate),D42*(1+Growth_Rate)-C42),0))
B43: 11 | C43: =IF(Need_1<>"","",C42*(1+Inflation_Choice)) | D43: =IF(Need_1<>"","",F42) | E43: =IF(Need_1<>"","",IF(Withdrawal_Timing="Start of year",IF(D43>=C43,1,0),IF(D43*(1+Growth_Rate)>=C43,1,0))) | F43: =IF(Need_1<>"","",IF(E43=1,IF(Withdrawal_Timing="Start of year",(D43-C43)*(1+Growth_Rate),D43*(1+Growth_Rate)-C43),0))
B44: 12 | C44: =IF(Need_1<>"","",C43*(1+Inflation_Choice)) | D44: =IF(Need_1<>"","",F43) | E44: =IF(Need_1<>"","",IF(Withdrawal_Timing="Start of year",IF(D44>=C44,1,0),IF(D44*(1+Growth_Rate)>=C44,1,0))) | F44: =IF(Need_1<>"","",IF(E44=1,IF(Withdrawal_Timing="Start of year",(D44-C44)*(1+Growth_Rate),D44*(1+Growth_Rate)-C44),0))
B45: 13 | C45: =IF(Need_1<>"","",C44*(1+Inflation_Choice)) | D45: =IF(Need_1<>"","",F44) | E45: =IF(Need_1<>"","",IF(Withdrawal_Timing="Start of year",IF(D45>=C45,1,0),IF(D45*(1+Growth_Rate)>=C45,1,0))) | F45: =IF(Need_1<>"","",IF(E45=1,IF(Withdrawal_Timing="Start of year",(D45-C45)*(1+Growth_Rate),D45*(1+Growth_Rate)-C45),0))
... B92: 60 | C92: =IF(Need_1<>"","",C91*(1+Inflation_Choice)) | D92: =IF(Need_1<>"","",F91) | E92: =IF(Need_1<>"","",IF(Withdrawal_Timing="Start of year",IF(D92>=C92,1,0),IF(D92*(1+Growth_Rate)>=C92,1,0))) | F92: =IF(Need_1<>"","",IF(E92=1,IF(Withdrawal_Timing="Start of year",(D92-C92)*(1+Growth_Rate),D92*(1+Growth_Rate)-C92),0))
B95: HOW IT WORKS
B96: • Each year (start-of-year timing): take the withdrawal, then the rest grows. End-of-year timing: the pot grows, then the withdrawal is taken. The withdrawal rises with inflation each year.
B97: • Years lasting = the number of years the full withdrawal could be paid (the "Paid in full" column).
B98: Edge rules and validation:
B99: • Start of year is the suggested (prudent) timing; end of year is optimistic.
B100: • If the money lasts all 60 years of the table it shows "60+ years".
B101: • Before tax: ARF and vested PRSA withdrawals pay income tax and USC.
B103: ADD TO MY PLAN (what this calculator sends to the plan)
B104: Goal | C104: ="No goal" -> No goal | E104: ƒx ="No goal"
B106: CHOICES STILL NEEDED (helper rows: blank = all inputs a result needs are filled)
B107: Needs: growth rate, inflation rate, Used_Retirement_Savings, withdrawal timing, yearly withdrawal | C107: =IF(Yearly_Withdrawal="","Choose your yearly withdrawal to see this",IF(NOT(ISNUMBER(Used_Retirement_Savings)),IF(Used_Retirement_Savings="",IF(Retirement_Savings="","Choose your retirement savings to see this",""),Used_Retirement_Savings),IF(Age_At_Start="","Choose your age when withdrawals start to see this",IF(Plan_To_Age="","Choose your plan-until age to see this",IF(Inflation_Choice="","Choose your inflation rate to see this",""))))) -> Choose your yearly withdrawal to see this
B108: Needs: retirement age, growth rate, inflation rate, plan-to age, Used_Retirement_Savings, withdrawal timing, yearly withdrawal | C108: =IF(Yearly_Withdrawal="","Choose your yearly withdrawal to see this",IF(NOT(ISNUMBER(Used_Retirement_Savings)),IF(Used_Retirement_Savings="",IF(Retirement_Savings="","Choose your retirement savings to see this",""),Used_Retirement_Savings),IF(Age_At_Start="","Choose your age when withdrawals start to see this",IF(Plan_To_Age="","Choose your plan-until age to see this",IF(Inflation_Choice="","Choose your inflation rate to see this",""))))) -> Choose your yearly withdrawal to see this
B109: Needs: Used_Retirement_Savings, yearly withdrawal | C109: =IF(Yearly_Withdrawal="","Choose your yearly withdrawal to see this",IF(NOT(ISNUMBER(Used_Retirement_Savings)),IF(Used_Retirement_Savings="",IF(Retirement_Savings="","Choose your retirement savings to see this",""),Used_Retirement_Savings),IF(Age_At_Start="","Choose your age when withdrawals start to see this",IF(Plan_To_Age="","Choose your plan-until age to see this","")))) -> Choose your yearly withdrawal to see this

Sheet C16 Drawdown scenarios
B1: C16 · Retirement drawdown scenarios | E1: Category: Pensions & Retirement · prototype id: drawdown
B2: Question it answers: How do different growth rates change things? | E2: =IF(Fill_Example="Yes","Example values are ON (README): grey Example only figures fill blank inputs.","Blank template: fill the yellow inputs (or switch on example values on the README).") -> Blank template: fill the yellow inputs (or switch on example values on the README).
B3: Shows how long your retirement savings could last at three growth rates, with withdrawals rising with prices.
B5: YOUR INFLATION CHOICE | C5: Your figure | D5: Unit | E5: Allowed | F5: Example only (grey; used only when "Fill example values" is Yes)
B6: Inflation you expect (your choice) | D6: % | E6: ="Type 3 · your choice · Generally the standard is 2% a year (ECB target); Ireland's prices are rising "&TEXT(Set_inflNow,"0.0%")&" now (CSO HICP flash, Sep 2026). Choose what you want to use. Allowed: 0% to 10% · steps of 0.25%" -> Type 3 · your choice · Generally the standard is 2% a year (ECB target); Ireland's prices are rising 3.9% now (CSO HICP flash, Sep 2026). Choose what you want to use. Allowed: 0% to 10% · steps of 0.25% | F6: 0.02 | G6: =IF(ISBLANK(C6),IF(Fill_Example="Yes",F6,""),C6)
B7: ="Everyone sees this differently. Ireland's prices are rising "&TEXT(Set_inflNow,"0.0%")&" now (CSO HICP flash, Sep 2026), mostly because of energy. Over decades, 2%–2.5% is the usual planning range (ECB target 2%). Enter 0% if you don't want to adjust for prices." -> Everyone sees this differently. Ireland's prices are rising 3.9% now (CSO HICP flash, Sep 2026), mostly because of energy. Over decades, 2%–2.5% is the usual planning range (ECB target 2%). Enter 0% if you don't want to adjust for prices.
B9: FROM YOUR STATEMENT (filled automatically by the document reader)
B10: Document: Pension benefit statement / Statement of Reasonable Projection. Blank = no statement uploaded, or the figure is not on it. Grey-blue cells are filled by the reader (you can type here to test).
B11: Projected fund at retirement (if shown) | D11: € | E11: Allowed: €0 to €100,000,000 | G11: Reader field: see note
B12: Fund value today | D12: € | E12: Allowed: €0 to €50,000,000 | G12: Reader field: see note
B13: Statement date | D13: date | E13: Allowed: a date (dd/mm/yyyy) | G13: Reader field: see note
B15: OR TYPE IT YOURSELF | C15: Your figure | D15: Unit | E15: Allowed | F15: Example only (grey; used only when "Fill example values" is Yes)
B16: Retirement savings | D16: € | E16: Type 3 · your figure · Your own figure. In the app it is pre-filled from Plan: pension projected to retirement. Allowed: €10,000 to €30,000,000 · steps of €10,000 | F16: 400000 | G16: =IF(ISBLANK(C16),IF(Fill_Example="Yes",F16,""),C16)
B17: Yearly withdrawal (first year) | D17: € | E17: Type 3 · your figure · Your own figure. Allowed: €1,000 to €2,000,000 · steps of €1,000 | F17: 20000 | G17: =IF(ISBLANK(C17),IF(Fill_Example="Yes",F17,""),C17)
B18: Cautious: growth a year | D18: % | E18: Type 3 · LifeMap standard · LifeMap uses 2% a year for a cautious mix (illustration). Change it if you want to use your own. Allowed: 0% to 8% · steps of 0.5% | F18: =Set_riskMu_1 -> 0.02 | G18: =IF(ISBLANK(C18),F18,C18) -> 0.02
B19: Balanced: growth a year | D19: % | E19: Type 3 · LifeMap standard · LifeMap uses 4% a year for a balanced mix (illustration). Change it if you want to use your own. Allowed: 0% to 8% · steps of 0.5% | F19: =Set_riskMu_2 -> 0.04 | G19: =IF(ISBLANK(C19),F19,C19) -> 0.04
B20: Growth: growth a year | D20: % | E20: Type 3 · LifeMap standard · LifeMap uses 6% a year for a growth mix (illustration). Change it if you want to use your own. Allowed: 0% to 8% · steps of 0.5% | F20: =Set_riskMu_3 -> 0.06 | G20: =IF(ISBLANK(C20),F20,C20) -> 0.06
B21: Withdrawal taken at the | E21: Type 3 · LifeMap standard · LifeMap uses the start of the year (the prudent choice). Change it if you want to use your own. Allowed: Start of year or End of year | F21: =IF(Set_ddTiming="end","End of year","Start of year") -> Start of year | G21: =IF(ISBLANK(C21),F21,C21) -> Start of year
B23: FIGURE USED (statement figure if present, else your figure)
B24: Retirement savings | C24: =IF(NOT(ISBLANK(Stmt_Projected_Fund)),Stmt_Projected_Fund,IF(NOT(ISBLANK(Stmt_Fund_Value)),Stmt_Fund_Value,Retirement_Savings)) | D24: =IF(NOT(ISBLANK(Stmt_Projected_Fund)),"From your statement (projected fund)",IF(NOT(ISBLANK(Stmt_Fund_Value)),"From your statement (fund value today)","Your figure")) -> Your figure | E24: ƒx =IF(NOT(ISBLANK(Stmt_Projected_Fund)),Stmt_Projected_Fund,IF(NOT(ISBLANK(Stmt_Fund_Value)),Stmt_Fund_Value,Retirement_Savings))
B25: Statement date check | C25: =IF(ISBLANK(Stmt_Statement_Date),"",IF(TODAY()-Stmt_Statement_Date>Statement_Max_Age_Days,"Needs a look: statement is more than 12 months old","Up to date")) | E25: ƒx =IF(ISBLANK(Stmt_Statement_Date),"",IF(TODAY()-Stmt_Statement_Date>Statement_Max_Age_Days,"Needs a look: statement is more than 12 months old","Up to date"))
B27: RESULTS | C27: Result | D27: Shown as | E27: Formula
B28: Balanced lasts (full years) | C28: =IF(Need_1<>"",Need_1,IF(Inflation_Choice="","Choose your inflation rate to see this",SUM(W_b_paid))) -> Choose your yearly withdrawal to see this | D28: =IF(Need_1<>"",Need_1,IF(ISNUMBER(Years_Balanced),IF(Years_Balanced>=Cap_Years,Cap_Years&"+ years",Years_Balanced&IF(Years_Balanced=1," year"," years")),"Choose your inflation rate to see this")) -> Choose your yearly withdrawal to see this | E28: ƒx =IF(Inflation_Choice="","Choose your inflation rate to see this",SUM(W_b_paid))
B29: Cautious lasts (full years) | C29: =IF(Need_1<>"",Need_1,IF(Inflation_Choice="","Choose your inflation rate to see this",SUM(W_c_paid))) -> Choose your yearly withdrawal to see this | D29: =IF(Need_1<>"",Need_1,IF(ISNUMBER(Years_Cautious),IF(Years_Cautious>=Cap_Years,Cap_Years&"+ years",Years_Cautious&IF(Years_Cautious=1," year"," years")),"Choose your inflation rate to see this")) -> Choose your yearly withdrawal to see this | E29: ƒx =IF(Inflation_Choice="","Choose your inflation rate to see this",SUM(W_c_paid))
B30: Growth lasts (full years) | C30: =IF(Need_1<>"",Need_1,IF(Inflation_Choice="","Choose your inflation rate to see this",SUM(W_g_paid))) -> Choose your yearly withdrawal to see this | D30: =IF(Need_1<>"",Need_1,IF(ISNUMBER(Years_Growth),IF(Years_Growth>=Cap_Years,Cap_Years&"+ years",Years_Growth&IF(Years_Growth=1," year"," years")),"Choose your inflation rate to see this")) -> Choose your yearly withdrawal to see this | E30: ƒx =IF(Inflation_Choice="","Choose your inflation rate to see this",SUM(W_g_paid))
B31: WORKING (one row per year; withdrawal at the start of the year, rising with inflation)
B32: Year | C32: Withdrawal | D32: Cautious: savings at start | E32: Cautious: paid? (1 = yes) | F32: Balanced: savings at start | G32: Balanced: paid? (1 = yes) | H32: Growth: savings at start | I32: Growth: paid? (1 = yes)
B33: 1 | C33: =IF(Need_1<>"","",Yearly_Withdrawal) | D33: =IF(Need_1<>"","",Used_Retirement_Savings) | E33: =IF(Need_1<>"","",IF(Withdrawal_Timing="Start of year",IF(D33>=C33,1,0),IF(D33*(1+DD_Cautious)>=C33,1,0))) | F33: =IF(Need_1<>"","",Used_Retirement_Savings) | G33: =IF(Need_1<>"","",IF(Withdrawal_Timing="Start of year",IF(F33>=C33,1,0),IF(F33*(1+DD_Balanced)>=C33,1,0))) | H33: =IF(Need_1<>"","",Used_Retirement_Savings) | I33: =IF(Need_1<>"","",IF(Withdrawal_Timing="Start of year",IF(H33>=C33,1,0),IF(H33*(1+DD_Growth)>=C33,1,0)))
B34: 2 | C34: =IF(Need_1<>"","",C33*(1+Inflation_Choice)) | D34: =IF(Need_1<>"","",IF(E33=1,IF(Withdrawal_Timing="Start of year",(D33-C33)*(1+DD_Cautious),D33*(1+DD_Cautious)-C33),0)) | E34: =IF(Need_1<>"","",IF(Withdrawal_Timing="Start of year",IF(D34>=C34,1,0),IF(D34*(1+DD_Cautious)>=C34,1,0))) | F34: =IF(Need_1<>"","",IF(G33=1,IF(Withdrawal_Timing="Start of year",(F33-C33)*(1+DD_Balanced),F33*(1+DD_Balanced)-C33),0)) | G34: =IF(Need_1<>"","",IF(Withdrawal_Timing="Start of year",IF(F34>=C34,1,0),IF(F34*(1+DD_Balanced)>=C34,1,0))) | H34: =IF(Need_1<>"","",IF(I33=1,IF(Withdrawal_Timing="Start of year",(H33-C33)*(1+DD_Growth),H33*(1+DD_Growth)-C33),0)) | I34: =IF(Need_1<>"","",IF(Withdrawal_Timing="Start of year",IF(H34>=C34,1,0),IF(H34*(1+DD_Growth)>=C34,1,0)))
B35: 3 | C35: =IF(Need_1<>"","",C34*(1+Inflation_Choice)) | D35: =IF(Need_1<>"","",IF(E34=1,IF(Withdrawal_Timing="Start of year",(D34-C34)*(1+DD_Cautious),D34*(1+DD_Cautious)-C34),0)) | E35: =IF(Need_1<>"","",IF(Withdrawal_Timing="Start of year",IF(D35>=C35,1,0),IF(D35*(1+DD_Cautious)>=C35,1,0))) | F35: =IF(Need_1<>"","",IF(G34=1,IF(Withdrawal_Timing="Start of year",(F34-C34)*(1+DD_Balanced),F34*(1+DD_Balanced)-C34),0)) | G35: =IF(Need_1<>"","",IF(Withdrawal_Timing="Start of year",IF(F35>=C35,1,0),IF(F35*(1+DD_Balanced)>=C35,1,0))) | H35: =IF(Need_1<>"","",IF(I34=1,IF(Withdrawal_Timing="Start of year",(H34-C34)*(1+DD_Growth),H34*(1+DD_Growth)-C34),0)) | I35: =IF(Need_1<>"","",IF(Withdrawal_Timing="Start of year",IF(H35>=C35,1,0),IF(H35*(1+DD_Growth)>=C35,1,0)))
B36: 4 | C36: =IF(Need_1<>"","",C35*(1+Inflation_Choice)) | D36: =IF(Need_1<>"","",IF(E35=1,IF(Withdrawal_Timing="Start of year",(D35-C35)*(1+DD_Cautious),D35*(1+DD_Cautious)-C35),0)) | E36: =IF(Need_1<>"","",IF(Withdrawal_Timing="Start of year",IF(D36>=C36,1,0),IF(D36*(1+DD_Cautious)>=C36,1,0))) | F36: =IF(Need_1<>"","",IF(G35=1,IF(Withdrawal_Timing="Start of year",(F35-C35)*(1+DD_Balanced),F35*(1+DD_Balanced)-C35),0)) | G36: =IF(Need_1<>"","",IF(Withdrawal_Timing="Start of year",IF(F36>=C36,1,0),IF(F36*(1+DD_Balanced)>=C36,1,0))) | H36: =IF(Need_1<>"","",IF(I35=1,IF(Withdrawal_Timing="Start of year",(H35-C35)*(1+DD_Growth),H35*(1+DD_Growth)-C35),0)) | I36: =IF(Need_1<>"","",IF(Withdrawal_Timing="Start of year",IF(H36>=C36,1,0),IF(H36*(1+DD_Growth)>=C36,1,0)))
B37: 5 | C37: =IF(Need_1<>"","",C36*(1+Inflation_Choice)) | D37: =IF(Need_1<>"","",IF(E36=1,IF(Withdrawal_Timing="Start of year",(D36-C36)*(1+DD_Cautious),D36*(1+DD_Cautious)-C36),0)) | E37: =IF(Need_1<>"","",IF(Withdrawal_Timing="Start of year",IF(D37>=C37,1,0),IF(D37*(1+DD_Cautious)>=C37,1,0))) | F37: =IF(Need_1<>"","",IF(G36=1,IF(Withdrawal_Timing="Start of year",(F36-C36)*(1+DD_Balanced),F36*(1+DD_Balanced)-C36),0)) | G37: =IF(Need_1<>"","",IF(Withdrawal_Timing="Start of year",IF(F37>=C37,1,0),IF(F37*(1+DD_Balanced)>=C37,1,0))) | H37: =IF(Need_1<>"","",IF(I36=1,IF(Withdrawal_Timing="Start of year",(H36-C36)*(1+DD_Growth),H36*(1+DD_Growth)-C36),0)) | I37: =IF(Need_1<>"","",IF(Withdrawal_Timing="Start of year",IF(H37>=C37,1,0),IF(H37*(1+DD_Growth)>=C37,1,0)))
