Workbook

Sheet README
A1: LifeGoals calculators: engineering workbook
A2: Version | B2: Version 1.0 · 1 Oct 2026
A3: Source file | B3: LifeGoals-Customer-Journey-Prototype.html (the CALCS array and its helpers fvL, fvA, pmt, payoff, lasts, pensionAt, todayM, inflation via S.infl, the "Adjust for inflation" switch and the Central Bank borrowing rules).
A4: Purpose | B4: An exact, cell-by-cell replica of every calculator in the prototype so the tool engineer can build them in the real system. Each calculator sheet reproduces the prototype's run(v) function step by step, with the same rounding, loop caps and edge rules. Every test case on the "Test cases" sheet was computed by running the prototype's own code in a headless browser and matched by this workbook (see calculator-verification-report.md).
A5: Numbering | B5: C01 to C28, in the exact order of the CALCS array in the prototype. The same numbers are used in the UI/UX designer's Word spec. Sheet tab = C-number + short name.
A6: How to read a calculator sheet | B6: 1. INPUTS: the sliders, with unit, default, min, max (slider), max if typed (euro fields accept up to 10× the slider top), step and where the prototype pre-fills the value from. 2. WHAT-IF INPUTS: the "What if…" card, where the tool has one. 3. CONTEXT INPUTS: other state the function reads (a stated repayment, a pension statement, the "Adjust for inflation" switch). 4. CALCULATION: every intermediate step as its own labelled row, with the JS it mirrors. 5. OUTPUTS: exactly the figures the prototype shows; "Value" is the full-precision number, "As shown in the prototype" is the text the customer sees (same rounding and wording rules), blank when the prototype does not show it. 6. Helper tables (to the right, from column K): one row per month or year for every loop in the JS, to the same cap.
A7: Colour legend | B7: Blue text = input you can change · Yellow fill = key assumption · Black text = formula · Green text = link to another sheet (the Assumptions sheet) · Green fill = output.
A8: Percentages | B8: Stored as fractions (4% = 0.04). The prototype holds most rates as whole percentages (4) and divides by 100; the results are the same.
A9: Inflation | B9: The client's own choice (Assumptions!C6 and C7). Default here: chosen, 2% (long-term standard). 3.5% is Ireland today (CSO, May 2026). With C6 = 0 the workbook behaves like the prototype before the client picks a rate (nominal figures, flat withdrawals).
A10: Growth set | B10: Standard (default) or Cautious, on Assumptions!C8. Only the pay-rise rate is used inside a calculator (C12); the other rates only pre-fill inputs.
A11: Rounding | B11: Money is shown to whole euros as the prototype does (eur(): round the absolute value, then a "−€" sign for negatives). Cells keep full precision. Month counts use yrs(): "N yr(s) M mo", or "M months" under a year.
A12: Functions used | B12: Excel 2007-compatible only: IF, AND, MAX, MIN, ABS, INT, MOD, ROUND, POWER, SQRT, SUM, INDEX, MATCH, FIXED. No XLOOKUP, FILTER, SEQUENCE, LET or LAMBDA. PMT/FV/NPER are not used: the annuity is written out so it matches the JS at 0% too, and loops are explicit tables (no closed-form NPER).
A13: Out of scope | B13: The main plan cashflow and goal-funding engine (project()) is not in this workbook; it is documented separately.
... A15: Sheets | B15: README · Index · Assumptions · C01 Borrowing · C02 Mortgage repayment · C03 Deposit · C04 Mortgage overpayment · C05 Interest rate impact · C06 Term comparison · C07 Rent vs buy · C08 Goal planner · C09 Compound growth · C10 Lump sum growth · C11 Emergency fund · C12 Retirement projection · C13 Contribution impact · C14 AVC impact · C15 Will my money last · C16 Drawdown scenarios · C17 Inflation adjusted return · C18 Regular investing · C19 Fees impact · C20 Risk and return · C21 Life cover · C22 Income protection gap · C23 Mortgage protection · C24 Net worth · C25 Monthly surplus · C26 Budget 50 30 20 · C27 Debt repayment · C28 Loan repayment · Test cases
A17: Legend samples
A18: Input
A19: Key assumption
A20: Formula
A21: Cross-sheet link

Sheet Index
A1: C-number | B1: Sheet | C1: Category | D1: Calculator | E1: Question shown | F1: Inputs (incl. what-if and context) | G1: Outputs
A2: C01 | B2: =HYPERLINK("#'C01 Borrowing'!A1","C01 Borrowing") -> C01 Borrowing | C2: Home & Mortgage | D2: How much could I borrow? | E2: What home price could be within reach? | F2: Your gross income; Partner income; Deposit saved; First-time buyer (1 = yes, 0 = no); Interest rate; Term; [what-if] Save extra towards deposit | G2: Homes up to about; Income multiple used (in the sentence); Limit that sets the amount (in the sentence); Borrowing by income (lti×); Borrowing by deposit (90% LTV); Your deposit; Monthly repayment (illustrative); "Add to my plan" goal amount (Buy a home); "Add to my plan" goal years
A3: C02 | B3: =HYPERLINK("#'C02 Mortgage repayment'!A1","C02 Mortgage repayment") -> C02 Mortgage repayment | C3: Home & Mortgage | D3: Monthly mortgage repayment | E3: What would my monthly repayment be? | F3: Mortgage amount; Interest rate; Term; [what-if] If rates changed by; [context] Stated monthly mortgage repayment (0 = none); [context] Customer has not moved loan, rate or term in this tool (1 = yes) | G3: Headline: monthly repayment (what-if repayment when dr ≠ 0); What-if: change vs now (in the sentence); Formula repayment (when the stated figure differs by ≥ €5); Repayment now; Change over a year; Mortgage free in (months); Total interest; Total repaid; "Add to my plan" goal amount; "Add to my plan" goal years
A4: C03 | B4: =HYPERLINK("#'C03 Deposit'!A1","C03 Deposit") -> C03 Deposit | C4: Home & Mortgage | D4: Deposit calculator | E4: How long until I have my deposit? | F4: Home price; Deposit needed; Saved so far; Monthly saving; [what-if] Save extra each month | G4: Time to your deposit (months); You need (sentence); Saving a month (sentence); Deposit needed; Still to save; "Add to my plan" goal amount (Home deposit); "Add to my plan" goal years
A5: C04 | B5: =HYPERLINK("#'C04 Mortgage overpayment'!A1","C04 Mortgage overpayment") -> C04 Mortgage overpayment | C5: Home & Mortgage | D5: Mortgage overpayment | E5: What if I paid a little extra each month? | F5: Mortgage balance; Interest rate; Years left; Extra each month; [context] Stated monthly mortgage repayment (0 = none); [context] Customer has not moved balance, rate or years in this tool (1 = yes) | G5: Mortgage free sooner by (months); Extra a month (sentence); On top of (repayment now, sentence); Mortgage free now in (months); With the extra (months); Interest saved; "Add to my plan" goal amount (Mortgage free); "Add to my plan" goal years
A6: C05 | B6: =HYPERLINK("#'C05 Interest rate impact'!A1","C05 Interest rate impact") -> C05 Interest rate impact | C6: Home & Mortgage | D6: Interest-rate impact | E6: What if my mortgage rate changed? | F6: Mortgage balance; Current rate; Years left; Rate change; [context] Stated monthly mortgage repayment (0 = none); [context] Customer has not moved balance, rate or years in this tool (1 = yes) | G6: Monthly change; New rate (sentence); Now; After change; Change over a year
A7: C06 | B7: =HYPERLINK("#'C06 Term comparison'!A1","C06 Term comparison") -> C06 Term comparison | C7: Home & Mortgage | D7: Mortgage term comparison | E7: Shorter or longer term: what is the trade-off? | F7: Mortgage amount; Interest rate; Term A; Term B | G7: Interest difference; Shorter term named in the sentence (years); Term A monthly; Term B monthly; Term A total interest; Term B total interest
A8: C07 | B8: =HYPERLINK("#'C07 Rent vs buy'!A1","C07 Rent vs buy") -> C07 Rent vs buy | C8: Home & Mortgage | D8: Rent vs buy | E8: How do renting and buying compare over time? | F8: Monthly rent; Home price; Deposit; Mortgage rate; Years; House price growth | G8: Home equity after the years; Rent paid; Interest + upkeep (buying); Home value; "Add to my plan" goal amount (Buy a home); "Add to my plan" goal years
A9: C08 | B9: =HYPERLINK("#'C08 Goal planner'!A1","C08 Goal planner") -> C08 Goal planner | C9: Savings & Goals | D9: Goal planner | E9: How much a month to reach my goal? | F9: Goal amount (today's prices); Years until the goal; Already saved; Growth / interest | G9: Monthly amount (illustrative); Goal in today's prices; Will cost about (in y yrs); Will cost about (sentence); Already saved; Inflation rate quoted (sentence); "Add to my plan" goal amount (My goal); "Add to my plan" goal years
A10: C09 | B10: =HYPERLINK("#'C09 Compound growth'!A1","C09 Compound growth") -> C09 Compound growth | C10: Savings & Goals | D10: Compound growth | E10: What could regular saving grow into? | F10: Starting amount; Monthly addition; Growth rate; Years | G10: Could grow to; Paid in; Illustrative growth; Worth in today's money (prices rising [inflation] a year); Worth about … in today's money (sentence); "Add to my plan" goal amount (Build wealth); "Add to my plan" goal years
A11: C10 | B11: =HYPERLINK("#'C10 Lump sum growth'!A1","C10 Lump sum growth") -> C10 Lump sum growth | C11: Investments | D11: Lump-sum growth | E11: What could a one-off amount become? | F11: Amount; Growth rate; Years; Yearly fees; [context] "Adjust for inflation" switch (1 = on) | G11: Headline figure; Real return a year (sentence); Growth after fees quoted (sentence); Cost of waiting (sentence); If you start today; If you start in 5 years; Worth in today's money (prices rising [inflation] a year); Fees cost; "Add to my plan" goal amount (Build wealth); "Add to my plan" goal years
A12: C11 | B12: =HYPERLINK("#'C11 Emergency fund'!A1","C11 Emergency fund") -> C11 Emergency fund | C12: Savings & Goals | D12: Emergency fund | E12: How strong is my financial cushion? | F12: Essential monthly spending; Months you want covered; Easy-access savings | G12: You currently have (months); Your target is (sentence); You are … away (sentence); Target cushion; Still to build; "Add to my plan" goal amount (Emergency fund); "Add to my plan" goal years
A13: C12 | B13: =HYPERLINK("#'C12 Retirement projection'!A1","C12 Retirement projection") -> C12 Retirement projection | C13: Pensions & Retirement | D13: Retirement projection | E13: Could your current path fund the retirement you want? | F13: Your age; Target retirement age; Pension value today; Monthly contributions; Desired yearly income; Other yearly income (e.g. State Pension); Growth after charges; [what-if] Retire later by; [what-if] Save more each month; [what-if] Spend less in retirement (per year); [context] Pension statement projection available (1 = yes); [context] Statement's projected fund; [context] Statement's retirement age; [context] Customer has not moved pot, contributions, growth or age in this tool (1 = yes) | G13: Projected fund; Illustrative gap of (sentence); Pay rise quoted (sentence); Illustrative target (25 × the income you need); Illustrative gap; Retiring at; Worth in today's money (prices rising [inflation] a year); Your statement projects (age nra); On our assumptions (age ra); "Add to my plan" goal amount (Comfortable retirement); "Add to my plan" goal years
A14: C13 | B14: =HYPERLINK("#'C13 Contribution impact'!A1","C13 Contribution impact") -> C13 Contribution impact | C14: Pensions & Retirement | D14: Contribution impact | E14: What difference would a small increase make? | F14: Salary; Increase contributions by; Years to retirement; Growth assumption; Your tax rate | G14: Could add to your pension; Extra per month; Cost after tax relief; Worth in today's money (prices rising [inflation] a year); "Add to my plan" goal amount (Boost my pension); "Add to my plan" goal years
A15: C14 | B15: =HYPERLINK("#'C14 AVC impact'!A1","C14 AVC impact") -> C14 AVC impact | C15: Pensions & Retirement | D15: AVC impact | E15: What could extra voluntary contributions add? | F15: AVC per month; Years to retirement; Growth assumption; Your tax rate | G15: Could add; Each AVC could cost about (sentence); Paid in; Net cost to you; Worth in today's money (prices rising [inflation] a year); "Add to my plan" goal amount (Boost my pension); "Add to my plan" goal years
A16: C15 | B16: =HYPERLINK("#'C15 Will my money last'!A1","C15 Will my money last") -> C15 Will my money last | C16: Pensions & Retirement | D16: Will my money last? | E16: How long could my retirement savings last? | F16: Retirement savings; Yearly withdrawal; Growth assumption | G16: Could last about (years); Withdrawing a year (sentence); Withdrawals rise with prices at (sentence); Withdrawal rate
A17: C16 | B17: =HYPERLINK("#'C16 Drawdown scenarios'!A1","C16 Drawdown scenarios") -> C16 Drawdown scenarios | C17: Pensions & Retirement | D17: Retirement drawdown scenarios | E17: How do different growth rates change things? | F17: Retirement savings; Yearly withdrawal | G17: Balanced scenario lasts (years); Cautious (2%); Balanced (4%); Growth (6%); Withdrawals rise with prices at (sentence)
A18: C17 | B18: =HYPERLINK("#'C17 Inflation adjusted return'!A1","C17 Inflation adjusted return") -> C17 Inflation adjusted return | C18: Investments | D18: Inflation-adjusted return | E18: What is my money really worth in future? | F18: Amount; Nominal return; Years | G18: Headline figure; Future value; Real return a year; Value in today's money; Real return (sentence, 1 dp)
A19: C18 | B19: =HYPERLINK("#'C18 Regular investing'!A1","C18 Regular investing") -> C18 Regular investing | C19: Investments | D19: Regular investing | E19: What could investing monthly build? | F19: Monthly amount; Years; Growth assumption; Yearly fees; [context] "Adjust for inflation" switch (1 = on) | G19: Headline figure; Real return a year (sentence); Growth after fees quoted (sentence); Fees quoted (sentence); Fees could cost (sentence); Paid in; Before fees; Fees cost; Worth in today's money (prices rising [inflation] a year); "Add to my plan" goal amount (Build wealth); "Add to my plan" goal years
A20: C19 | B20: =HYPERLINK("#'C19 Fees impact'!A1","C19 Fees impact") -> C19 Fees impact | C20: Investments | D20: Fees impact | E20: How much do fees really cost over time? | F20: Amount invested; Years; Growth before fees; Fee A; Fee B | G20: Difference; Fee difference quoted (sentence); With fee A; With fee B
A21: C20 | B21: =HYPERLINK("#'C20 Risk and return'!A1","C20 Risk and return") -> C20 Risk and return | C21: Investments | D21: Risk & return simulator | E21: What range of outcomes might each style have? | F21: Amount; Years; Style: 1 Cautious · 2 Balanced · 3 Growth | G21: Middle outcome (headline); A difficult year could see a fall of (sentence, %); Weaker outcome; Middle outcome; Stronger outcome
A22: C21 | B22: =HYPERLINK("#'C21 Life cover'!A1","C21 Life cover") -> C21 Life cover | C22: Protection | D22: Life cover estimator | E22: How much cover might my family need? | F22: Your yearly income; Years your family would need support; Mortgage balance; Other debts; Savings & investments; Existing cover (incl. work) | G22: Illustrative cover gap; Income replacement (60%); Debts to clear; Existing cover + savings; "Add to my plan" goal amount (Protect my family); "Add to my plan" goal years
A23: C22 | B23: =HYPERLINK("#'C22 Income protection gap'!A1","C22 Income protection gap") -> C22 Income protection gap | C23: Protection | D23: Income protection gap | E23: How long could I cope if I couldn't work? | F23: Essential monthly spending; Months of sick pay from work; Easy-access savings | G23: You could cope for about (months); Gap a month afterwards (sentence); Sick pay; Savings would cover; "Add to my plan" goal amount (Protect my income); "Add to my plan" goal years
A24: C23 | B24: =HYPERLINK("#'C23 Mortgage protection'!A1","C23 Mortgage protection") -> C23 Mortgage protection | C24: Protection | D24: Mortgage protection | E24: What cover would clear my mortgage? | F24: Mortgage balance; Interest rate; Years left; [context] Stated monthly mortgage repayment (0 = none); [context] Customer has not moved balance, rate or years in this tool (1 = yes) | G24: Cover needed today; Repaying a month (sentence); In 5 years; In 10 years; In 15 years
A25: C24 | B25: =HYPERLINK("#'C24 Net worth'!A1","C24 Net worth") -> C24 Net worth | C25: Everyday Money | D25: Net worth | E25: What am I worth, all in? | F25: Savings; Investments; Pensions; Property value; Mortgage; Other loans | G25: Your net worth; You own; You owe
A26: C25 | B26: =HYPERLINK("#'C25 Monthly surplus'!A1","C25 Monthly surplus") -> C25 Monthly surplus | C26: Everyday Money | D26: Monthly surplus | E26: What is left at the end of the month? | F26: Take-home pay per month; Essentials (rent/mortgage, bills, food); Lifestyle spending; Debt repayments | G26: Monthly surplus; % of take-home free for goals (sentence); Take-home; Going out; "Add to my plan" goal amount (Save my surplus); "Add to my plan" goal years
A27: C26 | B27: =HYPERLINK("#'C26 Budget 50 30 20'!A1","C26 Budget 50 30 20") -> C26 Budget 50 30 20 | C27: Everyday Money | D27: Budget (50/30/20) | E27: A simple way to split your pay | F27: Take-home pay per month | G27: Save each month; Needs (50%); Wants (30%); Savings & debt (20%)
A28: C27 | B28: =HYPERLINK("#'C27 Debt repayment'!A1","C27 Debt repayment") -> C27 Debt repayment | C28: Everyday Money | D28: Debt repayment | E28: How fast can I clear my debt? | F28: Balance; Interest (APR); Monthly payment; [what-if] Pay extra each month | G28: Debt free in (months); You would pay about … in interest (sentence); Total interest; "Add to my plan" goal amount (Debt free); "Add to my plan" goal years
A29: C28 | B29: =HYPERLINK("#'C28 Loan repayment'!A1","C28 Loan repayment") -> C28 Loan repayment | C29: Everyday Money | D29: Loan repayment | E29: What would a loan cost me? | F29: Loan amount; Interest (APR); Years | G29: Monthly repayment; Total interest (sentence); Total repaid

Sheet Assumptions
A1: Assumptions and constants used by the calculators
A2: Every rate, rule and constant a calculator uses sits in its own cell here and is referenced by the calculator sheets (green text there = a link to this sheet). Blue text on yellow = a key assumption you can change. Black = formula.
A4: CLIENT'S CHOICES (change these; every calculator sheet links here)
A5: Key | B5: Assumption | C5: Value | D5: Unit | F5: Source / note
A6: infl_on | B6: Client has chosen an inflation rate (1 = yes, 0 = not chosen yet) | C6: 1 | D6: flag | F6: Prototype state S.infl (null until the client picks). While 0, tools show nominal figures and prompt "Pick an inflation rate"; withdrawals stay flat.
A7: infl | B7: Inflation rate (the client's choice) | C7: 0.02 | D7: % | F7: Client's choice (S.infl): 2% = long-term standard; 3.5% = Ireland today (LifeGoals-Customer-Journey-Prototype.html: INFL_IE, CSO May 2026); or "Other" 0–10%. Default here 2%.
A8: set | B8: Growth assumptions set (Standard or Cautious) | C8: Standard | D8: text | F8: Client's choice (S.assume): Standard (default) or Cautious (the Financial Planner's set). AS_SETS in the prototype.
A10: INFLATION REFERENCE
A11: Key | B11: Assumption | C11: Value | D11: Unit | F11: Source / note
A12: infl_std | B12: Long-term standard inflation (also the internal fallback before the client chooses) | C12: 0.02 | D12: % | F12: INFL_STD = 0.02: planners' long-term standard (2% a year).
A13: infl_ie | B13: Ireland inflation today | C13: 0.035 | D13: % | F13: INFL_IE = 0.035: Ireland today, CSO, May 2026 (INFL_SRC).
A14: infl_eff | B14: Inflation used in calculations (AS.infl) | C14: =IF($C$6=1,$C$7,$C$12) -> 0.02 | D14: % | F14: applyAssume(): AS.infl = S.infl if chosen, else INFL_STD.
A16: GROWTH ASSUMPTIONS BY SET (AS_SETS)
A17: Key | B17: Rate | C17: Standard | D17: Cautious | E17: Active (selected set) | F17: Source / note
A18: wage | B18: Pay rises a year (retirement tool: contributions rise with pay) | C18: 0.025 | D18: 0.03 | E18: =INDEX(C18:D18,MATCH($C$8,$C$17:$D$17,0)) -> 0.025 | F18: LifeGoals-Customer-Journey-Prototype.html: AS_SETS.standard.wage / AS_SETS.cautious.wage
A19: cash | B19: Cash savings growth after tax (plan only; not used by a calculator) | C19: 0.01 | D19: 0.007 | E19: =INDEX(C19:D19,MATCH($C$8,$C$17:$D$17,0)) -> 0.01 | F19: LifeGoals-Customer-Journey-Prototype.html: AS_SETS.standard.cash / AS_SETS.cautious.cash
A20: inv | B20: Investment growth after charges and tax (plan only) | C20: 0.045 | D20: 0.03 | E20: =INDEX(C20:D20,MATCH($C$8,$C$17:$D$17,0)) -> 0.045 | F20: LifeGoals-Customer-Journey-Prototype.html: AS_SETS.standard.inv / AS_SETS.cautious.inv
A21: pen | B21: Pension growth after charges (pre-fills the growth input of retirement, contribution and AVC tools) | C21: 0.045 | D21: 0.04 | E21: =INDEX(C21:D21,MATCH($C$8,$C$17:$D$17,0)) -> 0.045 | F21: LifeGoals-Customer-Journey-Prototype.html: AS_SETS.standard.pen / AS_SETS.cautious.pen
A22: penRet | B22: Pension growth once retired (pre-fills "Will my money last?") | C22: 0.0315 | D22: 0.028 | E22: =INDEX(C22:D22,MATCH($C$8,$C$17:$D$17,0)) -> 0.0315 | F22: LifeGoals-Customer-Journey-Prototype.html: AS_SETS.standard.penRet / AS_SETS.cautious.penRet
A24: CENTRAL BANK OF IRELAND MORTGAGE MEASURES (C01 How much could I borrow?)
A25: Key | B25: Assumption | C25: Value | D25: Unit | F25: Source / note
A26: lti_ftb | B26: Loan-to-income limit, first-time buyers | C26: 4 | D26: n | F26: Central Bank of Ireland mortgage measures (from 1 Jan 2023): 4× gross income for first-time buyers. https://www.centralbank.ie/news/article/central-bank-announces-targeted-changes-to-mortgage-measures-framework
A27: lti_ssb | B27: Loan-to-income limit, second and subsequent buyers | C27: 3.5 | D27: n | F27: Central Bank of Ireland: 3.5× gross income for second and subsequent buyers. https://www.centralbank.ie/news/article/central-bank-announces-targeted-changes-to-mortgage-measures-framework
A28: ltv | B28: Loan-to-value limit (all buyers) | C28: 0.9 | D28: % | F28: Central Bank of Ireland: 90% LTV for first-time and second and subsequent buyers (10% deposit). https://www.centralbank.ie/news/article/central-bank-announces-targeted-changes-to-mortgage-measures-framework
A29: dep_mult | B29: Loan allowed per €1 of deposit at that LTV | C29: =ROUND(C28/(1-C28),10) -> 9 | D29: n | F29: LTV ÷ (1 − LTV) = 9. The prototype hard-codes dep × 9.
A31: FIGURES USED ONLY TO PRE-FILL INPUTS (calcPre; for the engineer's data mapping)
A32: Key | B32: Assumption | C32: Value | D32: Unit | F32: Source / note
A33: pen_typ_chg | B33: Typical pension charges already inside the pension growth rate | C33: 0.01 | D33: % | F33: PEN_TYP_CHG: growth = set rate + 1% − the statement's charges, if a statement gives them.
A34: sp | B34: State Pension a year | C34: 15564 | D34: € | F34: AS.sp: €15,564 a year from age 66. Retirement tool "Other yearly income" = Math.round(State Pension × entitlement factor).
A35: sp_full | B35: State Pension entitlement factor: "Expect full" | C35: 1 | D35: n | F35: finNums().sp
A36: sp_partly | B36: State Pension entitlement factor: "Partly" | C36: 0.6 | D36: n | F36: finNums().sp
A37: sp_notsure | B37: State Pension entitlement factor: "Not sure"/not given | C37: 0.8 | D37: n | F37: finNums().sp
A38: tx_band | B38: Standard-rate income tax band (single) | C38: 44000 | D38: € | F38: TX.band 2026: tax-rate input pre-fills 40% if income > €44,000, else 20%.
A40: CALCULATOR CONSTANTS (hard-coded in the prototype; one cell each)
A41: Key | B41: Assumption | C41: Value | D41: Unit | F41: Source / note
A42: payoff_cap | B42: payoff(): maximum months in the loop | C42: 1200 | D42: n | F42: LifeGoals-Customer-Journey-Prototype.html CALCS: payoff(): while (bal > 0.005 && m < 1200). Used by C02, C04, C27.
A43: payoff_tol | B43: payoff(): balance treated as paid off at or below | C43: 0.005 | D43: € | F43: LifeGoals-Customer-Journey-Prototype.html CALCS: payoff(): ignores a rounding cent so an exact repayment ends on the term.
A44: lasts_cap | B44: lasts(): maximum years in the loop ("60+") | C44: 60 | D44: n | F44: LifeGoals-Customer-Journey-Prototype.html CALCS: lasts(): while (y < 60). Used by C15, C16.
A45: diff_min | B45: Show the formula repayment when the stated one differs by at least | C45: 5 | D45: € | F45: LifeGoals-Customer-Journey-Prototype.html CALCS: repayment: Math.abs(own - calc) >= 5
A46: rb_term | B46: Rent vs buy: mortgage term (years) | C46: 30 | D46: n | F46: LifeGoals-Customer-Journey-Prototype.html CALCS: rentbuy: pmt(loan, v.rate, 30)
A47: rb_upkeep | B47: Rent vs buy: upkeep a year, % of price | C47: 0.01 | D47: % | F47: LifeGoals-Customer-Journey-Prototype.html CALCS: rentbuy: v.price * 0.01 * v.y
A48: lump_wait | B48: Lump-sum growth: years of waiting ("cost of waiting") | C48: 5 | D48: n | F48: LifeGoals-Customer-Journey-Prototype.html CALCS: lumpsum: Math.max(0, v.y - 5)
A49: ret_mult | B49: Retirement: target = yearly income needed × | C49: 25 | D49: n | F49: LifeGoals-Customer-Journey-Prototype.html CALCS: retirement: Math.max(0, d - less - o) * 25
A50: life_repl | B50: Life cover: income replacement | C50: 0.6 | D50: % | F50: LifeGoals-Customer-Journey-Prototype.html CALCS: lifecover: v.inc * 0.6 * v.y
A51: dd_g1 | B51: Drawdown scenarios: Cautious growth | C51: 0.02 | D51: % | F51: LifeGoals-Customer-Journey-Prototype.html CALCS: drawdown: [2,4,6]
A52: dd_g2 | B52: Drawdown scenarios: Balanced growth | C52: 0.04 | D52: % | F52: LifeGoals-Customer-Journey-Prototype.html CALCS: drawdown: [2,4,6]
A53: dd_g3 | B53: Drawdown scenarios: Growth growth | C53: 0.06 | D53: % | F53: LifeGoals-Customer-Journey-Prototype.html CALCS: drawdown: [2,4,6]
... A59: rr_vol3 | B59: Risk & return: Growth volatility | C59: 0.16 | D59: % | F59: LifeGoals-Customer-Journey-Prototype.html CALCS: riskreturn
A60: rr_name1 | B60: Risk & return: style 1 name | C60: Cautious | D60: text | F60: LifeGoals-Customer-Journey-Prototype.html CALCS: riskreturn
A61: rr_name2 | B61: Risk & return: style 2 name | C61: Balanced | D61: text | F61: LifeGoals-Customer-Journey-Prototype.html CALCS: riskreturn
A62: rr_name3 | B62: Risk & return: style 3 name | C62: Growth | D62: text | F62: LifeGoals-Customer-Journey-Prototype.html CALCS: riskreturn
A63: rr_fall | B63: Risk & return: difficult-year fall = volatility × | C63: 1.6 | D63: n | F63: LifeGoals-Customer-Journey-Prototype.html CALCS: riskreturn: Math.round(vol * 1.6)
A64: bud_needs | B64: Budget: needs | C64: 0.5 | D64: % | F64: LifeGoals-Customer-Journey-Prototype.html CALCS: budget: 50/30/20
A65: bud_wants | B65: Budget: wants | C65: 0.3 | D65: % | F65: LifeGoals-Customer-Journey-Prototype.html CALCS: budget
A66: bud_save | B66: Budget: savings and debt | C66: 0.2 | D66: % | F66: LifeGoals-Customer-Journey-Prototype.html CALCS: budget
A67: mp_y1 | B67: Mortgage protection: checkpoint 1 (years) | C67: 5 | D67: n | F67: LifeGoals-Customer-Journey-Prototype.html CALCS: mortgageprotect: after(5)
A68: mp_y2 | B68: Mortgage protection: checkpoint 2 (years) | C68: 10 | D68: n | F68: LifeGoals-Customer-Journey-Prototype.html CALCS: mortgageprotect: after(10)
A69: mp_y3 | B69: Mortgage protection: checkpoint 3 (years) | C69: 15 | D69: n | F69: LifeGoals-Customer-Journey-Prototype.html CALCS: mortgageprotect: after(15)
A70: home_goal_pct | B70: "Add to my plan" (borrow): home goal = % of price | C70: 0.1 | D70: % | F70: LifeGoals-Customer-Journey-Prototype.html CALCS: borrow: Math.round(price * 0.1)
A71: home_goal_years | B71: "Add to my plan": home goal years (borrow, repayment, rent vs buy) | C71: 3 | D71: n | F71: LifeGoals-Customer-Journey-Prototype.html CALCS: goal years:3
A72: em_goal_years | B72: "Add to my plan": emergency fund goal years | C72: 2 | D72: n | F72: LifeGoals-Customer-Journey-Prototype.html CALCS: emergency: years:2
A73: protect_goal_years | B73: "Add to my plan": protection goal years | C73: 1 | D73: n | F73: LifeGoals-Customer-Journey-Prototype.html CALCS: lifecover / incomegap: years:1
A74: surplus_goal_years | B74: "Add to my plan": save my surplus goal years | C74: 1 | D74: n | F74: LifeGoals-Customer-Journey-Prototype.html CALCS: surplus: years:1
A75: debt_goal_min_years | B75: "Add to my plan": minimum debt goal years | C75: 1 | D75: n | F75: LifeGoals-Customer-Journey-Prototype.html CALCS: debtpay: Math.max(1, ...)

Sheet C01 Borrowing
A1: C01 · How much could I borrow?
A2: Question shown: "What home price could be within reach?" · Category: Home & Mortgage · Prototype id: borrow
A3: Replicates: CALCS 'borrow' run(v); helper pmt(P, r, y).
A4: Edge rules: Income multiple: 4× for first-time buyers (ftb ≠ 0), 3.5× otherwise. Loan = the lower of income × multiple and deposit × 9 (90% LTV). When the two limits are equal the text says the income limit sets the amount (JS: byDep < byInc). pmt() uses the monthly rate r/12 and, at 0%, P/n.
A5: Legend: blue = input (change these) · black = formula · green = link to the Assumptions sheet · yellow fill = key assumption. Money cells show whole euros but keep full precision, as the prototype does.
A8: INPUTS
A9: Input | B9: Value | C9: Unit | D9: Default | E9: Min | F9: Max (slider) | G9: Max if typed | H9: Step | I9: Pre-filled from (if the prototype pre-fills it)
A10: Your gross income | B10: 60000 | C10: € | D10: 60000 | E10: 15000 | F10: 250000 | G10: 2500000 | H10: 1000 | I10: Your finances: your income (if given)
A11: Partner income | B11: 0 | C11: € | D11: 0 | E11: 0 | F11: 250000 | G11: 2500000 | H11: 1000 | I11: Your finances: partner's income (if given)
A12: Deposit saved | B12: 25000 | C12: € | D12: 25000 | E12: 0 | F12: 200000 | G12: 2000000 | H12: 1000 | I12: Plan: the home goal's amount already saved (if any)
A13: First-time buyer (1 = yes, 0 = no) | B13: 1 | D13: 1 | E13: 0 | F13: 1 | G13: 1 | H13: 1 | I13: Your finances: home status (owns a home → 0, otherwise 1)
A14: Interest rate | B14: 0.04 | C14: % (stored as a fraction) | D14: 0.04 | E14: 0.01 | F14: 0.08 | G14: 0.08 | H14: 0.001
A15: Term | B15: 30 | C15: years | D15: 30 | E15: 10 | F15: 35 | G15: 35 | H15: 1
A17: WHAT-IF INPUTS (the "What if…" card)
A18: Input | B18: Value | C18: Unit | D18: Default | E18: Min | F18: Max (slider) | G18: Max if typed | H18: Step | I18: Pre-filled from (if the prototype pre-fills it)
A19: Save extra towards deposit | B19: 0 | C19: € | D19: 0 | E19: 0 | F19: 50000 | G19: 500000 | H19: 1000
A21: CALCULATION
A22: Calculation step | B22: Value | C22: Unit | D22: JS equivalent (prototype run function)
A23: Income multiple (Central Bank limit) | B23: =IF($B$13<>0,Assumptions!$C$26,Assumptions!$C$27) -> 4 | C23: n | D23: lti = v.ftb ? 4 : 3.5
A24: Deposit incl. what-if extra | B24: =$B$12+$B$19 -> 25000 | C24: € | D24: dep = v.dep + (v.xdep || 0)
A25: Borrowing by income | B25: =($B$10+$B$11)*$B$23 -> 240000 | C25: € | D25: byInc = (v.inc + v.inc2) * lti
A26: Borrowing by deposit (90% LTV) | B26: =$B$24*Assumptions!$C$29 -> 225000 | C26: € | D26: byDep = dep * 9
A27: Loan (lower of the two) | B27: =MIN($B$25,$B$26) -> 225000 | C27: € | D27: loan = Math.min(byInc, byDep)
A28: Home price within reach | B28: =$B$27+$B$24 -> 250000 | C28: € | D28: price = loan + dep
A29: Monthly interest rate | B29: =$B$14/12 -> 0.0033333333 | C29: rate (fraction) | D29: i = r / 100 / 12
A30: Number of monthly payments | B30: =$B$15*12 -> 360 | C30: n | D30: n = y * 12
A31: Monthly repayment (illustrative) | B31: =IF(($B$30)=0,0,IF($B$29<>0,$B$27*$B$29/(1-POWER(1+$B$29,-($B$30))),$B$27/($B$30))) -> 1074.1844 | C31: € | D31: pmt(loan, v.rate, v.term)
A32: Which limit sets the amount | B32: =IF($B$26<$B$25,"deposit","income limit") -> deposit | C32: text | D32: byDep < byInc ? 'deposit' : 'income limit'
A34: OUTPUTS
A35: Output | B35: Value | C35: As shown in the prototype | D35: Shown when / where it appears
A36: Headline label | C36: ="Homes up to about" -> Homes up to about | D36: Always
A37: Homes up to about | B37: =$B$28 -> 250000 | C37: =IF(($B$28)<0,"−€","€")&FIXED(ROUND(ABS($B$28),0),0) -> €250,000 | D37: Headline figure
A38: Income multiple used (in the sentence) | B38: =$B$23 -> 4 | C38: =$B$23&"" -> 4 | D38: Sentence
A39: Limit that sets the amount (in the sentence) | C39: =$B$32 -> deposit | D39: Sentence
A40: Borrowing by income (lti×) | B40: =$B$25 -> 240000 | C40: =IF(($B$25)<0,"−€","€")&FIXED(ROUND(ABS($B$25),0),0) -> €240,000 | D40: Row 1
A41: Borrowing by deposit (90% LTV) | B41: =$B$26 -> 225000 | C41: =IF(($B$26)<0,"−€","€")&FIXED(ROUND(ABS($B$26),0),0) -> €225,000 | D41: Row 2
A42: Your deposit | B42: =$B$24 -> 25000 | C42: =IF(($B$24)<0,"−€","€")&FIXED(ROUND(ABS($B$24),0),0) -> €25,000 | D42: Row 3
A43: Monthly repayment (illustrative) | B43: =$B$31 -> 1074.1844 | C43: =IF(($B$31)<0,"−€","€")&FIXED(ROUND(ABS($B$31),0),0) -> €1,074 | D43: Row 4
A44: "Add to my plan" goal amount (Buy a home) | B44: =INT(($B$28*Assumptions!$C$70)+0.5) -> 25000 | C44: =$B$44&"" -> 25000 | D44: Add to my plan: Math.round(price × 10%)
A45: "Add to my plan" goal years | B45: =Assumptions!$C$71 -> 3 | C45: =$B$45&"" -> 3 | D45: Add to my plan

Sheet C02 Mortgage repayment
A1: C02 · Monthly mortgage repayment
A2: Question shown: "What would my monthly repayment be?" · Category: Home & Mortgage · Prototype id: repayment
A3: Replicates: CALCS 'repayment' run(v); helpers pmt(), payoff(), mine(), statedM().
A4: Edge rules: Uses the customer's stated repayment (statement or typed) instead of the formula while loan, rate and term are untouched. With a what-if rate change (dr ≠ 0) the result is base + pmt(new rate) − pmt(rate) and the payoff rows are hidden. payoff(): month-by-month to 1,200 months; stops when balance ≤ €0.005; returns Infinity ("Not at this repayment") as soon as the payment ≤ that month's interest.
A5: Legend: blue = input (change these) · black = formula · green = link to the Assumptions sheet · yellow fill = key assumption. Money cells show whole euros but keep full precision, as the prototype does. | K5: One row per month, capped at 1,200 months like the JS loop.
K6: Payoff of the mortgage at the current repayment: payoff(v.loan, v.rate, base)
K7: Month | L7: Loop runs this month (bal > 0.005, month ≤ cap, not stopped) | M7: Opening balance | N7: Interest (bal × i) | O7: Closing balance (bal + it − pay) | P7: Payment ≤ interest: never pays off (1) | Q7: Cumulative interest
A8: INPUTS | K8: 1 | L8: =IF(AND(K8<=Assumptions!$C$42,$B$10>Assumptions!$C$43),1,0) -> 1 | M8: =$B$10 -> 300000 | N8: =IF(L8=1,M8*$B$25,0) -> 1000 | O8: =IF(L8=1,M8+N8-$B$29,M8) -> 299567.75 | P8: =IF(L8=1,IF($B$29<=N8,1,0),0) -> 0 | Q8: =N8 -> 1000
A9: Input | B9: Value | C9: Unit | D9: Default | E9: Min | F9: Max (slider) | G9: Max if typed | H9: Step | I9: Pre-filled from (if the prototype pre-fills it) | K9: =K8+1 -> 2 | L9: =IF(AND(K9<=Assumptions!$C$42,L8=1,P8=0,O8>Assumptions!$C$43),1,0) -> 1 | M9: =O8 -> 299567.75 | N9: =IF(L9=1,M9*$B$25,0) -> 998.55918 | O9: =IF(L9=1,M9+N9-$B$29,M9) -> 299134.07 | P9: =IF(L9=1,IF($B$29<=N9,1,0),0) -> 0 | Q9: =Q8+N9 -> 1998.5592
A10: Mortgage amount | B10: 300000 | C10: € | D10: 300000 | E10: 50000 | F10: 1000000 | G10: 10000000 | H10: 1000 | I10: Your finances or mortgage statement: mortgage balance (if you have a mortgage) | K10: =K9+1 -> 3 | L10: =IF(AND(K10<=Assumptions!$C$42,L9=1,P9=0,O9>Assumptions!$C$43),1,0) -> 1 | M10: =O9 -> 299134.07 | N10: =IF(L10=1,M10*$B$25,0) -> 997.11356 | O10: =IF(L10=1,M10+N10-$B$29,M10) -> 298698.94 | P10: =IF(L10=1,IF($B$29<=N10,1,0),0) -> 0 | Q10: =Q9+N10 -> 2995.6727
A11: Interest rate | B11: 0.04 | C11: % (stored as a fraction) | D11: 0.04 | E11: 0.01 | F11: 0.08 | G11: 0.08 | H11: 0.0005 | I11: Your finances or mortgage statement: mortgage rate | K11: =K10+1 -> 4 | L11: =IF(AND(K11<=Assumptions!$C$42,L10=1,P10=0,O10>Assumptions!$C$43),1,0) -> 1 | M11: =O10 -> 298698.94 | N11: =IF(L11=1,M11*$B$25,0) -> 995.66312 | O11: =IF(L11=1,M11+N11-$B$29,M11) -> 298262.35 | P11: =IF(L11=1,IF($B$29<=N11,1,0),0) -> 0 | Q11: =Q10+N11 -> 3991.3359
A12: Term | B12: 30 | C12: years | D12: 30 | E12: 5 | F12: 35 | G12: 35 | H12: 1 | I12: Your finances or mortgage statement: years left (25 if not given) | K12: =K11+1 -> 5 | L12: =IF(AND(K12<=Assumptions!$C$42,L11=1,P11=0,O11>Assumptions!$C$43),1,0) -> 1 | M12: =O11 -> 298262.35 | N12: =IF(L12=1,M12*$B$25,0) -> 994.20784 | O12: =IF(L12=1,M12+N12-$B$29,M12) -> 297824.31 | P12: =IF(L12=1,IF($B$29<=N12,1,0),0) -> 0 | Q12: =Q11+N12 -> 4985.5437
K13: =K12+1 -> 6 | L13: =IF(AND(K13<=Assumptions!$C$42,L12=1,P12=0,O12>Assumptions!$C$43),1,0) -> 1 | M13: =O12 -> 297824.31 | N13: =IF(L13=1,M13*$B$25,0) -> 992.74771 | O13: =IF(L13=1,M13+N13-$B$29,M13) -> 297384.82 | P13: =IF(L13=1,IF($B$29<=N13,1,0),0) -> 0 | Q13: =Q12+N13 -> 5978.2914
A14: WHAT-IF INPUTS (the "What if…" card) | K14: =K13+1 -> 7 | L14: =IF(AND(K14<=Assumptions!$C$42,L13=1,P13=0,O13>Assumptions!$C$43),1,0) -> 1 | M14: =O13 -> 297384.82 | N14: =IF(L14=1,M14*$B$25,0) -> 991.28272 | O14: =IF(L14=1,M14+N14-$B$29,M14) -> 296943.85 | P14: =IF(L14=1,IF($B$29<=N14,1,0),0) -> 0 | Q14: =Q13+N14 -> 6969.5741
A15: Input | B15: Value | C15: Unit | D15: Default | E15: Min | F15: Max (slider) | G15: Max if typed | H15: Step | I15: Pre-filled from (if the prototype pre-fills it) | K15: =K14+1 -> 8 | L15: =IF(AND(K15<=Assumptions!$C$42,L14=1,P14=0,O14>Assumptions!$C$43),1,0) -> 1 | M15: =O14 -> 296943.85 | N15: =IF(L15=1,M15*$B$25,0) -> 989.81284 | O15: =IF(L15=1,M15+N15-$B$29,M15) -> 296501.42 | P15: =IF(L15=1,IF($B$29<=N15,1,0),0) -> 0 | Q15: =Q14+N15 -> 7959.387
A16: If rates changed by | B16: 0 | C16: % (stored as a fraction) | D16: 0 | E16: -0.02 | F16: 0.03 | G16: 0.03 | H16: 0.0025 | K16: =K15+1 -> 9 | L16: =IF(AND(K16<=Assumptions!$C$42,L15=1,P15=0,O15>Assumptions!$C$43),1,0) -> 1 | M16: =O15 -> 296501.42 | N16: =IF(L16=1,M16*$B$25,0) -> 988.33807 | O16: =IF(L16=1,M16+N16-$B$29,M16) -> 296057.51 | P16: =IF(L16=1,IF($B$29<=N16,1,0),0) -> 0 | Q16: =Q15+N16 -> 8947.725
K17: =K16+1 -> 10 | L17: =IF(AND(K17<=Assumptions!$C$42,L16=1,P16=0,O16>Assumptions!$C$43),1,0) -> 1 | M17: =O16 -> 296057.51 | N17: =IF(L17=1,M17*$B$25,0) -> 986.85837 | O17: =IF(L17=1,M17+N17-$B$29,M17) -> 295612.12 | P17: =IF(L17=1,IF($B$29<=N17,1,0),0) -> 0 | Q17: =Q16+N17 -> 9934.5834
A18: CONTEXT INPUTS (state the prototype reads besides the sliders) | K18: =K17+1 -> 11 | L18: =IF(AND(K18<=Assumptions!$C$42,L17=1,P17=0,O17>Assumptions!$C$43),1,0) -> 1 | M18: =O17 -> 295612.12 | N18: =IF(L18=1,M18*$B$25,0) -> 985.37375 | O18: =IF(L18=1,M18+N18-$B$29,M18) -> 295165.25 | P18: =IF(L18=1,IF($B$29<=N18,1,0),0) -> 0 | Q18: =Q17+N18 -> 10919.957
A19: Input | B19: Value | C19: Unit | D19: Default | E19: Min | F19: Max (slider) | G19: Max if typed | H19: Step | I19: Pre-filled from (if the prototype pre-fills it) | K19: =K18+1 -> 12 | L19: =IF(AND(K19<=Assumptions!$C$42,L18=1,P18=0,O18>Assumptions!$C$43),1,0) -> 1 | M19: =O18 -> 295165.25 | N19: =IF(L19=1,M19*$B$25,0) -> 983.88417 | O19: =IF(L19=1,M19+N19-$B$29,M19) -> 294716.89 | P19: =IF(L19=1,IF($B$29<=N19,1,0),0) -> 0 | Q19: =Q18+N19 -> 11903.841
A20: Stated monthly mortgage repayment (0 = none) | B20: 0 | C20: € | D20: 0 | E20: 0 | F20: 100000 | G20: 100000 | I20: Pre-filled from Your finances / mortgage statement: the stated monthly repayment (statement or typed; estimates do not count). 0 = no stated repayment. | K20: =K19+1 -> 13 | L20: =IF(AND(K20<=Assumptions!$C$42,L19=1,P19=0,O19>Assumptions!$C$43),1,0) -> 1 | M20: =O19 -> 294716.89 | N20: =IF(L20=1,M20*$B$25,0) -> 982.38964 | O20: =IF(L20=1,M20+N20-$B$29,M20) -> 294267.03 | P20: =IF(L20=1,IF($B$29<=N20,1,0),0) -> 0 | Q20: =Q19+N20 -> 12886.231
A21: Customer has not moved loan, rate or term in this tool (1 = yes) | B21: 1 | C21: flag | D21: 1 | E21: 0 | F21: 1 | G21: 1 | H21: 1 | I21: mine(): 1 while the customer has not moved any of the listed sliders in this tool; 0 once they have (the stated figure then stops applying). | K21: =K20+1 -> 14 | L21: =IF(AND(K21<=Assumptions!$C$42,L20=1,P20=0,O20>Assumptions!$C$43),1,0) -> 1 | M21: =O20 -> 294267.03 | N21: =IF(L21=1,M21*$B$25,0) -> 980.89011 | O21: =IF(L21=1,M21+N21-$B$29,M21) -> 293815.68 | P21: =IF(L21=1,IF($B$29<=N21,1,0),0) -> 0 | Q21: =Q20+N21 -> 13867.121
K22: =K21+1 -> 15 | L22: =IF(AND(K22<=Assumptions!$C$42,L21=1,P21=0,O21>Assumptions!$C$43),1,0) -> 1 | M22: =O21 -> 293815.68 | N22: =IF(L22=1,M22*$B$25,0) -> 979.3856 | O22: =IF(L22=1,M22+N22-$B$29,M22) -> 293362.82 | P22: =IF(L22=1,IF($B$29<=N22,1,0),0) -> 0 | Q22: =Q21+N22 -> 14846.507
A23: CALCULATION | K23: =K22+1 -> 16 | L23: =IF(AND(K23<=Assumptions!$C$42,L22=1,P22=0,O22>Assumptions!$C$43),1,0) -> 1 | M23: =O22 -> 293362.82 | N23: =IF(L23=1,M23*$B$25,0) -> 977.87606 | O23: =IF(L23=1,M23+N23-$B$29,M23) -> 292908.45 | P23: =IF(L23=1,IF($B$29<=N23,1,0),0) -> 0 | Q23: =Q22+N23 -> 15824.383
A24: Calculation step | B24: Value | C24: Unit | D24: JS equivalent (prototype run function) | K24: =K23+1 -> 17 | L24: =IF(AND(K24<=Assumptions!$C$42,L23=1,P23=0,O23>Assumptions!$C$43),1,0) -> 1 | M24: =O23 -> 292908.45 | N24: =IF(L24=1,M24*$B$25,0) -> 976.3615 | O24: =IF(L24=1,M24+N24-$B$29,M24) -> 292452.56 | P24: =IF(L24=1,IF($B$29<=N24,1,0),0) -> 0 | Q24: =Q23+N24 -> 16800.744
A25: Monthly interest rate | B25: =$B$11/12 -> 0.0033333333 | C25: rate (fraction) | D25: i = r / 100 / 12 | K25: =K24+1 -> 18 | L25: =IF(AND(K25<=Assumptions!$C$42,L24=1,P24=0,O24>Assumptions!$C$43),1,0) -> 1 | M25: =O24 -> 292452.56 | N25: =IF(L25=1,M25*$B$25,0) -> 974.84188 | O25: =IF(L25=1,M25+N25-$B$29,M25) -> 291995.16 | P25: =IF(L25=1,IF($B$29<=N25,1,0),0) -> 0 | Q25: =Q24+N25 -> 17775.586
A26: Number of monthly payments | B26: =$B$12*12 -> 360 | C26: n | D26: n = y * 12 | K26: =K25+1 -> 19 | L26: =IF(AND(K26<=Assumptions!$C$42,L25=1,P25=0,O25>Assumptions!$C$43),1,0) -> 1 | M26: =O25 -> 291995.16 | N26: =IF(L26=1,M26*$B$25,0) -> 973.3172 | O26: =IF(L26=1,M26+N26-$B$29,M26) -> 291536.23 | P26: =IF(L26=1,IF($B$29<=N26,1,0),0) -> 0 | Q26: =Q25+N26 -> 18748.903
A27: Formula repayment | B27: =IF(($B$26)=0,0,IF($B$25<>0,$B$10*$B$25/(1-POWER(1+$B$25,-($B$26))),$B$10/($B$26))) -> 1432.2459 | C27: € | D27: calc = pmt(v.loan, v.rate, v.term) | K27: =K26+1 -> 20 | L27: =IF(AND(K27<=Assumptions!$C$42,L26=1,P26=0,O26>Assumptions!$C$43),1,0) -> 1 | M27: =O26 -> 291536.23 | N27: =IF(L27=1,M27*$B$25,0) -> 971.78744 | O27: =IF(L27=1,M27+N27-$B$29,M27) -> 291075.77 | P27: =IF(L27=1,IF($B$29<=N27,1,0),0) -> 0 | Q27: =Q26+N27 -> 19720.691
A28: Stated repayment in use (0 = none) | B28: =IF(AND($B$21=1,$B$20>0),$B$20,0) -> 0 | C28: € | D28: own = mine(...) ? statedM('mortPayM') : null | K28: =K27+1 -> 21 | L28: =IF(AND(K28<=Assumptions!$C$42,L27=1,P27=0,O27>Assumptions!$C$43),1,0) -> 1 | M28: =O27 -> 291075.77 | N28: =IF(L28=1,M28*$B$25,0) -> 970.25258 | O28: =IF(L28=1,M28+N28-$B$29,M28) -> 290613.78 | P28: =IF(L28=1,IF($B$29<=N28,1,0),0) -> 0 | Q28: =Q27+N28 -> 20690.943
A29: Repayment now | B29: =IF($B$28>0,$B$28,$B$27) -> 1432.2459 | C29: € | D29: base = own || calc | K29: =K28+1 -> 22 | L29: =IF(AND(K29<=Assumptions!$C$42,L28=1,P28=0,O28>Assumptions!$C$43),1,0) -> 1 | M29: =O28 -> 290613.78 | N29: =IF(L29=1,M29*$B$25,0) -> 968.7126 | O29: =IF(L29=1,M29+N29-$B$29,M29) -> 290150.25 | P29: =IF(L29=1,IF($B$29<=N29,1,0),0) -> 0 | Q29: =Q28+N29 -> 21659.656
A30: What-if rate | B30: =$B$11+$B$16 -> 0.04 | C30: % (fraction) | D30: r = v.rate + (v.dr || 0) | K30: =K29+1 -> 23 | L30: =IF(AND(K30<=Assumptions!$C$42,L29=1,P29=0,O29>Assumptions!$C$43),1,0) -> 1 | M30: =O29 -> 290150.25 | N30: =IF(L30=1,M30*$B$25,0) -> 967.16749 | O30: =IF(L30=1,M30+N30-$B$29,M30) -> 289685.17 | P30: =IF(L30=1,IF($B$29<=N30,1,0),0) -> 0 | Q30: =Q29+N30 -> 22626.823
A31: What-if monthly rate | B31: =$B$30/12 -> 0.0033333333 | C31: rate (fraction) | K31: =K30+1 -> 24 | L31: =IF(AND(K31<=Assumptions!$C$42,L30=1,P30=0,O30>Assumptions!$C$43),1,0) -> 1 | M31: =O30 -> 289685.17 | N31: =IF(L31=1,M31*$B$25,0) -> 965.61723 | O31: =IF(L31=1,M31+N31-$B$29,M31) -> 289218.54 | P31: =IF(L31=1,IF($B$29<=N31,1,0),0) -> 0 | Q31: =Q30+N31 -> 23592.441
A32: Formula repayment at the what-if rate | B32: =IF(($B$26)=0,0,IF($B$31<>0,$B$10*$B$31/(1-POWER(1+$B$31,-($B$26))),$B$10/($B$26))) -> 1432.2459 | C32: € | D32: pmt(v.loan, r, v.term) | K32: =K31+1 -> 25 | L32: =IF(AND(K32<=Assumptions!$C$42,L31=1,P31=0,O31>Assumptions!$C$43),1,0) -> 1 | M32: =O31 -> 289218.54 | N32: =IF(L32=1,M32*$B$25,0) -> 964.0618 | O32: =IF(L32=1,M32+N32-$B$29,M32) -> 288750.36 | P32: =IF(L32=1,IF($B$29<=N32,1,0),0) -> 0 | Q32: =Q31+N32 -> 24556.502
A33: What-if repayment | B33: =IF($B$16<>0,$B$29+$B$32-$B$27,$B$29) -> 1432.2459 | C33: € | D33: m = v.dr ? base + pmt(v.loan, r, v.term) - calc : base | K33: =K32+1 -> 26 | L33: =IF(AND(K33<=Assumptions!$C$42,L32=1,P32=0,O32>Assumptions!$C$43),1,0) -> 1 | M33: =O32 -> 288750.36 | N33: =IF(L33=1,M33*$B$25,0) -> 962.50118 | O33: =IF(L33=1,M33+N33-$B$29,M33) -> 288280.61 | P33: =IF(L33=1,IF($B$29<=N33,1,0),0) -> 0 | Q33: =Q32+N33 -> 25519.004
A34: Payoff never ends (1 = payment ≤ interest) | B34: =MAX($P$8:$P$1207) -> 0 | C34: flag | D34: po.m === Infinity | K34: =K33+1 -> 27 | L34: =IF(AND(K34<=Assumptions!$C$42,L33=1,P33=0,O33>Assumptions!$C$43),1,0) -> 1 | M34: =O33 -> 288280.61 | N34: =IF(L34=1,M34*$B$25,0) -> 960.93537 | O34: =IF(L34=1,M34+N34-$B$29,M34) -> 287809.3 | P34: =IF(L34=1,IF($B$29<=N34,1,0),0) -> 0 | Q34: =Q33+N34 -> 26479.939
A35: Months to mortgage free | B35: =SUM($L$8:$L$1207) -> 360 | C35: n | D35: po.m (payoff months) | K35: =K34+1 -> 28 | L35: =IF(AND(K35<=Assumptions!$C$42,L34=1,P34=0,O34>Assumptions!$C$43),1,0) -> 1 | M35: =O34 -> 287809.3 | N35: =IF(L35=1,M35*$B$25,0) -> 959.36433 | O35: =IF(L35=1,M35+N35-$B$29,M35) -> 287336.42 | P35: =IF(L35=1,IF($B$29<=N35,1,0),0) -> 0 | Q35: =Q34+N35 -> 27439.303
A36: Total interest | B36: =$Q$1207 -> 215608.52 | C36: € | D36: po.int | K36: =K35+1 -> 29 | L36: =IF(AND(K36<=Assumptions!$C$42,L35=1,P35=0,O35>Assumptions!$C$43),1,0) -> 1 | M36: =O35 -> 287336.42 | N36: =IF(L36=1,M36*$B$25,0) -> 957.78806 | O36: =IF(L36=1,M36+N36-$B$29,M36) -> 286861.96 | P36: =IF(L36=1,IF($B$29<=N36,1,0),0) -> 0 | Q36: =Q35+N36 -> 28397.091
A37: Stated figure differs from formula by ≥ €5 (1 = yes) | B37: =IF(AND($B$28>0,ABS($B$28-$B$27)>=Assumptions!$C$45),1,0) -> 0 | C37: flag | D37: own && Math.abs(own - calc) >= 5 | K37: =K36+1 -> 30 | L37: =IF(AND(K37<=Assumptions!$C$42,L36=1,P36=0,O36>Assumptions!$C$43),1,0) -> 1 | M37: =O36 -> 286861.96 | N37: =IF(L37=1,M37*$B$25,0) -> 956.20654 | O37: =IF(L37=1,M37+N37-$B$29,M37) -> 286385.92 | P37: =IF(L37=1,IF($B$29<=N37,1,0),0) -> 0 | Q37: =Q36+N37 -> 29353.298
K38: =K37+1 -> 31 | L38: =IF(AND(K38<=Assumptions!$C$42,L37=1,P37=0,O37>Assumptions!$C$43),1,0) -> 1 | M38: =O37 -> 286385.92 | N38: =IF(L38=1,M38*$B$25,0) -> 954.61974 | O38: =IF(L38=1,M38+N38-$B$29,M38) -> 285908.3 | P38: =IF(L38=1,IF($B$29<=N38,1,0),0) -> 0 | Q38: =Q37+N38 -> 30307.918
A39: OUTPUTS | K39: =K38+1 -> 32 | L39: =IF(AND(K39<=Assumptions!$C$42,L38=1,P38=0,O38>Assumptions!$C$43),1,0) -> 1 | M39: =O38 -> 285908.3 | N39: =IF(L39=1,M39*$B$25,0) -> 953.02765 | O39: =IF(L39=1,M39+N39-$B$29,M39) -> 285429.08 | P39: =IF(L39=1,IF($B$29<=N39,1,0),0) -> 0 | Q39: =Q38+N39 -> 31260.945
A40: Output | B40: Value | C40: As shown in the prototype | D40: Shown when / where it appears | K40: =K39+1 -> 33 | L40: =IF(AND(K40<=Assumptions!$C$42,L39=1,P39=0,O39>Assumptions!$C$43),1,0) -> 1 | M40: =O39 -> 285429.08 | N40: =IF(L40=1,M40*$B$25,0) -> 951.43026 | O40: =IF(L40=1,M40+N40-$B$29,M40) -> 284948.26 | P40: =IF(L40=1,IF($B$29<=N40,1,0),0) -> 0 | Q40: =Q39+N40 -> 32212.376
A41: Headline label | C41: =IF($B$16<>0,"If your rate changed to "&FIXED($B$30*100,2,TRUE())&"%",IF($B$28>0,"Your monthly repayment","Monthly repayment")) -> Monthly repayment | D41: Always | K41: =K40+1 -> 34 | L41: =IF(AND(K41<=Assumptions!$C$42,L40=1,P40=0,O40>Assumptions!$C$43),1,0) -> 1 | M41: =O40 -> 284948.26 | N41: =IF(L41=1,M41*$B$25,0) -> 949.82754 | O41: =IF(L41=1,M41+N41-$B$29,M41) -> 284465.84 | P41: =IF(L41=1,IF($B$29<=N41,1,0),0) -> 0 | Q41: =Q40+N41 -> 33162.203
A42: Headline: monthly repayment (what-if repayment when dr ≠ 0) | B42: =IF($B$16<>0,$B$33,$B$29) -> 1432.2459 | C42: =IF((IF($B$16<>0,$B$33,$B$29))<0,"−€","€")&FIXED(ROUND(ABS(IF($B$16<>0,$B$33,$B$29)),0),0) -> €1,432 | D42: Headline figure | K42: =K41+1 -> 35 | L42: =IF(AND(K42<=Assumptions!$C$42,L41=1,P41=0,O41>Assumptions!$C$43),1,0) -> 1 | M42: =O41 -> 284465.84 | N42: =IF(L42=1,M42*$B$25,0) -> 948.21948 | O42: =IF(L42=1,M42+N42-$B$29,M42) -> 283981.82 | P42: =IF(L42=1,IF($B$29<=N42,1,0),0) -> 0 | Q42: =Q41+N42 -> 34110.423
A43: What-if: change vs now (in the sentence) | B43: =IF($B$16<>0,ABS($B$33-$B$29),"") | C43: =IF($B$16<>0,IF((ABS($B$33-$B$29))<0,"−€","€")&FIXED(ROUND(ABS(ABS($B$33-$B$29)),0),0)&IF($B$33>=$B$29," more"," less"),"") | D43: Sentence, only when dr ≠ 0 | K43: =K42+1 -> 36 | L43: =IF(AND(K43<=Assumptions!$C$42,L42=1,P42=0,O42>Assumptions!$C$43),1,0) -> 1 | M43: =O42 -> 283981.82 | N43: =IF(L43=1,M43*$B$25,0) -> 946.60606 | O43: =IF(L43=1,M43+N43-$B$29,M43) -> 283496.18 | P43: =IF(L43=1,IF($B$29<=N43,1,0),0) -> 0 | Q43: =Q42+N43 -> 35057.029
A44: Formula repayment (when the stated figure differs by ≥ €5) | B44: =IF(AND($B$16=0,$B$37=1),$B$27,"") | C44: =IF(AND($B$16=0,$B$37=1),IF(($B$27)<0,"−€","€")&FIXED(ROUND(ABS($B$27),0),0),"") | D44: Sentence, only when using a stated repayment that differs | K44: =K43+1 -> 37 | L44: =IF(AND(K44<=Assumptions!$C$42,L43=1,P43=0,O43>Assumptions!$C$43),1,0) -> 1 | M44: =O43 -> 283496.18 | N44: =IF(L44=1,M44*$B$25,0) -> 944.98726 | O44: =IF(L44=1,M44+N44-$B$29,M44) -> 283008.92 | P44: =IF(L44=1,IF($B$29<=N44,1,0),0) -> 0 | Q44: =Q43+N44 -> 36002.016
A45: Repayment now | B45: =IF($B$16<>0,$B$29,"") | C45: =IF($B$16<>0,IF(($B$29)<0,"−€","€")&FIXED(ROUND(ABS($B$29),0),0),"") | D45: Row, only when dr ≠ 0 | K45: =K44+1 -> 38 | L45: =IF(AND(K45<=Assumptions!$C$42,L44=1,P44=0,O44>Assumptions!$C$43),1,0) -> 1 | M45: =O44 -> 283008.92 | N45: =IF(L45=1,M45*$B$25,0) -> 943.36306 | O45: =IF(L45=1,M45+N45-$B$29,M45) -> 282520.04 | P45: =IF(L45=1,IF($B$29<=N45,1,0),0) -> 0 | Q45: =Q44+N45 -> 36945.379
A46: Change over a year | B46: =IF($B$16<>0,($B$33-$B$29)*12,"") | C46: =IF($B$16<>0,IF((($B$33-$B$29)*12)<0,"−€","€")&FIXED(ROUND(ABS(($B$33-$B$29)*12),0),0),"") | D46: Row, only when dr ≠ 0 | K46: =K45+1 -> 39 | L46: =IF(AND(K46<=Assumptions!$C$42,L45=1,P45=0,O45>Assumptions!$C$43),1,0) -> 1 | M46: =O45 -> 282520.04 | N46: =IF(L46=1,M46*$B$25,0) -> 941.73345 | O46: =IF(L46=1,M46+N46-$B$29,M46) -> 282029.52 | P46: =IF(L46=1,IF($B$29<=N46,1,0),0) -> 0 | Q46: =Q45+N46 -> 37887.112
A47: Mortgage free in (months) | B47: =IF($B$16=0,IF($B$34=1,"Never",$B$35),"") -> 360 | C47: =IF($B$16=0,IF($B$34=1,"Not at this repayment",IF(INT($B$35/12)>0,INT($B$35/12)&" yr"&IF(INT($B$35/12)>1,"s","")&IF(ROUND(MOD($B$35,12),0)<>0," "&ROUND(MOD($B$35,12),0)&" mo",""),ROUND(MOD($B$35,12),0)&" months")),"") -> 30 yrs | D47: Row, only when dr = 0 | K47: =K46+1 -> 40 | L47: =IF(AND(K47<=Assumptions!$C$42,L46=1,P46=0,O46>Assumptions!$C$43),1,0) -> 1 | M47: =O46 -> 282029.52 | N47: =IF(L47=1,M47*$B$25,0) -> 940.09841 | O47: =IF(L47=1,M47+N47-$B$29,M47) -> 281537.38 | P47: =IF(L47=1,IF($B$29<=N47,1,0),0) -> 0 | Q47: =Q46+N47 -> 38827.211
A48: Total interest | B48: =IF(AND($B$16=0,$B$34=0),$B$36,"") -> 215608.52 | C48: =IF($B$16=0,IF($B$34=1,"—",IF(($B$36)<0,"−€","€")&FIXED(ROUND(ABS($B$36),0),0)),"") -> €215,609 | D48: Row, only when dr = 0 | K48: =K47+1 -> 41 | L48: =IF(AND(K48<=Assumptions!$C$42,L47=1,P47=0,O47>Assumptions!$C$43),1,0) -> 1 | M48: =O47 -> 281537.38 | N48: =IF(L48=1,M48*$B$25,0) -> 938.45792 | O48: =IF(L48=1,M48+N48-$B$29,M48) -> 281043.59 | P48: =IF(L48=1,IF($B$29<=N48,1,0),0) -> 0 | Q48: =Q47+N48 -> 39765.669
A49: Total repaid | B49: =IF(AND($B$16=0,$B$34=0),$B$10+$B$36,"") -> 515608.52 | C49: =IF($B$16=0,IF($B$34=1,"—",IF(($B$10+$B$36)<0,"−€","€")&FIXED(ROUND(ABS($B$10+$B$36),0),0)),"") -> €515,609 | D49: Row, only when dr = 0 | K49: =K48+1 -> 42 | L49: =IF(AND(K49<=Assumptions!$C$42,L48=1,P48=0,O48>Assumptions!$C$43),1,0) -> 1 | M49: =O48 -> 281043.59 | N49: =IF(L49=1,M49*$B$25,0) -> 936.81196 | O49: =IF(L49=1,M49+N49-$B$29,M49) -> 280548.15 | P49: =IF(L49=1,IF($B$29<=N49,1,0),0) -> 0 | Q49: =Q48+N49 -> 40702.481
A50: "Add to my plan" goal amount | B50: =$B$10 -> 300000 | C50: =$B$50&"" -> 300000 | D50: Add to my plan | K50: =K49+1 -> 43 | L50: =IF(AND(K50<=Assumptions!$C$42,L49=1,P49=0,O49>Assumptions!$C$43),1,0) -> 1 | M50: =O49 -> 280548.15 | N50: =IF(L50=1,M50*$B$25,0) -> 935.16051 | O50: =IF(L50=1,M50+N50-$B$29,M50) -> 280051.07 | P50: =IF(L50=1,IF($B$29<=N50,1,0),0) -> 0 | Q50: =Q49+N50 -> 41637.641
A51: "Add to my plan" goal years | B51: =Assumptions!$C$71 -> 3 | C51: =$B$51&"" -> 3 | D51: Add to my plan | K51: =K50+1 -> 44 | L51: =IF(AND(K51<=Assumptions!$C$42,L50=1,P50=0,O50>Assumptions!$C$43),1,0) -> 1 | M51: =O50 -> 280051.07 | N51: =IF(L51=1,M51*$B$25,0) -> 933.50356 | O51: =IF(L51=1,M51+N51-$B$29,M51) -> 279552.33 | P51: =IF(L51=1,IF($B$29<=N51,1,0),0) -> 0 | Q51: =Q50+N51 -> 42571.145
K52: =K51+1 -> 45 | L52: =IF(AND(K52<=Assumptions!$C$42,L51=1,P51=0,O51>Assumptions!$C$43),1,0) -> 1 | M52: =O51 -> 279552.33 | N52: =IF(L52=1,M52*$B$25,0) -> 931.84109 | O52: =IF(L52=1,M52+N52-$B$29,M52) -> 279051.92 | P52: =IF(L52=1,IF($B$29<=N52,1,0),0) -> 0 | Q52: =Q51+N52 -> 43502.986
K53: =K52+1 -> 46 | L53: =IF(AND(K53<=Assumptions!$C$42,L52=1,P52=0,O52>Assumptions!$C$43),1,0) -> 1 | M53: =O52 -> 279051.92 | N53: =IF(L53=1,M53*$B$25,0) -> 930.17307 | O53: =IF(L53=1,M53+N53-$B$29,M53) -> 278549.85 | P53: =IF(L53=1,IF($B$29<=N53,1,0),0) -> 0 | Q53: =Q52+N53 -> 44433.159
K54: =K53+1 -> 47 | L54: =IF(AND(K54<=Assumptions!$C$42,L53=1,P53=0,O53>Assumptions!$C$43),1,0) -> 1 | M54: =O53 -> 278549.85 | N54: =IF(L54=1,M54*$B$25,0) -> 928.49949 | O54: =IF(L54=1,M54+N54-$B$29,M54) -> 278046.1 | P54: =IF(L54=1,IF($B$29<=N54,1,0),0) -> 0 | Q54: =Q53+N54 -> 45361.658
K55: =K54+1 -> 48 | L55: =IF(AND(K55<=Assumptions!$C$42,L54=1,P54=0,O54>Assumptions!$C$43),1,0) -> 1 | M55: =O54 -> 278046.1 | N55: =IF(L55=1,M55*$B$25,0) -> 926.82034 | O55: =IF(L55=1,M55+N55-$B$29,M55) -> 277540.68 | P55: =IF(L55=1,IF($B$29<=N55,1,0),0) -> 0 | Q55: =Q54+N55 -> 46288.479
K56: =K55+1 -> 49 | L56: =IF(AND(K56<=Assumptions!$C$42,L55=1,P55=0,O55>Assumptions!$C$43),1,0) -> 1 | M56: =O55 -> 277540.68 | N56: =IF(L56=1,M56*$B$25,0) -> 925.13559 | O56: =IF(L56=1,M56+N56-$B$29,M56) -> 277033.57 | P56: =IF(L56=1,IF($B$29<=N56,1,0),0) -> 0 | Q56: =Q55+N56 -> 47213.614
K57: =K56+1 -> 50 | L57: =IF(AND(K57<=Assumptions!$C$42,L56=1,P56=0,O56>Assumptions!$C$43),1,0) -> 1 | M57: =O56 -> 277033.57 | N57: =IF(L57=1,M57*$B$25,0) -> 923.44522 | O57: =IF(L57=1,M57+N57-$B$29,M57) -> 276524.77 | P57: =IF(L57=1,IF($B$29<=N57,1,0),0) -> 0 | Q57: =Q56+N57 -> 48137.06
K58: =K57+1 -> 51 | L58: =IF(AND(K58<=Assumptions!$C$42,L57=1,P57=0,O57>Assumptions!$C$43),1,0) -> 1 | M58: =O57 -> 276524.77 | N58: =IF(L58=1,M58*$B$25,0) -> 921.74922 | O58: =IF(L58=1,M58+N58-$B$29,M58) -> 276014.27 | P58: =IF(L58=1,IF($B$29<=N58,1,0),0) -> 0 | Q58: =Q57+N58 -> 49058.809
K59: =K58+1 -> 52 | L59: =IF(AND(K59<=Assumptions!$C$42,L58=1,P58=0,O58>Assumptions!$C$43),1,0) -> 1 | M59: =O58 -> 276014.27 | N59: =IF(L59=1,M59*$B$25,0) -> 920.04756 | O59: =IF(L59=1,M59+N59-$B$29,M59) -> 275502.07 | P59: =IF(L59=1,IF($B$29<=N59,1,0),0) -> 0 | Q59: =Q58+N59 -> 49978.856
K60: =K59+1 -> 53 | L60: =IF(AND(K60<=Assumptions!$C$42,L59=1,P59=0,O59>Assumptions!$C$43),1,0) -> 1 | M60: =O59 -> 275502.07 | N60: =IF(L60=1,M60*$B$25,0) -> 918.34023 | O60: =IF(L60=1,M60+N60-$B$29,M60) -> 274988.16 | P60: =IF(L60=1,IF($B$29<=N60,1,0),0) -> 0 | Q60: =Q59+N60 -> 50897.197
K61: =K60+1 -> 54 | L61: =IF(AND(K61<=Assumptions!$C$42,L60=1,P60=0,O60>Assumptions!$C$43),1,0) -> 1 | M61: =O60 -> 274988.16 | N61: =IF(L61=1,M61*$B$25,0) -> 916.62722 | O61: =IF(L61=1,M61+N61-$B$29,M61) -> 274472.55 | P61: =IF(L61=1,IF($B$29<=N61,1,0),0) -> 0 | Q61: =Q60+N61 -> 51813.824
K62: =K61+1 -> 55 | L62: =IF(AND(K62<=Assumptions!$C$42,L61=1,P61=0,O61>Assumptions!$C$43),1,0) -> 1 | M62: =O61 -> 274472.55 | N62: =IF(L62=1,M62*$B$25,0) -> 914.90849 | O62: =IF(L62=1,M62+N62-$B$29,M62) -> 273955.21 | P62: =IF(L62=1,IF($B$29<=N62,1,0),0) -> 0 | Q62: =Q61+N62 -> 52728.732
K63: =K62+1 -> 56 | L63: =IF(AND(K63<=Assumptions!$C$42,L62=1,P62=0,O62>Assumptions!$C$43),1,0) -> 1 | M63: =O62 -> 273955.21 | N63: =IF(L63=1,M63*$B$25,0) -> 913.18403 | O63: =IF(L63=1,M63+N63-$B$29,M63) -> 273436.15 | P63: =IF(L63=1,IF($B$29<=N63,1,0),0) -> 0 | Q63: =Q62+N63 -> 53641.916
... K1207: =K1206+1 -> 1200 | L1207: =IF(AND(K1207<=Assumptions!$C$42,L1206=1,P1206=0,O1206>Assumptions!$C$43),1,0) -> 0 | M1207: =O1206 -> 1.0406211e-08 | N1207: =IF(L1207=1,M1207*$B$25,0) -> 0 | O1207: =IF(L1207=1,M1207+N1207-$B$29,M1207) -> 1.0406211e-08 | P1207: =IF(L1207=1,IF($B$29<=N1207,1,0),0) -> 0 | Q1207: =Q1206+N1207 -> 215608.52

Sheet C03 Deposit
A1: C03 · Deposit calculator
A2: Question shown: "How long until I have my deposit?" · Category: Home & Mortgage · Prototype id: deposit
A3: Replicates: CALCS 'deposit' run(v); helper yrs(m).
A4: Edge rules: Closed form in the JS (no loop): months = ceil(still to save ÷ monthly saving incl. what-if extra). "You have it" when nothing is left to save. Goal years = max(1, ceil(unrounded months ÷ 12)). yrs() shows "N months" below a year (also "1 months", "0 months").
A5: Legend: blue = input (change these) · black = formula · green = link to the Assumptions sheet · yellow fill = key assumption. Money cells show whole euros but keep full precision, as the prototype does.
A8: INPUTS
A9: Input | B9: Value | C9: Unit | D9: Default | E9: Min | F9: Max (slider) | G9: Max if typed | H9: Step | I9: Pre-filled from (if the prototype pre-fills it)
A10: Home price | B10: 350000 | C10: € | D10: 350000 | E10: 100000 | F10: 1000000 | G10: 10000000 | H10: 5000
A11: Deposit needed | B11: 0.1 | C11: % (stored as a fraction) | D11: 0.1 | E11: 0.05 | F11: 0.3 | G11: 0.3 | H11: 0.01
A12: Saved so far | B12: 12000 | C12: € | D12: 12000 | E12: 0 | F12: 200000 | G12: 2000000 | H12: 500 | I12: Plan: the home goal's amount already saved (if any)
A13: Monthly saving | B13: 800 | C13: € | D13: 800 | E13: 50 | F13: 5000 | G13: 50000 | H13: 50
A15: WHAT-IF INPUTS (the "What if…" card)
A16: Input | B16: Value | C16: Unit | D16: Default | E16: Min | F16: Max (slider) | G16: Max if typed | H16: Step | I16: Pre-filled from (if the prototype pre-fills it)
A17: Save extra each month | B17: 0 | C17: € | D17: 0 | E17: 0 | F17: 1500 | G17: 15000 | H17: 50
A19: CALCULATION
A20: Calculation step | B20: Value | C20: Unit | D20: JS equivalent (prototype run function)
A21: Deposit needed | B21: =$B$10*$B$11 -> 35000 | C21: € | D21: need = v.price * v.pc / 100
A22: Still to save | B22: =MAX(0,$B$21-$B$12) -> 23000 | C22: € | D22: left = Math.max(0, need - v.saved)
A23: Monthly saving incl. what-if extra | B23: =$B$13+$B$17 -> 800 | C23: € | D23: v.mo + (v.xmo || 0)
A24: Months (unrounded) | B24: =IF($B$23=0,0,$B$22/$B$23) -> 28.75 | C24: num | D24: m = left / (v.mo + (v.xmo || 0)) [0 saving is outside the input range]
A25: Months (rounded up) | B25: =(-INT(-($B$24))) -> 29 | C25: n | D25: Math.ceil(m)
A27: OUTPUTS
A28: Output | B28: Value | C28: As shown in the prototype | D28: Shown when / where it appears
A29: Headline label | C29: ="Time to your deposit" -> Time to your deposit | D29: Always
A30: Time to your deposit (months) | B30: =IF($B$22<>0,$B$25,0) -> 29 | C30: =IF($B$22<>0,IF(INT($B$25/12)>0,INT($B$25/12)&" yr"&IF(INT($B$25/12)>1,"s","")&IF(ROUND(MOD($B$25,12),0)<>0," "&ROUND(MOD($B$25,12),0)&" mo",""),ROUND(MOD($B$25,12),0)&" months"),"You have it") -> 2 yrs 5 mo | D30: Headline
A31: You need (sentence) | B31: =$B$21 -> 35000 | C31: =IF(($B$21)<0,"−€","€")&FIXED(ROUND(ABS($B$21),0),0) -> €35,000 | D31: Sentence
A32: Saving a month (sentence) | B32: =$B$23 -> 800 | C32: =IF(($B$23)<0,"−€","€")&FIXED(ROUND(ABS($B$23),0),0) -> €800 | D32: Sentence
A33: Deposit needed | B33: =$B$21 -> 35000 | C33: =IF(($B$21)<0,"−€","€")&FIXED(ROUND(ABS($B$21),0),0) -> €35,000 | D33: Row 1
A34: Still to save | B34: =$B$22 -> 23000 | C34: =IF(($B$22)<0,"−€","€")&FIXED(ROUND(ABS($B$22),0),0) -> €23,000 | D34: Row 2
A35: "Add to my plan" goal amount (Home deposit) | B35: =INT(($B$21)+0.5) -> 35000 | C35: =$B$35&"" -> 35000 | D35: Add to my plan
A36: "Add to my plan" goal years | B36: =MAX(1,(-INT(-($B$24/12)))) -> 3 | C36: =$B$36&"" -> 3 | D36: Add to my plan

Sheet C04 Mortgage overpayment
A1: C04 · Mortgage overpayment
A2: Question shown: "What if I paid a little extra each month?" · Category: Home & Mortgage · Prototype id: overpay
A3: Replicates: CALCS 'overpay' run(v); helpers pmt(), payoff() ×2, mine(), statedM(), yrs().
A4: Edge rules: Repayment = stated repayment while balance, rate and years are untouched, else pmt(). Two payoffs: at the repayment (A) and at repayment + extra (B). Headline "—" if A never pays off. If B never pays off either, the row shows "Infinity yrs" and the goal years Infinity (JS behaviour, replicated). Both payoffs stop at 1,200 months.
A5: Legend: blue = input (change these) · black = formula · green = link to the Assumptions sheet · yellow fill = key assumption. Money cells show whole euros but keep full precision, as the prototype does. | K5: One row per month, capped at 1,200 months like the JS loop. | S5: One row per month, capped at 1,200 months like the JS loop.
K6: A: payoff(v.bal, v.rate, p) | S6: B: payoff(v.bal, v.rate, p + v.x)
K7: Month | L7: Loop runs this month (bal > 0.005, month ≤ cap, not stopped) | M7: Opening balance | N7: Interest (bal × i) | O7: Closing balance (bal + it − pay) | P7: Payment ≤ interest: never pays off (1) | Q7: Cumulative interest | S7: Month | T7: Loop runs this month (bal > 0.005, month ≤ cap, not stopped) | U7: Opening balance | V7: Interest (bal × i) | W7: Closing balance (bal + it − pay) | X7: Payment ≤ interest: never pays off (1) | Y7: Cumulative interest
A8: INPUTS | K8: 1 | L8: =IF(AND(K8<=Assumptions!$C$42,$B$10>Assumptions!$C$43),1,0) -> 1 | M8: =$B$10 -> 250000 | N8: =IF(L8=1,M8*$B$22,0) -> 833.33333 | O8: =IF(L8=1,M8+N8-$B$26,M8) -> 249513.74 | P8: =IF(L8=1,IF($B$26<=N8,1,0),0) -> 0 | Q8: =N8 -> 833.33333 | S8: 1 | T8: =IF(AND(S8<=Assumptions!$C$42,$B$10>Assumptions!$C$43),1,0) -> 1 | U8: =$B$10 -> 250000 | V8: =IF(T8=1,U8*$B$22,0) -> 833.33333 | W8: =IF(T8=1,U8+V8-$B$27,U8) -> 249313.74 | X8: =IF(T8=1,IF($B$27<=V8,1,0),0) -> 0 | Y8: =V8 -> 833.33333
A9: Input | B9: Value | C9: Unit | D9: Default | E9: Min | F9: Max (slider) | G9: Max if typed | H9: Step | I9: Pre-filled from (if the prototype pre-fills it) | K9: =K8+1 -> 2 | L9: =IF(AND(K9<=Assumptions!$C$42,L8=1,P8=0,O8>Assumptions!$C$43),1,0) -> 1 | M9: =O8 -> 249513.74 | N9: =IF(L9=1,M9*$B$22,0) -> 831.71247 | O9: =IF(L9=1,M9+N9-$B$26,M9) -> 249025.86 | P9: =IF(L9=1,IF($B$26<=N9,1,0),0) -> 0 | Q9: =Q8+N9 -> 1665.0458 | S9: =S8+1 -> 2 | T9: =IF(AND(S9<=Assumptions!$C$42,T8=1,X8=0,W8>Assumptions!$C$43),1,0) -> 1 | U9: =W8 -> 249313.74 | V9: =IF(T9=1,U9*$B$22,0) -> 831.0458 | W9: =IF(T9=1,U9+V9-$B$27,U9) -> 248625.19 | X9: =IF(T9=1,IF($B$27<=V9,1,0),0) -> 0 | Y9: =Y8+V9 -> 1664.3791
A10: Mortgage balance | B10: 250000 | C10: € | D10: 250000 | E10: 20000 | F10: 1000000 | G10: 10000000 | H10: 1000 | I10: Your finances or mortgage statement: mortgage balance | K10: =K9+1 -> 3 | L10: =IF(AND(K10<=Assumptions!$C$42,L9=1,P9=0,O9>Assumptions!$C$43),1,0) -> 1 | M10: =O9 -> 249025.86 | N10: =IF(L10=1,M10*$B$22,0) -> 830.08621 | O10: =IF(L10=1,M10+N10-$B$26,M10) -> 248536.36 | P10: =IF(L10=1,IF($B$26<=N10,1,0),0) -> 0 | Q10: =Q9+N10 -> 2495.132 | S10: =S9+1 -> 3 | T10: =IF(AND(S10<=Assumptions!$C$42,T9=1,X9=0,W9>Assumptions!$C$43),1,0) -> 1 | U10: =W9 -> 248625.19 | V10: =IF(T10=1,U10*$B$22,0) -> 828.75065 | W10: =IF(T10=1,U10+V10-$B$27,U10) -> 247934.35 | X10: =IF(T10=1,IF($B$27<=V10,1,0),0) -> 0 | Y10: =Y9+V10 -> 2493.1298
A11: Interest rate | B11: 0.04 | C11: % (stored as a fraction) | D11: 0.04 | E11: 0.01 | F11: 0.08 | G11: 0.08 | H11: 0.0005 | I11: Your finances or mortgage statement: mortgage rate | K11: =K10+1 -> 4 | L11: =IF(AND(K11<=Assumptions!$C$42,L10=1,P10=0,O10>Assumptions!$C$43),1,0) -> 1 | M11: =O10 -> 248536.36 | N11: =IF(L11=1,M11*$B$22,0) -> 828.45452 | O11: =IF(L11=1,M11+N11-$B$26,M11) -> 248045.22 | P11: =IF(L11=1,IF($B$26<=N11,1,0),0) -> 0 | Q11: =Q10+N11 -> 3323.5865 | S11: =S10+1 -> 4 | T11: =IF(AND(S11<=Assumptions!$C$42,T10=1,X10=0,W10>Assumptions!$C$43),1,0) -> 1 | U11: =W10 -> 247934.35 | V11: =IF(T11=1,U11*$B$22,0) -> 826.44784 | W11: =IF(T11=1,U11+V11-$B$27,U11) -> 247241.21 | X11: =IF(T11=1,IF($B$27<=V11,1,0),0) -> 0 | Y11: =Y10+V11 -> 3319.5776
A12: Years left | B12: 25 | C12: years | D12: 25 | E12: 3 | F12: 35 | G12: 35 | H12: 1 | I12: Your finances or mortgage statement: years left (25 if not given) | K12: =K11+1 -> 5 | L12: =IF(AND(K12<=Assumptions!$C$42,L11=1,P11=0,O11>Assumptions!$C$43),1,0) -> 1 | M12: =O11 -> 248045.22 | N12: =IF(L12=1,M12*$B$22,0) -> 826.81739 | O12: =IF(L12=1,M12+N12-$B$26,M12) -> 247552.44 | P12: =IF(L12=1,IF($B$26<=N12,1,0),0) -> 0 | Q12: =Q11+N12 -> 4150.4039 | S12: =S11+1 -> 5 | T12: =IF(AND(S12<=Assumptions!$C$42,T11=1,X11=0,W11>Assumptions!$C$43),1,0) -> 1 | U12: =W11 -> 247241.21 | V12: =IF(T12=1,U12*$B$22,0) -> 824.13736 | W12: =IF(T12=1,U12+V12-$B$27,U12) -> 246545.75 | X12: =IF(T12=1,IF($B$27<=V12,1,0),0) -> 0 | Y12: =Y11+V12 -> 4143.715
A13: Extra each month | B13: 200 | C13: € | D13: 200 | E13: 0 | F13: 2000 | G13: 20000 | H13: 25 | K13: =K12+1 -> 6 | L13: =IF(AND(K13<=Assumptions!$C$42,L12=1,P12=0,O12>Assumptions!$C$43),1,0) -> 1 | M13: =O12 -> 247552.44 | N13: =IF(L13=1,M13*$B$22,0) -> 825.17481 | O13: =IF(L13=1,M13+N13-$B$26,M13) -> 247058.03 | P13: =IF(L13=1,IF($B$26<=N13,1,0),0) -> 0 | Q13: =Q12+N13 -> 4975.5787 | S13: =S12+1 -> 6 | T13: =IF(AND(S13<=Assumptions!$C$42,T12=1,X12=0,W12>Assumptions!$C$43),1,0) -> 1 | U13: =W12 -> 246545.75 | V13: =IF(T13=1,U13*$B$22,0) -> 821.81918 | W13: =IF(T13=1,U13+V13-$B$27,U13) -> 245847.98 | X13: =IF(T13=1,IF($B$27<=V13,1,0),0) -> 0 | Y13: =Y12+V13 -> 4965.5342
K14: =K13+1 -> 7 | L14: =IF(AND(K14<=Assumptions!$C$42,L13=1,P13=0,O13>Assumptions!$C$43),1,0) -> 1 | M14: =O13 -> 247058.03 | N14: =IF(L14=1,M14*$B$22,0) -> 823.52675 | O14: =IF(L14=1,M14+N14-$B$26,M14) -> 246561.96 | P14: =IF(L14=1,IF($B$26<=N14,1,0),0) -> 0 | Q14: =Q13+N14 -> 5799.1055 | S14: =S13+1 -> 7 | T14: =IF(AND(S14<=Assumptions!$C$42,T13=1,X13=0,W13>Assumptions!$C$43),1,0) -> 1 | U14: =W13 -> 245847.98 | V14: =IF(T14=1,U14*$B$22,0) -> 819.49327 | W14: =IF(T14=1,U14+V14-$B$27,U14) -> 245147.88 | X14: =IF(T14=1,IF($B$27<=V14,1,0),0) -> 0 | Y14: =Y13+V14 -> 5785.0274
A15: CONTEXT INPUTS (state the prototype reads besides the sliders) | K15: =K14+1 -> 8 | L15: =IF(AND(K15<=Assumptions!$C$42,L14=1,P14=0,O14>Assumptions!$C$43),1,0) -> 1 | M15: =O14 -> 246561.96 | N15: =IF(L15=1,M15*$B$22,0) -> 821.8732 | O15: =IF(L15=1,M15+N15-$B$26,M15) -> 246064.24 | P15: =IF(L15=1,IF($B$26<=N15,1,0),0) -> 0 | Q15: =Q14+N15 -> 6620.9787 | S15: =S14+1 -> 8 | T15: =IF(AND(S15<=Assumptions!$C$42,T14=1,X14=0,W14>Assumptions!$C$43),1,0) -> 1 | U15: =W14 -> 245147.88 | V15: =IF(T15=1,U15*$B$22,0) -> 817.15961 | W15: =IF(T15=1,U15+V15-$B$27,U15) -> 244445.45 | X15: =IF(T15=1,IF($B$27<=V15,1,0),0) -> 0 | Y15: =Y14+V15 -> 6602.1871
A16: Input | B16: Value | C16: Unit | D16: Default | E16: Min | F16: Max (slider) | G16: Max if typed | H16: Step | I16: Pre-filled from (if the prototype pre-fills it) | K16: =K15+1 -> 9 | L16: =IF(AND(K16<=Assumptions!$C$42,L15=1,P15=0,O15>Assumptions!$C$43),1,0) -> 1 | M16: =O15 -> 246064.24 | N16: =IF(L16=1,M16*$B$22,0) -> 820.21414 | O16: =IF(L16=1,M16+N16-$B$26,M16) -> 245564.86 | P16: =IF(L16=1,IF($B$26<=N16,1,0),0) -> 0 | Q16: =Q15+N16 -> 7441.1928 | S16: =S15+1 -> 9 | T16: =IF(AND(S16<=Assumptions!$C$42,T15=1,X15=0,W15>Assumptions!$C$43),1,0) -> 1 | U16: =W15 -> 244445.45 | V16: =IF(T16=1,U16*$B$22,0) -> 814.81817 | W16: =IF(T16=1,U16+V16-$B$27,U16) -> 243740.68 | X16: =IF(T16=1,IF($B$27<=V16,1,0),0) -> 0 | Y16: =Y15+V16 -> 7417.0052
A17: Stated monthly mortgage repayment (0 = none) | B17: 0 | C17: € | D17: 0 | E17: 0 | F17: 100000 | G17: 100000 | I17: Pre-filled from Your finances / mortgage statement: the stated monthly repayment (statement or typed; estimates do not count). 0 = no stated repayment. | K17: =K16+1 -> 10 | L17: =IF(AND(K17<=Assumptions!$C$42,L16=1,P16=0,O16>Assumptions!$C$43),1,0) -> 1 | M17: =O16 -> 245564.86 | N17: =IF(L17=1,M17*$B$22,0) -> 818.54955 | O17: =IF(L17=1,M17+N17-$B$26,M17) -> 245063.82 | P17: =IF(L17=1,IF($B$26<=N17,1,0),0) -> 0 | Q17: =Q16+N17 -> 8259.7424 | S17: =S16+1 -> 10 | T17: =IF(AND(S17<=Assumptions!$C$42,T16=1,X16=0,W16>Assumptions!$C$43),1,0) -> 1 | U17: =W16 -> 243740.68 | V17: =IF(T17=1,U17*$B$22,0) -> 812.46892 | W17: =IF(T17=1,U17+V17-$B$27,U17) -> 243033.55 | X17: =IF(T17=1,IF($B$27<=V17,1,0),0) -> 0 | Y17: =Y16+V17 -> 8229.4741
A18: Customer has not moved balance, rate or years in this tool (1 = yes) | B18: 1 | C18: flag | D18: 1 | E18: 0 | F18: 1 | G18: 1 | H18: 1 | I18: mine(): 1 while the customer has not moved any of the listed sliders in this tool; 0 once they have (the stated figure then stops applying). | K18: =K17+1 -> 11 | L18: =IF(AND(K18<=Assumptions!$C$42,L17=1,P17=0,O17>Assumptions!$C$43),1,0) -> 1 | M18: =O17 -> 245063.82 | N18: =IF(L18=1,M18*$B$22,0) -> 816.8794 | O18: =IF(L18=1,M18+N18-$B$26,M18) -> 244561.11 | P18: =IF(L18=1,IF($B$26<=N18,1,0),0) -> 0 | Q18: =Q17+N18 -> 9076.6218 | S18: =S17+1 -> 11 | T18: =IF(AND(S18<=Assumptions!$C$42,T17=1,X17=0,W17>Assumptions!$C$43),1,0) -> 1 | U18: =W17 -> 243033.55 | V18: =IF(T18=1,U18*$B$22,0) -> 810.11184 | W18: =IF(T18=1,U18+V18-$B$27,U18) -> 242324.07 | X18: =IF(T18=1,IF($B$27<=V18,1,0),0) -> 0 | Y18: =Y17+V18 -> 9039.586
K19: =K18+1 -> 12 | L19: =IF(AND(K19<=Assumptions!$C$42,L18=1,P18=0,O18>Assumptions!$C$43),1,0) -> 1 | M19: =O18 -> 244561.11 | N19: =IF(L19=1,M19*$B$22,0) -> 815.2037 | O19: =IF(L19=1,M19+N19-$B$26,M19) -> 244056.72 | P19: =IF(L19=1,IF($B$26<=N19,1,0),0) -> 0 | Q19: =Q18+N19 -> 9891.8255 | S19: =S18+1 -> 12 | T19: =IF(AND(S19<=Assumptions!$C$42,T18=1,X18=0,W18>Assumptions!$C$43),1,0) -> 1 | U19: =W18 -> 242324.07 | V19: =IF(T19=1,U19*$B$22,0) -> 807.74691 | W19: =IF(T19=1,U19+V19-$B$27,U19) -> 241612.23 | X19: =IF(T19=1,IF($B$27<=V19,1,0),0) -> 0 | Y19: =Y18+V19 -> 9847.3329
A20: CALCULATION | K20: =K19+1 -> 13 | L20: =IF(AND(K20<=Assumptions!$C$42,L19=1,P19=0,O19>Assumptions!$C$43),1,0) -> 1 | M20: =O19 -> 244056.72 | N20: =IF(L20=1,M20*$B$22,0) -> 813.5224 | O20: =IF(L20=1,M20+N20-$B$26,M20) -> 243550.65 | P20: =IF(L20=1,IF($B$26<=N20,1,0),0) -> 0 | Q20: =Q19+N20 -> 10705.348 | S20: =S19+1 -> 13 | T20: =IF(AND(S20<=Assumptions!$C$42,T19=1,X19=0,W19>Assumptions!$C$43),1,0) -> 1 | U20: =W19 -> 241612.23 | V20: =IF(T20=1,U20*$B$22,0) -> 805.37409 | W20: =IF(T20=1,U20+V20-$B$27,U20) -> 240898.01 | X20: =IF(T20=1,IF($B$27<=V20,1,0),0) -> 0 | Y20: =Y19+V20 -> 10652.707
A21: Calculation step | B21: Value | C21: Unit | D21: JS equivalent (prototype run function) | K21: =K20+1 -> 14 | L21: =IF(AND(K21<=Assumptions!$C$42,L20=1,P20=0,O20>Assumptions!$C$43),1,0) -> 1 | M21: =O20 -> 243550.65 | N21: =IF(L21=1,M21*$B$22,0) -> 811.8355 | O21: =IF(L21=1,M21+N21-$B$26,M21) -> 243042.89 | P21: =IF(L21=1,IF($B$26<=N21,1,0),0) -> 0 | Q21: =Q20+N21 -> 11517.183 | S21: =S20+1 -> 14 | T21: =IF(AND(S21<=Assumptions!$C$42,T20=1,X20=0,W20>Assumptions!$C$43),1,0) -> 1 | U21: =W20 -> 240898.01 | V21: =IF(T21=1,U21*$B$22,0) -> 802.99337 | W21: =IF(T21=1,U21+V21-$B$27,U21) -> 240181.41 | X21: =IF(T21=1,IF($B$27<=V21,1,0),0) -> 0 | Y21: =Y20+V21 -> 11455.7
A22: Monthly interest rate | B22: =$B$11/12 -> 0.0033333333 | C22: rate (fraction) | D22: i = r / 100 / 12 | K22: =K21+1 -> 15 | L22: =IF(AND(K22<=Assumptions!$C$42,L21=1,P21=0,O21>Assumptions!$C$43),1,0) -> 1 | M22: =O21 -> 243042.89 | N22: =IF(L22=1,M22*$B$22,0) -> 810.14298 | O22: =IF(L22=1,M22+N22-$B$26,M22) -> 242533.44 | P22: =IF(L22=1,IF($B$26<=N22,1,0),0) -> 0 | Q22: =Q21+N22 -> 12327.326 | S22: =S21+1 -> 15 | T22: =IF(AND(S22<=Assumptions!$C$42,T21=1,X21=0,W21>Assumptions!$C$43),1,0) -> 1 | U22: =W21 -> 240181.41 | V22: =IF(T22=1,U22*$B$22,0) -> 800.6047 | W22: =IF(T22=1,U22+V22-$B$27,U22) -> 239462.42 | X22: =IF(T22=1,IF($B$27<=V22,1,0),0) -> 0 | Y22: =Y21+V22 -> 12256.305
A23: Number of monthly payments | B23: =$B$12*12 -> 300 | C23: n | D23: n = y * 12 | K23: =K22+1 -> 16 | L23: =IF(AND(K23<=Assumptions!$C$42,L22=1,P22=0,O22>Assumptions!$C$43),1,0) -> 1 | M23: =O22 -> 242533.44 | N23: =IF(L23=1,M23*$B$22,0) -> 808.44482 | O23: =IF(L23=1,M23+N23-$B$26,M23) -> 242022.3 | P23: =IF(L23=1,IF($B$26<=N23,1,0),0) -> 0 | Q23: =Q22+N23 -> 13135.771 | S23: =S22+1 -> 16 | T23: =IF(AND(S23<=Assumptions!$C$42,T22=1,X22=0,W22>Assumptions!$C$43),1,0) -> 1 | U23: =W22 -> 239462.42 | V23: =IF(T23=1,U23*$B$22,0) -> 798.20808 | W23: =IF(T23=1,U23+V23-$B$27,U23) -> 238741.04 | X23: =IF(T23=1,IF($B$27<=V23,1,0),0) -> 0 | Y23: =Y22+V23 -> 13054.513
A24: Formula repayment | B24: =IF(($B$23)=0,0,IF($B$22<>0,$B$10*$B$22/(1-POWER(1+$B$22,-($B$23))),$B$10/($B$23))) -> 1319.5921 | C24: € | D24: pmt(v.bal, v.rate, v.yrs) | K24: =K23+1 -> 17 | L24: =IF(AND(K24<=Assumptions!$C$42,L23=1,P23=0,O23>Assumptions!$C$43),1,0) -> 1 | M24: =O23 -> 242022.3 | N24: =IF(L24=1,M24*$B$22,0) -> 806.74099 | O24: =IF(L24=1,M24+N24-$B$26,M24) -> 241509.45 | P24: =IF(L24=1,IF($B$26<=N24,1,0),0) -> 0 | Q24: =Q23+N24 -> 13942.512 | S24: =S23+1 -> 17 | T24: =IF(AND(S24<=Assumptions!$C$42,T23=1,X23=0,W23>Assumptions!$C$43),1,0) -> 1 | U24: =W23 -> 238741.04 | V24: =IF(T24=1,U24*$B$22,0) -> 795.80347 | W24: =IF(T24=1,U24+V24-$B$27,U24) -> 238017.25 | X24: =IF(T24=1,IF($B$27<=V24,1,0),0) -> 0 | Y24: =Y23+V24 -> 13850.317
A25: Stated repayment in use (0 = none) | B25: =IF(AND($B$18=1,$B$17>0),$B$17,0) -> 0 | C25: € | D25: own = mine(...) ? statedM('mortPayM') : null | K25: =K24+1 -> 18 | L25: =IF(AND(K25<=Assumptions!$C$42,L24=1,P24=0,O24>Assumptions!$C$43),1,0) -> 1 | M25: =O24 -> 241509.45 | N25: =IF(L25=1,M25*$B$22,0) -> 805.03149 | O25: =IF(L25=1,M25+N25-$B$26,M25) -> 240994.89 | P25: =IF(L25=1,IF($B$26<=N25,1,0),0) -> 0 | Q25: =Q24+N25 -> 14747.544 | S25: =S24+1 -> 18 | T25: =IF(AND(S25<=Assumptions!$C$42,T24=1,X24=0,W24>Assumptions!$C$43),1,0) -> 1 | U25: =W24 -> 238017.25 | V25: =IF(T25=1,U25*$B$22,0) -> 793.39084 | W25: =IF(T25=1,U25+V25-$B$27,U25) -> 237291.05 | X25: =IF(T25=1,IF($B$27<=V25,1,0),0) -> 0 | Y25: =Y24+V25 -> 14643.707
A26: Repayment now | B26: =IF($B$25>0,$B$25,$B$24) -> 1319.5921 | C26: € | D26: p = own || pmt(...) | K26: =K25+1 -> 19 | L26: =IF(AND(K26<=Assumptions!$C$42,L25=1,P25=0,O25>Assumptions!$C$43),1,0) -> 1 | M26: =O25 -> 240994.89 | N26: =IF(L26=1,M26*$B$22,0) -> 803.31629 | O26: =IF(L26=1,M26+N26-$B$26,M26) -> 240478.61 | P26: =IF(L26=1,IF($B$26<=N26,1,0),0) -> 0 | Q26: =Q25+N26 -> 15550.86 | S26: =S25+1 -> 19 | T26: =IF(AND(S26<=Assumptions!$C$42,T25=1,X25=0,W25>Assumptions!$C$43),1,0) -> 1 | U26: =W25 -> 237291.05 | V26: =IF(T26=1,U26*$B$22,0) -> 790.97017 | W26: =IF(T26=1,U26+V26-$B$27,U26) -> 236562.43 | X26: =IF(T26=1,IF($B$27<=V26,1,0),0) -> 0 | Y26: =Y25+V26 -> 15434.678
A27: Repayment with the extra | B27: =$B$26+$B$13 -> 1519.5921 | C27: € | D27: p + v.x | K27: =K26+1 -> 20 | L27: =IF(AND(K27<=Assumptions!$C$42,L26=1,P26=0,O26>Assumptions!$C$43),1,0) -> 1 | M27: =O26 -> 240478.61 | N27: =IF(L27=1,M27*$B$22,0) -> 801.59537 | O27: =IF(L27=1,M27+N27-$B$26,M27) -> 239960.61 | P27: =IF(L27=1,IF($B$26<=N27,1,0),0) -> 0 | Q27: =Q26+N27 -> 16352.455 | S27: =S26+1 -> 20 | T27: =IF(AND(S27<=Assumptions!$C$42,T26=1,X26=0,W26>Assumptions!$C$43),1,0) -> 1 | U27: =W26 -> 236562.43 | V27: =IF(T27=1,U27*$B$22,0) -> 788.54143 | W27: =IF(T27=1,U27+V27-$B$27,U27) -> 235831.38 | X27: =IF(T27=1,IF($B$27<=V27,1,0),0) -> 0 | Y27: =Y26+V27 -> 16223.219
A28: A never pays off (1) | B28: =MAX($P$8:$P$1207) -> 0 | C28: flag | D28: a.m === Infinity | K28: =K27+1 -> 21 | L28: =IF(AND(K28<=Assumptions!$C$42,L27=1,P27=0,O27>Assumptions!$C$43),1,0) -> 1 | M28: =O27 -> 239960.61 | N28: =IF(L28=1,M28*$B$22,0) -> 799.86871 | O28: =IF(L28=1,M28+N28-$B$26,M28) -> 239440.89 | P28: =IF(L28=1,IF($B$26<=N28,1,0),0) -> 0 | Q28: =Q27+N28 -> 17152.324 | S28: =S27+1 -> 21 | T28: =IF(AND(S28<=Assumptions!$C$42,T27=1,X27=0,W27>Assumptions!$C$43),1,0) -> 1 | U28: =W27 -> 235831.38 | V28: =IF(T28=1,U28*$B$22,0) -> 786.10459 | W28: =IF(T28=1,U28+V28-$B$27,U28) -> 235097.89 | X28: =IF(T28=1,IF($B$27<=V28,1,0),0) -> 0 | Y28: =Y27+V28 -> 17009.324
A29: A months | B29: =SUM($L$8:$L$1207) -> 300 | C29: n | D29: a.m | K29: =K28+1 -> 22 | L29: =IF(AND(K29<=Assumptions!$C$42,L28=1,P28=0,O28>Assumptions!$C$43),1,0) -> 1 | M29: =O28 -> 239440.89 | N29: =IF(L29=1,M29*$B$22,0) -> 798.1363 | O29: =IF(L29=1,M29+N29-$B$26,M29) -> 238919.43 | P29: =IF(L29=1,IF($B$26<=N29,1,0),0) -> 0 | Q29: =Q28+N29 -> 17950.46 | S29: =S28+1 -> 22 | T29: =IF(AND(S29<=Assumptions!$C$42,T28=1,X28=0,W28>Assumptions!$C$43),1,0) -> 1 | U29: =W28 -> 235097.89 | V29: =IF(T29=1,U29*$B$22,0) -> 783.65963 | W29: =IF(T29=1,U29+V29-$B$27,U29) -> 234361.96 | X29: =IF(T29=1,IF($B$27<=V29,1,0),0) -> 0 | Y29: =Y28+V29 -> 17792.983
A30: A total interest | B30: =$Q$1207 -> 145877.63 | C30: € | D30: a.int | K30: =K29+1 -> 23 | L30: =IF(AND(K30<=Assumptions!$C$42,L29=1,P29=0,O29>Assumptions!$C$43),1,0) -> 1 | M30: =O29 -> 238919.43 | N30: =IF(L30=1,M30*$B$22,0) -> 796.39811 | O30: =IF(L30=1,M30+N30-$B$26,M30) -> 238396.24 | P30: =IF(L30=1,IF($B$26<=N30,1,0),0) -> 0 | Q30: =Q29+N30 -> 18746.858 | S30: =S29+1 -> 23 | T30: =IF(AND(S30<=Assumptions!$C$42,T29=1,X29=0,W29>Assumptions!$C$43),1,0) -> 1 | U30: =W29 -> 234361.96 | V30: =IF(T30=1,U30*$B$22,0) -> 781.20652 | W30: =IF(T30=1,U30+V30-$B$27,U30) -> 233623.57 | X30: =IF(T30=1,IF($B$27<=V30,1,0),0) -> 0 | Y30: =Y29+V30 -> 18574.19
A31: B never pays off (1) | B31: =MAX($X$8:$X$1207) -> 0 | C31: flag | D31: b.m === Infinity | K31: =K30+1 -> 24 | L31: =IF(AND(K31<=Assumptions!$C$42,L30=1,P30=0,O30>Assumptions!$C$43),1,0) -> 1 | M31: =O30 -> 238396.24 | N31: =IF(L31=1,M31*$B$22,0) -> 794.65413 | O31: =IF(L31=1,M31+N31-$B$26,M31) -> 237871.3 | P31: =IF(L31=1,IF($B$26<=N31,1,0),0) -> 0 | Q31: =Q30+N31 -> 19541.513 | S31: =S30+1 -> 24 | T31: =IF(AND(S31<=Assumptions!$C$42,T30=1,X30=0,W30>Assumptions!$C$43),1,0) -> 1 | U31: =W30 -> 233623.57 | V31: =IF(T31=1,U31*$B$22,0) -> 778.74524 | W31: =IF(T31=1,U31+V31-$B$27,U31) -> 232882.72 | X31: =IF(T31=1,IF($B$27<=V31,1,0),0) -> 0 | Y31: =Y30+V31 -> 19352.935
A32: B months | B32: =SUM($T$8:$T$1207) -> 239 | C32: n | D32: b.m | K32: =K31+1 -> 25 | L32: =IF(AND(K32<=Assumptions!$C$42,L31=1,P31=0,O31>Assumptions!$C$43),1,0) -> 1 | M32: =O31 -> 237871.3 | N32: =IF(L32=1,M32*$B$22,0) -> 792.90434 | O32: =IF(L32=1,M32+N32-$B$26,M32) -> 237344.61 | P32: =IF(L32=1,IF($B$26<=N32,1,0),0) -> 0 | Q32: =Q31+N32 -> 20334.417 | S32: =S31+1 -> 25 | T32: =IF(AND(S32<=Assumptions!$C$42,T31=1,X31=0,W31>Assumptions!$C$43),1,0) -> 1 | U32: =W31 -> 232882.72 | V32: =IF(T32=1,U32*$B$22,0) -> 776.27575 | W32: =IF(T32=1,U32+V32-$B$27,U32) -> 232139.41 | X32: =IF(T32=1,IF($B$27<=V32,1,0),0) -> 0 | Y32: =Y31+V32 -> 20129.211
A33: B total interest | B33: =$Y$1207 -> 113000.41 | C33: € | D33: b.int | K33: =K32+1 -> 26 | L33: =IF(AND(K33<=Assumptions!$C$42,L32=1,P32=0,O32>Assumptions!$C$43),1,0) -> 1 | M33: =O32 -> 237344.61 | N33: =IF(L33=1,M33*$B$22,0) -> 791.14871 | O33: =IF(L33=1,M33+N33-$B$26,M33) -> 236816.17 | P33: =IF(L33=1,IF($B$26<=N33,1,0),0) -> 0 | Q33: =Q32+N33 -> 21125.566 | S33: =S32+1 -> 26 | T33: =IF(AND(S33<=Assumptions!$C$42,T32=1,X32=0,W32>Assumptions!$C$43),1,0) -> 1 | U33: =W32 -> 232139.41 | V33: =IF(T33=1,U33*$B$22,0) -> 773.79803 | W33: =IF(T33=1,U33+V33-$B$27,U33) -> 231393.61 | X33: =IF(T33=1,IF($B$27<=V33,1,0),0) -> 0 | Y33: =Y32+V33 -> 20903.009
A34: Months sooner | B34: =IF($B$31=1,0,MAX(0,$B$29-$B$32)) -> 61 | C34: n | D34: Math.max(0, a.m - b.m) (a.m − Infinity → 0) | K34: =K33+1 -> 27 | L34: =IF(AND(K34<=Assumptions!$C$42,L33=1,P33=0,O33>Assumptions!$C$43),1,0) -> 1 | M34: =O33 -> 236816.17 | N34: =IF(L34=1,M34*$B$22,0) -> 789.38724 | O34: =IF(L34=1,M34+N34-$B$26,M34) -> 236285.97 | P34: =IF(L34=1,IF($B$26<=N34,1,0),0) -> 0 | Q34: =Q33+N34 -> 21914.953 | S34: =S33+1 -> 27 | T34: =IF(AND(S34<=Assumptions!$C$42,T33=1,X33=0,W33>Assumptions!$C$43),1,0) -> 1 | U34: =W33 -> 231393.61 | V34: =IF(T34=1,U34*$B$22,0) -> 771.31205 | W34: =IF(T34=1,U34+V34-$B$27,U34) -> 230645.33 | X34: =IF(T34=1,IF($B$27<=V34,1,0),0) -> 0 | Y34: =Y33+V34 -> 21674.321
A35: Interest saved | B35: =$B$30-$B$33 -> 32877.222 | C35: € | D35: a.int - b.int | K35: =K34+1 -> 28 | L35: =IF(AND(K35<=Assumptions!$C$42,L34=1,P34=0,O34>Assumptions!$C$43),1,0) -> 1 | M35: =O34 -> 236285.97 | N35: =IF(L35=1,M35*$B$22,0) -> 787.61989 | O35: =IF(L35=1,M35+N35-$B$26,M35) -> 235753.99 | P35: =IF(L35=1,IF($B$26<=N35,1,0),0) -> 0 | Q35: =Q34+N35 -> 22702.573 | S35: =S34+1 -> 28 | T35: =IF(AND(S35<=Assumptions!$C$42,T34=1,X34=0,W34>Assumptions!$C$43),1,0) -> 1 | U35: =W34 -> 230645.33 | V35: =IF(T35=1,U35*$B$22,0) -> 768.81778 | W35: =IF(T35=1,U35+V35-$B$27,U35) -> 229894.56 | X35: =IF(T35=1,IF($B$27<=V35,1,0),0) -> 0 | Y35: =Y34+V35 -> 22443.139
K36: =K35+1 -> 29 | L36: =IF(AND(K36<=Assumptions!$C$42,L35=1,P35=0,O35>Assumptions!$C$43),1,0) -> 1 | M36: =O35 -> 235753.99 | N36: =IF(L36=1,M36*$B$22,0) -> 785.84665 | O36: =IF(L36=1,M36+N36-$B$26,M36) -> 235220.25 | P36: =IF(L36=1,IF($B$26<=N36,1,0),0) -> 0 | Q36: =Q35+N36 -> 23488.419 | S36: =S35+1 -> 29 | T36: =IF(AND(S36<=Assumptions!$C$42,T35=1,X35=0,W35>Assumptions!$C$43),1,0) -> 1 | U36: =W35 -> 229894.56 | V36: =IF(T36=1,U36*$B$22,0) -> 766.3152 | W36: =IF(T36=1,U36+V36-$B$27,U36) -> 229141.28 | X36: =IF(T36=1,IF($B$27<=V36,1,0),0) -> 0 | Y36: =Y35+V36 -> 23209.454
A37: OUTPUTS | K37: =K36+1 -> 30 | L37: =IF(AND(K37<=Assumptions!$C$42,L36=1,P36=0,O36>Assumptions!$C$43),1,0) -> 1 | M37: =O36 -> 235220.25 | N37: =IF(L37=1,M37*$B$22,0) -> 784.06749 | O37: =IF(L37=1,M37+N37-$B$26,M37) -> 234684.72 | P37: =IF(L37=1,IF($B$26<=N37,1,0),0) -> 0 | Q37: =Q36+N37 -> 24272.487 | S37: =S36+1 -> 30 | T37: =IF(AND(S37<=Assumptions!$C$42,T36=1,X36=0,W36>Assumptions!$C$43),1,0) -> 1 | U37: =W36 -> 229141.28 | V37: =IF(T37=1,U37*$B$22,0) -> 763.80428 | W37: =IF(T37=1,U37+V37-$B$27,U37) -> 228385.5 | X37: =IF(T37=1,IF($B$27<=V37,1,0),0) -> 0 | Y37: =Y36+V37 -> 23973.258
A38: Output | B38: Value | C38: As shown in the prototype | D38: Shown when / where it appears | K38: =K37+1 -> 31 | L38: =IF(AND(K38<=Assumptions!$C$42,L37=1,P37=0,O37>Assumptions!$C$43),1,0) -> 1 | M38: =O37 -> 234684.72 | N38: =IF(L38=1,M38*$B$22,0) -> 782.28241 | O38: =IF(L38=1,M38+N38-$B$26,M38) -> 234147.41 | P38: =IF(L38=1,IF($B$26<=N38,1,0),0) -> 0 | Q38: =Q37+N38 -> 25054.769 | S38: =S37+1 -> 31 | T38: =IF(AND(S38<=Assumptions!$C$42,T37=1,X37=0,W37>Assumptions!$C$43),1,0) -> 1 | U38: =W37 -> 228385.5 | V38: =IF(T38=1,U38*$B$22,0) -> 761.28498 | W38: =IF(T38=1,U38+V38-$B$27,U38) -> 227627.19 | X38: =IF(T38=1,IF($B$27<=V38,1,0),0) -> 0 | Y38: =Y37+V38 -> 24734.543
A39: Headline label | C39: ="Mortgage free sooner by" -> Mortgage free sooner by | D39: Always | K39: =K38+1 -> 32 | L39: =IF(AND(K39<=Assumptions!$C$42,L38=1,P38=0,O38>Assumptions!$C$43),1,0) -> 1 | M39: =O38 -> 234147.41 | N39: =IF(L39=1,M39*$B$22,0) -> 780.49138 | O39: =IF(L39=1,M39+N39-$B$26,M39) -> 233608.31 | P39: =IF(L39=1,IF($B$26<=N39,1,0),0) -> 0 | Q39: =Q38+N39 -> 25835.261 | S39: =S38+1 -> 32 | T39: =IF(AND(S39<=Assumptions!$C$42,T38=1,X38=0,W38>Assumptions!$C$43),1,0) -> 1 | U39: =W38 -> 227627.19 | V39: =IF(T39=1,U39*$B$22,0) -> 758.75729 | W39: =IF(T39=1,U39+V39-$B$27,U39) -> 226866.35 | X39: =IF(T39=1,IF($B$27<=V39,1,0),0) -> 0 | Y39: =Y38+V39 -> 25493.3
A40: Mortgage free sooner by (months) | B40: =IF($B$28=1,"",$B$34) -> 61 | C40: =IF($B$28=1,"—",IF(INT($B$34/12)>0,INT($B$34/12)&" yr"&IF(INT($B$34/12)>1,"s","")&IF(ROUND(MOD($B$34,12),0)<>0," "&ROUND(MOD($B$34,12),0)&" mo",""),ROUND(MOD($B$34,12),0)&" months")) -> 5 yrs 1 mo | D40: Headline | K40: =K39+1 -> 33 | L40: =IF(AND(K40<=Assumptions!$C$42,L39=1,P39=0,O39>Assumptions!$C$43),1,0) -> 1 | M40: =O39 -> 233608.31 | N40: =IF(L40=1,M40*$B$22,0) -> 778.69438 | O40: =IF(L40=1,M40+N40-$B$26,M40) -> 233067.42 | P40: =IF(L40=1,IF($B$26<=N40,1,0),0) -> 0 | Q40: =Q39+N40 -> 26613.955 | S40: =S39+1 -> 33 | T40: =IF(AND(S40<=Assumptions!$C$42,T39=1,X39=0,W39>Assumptions!$C$43),1,0) -> 1 | U40: =W39 -> 226866.35 | V40: =IF(T40=1,U40*$B$22,0) -> 756.22118 | W40: =IF(T40=1,U40+V40-$B$27,U40) -> 226102.98 | X40: =IF(T40=1,IF($B$27<=V40,1,0),0) -> 0 | Y40: =Y39+V40 -> 26249.522
A41: Extra a month (sentence) | B41: =$B$13 -> 200 | C41: =IF(($B$13)<0,"−€","€")&FIXED(ROUND(ABS($B$13),0),0) -> €200 | D41: Sentence | K41: =K40+1 -> 34 | L41: =IF(AND(K41<=Assumptions!$C$42,L40=1,P40=0,O40>Assumptions!$C$43),1,0) -> 1 | M41: =O40 -> 233067.42 | N41: =IF(L41=1,M41*$B$22,0) -> 776.89139 | O41: =IF(L41=1,M41+N41-$B$26,M41) -> 232524.72 | P41: =IF(L41=1,IF($B$26<=N41,1,0),0) -> 0 | Q41: =Q40+N41 -> 27390.846 | S41: =S40+1 -> 34 | T41: =IF(AND(S41<=Assumptions!$C$42,T40=1,X40=0,W40>Assumptions!$C$43),1,0) -> 1 | U41: =W40 -> 226102.98 | V41: =IF(T41=1,U41*$B$22,0) -> 753.67661 | W41: =IF(T41=1,U41+V41-$B$27,U41) -> 225337.07 | X41: =IF(T41=1,IF($B$27<=V41,1,0),0) -> 0 | Y41: =Y40+V41 -> 27003.198
A42: On top of (repayment now, sentence) | B42: =$B$26 -> 1319.5921 | C42: =IF(($B$26)<0,"−€","€")&FIXED(ROUND(ABS($B$26),0),0) -> €1,320 | D42: Sentence | K42: =K41+1 -> 35 | L42: =IF(AND(K42<=Assumptions!$C$42,L41=1,P41=0,O41>Assumptions!$C$43),1,0) -> 1 | M42: =O41 -> 232524.72 | N42: =IF(L42=1,M42*$B$22,0) -> 775.08238 | O42: =IF(L42=1,M42+N42-$B$26,M42) -> 231980.21 | P42: =IF(L42=1,IF($B$26<=N42,1,0),0) -> 0 | Q42: =Q41+N42 -> 28165.929 | S42: =S41+1 -> 35 | T42: =IF(AND(S42<=Assumptions!$C$42,T41=1,X41=0,W41>Assumptions!$C$43),1,0) -> 1 | U42: =W41 -> 225337.07 | V42: =IF(T42=1,U42*$B$22,0) -> 751.12356 | W42: =IF(T42=1,U42+V42-$B$27,U42) -> 224568.6 | X42: =IF(T42=1,IF($B$27<=V42,1,0),0) -> 0 | Y42: =Y41+V42 -> 27754.322
A43: Mortgage free now in (months) | B43: =IF($B$28=1,"",$B$29) -> 300 | C43: =IF($B$28=1,"—",IF(INT($B$29/12)>0,INT($B$29/12)&" yr"&IF(INT($B$29/12)>1,"s","")&IF(ROUND(MOD($B$29,12),0)<>0," "&ROUND(MOD($B$29,12),0)&" mo",""),ROUND(MOD($B$29,12),0)&" months")) -> 25 yrs | D43: Row 1 | K43: =K42+1 -> 36 | L43: =IF(AND(K43<=Assumptions!$C$42,L42=1,P42=0,O42>Assumptions!$C$43),1,0) -> 1 | M43: =O42 -> 231980.21 | N43: =IF(L43=1,M43*$B$22,0) -> 773.26735 | O43: =IF(L43=1,M43+N43-$B$26,M43) -> 231433.88 | P43: =IF(L43=1,IF($B$26<=N43,1,0),0) -> 0 | Q43: =Q42+N43 -> 28939.196 | S43: =S42+1 -> 36 | T43: =IF(AND(S43<=Assumptions!$C$42,T42=1,X42=0,W42>Assumptions!$C$43),1,0) -> 1 | U43: =W42 -> 224568.6 | V43: =IF(T43=1,U43*$B$22,0) -> 748.56199 | W43: =IF(T43=1,U43+V43-$B$27,U43) -> 223797.57 | X43: =IF(T43=1,IF($B$27<=V43,1,0),0) -> 0 | Y43: =Y42+V43 -> 28502.884
A44: With the extra (months) | B44: =IF($B$31=1,"Infinity",$B$32) -> 239 | C44: =IF($B$31=1,"Infinity yrs",IF(INT($B$32/12)>0,INT($B$32/12)&" yr"&IF(INT($B$32/12)>1,"s","")&IF(ROUND(MOD($B$32,12),0)<>0," "&ROUND(MOD($B$32,12),0)&" mo",""),ROUND(MOD($B$32,12),0)&" months")) -> 19 yrs 11 mo | D44: Row 2 | K44: =K43+1 -> 37 | L44: =IF(AND(K44<=Assumptions!$C$42,L43=1,P43=0,O43>Assumptions!$C$43),1,0) -> 1 | M44: =O43 -> 231433.88 | N44: =IF(L44=1,M44*$B$22,0) -> 771.44627 | O44: =IF(L44=1,M44+N44-$B$26,M44) -> 230885.73 | P44: =IF(L44=1,IF($B$26<=N44,1,0),0) -> 0 | Q44: =Q43+N44 -> 29710.642 | S44: =S43+1 -> 37 | T44: =IF(AND(S44<=Assumptions!$C$42,T43=1,X43=0,W43>Assumptions!$C$43),1,0) -> 1 | U44: =W43 -> 223797.57 | V44: =IF(T44=1,U44*$B$22,0) -> 745.99189 | W44: =IF(T44=1,U44+V44-$B$27,U44) -> 223023.97 | X44: =IF(T44=1,IF($B$27<=V44,1,0),0) -> 0 | Y44: =Y43+V44 -> 29248.876
A45: Interest saved | B45: =$B$35 -> 32877.222 | C45: =IF(($B$35)<0,"−€","€")&FIXED(ROUND(ABS($B$35),0),0) -> €32,877 | D45: Row 3 (also in the sentence) | K45: =K44+1 -> 38 | L45: =IF(AND(K45<=Assumptions!$C$42,L44=1,P44=0,O44>Assumptions!$C$43),1,0) -> 1 | M45: =O44 -> 230885.73 | N45: =IF(L45=1,M45*$B$22,0) -> 769.61912 | O45: =IF(L45=1,M45+N45-$B$26,M45) -> 230335.76 | P45: =IF(L45=1,IF($B$26<=N45,1,0),0) -> 0 | Q45: =Q44+N45 -> 30480.262 | S45: =S44+1 -> 38 | T45: =IF(AND(S45<=Assumptions!$C$42,T44=1,X44=0,W44>Assumptions!$C$43),1,0) -> 1 | U45: =W44 -> 223023.97 | V45: =IF(T45=1,U45*$B$22,0) -> 743.41323 | W45: =IF(T45=1,U45+V45-$B$27,U45) -> 222247.79 | X45: =IF(T45=1,IF($B$27<=V45,1,0),0) -> 0 | Y45: =Y44+V45 -> 29992.289
A46: "Add to my plan" goal amount (Mortgage free) | B46: =$B$10 -> 250000 | C46: =$B$46&"" -> 250000 | D46: Add to my plan | K46: =K45+1 -> 39 | L46: =IF(AND(K46<=Assumptions!$C$42,L45=1,P45=0,O45>Assumptions!$C$43),1,0) -> 1 | M46: =O45 -> 230335.76 | N46: =IF(L46=1,M46*$B$22,0) -> 767.78587 | O46: =IF(L46=1,M46+N46-$B$26,M46) -> 229783.96 | P46: =IF(L46=1,IF($B$26<=N46,1,0),0) -> 0 | Q46: =Q45+N46 -> 31248.047 | S46: =S45+1 -> 39 | T46: =IF(AND(S46<=Assumptions!$C$42,T45=1,X45=0,W45>Assumptions!$C$43),1,0) -> 1 | U46: =W45 -> 222247.79 | V46: =IF(T46=1,U46*$B$22,0) -> 740.82596 | W46: =IF(T46=1,U46+V46-$B$27,U46) -> 221469.02 | X46: =IF(T46=1,IF($B$27<=V46,1,0),0) -> 0 | Y46: =Y45+V46 -> 30733.115
A47: "Add to my plan" goal years | B47: =IF($B$31=1,"Infinity",(-INT(-($B$32/12)))) -> 20 | C47: =$B$47&"" -> 20 | D47: Add to my plan: Math.ceil(b.m / 12) | K47: =K46+1 -> 40 | L47: =IF(AND(K47<=Assumptions!$C$42,L46=1,P46=0,O46>Assumptions!$C$43),1,0) -> 1 | M47: =O46 -> 229783.96 | N47: =IF(L47=1,M47*$B$22,0) -> 765.94652 | O47: =IF(L47=1,M47+N47-$B$26,M47) -> 229230.31 | P47: =IF(L47=1,IF($B$26<=N47,1,0),0) -> 0 | Q47: =Q46+N47 -> 32013.994 | S47: =S46+1 -> 40 | T47: =IF(AND(S47<=Assumptions!$C$42,T46=1,X46=0,W46>Assumptions!$C$43),1,0) -> 1 | U47: =W46 -> 221469.02 | V47: =IF(T47=1,U47*$B$22,0) -> 738.23008 | W47: =IF(T47=1,U47+V47-$B$27,U47) -> 220687.66 | X47: =IF(T47=1,IF($B$27<=V47,1,0),0) -> 0 | Y47: =Y46+V47 -> 31471.345
K48: =K47+1 -> 41 | L48: =IF(AND(K48<=Assumptions!$C$42,L47=1,P47=0,O47>Assumptions!$C$43),1,0) -> 1 | M48: =O47 -> 229230.31 | N48: =IF(L48=1,M48*$B$22,0) -> 764.10103 | O48: =IF(L48=1,M48+N48-$B$26,M48) -> 228674.82 | P48: =IF(L48=1,IF($B$26<=N48,1,0),0) -> 0 | Q48: =Q47+N48 -> 32778.095 | S48: =S47+1 -> 41 | T48: =IF(AND(S48<=Assumptions!$C$42,T47=1,X47=0,W47>Assumptions!$C$43),1,0) -> 1 | U48: =W47 -> 220687.66 | V48: =IF(T48=1,U48*$B$22,0) -> 735.62554 | W48: =IF(T48=1,U48+V48-$B$27,U48) -> 219903.69 | X48: =IF(T48=1,IF($B$27<=V48,1,0),0) -> 0 | Y48: =Y47+V48 -> 32206.97
K49: =K48+1 -> 42 | L49: =IF(AND(K49<=Assumptions!$C$42,L48=1,P48=0,O48>Assumptions!$C$43),1,0) -> 1 | M49: =O48 -> 228674.82 | N49: =IF(L49=1,M49*$B$22,0) -> 762.2494 | O49: =IF(L49=1,M49+N49-$B$26,M49) -> 228117.48 | P49: =IF(L49=1,IF($B$26<=N49,1,0),0) -> 0 | Q49: =Q48+N49 -> 33540.344 | S49: =S48+1 -> 42 | T49: =IF(AND(S49<=Assumptions!$C$42,T48=1,X48=0,W48>Assumptions!$C$43),1,0) -> 1 | U49: =W48 -> 219903.69 | V49: =IF(T49=1,U49*$B$22,0) -> 733.01231 | W49: =IF(T49=1,U49+V49-$B$27,U49) -> 219117.11 | X49: =IF(T49=1,IF($B$27<=V49,1,0),0) -> 0 | Y49: =Y48+V49 -> 32939.983
K50: =K49+1 -> 43 | L50: =IF(AND(K50<=Assumptions!$C$42,L49=1,P49=0,O49>Assumptions!$C$43),1,0) -> 1 | M50: =O49 -> 228117.48 | N50: =IF(L50=1,M50*$B$22,0) -> 760.39159 | O50: =IF(L50=1,M50+N50-$B$26,M50) -> 227558.28 | P50: =IF(L50=1,IF($B$26<=N50,1,0),0) -> 0 | Q50: =Q49+N50 -> 34300.736 | S50: =S49+1 -> 43 | T50: =IF(AND(S50<=Assumptions!$C$42,T49=1,X49=0,W49>Assumptions!$C$43),1,0) -> 1 | U50: =W49 -> 219117.11 | V50: =IF(T50=1,U50*$B$22,0) -> 730.39038 | W50: =IF(T50=1,U50+V50-$B$27,U50) -> 218327.91 | X50: =IF(T50=1,IF($B$27<=V50,1,0),0) -> 0 | Y50: =Y49+V50 -> 33670.373
K51: =K50+1 -> 44 | L51: =IF(AND(K51<=Assumptions!$C$42,L50=1,P50=0,O50>Assumptions!$C$43),1,0) -> 1 | M51: =O50 -> 227558.28 | N51: =IF(L51=1,M51*$B$22,0) -> 758.52759 | O51: =IF(L51=1,M51+N51-$B$26,M51) -> 226997.21 | P51: =IF(L51=1,IF($B$26<=N51,1,0),0) -> 0 | Q51: =Q50+N51 -> 35059.264 | S51: =S50+1 -> 44 | T51: =IF(AND(S51<=Assumptions!$C$42,T50=1,X50=0,W50>Assumptions!$C$43),1,0) -> 1 | U51: =W50 -> 218327.91 | V51: =IF(T51=1,U51*$B$22,0) -> 727.75971 | W51: =IF(T51=1,U51+V51-$B$27,U51) -> 217536.08 | X51: =IF(T51=1,IF($B$27<=V51,1,0),0) -> 0 | Y51: =Y50+V51 -> 34398.133
K52: =K51+1 -> 45 | L52: =IF(AND(K52<=Assumptions!$C$42,L51=1,P51=0,O51>Assumptions!$C$43),1,0) -> 1 | M52: =O51 -> 226997.21 | N52: =IF(L52=1,M52*$B$22,0) -> 756.65737 | O52: =IF(L52=1,M52+N52-$B$26,M52) -> 226434.28 | P52: =IF(L52=1,IF($B$26<=N52,1,0),0) -> 0 | Q52: =Q51+N52 -> 35815.921 | S52: =S51+1 -> 45 | T52: =IF(AND(S52<=Assumptions!$C$42,T51=1,X51=0,W51>Assumptions!$C$43),1,0) -> 1 | U52: =W51 -> 217536.08 | V52: =IF(T52=1,U52*$B$22,0) -> 725.12027 | W52: =IF(T52=1,U52+V52-$B$27,U52) -> 216741.61 | X52: =IF(T52=1,IF($B$27<=V52,1,0),0) -> 0 | Y52: =Y51+V52 -> 35123.253
K53: =K52+1 -> 46 | L53: =IF(AND(K53<=Assumptions!$C$42,L52=1,P52=0,O52>Assumptions!$C$43),1,0) -> 1 | M53: =O52 -> 226434.28 | N53: =IF(L53=1,M53*$B$22,0) -> 754.78092 | O53: =IF(L53=1,M53+N53-$B$26,M53) -> 225869.47 | P53: =IF(L53=1,IF($B$26<=N53,1,0),0) -> 0 | Q53: =Q52+N53 -> 36570.702 | S53: =S52+1 -> 46 | T53: =IF(AND(S53<=Assumptions!$C$42,T52=1,X52=0,W52>Assumptions!$C$43),1,0) -> 1 | U53: =W52 -> 216741.61 | V53: =IF(T53=1,U53*$B$22,0) -> 722.47203 | W53: =IF(T53=1,U53+V53-$B$27,U53) -> 215944.49 | X53: =IF(T53=1,IF($B$27<=V53,1,0),0) -> 0 | Y53: =Y52+V53 -> 35845.725
K54: =K53+1 -> 47 | L54: =IF(AND(K54<=Assumptions!$C$42,L53=1,P53=0,O53>Assumptions!$C$43),1,0) -> 1 | M54: =O53 -> 225869.47 | N54: =IF(L54=1,M54*$B$22,0) -> 752.89822 | O54: =IF(L54=1,M54+N54-$B$26,M54) -> 225302.77 | P54: =IF(L54=1,IF($B$26<=N54,1,0),0) -> 0 | Q54: =Q53+N54 -> 37323.6 | S54: =S53+1 -> 47 | T54: =IF(AND(S54<=Assumptions!$C$42,T53=1,X53=0,W53>Assumptions!$C$43),1,0) -> 1 | U54: =W53 -> 215944.49 | V54: =IF(T54=1,U54*$B$22,0) -> 719.81496 | W54: =IF(T54=1,U54+V54-$B$27,U54) -> 215144.71 | X54: =IF(T54=1,IF($B$27<=V54,1,0),0) -> 0 | Y54: =Y53+V54 -> 36565.54
K55: =K54+1 -> 48 | L55: =IF(AND(K55<=Assumptions!$C$42,L54=1,P54=0,O54>Assumptions!$C$43),1,0) -> 1 | M55: =O54 -> 225302.77 | N55: =IF(L55=1,M55*$B$22,0) -> 751.00924 | O55: =IF(L55=1,M55+N55-$B$26,M55) -> 224734.19 | P55: =IF(L55=1,IF($B$26<=N55,1,0),0) -> 0 | Q55: =Q54+N55 -> 38074.609 | S55: =S54+1 -> 48 | T55: =IF(AND(S55<=Assumptions!$C$42,T54=1,X54=0,W54>Assumptions!$C$43),1,0) -> 1 | U55: =W54 -> 215144.71 | V55: =IF(T55=1,U55*$B$22,0) -> 717.14904 | W55: =IF(T55=1,U55+V55-$B$27,U55) -> 214342.27 | X55: =IF(T55=1,IF($B$27<=V55,1,0),0) -> 0 | Y55: =Y54+V55 -> 37282.689
K56: =K55+1 -> 49 | L56: =IF(AND(K56<=Assumptions!$C$42,L55=1,P55=0,O55>Assumptions!$C$43),1,0) -> 1 | M56: =O55 -> 224734.19 | N56: =IF(L56=1,M56*$B$22,0) -> 749.11396 | O56: =IF(L56=1,M56+N56-$B$26,M56) -> 224163.71 | P56: =IF(L56=1,IF($B$26<=N56,1,0),0) -> 0 | Q56: =Q55+N56 -> 38823.723 | S56: =S55+1 -> 49 | T56: =IF(AND(S56<=Assumptions!$C$42,T55=1,X55=0,W55>Assumptions!$C$43),1,0) -> 1 | U56: =W55 -> 214342.27 | V56: =IF(T56=1,U56*$B$22,0) -> 714.47423 | W56: =IF(T56=1,U56+V56-$B$27,U56) -> 213537.15 | X56: =IF(T56=1,IF($B$27<=V56,1,0),0) -> 0 | Y56: =Y55+V56 -> 37997.163
K57: =K56+1 -> 50 | L57: =IF(AND(K57<=Assumptions!$C$42,L56=1,P56=0,O56>Assumptions!$C$43),1,0) -> 1 | M57: =O56 -> 224163.71 | N57: =IF(L57=1,M57*$B$22,0) -> 747.21237 | O57: =IF(L57=1,M57+N57-$B$26,M57) -> 223591.33 | P57: =IF(L57=1,IF($B$26<=N57,1,0),0) -> 0 | Q57: =Q56+N57 -> 39570.936 | S57: =S56+1 -> 50 | T57: =IF(AND(S57<=Assumptions!$C$42,T56=1,X56=0,W56>Assumptions!$C$43),1,0) -> 1 | U57: =W56 -> 213537.15 | V57: =IF(T57=1,U57*$B$22,0) -> 711.7905 | W57: =IF(T57=1,U57+V57-$B$27,U57) -> 212729.35 | X57: =IF(T57=1,IF($B$27<=V57,1,0),0) -> 0 | Y57: =Y56+V57 -> 38708.954
K58: =K57+1 -> 51 | L58: =IF(AND(K58<=Assumptions!$C$42,L57=1,P57=0,O57>Assumptions!$C$43),1,0) -> 1 | M58: =O57 -> 223591.33 | N58: =IF(L58=1,M58*$B$22,0) -> 745.30444 | O58: =IF(L58=1,M58+N58-$B$26,M58) -> 223017.04 | P58: =IF(L58=1,IF($B$26<=N58,1,0),0) -> 0 | Q58: =Q57+N58 -> 40316.24 | S58: =S57+1 -> 51 | T58: =IF(AND(S58<=Assumptions!$C$42,T57=1,X57=0,W57>Assumptions!$C$43),1,0) -> 1 | U58: =W57 -> 212729.35 | V58: =IF(T58=1,U58*$B$22,0) -> 709.09783 | W58: =IF(T58=1,U58+V58-$B$27,U58) -> 211918.85 | X58: =IF(T58=1,IF($B$27<=V58,1,0),0) -> 0 | Y58: =Y57+V58 -> 39418.052
K59: =K58+1 -> 52 | L59: =IF(AND(K59<=Assumptions!$C$42,L58=1,P58=0,O58>Assumptions!$C$43),1,0) -> 1 | M59: =O58 -> 223017.04 | N59: =IF(L59=1,M59*$B$22,0) -> 743.39014 | O59: =IF(L59=1,M59+N59-$B$26,M59) -> 222440.84 | P59: =IF(L59=1,IF($B$26<=N59,1,0),0) -> 0 | Q59: =Q58+N59 -> 41059.63 | S59: =S58+1 -> 52 | T59: =IF(AND(S59<=Assumptions!$C$42,T58=1,X58=0,W58>Assumptions!$C$43),1,0) -> 1 | U59: =W58 -> 211918.85 | V59: =IF(T59=1,U59*$B$22,0) -> 706.39618 | W59: =IF(T59=1,U59+V59-$B$27,U59) -> 211105.66 | X59: =IF(T59=1,IF($B$27<=V59,1,0),0) -> 0 | Y59: =Y58+V59 -> 40124.448
... K1207: =K1206+1 -> 1200 | L1207: =IF(AND(K1207<=Assumptions!$C$42,L1206=1,P1206=0,O1206>Assumptions!$C$43),1,0) -> 0 | M1207: =O1206 -> 8.1054168e-09 | N1207: =IF(L1207=1,M1207*$B$22,0) -> 0 | O1207: =IF(L1207=1,M1207+N1207-$B$26,M1207) -> 8.1054168e-09 | P1207: =IF(L1207=1,IF($B$26<=N1207,1,0),0) -> 0 | Q1207: =Q1206+N1207 -> 145877.63 | S1207: =S1206+1 -> 1200 | T1207: =IF(AND(S1207<=Assumptions!$C$42,T1206=1,X1206=0,W1206>Assumptions!$C$43),1,0) -> 0 | U1207: =W1206 -> -182.10371 | V1207: =IF(T1207=1,U1207*$B$22,0) -> 0 | W1207: =IF(T1207=1,U1207+V1207-$B$27,U1207) -> -182.10371 | X1207: =IF(T1207=1,IF($B$27<=V1207,1,0),0) -> 0 | Y1207: =Y1206+V1207 -> 113000.41

Sheet C05 Interest rate impact
A1: C05 · Interest-rate impact
A2: Question shown: "What if my mortgage rate changed?" · Category: Home & Mortgage · Prototype id: ratechange
A3: Replicates: CALCS 'ratechange' run(v); helpers pmt(), mine(), statedM().
A4: Edge rules: Repayment now = stated repayment (while loan, rate and years are untouched) or pmt(). After change = now + pmt(rate + change) − pmt(rate), so a stated figure is shifted by the formula difference. Headline shows "+" when the change is ≥ 0 (also "+€0").
A5: Legend: blue = input (change these) · black = formula · green = link to the Assumptions sheet · yellow fill = key assumption. Money cells show whole euros but keep full precision, as the prototype does.
A8: INPUTS
A9: Input | B9: Value | C9: Unit | D9: Default | E9: Min | F9: Max (slider) | G9: Max if typed | H9: Step | I9: Pre-filled from (if the prototype pre-fills it)
A10: Mortgage balance | B10: 300000 | C10: € | D10: 300000 | E10: 50000 | F10: 1000000 | G10: 10000000 | H10: 1000 | I10: Your finances or mortgage statement: mortgage balance
A11: Current rate | B11: 0.04 | C11: % (stored as a fraction) | D11: 0.04 | E11: 0.01 | F11: 0.08 | G11: 0.08 | H11: 0.0005 | I11: Your finances or mortgage statement: mortgage rate
A12: Years left | B12: 25 | C12: years | D12: 25 | E12: 5 | F12: 35 | G12: 35 | H12: 1 | I12: Your finances or mortgage statement: years left (25 if not given)
A13: Rate change | B13: 0.01 | C13: % (stored as a fraction) | D13: 0.01 | E13: -0.02 | F13: 0.03 | G13: 0.03 | H13: 0.0025
A15: CONTEXT INPUTS (state the prototype reads besides the sliders)
A16: Input | B16: Value | C16: Unit | D16: Default | E16: Min | F16: Max (slider) | G16: Max if typed | H16: Step | I16: Pre-filled from (if the prototype pre-fills it)
A17: Stated monthly mortgage repayment (0 = none) | B17: 0 | C17: € | D17: 0 | E17: 0 | F17: 100000 | G17: 100000 | I17: Pre-filled from Your finances / mortgage statement: the stated monthly repayment (statement or typed; estimates do not count). 0 = no stated repayment.
A18: Customer has not moved balance, rate or years in this tool (1 = yes) | B18: 1 | C18: flag | D18: 1 | E18: 0 | F18: 1 | G18: 1 | H18: 1 | I18: mine(): 1 while the customer has not moved any of the listed sliders in this tool; 0 once they have (the stated figure then stops applying).
A20: CALCULATION
A21: Calculation step | B21: Value | C21: Unit | D21: JS equivalent (prototype run function)
A22: Monthly interest rate | B22: =$B$11/12 -> 0.0033333333 | C22: rate (fraction) | D22: i = r / 100 / 12
A23: Number of monthly payments | B23: =$B$12*12 -> 300 | C23: n | D23: n = y * 12
A24: Formula repayment | B24: =IF(($B$23)=0,0,IF($B$22<>0,$B$10*$B$22/(1-POWER(1+$B$22,-($B$23))),$B$10/($B$23))) -> 1583.5105 | C24: € | D24: calc = pmt(v.loan, v.rate, v.term)
A25: Stated repayment in use (0 = none) | B25: =IF(AND($B$18=1,$B$17>0),$B$17,0) -> 0 | C25: € | D25: own
A26: Repayment now | B26: =IF($B$25>0,$B$25,$B$24) -> 1583.5105 | C26: € | D26: a = own || calc
A27: New rate | B27: =$B$11+$B$13 -> 0.05 | C27: % (fraction) | D27: v.rate + v.d
A28: New monthly rate | B28: =$B$27/12 -> 0.0041666667 | C28: rate (fraction)
A29: Formula repayment at the new rate | B29: =IF(($B$23)=0,0,IF($B$28<>0,$B$10*$B$28/(1-POWER(1+$B$28,-($B$23))),$B$10/($B$23))) -> 1753.7701 | C29: € | D29: pmt(v.loan, v.rate + v.d, v.term)
A30: Repayment after the change | B30: =$B$26+$B$29-$B$24 -> 1753.7701 | C30: € | D30: b = a + pmt(...) - calc
A31: Monthly change | B31: =$B$30-$B$26 -> 170.2596 | C31: € | D31: b - a
A33: OUTPUTS
A34: Output | B34: Value | C34: As shown in the prototype | D34: Shown when / where it appears
A35: Headline label | C35: ="Monthly change" -> Monthly change | D35: Always
A36: Monthly change | B36: =$B$31 -> 170.2596 | C36: =IF($B$30>=$B$26,"+","")&IF(($B$31)<0,"−€","€")&FIXED(ROUND(ABS($B$31),0),0) -> +€170 | D36: Headline
A37: New rate (sentence) | B37: =$B$27 -> 0.05 | C37: =FIXED($B$27*100,2,TRUE())&"%" -> 5.00% | D37: Sentence
A38: Now | B38: =$B$26 -> 1583.5105 | C38: =IF(($B$26)<0,"−€","€")&FIXED(ROUND(ABS($B$26),0),0) -> €1,584 | D38: Row 1
A39: After change | B39: =$B$30 -> 1753.7701 | C39: =IF(($B$30)<0,"−€","€")&FIXED(ROUND(ABS($B$30),0),0) -> €1,754 | D39: Row 2
A40: Change over a year | B40: =($B$30-$B$26)*12 -> 2043.1152 | C40: =IF((($B$30-$B$26)*12)<0,"−€","€")&FIXED(ROUND(ABS(($B$30-$B$26)*12),0),0) -> €2,043 | D40: Row 3

Sheet C06 Term comparison
A1: C06 · Mortgage term comparison
A2: Question shown: "Shorter or longer term: what is the trade-off?" · Category: Home & Mortgage · Prototype id: term
A3: Replicates: CALCS 'term' run(v); helper pmt().
A4: Edge rules: Total interest = monthly × years × 12 − loan (no loop). The sentence names the shorter term; if both terms are equal it still says it "costs more each month".
A5: Legend: blue = input (change these) · black = formula · green = link to the Assumptions sheet · yellow fill = key assumption. Money cells show whole euros but keep full precision, as the prototype does.
A8: INPUTS
A9: Input | B9: Value | C9: Unit | D9: Default | E9: Min | F9: Max (slider) | G9: Max if typed | H9: Step | I9: Pre-filled from (if the prototype pre-fills it)
A10: Mortgage amount | B10: 300000 | C10: € | D10: 300000 | E10: 50000 | F10: 1000000 | G10: 10000000 | H10: 1000 | I10: Your finances or mortgage statement: mortgage balance
A11: Interest rate | B11: 0.04 | C11: % (stored as a fraction) | D11: 0.04 | E11: 0.01 | F11: 0.08 | G11: 0.08 | H11: 0.0005 | I11: Your finances or mortgage statement: mortgage rate
A12: Term A | B12: 25 | C12: years | D12: 25 | E12: 5 | F12: 35 | G12: 35 | H12: 1 | I12: Your finances or mortgage statement: years left (25 if not given)
A13: Term B | B13: 35 | C13: years | D13: 35 | E13: 5 | F13: 35 | G13: 35 | H13: 1
A15: CALCULATION
A16: Calculation step | B16: Value | C16: Unit | D16: JS equivalent (prototype run function)
A17: Monthly interest rate | B17: =$B$11/12 -> 0.0033333333 | C17: rate (fraction) | D17: i = r / 100 / 12
A18: Term A monthly | B18: =IF(($B$12*12)=0,0,IF($B$17<>0,$B$10*$B$17/(1-POWER(1+$B$17,-($B$12*12))),$B$10/($B$12*12))) -> 1583.5105 | C18: € | D18: ma = pmt(v.loan, v.rate, v.a)
A19: Term B monthly | B19: =IF(($B$13*12)=0,0,IF($B$17<>0,$B$10*$B$17/(1-POWER(1+$B$17,-($B$13*12))),$B$10/($B$13*12))) -> 1328.3242 | C19: € | D19: mb = pmt(v.loan, v.rate, v.b)
A20: Term A total interest | B20: =$B$18*$B$12*12-$B$10 -> 175053.16 | C20: € | D20: ia = ma * v.a * 12 - v.loan
A21: Term B total interest | B21: =$B$19*$B$13*12-$B$10 -> 257896.17 | C21: € | D21: ib = mb * v.b * 12 - v.loan
A23: OUTPUTS
A24: Output | B24: Value | C24: As shown in the prototype | D24: Shown when / where it appears
A25: Headline label | C25: ="Interest difference" -> Interest difference | D25: Always
A26: Interest difference | B26: =ABS($B$21-$B$20) -> 82843.017 | C26: =IF((ABS($B$21-$B$20))<0,"−€","€")&FIXED(ROUND(ABS(ABS($B$21-$B$20)),0),0) -> €82,843 | D26: Headline
A27: Shorter term named in the sentence (years) | B27: =MIN($B$12,$B$13) -> 25 | C27: =MIN($B$12,$B$13)&"" -> 25 | D27: Sentence
A28: Term A monthly | B28: =$B$18 -> 1583.5105 | C28: =IF(($B$18)<0,"−€","€")&FIXED(ROUND(ABS($B$18),0),0) -> €1,584 | D28: Row 1
A29: Term B monthly | B29: =$B$19 -> 1328.3242 | C29: =IF(($B$19)<0,"−€","€")&FIXED(ROUND(ABS($B$19),0),0) -> €1,328 | D29: Row 2
A30: Term A total interest | B30: =$B$20 -> 175053.16 | C30: =IF(($B$20)<0,"−€","€")&FIXED(ROUND(ABS($B$20),0),0) -> €175,053 | D30: Row 3
A31: Term B total interest | B31: =$B$21 -> 257896.17 | C31: =IF(($B$21)<0,"−€","€")&FIXED(ROUND(ABS($B$21),0),0) -> €257,896 | D31: Row 4

Sheet C07 Rent vs buy
A1: C07 · Rent vs buy
A2: Question shown: "How do renting and buying compare over time?" · Category: Home & Mortgage · Prototype id: rentbuy
A3: Replicates: CALCS 'rentbuy' run(v); helpers pmt(), fvL(); month-by-month loop for (k = 0; k < v.y*12; k++).
A4: Edge rules: Mortgage repayment is always over 30 years. Balance after the chosen years comes from an explicit monthly loop (no early stop). Upkeep = 1% of the price a year. A deposit above the price gives a negative loan and is not blocked (JS behaviour).
A5: Legend: blue = input (change these) · black = formula · green = link to the Assumptions sheet · yellow fill = key assumption. Money cells show whole euros but keep full precision, as the prototype does. | K5: 360 rows = 30 years, the most the Years input allows.
K6: Mortgage balance month by month: bal -= m - bal × i
K7: Month | L7: Month within the chosen years (k ≤ y × 12) | M7: Opening balance | N7: Interest | O7: Closing balance | P7: Cumulative interest
A8: INPUTS | K8: 1 | L8: =IF(K8<=$B$14*12,1,0) -> 1 | M8: =$B$19 -> 315000 | N8: =IF(L8=1,M8*$B$23,0) -> 1050 | O8: =IF(L8=1,M8-($B$22-N8),M8) -> 314546.14 | P8: =N8 -> 1050
A9: Input | B9: Value | C9: Unit | D9: Default | E9: Min | F9: Max (slider) | G9: Max if typed | H9: Step | I9: Pre-filled from (if the prototype pre-fills it) | K9: =K8+1 -> 2 | L9: =IF(K9<=$B$14*12,1,0) -> 1 | M9: =O8 -> 314546.14 | N9: =IF(L9=1,M9*$B$23,0) -> 1048.4871 | O9: =IF(L9=1,M9-($B$22-N9),M9) -> 314090.77 | P9: =P8+N9 -> 2098.4871
A10: Monthly rent | B10: 1800 | C10: € | D10: 1800 | E10: 500 | F10: 5000 | G10: 50000 | H10: 50 | K10: =K9+1 -> 3 | L10: =IF(K10<=$B$14*12,1,0) -> 1 | M10: =O9 -> 314090.77 | N10: =IF(L10=1,M10*$B$23,0) -> 1046.9692 | O10: =IF(L10=1,M10-($B$22-N10),M10) -> 313633.88 | P10: =P9+N10 -> 3145.4564
A11: Home price | B11: 350000 | C11: € | D11: 350000 | E11: 100000 | F11: 1000000 | G11: 10000000 | H11: 5000 | K11: =K10+1 -> 4 | L11: =IF(K11<=$B$14*12,1,0) -> 1 | M11: =O10 -> 313633.88 | N11: =IF(L11=1,M11*$B$23,0) -> 1045.4463 | O11: =IF(L11=1,M11-($B$22-N11),M11) -> 313175.47 | P11: =P10+N11 -> 4190.9026
A12: Deposit | B12: 35000 | C12: € | D12: 35000 | E12: 0 | F12: 300000 | G12: 3000000 | H12: 1000 | K12: =K11+1 -> 5 | L12: =IF(K12<=$B$14*12,1,0) -> 1 | M12: =O11 -> 313175.47 | N12: =IF(L12=1,M12*$B$23,0) -> 1043.9182 | O12: =IF(L12=1,M12-($B$22-N12),M12) -> 312715.53 | P12: =P11+N12 -> 5234.8209
A13: Mortgage rate | B13: 0.04 | C13: % (stored as a fraction) | D13: 0.04 | E13: 0.01 | F13: 0.08 | G13: 0.08 | H13: 0.001 | K13: =K12+1 -> 6 | L13: =IF(K13<=$B$14*12,1,0) -> 1 | M13: =O12 -> 312715.53 | N13: =IF(L13=1,M13*$B$23,0) -> 1042.3851 | O13: =IF(L13=1,M13-($B$22-N13),M13) -> 312254.06 | P13: =P12+N13 -> 6277.206
A14: Years | B14: 10 | C14: years | D14: 10 | E14: 1 | F14: 30 | G14: 30 | H14: 1 | K14: =K13+1 -> 7 | L14: =IF(K14<=$B$14*12,1,0) -> 1 | M14: =O13 -> 312254.06 | N14: =IF(L14=1,M14*$B$23,0) -> 1040.8469 | O14: =IF(L14=1,M14-($B$22-N14),M14) -> 311791.05 | P14: =P13+N14 -> 7318.0528
A15: House price growth | B15: 0.02 | C15: % (stored as a fraction) | D15: 0.02 | E15: 0 | F15: 0.06 | G15: 0.06 | H15: 0.005 | K15: =K14+1 -> 8 | L15: =IF(K15<=$B$14*12,1,0) -> 1 | M15: =O14 -> 311791.05 | N15: =IF(L15=1,M15*$B$23,0) -> 1039.3035 | O15: =IF(L15=1,M15-($B$22-N15),M15) -> 311326.49 | P15: =P14+N15 -> 8357.3563
K16: =K15+1 -> 9 | L16: =IF(K16<=$B$14*12,1,0) -> 1 | M16: =O15 -> 311326.49 | N16: =IF(L16=1,M16*$B$23,0) -> 1037.755 | O16: =IF(L16=1,M16-($B$22-N16),M16) -> 310860.39 | P16: =P15+N16 -> 9395.1113
A17: CALCULATION | K17: =K16+1 -> 10 | L17: =IF(K17<=$B$14*12,1,0) -> 1 | M17: =O16 -> 310860.39 | N17: =IF(L17=1,M17*$B$23,0) -> 1036.2013 | O17: =IF(L17=1,M17-($B$22-N17),M17) -> 310392.73 | P17: =P16+N17 -> 10431.313
A18: Calculation step | B18: Value | C18: Unit | D18: JS equivalent (prototype run function) | K18: =K17+1 -> 11 | L18: =IF(K18<=$B$14*12,1,0) -> 1 | M18: =O17 -> 310392.73 | N18: =IF(L18=1,M18*$B$23,0) -> 1034.6424 | O18: =IF(L18=1,M18-($B$22-N18),M18) -> 309923.52 | P18: =P17+N18 -> 11465.955
A19: Loan | B19: =$B$11-$B$12 -> 315000 | C19: € | D19: loan = v.price - v.dep | K19: =K18+1 -> 12 | L19: =IF(K19<=$B$14*12,1,0) -> 1 | M19: =O18 -> 309923.52 | N19: =IF(L19=1,M19*$B$23,0) -> 1033.0784 | O19: =IF(L19=1,M19-($B$22-N19),M19) -> 309452.74 | P19: =P18+N19 -> 12499.033
A20: Monthly rate for the repayment | B20: =$B$13/12 -> 0.0033333333 | C20: rate (fraction) | D20: pmt(): i = r / 100 / 12 | K20: =K19+1 -> 13 | L20: =IF(K20<=$B$14*12,1,0) -> 1 | M20: =O19 -> 309452.74 | N20: =IF(L20=1,M20*$B$23,0) -> 1031.5091 | O20: =IF(L20=1,M20-($B$22-N20),M20) -> 308980.39 | P20: =P19+N20 -> 13530.543
A21: Repayment term in months (30 years) | B21: =Assumptions!$C$46*12 -> 360 | C21: n | D21: pmt(loan, v.rate, 30) | K21: =K20+1 -> 14 | L21: =IF(K21<=$B$14*12,1,0) -> 1 | M21: =O20 -> 308980.39 | N21: =IF(L21=1,M21*$B$23,0) -> 1029.9346 | O21: =IF(L21=1,M21-($B$22-N21),M21) -> 308506.46 | P21: =P20+N21 -> 14560.477
A22: Monthly repayment | B22: =IF(($B$21)=0,0,IF($B$20<>0,$B$19*$B$20/(1-POWER(1+$B$20,-($B$21))),$B$19/($B$21))) -> 1503.8582 | C22: € | D22: m = pmt(loan, v.rate, 30) | K22: =K21+1 -> 15 | L22: =IF(K22<=$B$14*12,1,0) -> 1 | M22: =O21 -> 308506.46 | N22: =IF(L22=1,M22*$B$23,0) -> 1028.3549 | O22: =IF(L22=1,M22-($B$22-N22),M22) -> 308030.96 | P22: =P21+N22 -> 15588.832
A23: Monthly rate in the loop | B23: =$B$13/12 -> 0.0033333333 | C23: rate (fraction) | D23: i = v.rate / 1200 | K23: =K22+1 -> 16 | L23: =IF(K23<=$B$14*12,1,0) -> 1 | M23: =O22 -> 308030.96 | N23: =IF(L23=1,M23*$B$23,0) -> 1026.7699 | O23: =IF(L23=1,M23-($B$22-N23),M23) -> 307553.87 | P23: =P22+N23 -> 16615.602
A24: Balance after the chosen years | B24: =INDEX($O$8:$O$367,MAX(1,$B$14*12)) -> 248169.47 | C24: € | D24: bal after the loop | K24: =K23+1 -> 17 | L24: =IF(K24<=$B$14*12,1,0) -> 1 | M24: =O23 -> 307553.87 | N24: =IF(L24=1,M24*$B$23,0) -> 1025.1796 | O24: =IF(L24=1,M24-($B$22-N24),M24) -> 307075.19 | P24: =P23+N24 -> 17640.781
A25: Interest paid over the years | B25: =$P$367 -> 113632.45 | C25: € | D25: int | K25: =K24+1 -> 18 | L25: =IF(K25<=$B$14*12,1,0) -> 1 | M25: =O24 -> 307075.19 | N25: =IF(L25=1,M25*$B$23,0) -> 1023.584 | O25: =IF(L25=1,M25-($B$22-N25),M25) -> 306594.92 | P25: =P24+N25 -> 18664.365
A26: Rent paid | B26: =$B$10*12*$B$14 -> 216000 | C26: € | D26: rentCost = v.rent * 12 * v.y | K26: =K25+1 -> 19 | L26: =IF(K26<=$B$14*12,1,0) -> 1 | M26: =O25 -> 306594.92 | N26: =IF(L26=1,M26*$B$23,0) -> 1021.9831 | O26: =IF(L26=1,M26-($B$22-N26),M26) -> 306113.04 | P26: =P25+N26 -> 19686.348
A27: Upkeep | B27: =$B$11*Assumptions!$C$47*$B$14 -> 35000 | C27: € | D27: upkeep = v.price * 0.01 * v.y | K27: =K26+1 -> 20 | L27: =IF(K27<=$B$14*12,1,0) -> 1 | M27: =O26 -> 306113.04 | N27: =IF(L27=1,M27*$B$23,0) -> 1020.3768 | O27: =IF(L27=1,M27-($B$22-N27),M27) -> 305629.56 | P27: =P26+N27 -> 20706.725
A28: Home value | B28: =$B$11*POWER(1+$B$15,$B$14) -> 426648.05 | C28: € | D28: value = fvL(v.price, v.g, v.y) | K28: =K27+1 -> 21 | L28: =IF(K28<=$B$14*12,1,0) -> 1 | M28: =O27 -> 305629.56 | N28: =IF(L28=1,M28*$B$23,0) -> 1018.7652 | O28: =IF(L28=1,M28-($B$22-N28),M28) -> 305144.47 | P28: =P27+N28 -> 21725.491
A29: Home equity | B29: =$B$28-$B$24 -> 178478.58 | C29: € | D29: equity = value - bal | K29: =K28+1 -> 22 | L29: =IF(K29<=$B$14*12,1,0) -> 1 | M29: =O28 -> 305144.47 | N29: =IF(L29=1,M29*$B$23,0) -> 1017.1482 | O29: =IF(L29=1,M29-($B$22-N29),M29) -> 304657.76 | P29: =P28+N29 -> 22742.639
K30: =K29+1 -> 23 | L30: =IF(K30<=$B$14*12,1,0) -> 1 | M30: =O29 -> 304657.76 | N30: =IF(L30=1,M30*$B$23,0) -> 1015.5259 | O30: =IF(L30=1,M30-($B$22-N30),M30) -> 304169.43 | P30: =P29+N30 -> 23758.165
A31: OUTPUTS | K31: =K30+1 -> 24 | L31: =IF(K31<=$B$14*12,1,0) -> 1 | M31: =O30 -> 304169.43 | N31: =IF(L31=1,M31*$B$23,0) -> 1013.8981 | O31: =IF(L31=1,M31-($B$22-N31),M31) -> 303679.47 | P31: =P30+N31 -> 24772.063
A32: Output | B32: Value | C32: As shown in the prototype | D32: Shown when / where it appears | K32: =K31+1 -> 25 | L32: =IF(K32<=$B$14*12,1,0) -> 1 | M32: =O31 -> 303679.47 | N32: =IF(L32=1,M32*$B$23,0) -> 1012.2649 | O32: =IF(L32=1,M32-($B$22-N32),M32) -> 303187.87 | P32: =P31+N32 -> 25784.328
A33: Headline label | C33: ="Home equity after "&$B$14&" yrs" -> Home equity after 10 yrs | D33: Always | K33: =K32+1 -> 26 | L33: =IF(K33<=$B$14*12,1,0) -> 1 | M33: =O32 -> 303187.87 | N33: =IF(L33=1,M33*$B$23,0) -> 1010.6262 | O33: =IF(L33=1,M33-($B$22-N33),M33) -> 302694.64 | P33: =P32+N33 -> 26794.954
A34: Home equity after the years | B34: =$B$29 -> 178478.58 | C34: =IF(($B$29)<0,"−€","€")&FIXED(ROUND(ABS($B$29),0),0) -> €178,479 | D34: Headline | K34: =K33+1 -> 27 | L34: =IF(K34<=$B$14*12,1,0) -> 1 | M34: =O33 -> 302694.64 | N34: =IF(L34=1,M34*$B$23,0) -> 1008.9821 | O34: =IF(L34=1,M34-($B$22-N34),M34) -> 302199.77 | P34: =P33+N34 -> 27803.936
A35: Rent paid | B35: =$B$26 -> 216000 | C35: =IF(($B$26)<0,"−€","€")&FIXED(ROUND(ABS($B$26),0),0) -> €216,000 | D35: Row 1 (also in the sentence) | K35: =K34+1 -> 28 | L35: =IF(K35<=$B$14*12,1,0) -> 1 | M35: =O34 -> 302199.77 | N35: =IF(L35=1,M35*$B$23,0) -> 1007.3326 | O35: =IF(L35=1,M35-($B$22-N35),M35) -> 301703.24 | P35: =P34+N35 -> 28811.269
A36: Interest + upkeep (buying) | B36: =$B$25+$B$27 -> 148632.45 | C36: =IF(($B$25+$B$27)<0,"−€","€")&FIXED(ROUND(ABS($B$25+$B$27),0),0) -> €148,632 | D36: Row 2 (also in the sentence) | K36: =K35+1 -> 29 | L36: =IF(K36<=$B$14*12,1,0) -> 1 | M36: =O35 -> 301703.24 | N36: =IF(L36=1,M36*$B$23,0) -> 1005.6775 | O36: =IF(L36=1,M36-($B$22-N36),M36) -> 301205.06 | P36: =P35+N36 -> 29816.946
A37: Home value | B37: =$B$28 -> 426648.05 | C37: =IF(($B$28)<0,"−€","€")&FIXED(ROUND(ABS($B$28),0),0) -> €426,648 | D37: Row 3 | K37: =K36+1 -> 30 | L37: =IF(K37<=$B$14*12,1,0) -> 1 | M37: =O36 -> 301205.06 | N37: =IF(L37=1,M37*$B$23,0) -> 1004.0169 | O37: =IF(L37=1,M37-($B$22-N37),M37) -> 300705.22 | P37: =P36+N37 -> 30820.963
A38: "Add to my plan" goal amount (Buy a home) | B38: =$B$12 -> 35000 | C38: =$B$38&"" -> 35000 | D38: Add to my plan | K38: =K37+1 -> 31 | L38: =IF(K38<=$B$14*12,1,0) -> 1 | M38: =O37 -> 300705.22 | N38: =IF(L38=1,M38*$B$23,0) -> 1002.3507 | O38: =IF(L38=1,M38-($B$22-N38),M38) -> 300203.71 | P38: =P37+N38 -> 31823.314
A39: "Add to my plan" goal years | B39: =Assumptions!$C$71 -> 3 | C39: =$B$39&"" -> 3 | D39: Add to my plan | K39: =K38+1 -> 32 | L39: =IF(K39<=$B$14*12,1,0) -> 1 | M39: =O38 -> 300203.71 | N39: =IF(L39=1,M39*$B$23,0) -> 1000.679 | O39: =IF(L39=1,M39-($B$22-N39),M39) -> 299700.53 | P39: =P38+N39 -> 32823.993
K40: =K39+1 -> 33 | L40: =IF(K40<=$B$14*12,1,0) -> 1 | M40: =O39 -> 299700.53 | N40: =IF(L40=1,M40*$B$23,0) -> 999.00177 | O40: =IF(L40=1,M40-($B$22-N40),M40) -> 299195.67 | P40: =P39+N40 -> 33822.994
K41: =K40+1 -> 34 | L41: =IF(K41<=$B$14*12,1,0) -> 1 | M41: =O40 -> 299195.67 | N41: =IF(L41=1,M41*$B$23,0) -> 997.31891 | O41: =IF(L41=1,M41-($B$22-N41),M41) -> 298689.14 | P41: =P40+N41 -> 34820.313
K42: =K41+1 -> 35 | L42: =IF(K42<=$B$14*12,1,0) -> 1 | M42: =O41 -> 298689.14 | N42: =IF(L42=1,M42*$B$23,0) -> 995.63045 | O42: =IF(L42=1,M42-($B$22-N42),M42) -> 298180.91 | P42: =P41+N42 -> 35815.944
K43: =K42+1 -> 36 | L43: =IF(K43<=$B$14*12,1,0) -> 1 | M43: =O42 -> 298180.91 | N43: =IF(L43=1,M43*$B$23,0) -> 993.93636 | O43: =IF(L43=1,M43-($B$22-N43),M43) -> 297670.99 | P43: =P42+N43 -> 36809.88
K44: =K43+1 -> 37 | L44: =IF(K44<=$B$14*12,1,0) -> 1 | M44: =O43 -> 297670.99 | N44: =IF(L44=1,M44*$B$23,0) -> 992.23662 | O44: =IF(L44=1,M44-($B$22-N44),M44) -> 297159.36 | P44: =P43+N44 -> 37802.117
K45: =K44+1 -> 38 | L45: =IF(K45<=$B$14*12,1,0) -> 1 | M45: =O44 -> 297159.36 | N45: =IF(L45=1,M45*$B$23,0) -> 990.53121 | O45: =IF(L45=1,M45-($B$22-N45),M45) -> 296646.04 | P45: =P44+N45 -> 38792.648
K46: =K45+1 -> 39 | L46: =IF(K46<=$B$14*12,1,0) -> 1 | M46: =O45 -> 296646.04 | N46: =IF(L46=1,M46*$B$23,0) -> 988.82012 | O46: =IF(L46=1,M46-($B$22-N46),M46) -> 296131 | P46: =P45+N46 -> 39781.468
K47: =K46+1 -> 40 | L47: =IF(K47<=$B$14*12,1,0) -> 1 | M47: =O46 -> 296131 | N47: =IF(L47=1,M47*$B$23,0) -> 987.10333 | O47: =IF(L47=1,M47-($B$22-N47),M47) -> 295614.24 | P47: =P46+N47 -> 40768.571
K48: =K47+1 -> 41 | L48: =IF(K48<=$B$14*12,1,0) -> 1 | M48: =O47 -> 295614.24 | N48: =IF(L48=1,M48*$B$23,0) -> 985.38081 | O48: =IF(L48=1,M48-($B$22-N48),M48) -> 295095.77 | P48: =P47+N48 -> 41753.952
K49: =K48+1 -> 42 | L49: =IF(K49<=$B$14*12,1,0) -> 1 | M49: =O48 -> 295095.77 | N49: =IF(L49=1,M49*$B$23,0) -> 983.65256 | O49: =IF(L49=1,M49-($B$22-N49),M49) -> 294575.56 | P49: =P48+N49 -> 42737.605
K50: =K49+1 -> 43 | L50: =IF(K50<=$B$14*12,1,0) -> 1 | M50: =O49 -> 294575.56 | N50: =IF(L50=1,M50*$B$23,0) -> 981.91854 | O50: =IF(L50=1,M50-($B$22-N50),M50) -> 294053.62 | P50: =P49+N50 -> 43719.523
K51: =K50+1 -> 44 | L51: =IF(K51<=$B$14*12,1,0) -> 1 | M51: =O50 -> 294053.62 | N51: =IF(L51=1,M51*$B$23,0) -> 980.17874 | O51: =IF(L51=1,M51-($B$22-N51),M51) -> 293529.94 | P51: =P50+N51 -> 44699.702
... K367: =K366+1 -> 360 | L367: =IF(K367<=$B$14*12,1,0) -> 0 | M367: =O366 -> 248169.47 | N367: =IF(L367=1,M367*$B$23,0) -> 0 | O367: =IF(L367=1,M367-($B$22-N367),M367) -> 248169.47 | P367: =P366+N367 -> 113632.45

Sheet C08 Goal planner
A1: C08 · Goal planner
A2: Question shown: "How much a month to reach my goal?" · Category: Savings & Goals · Prototype id: goalplanner
A3: Replicates: CALCS 'goalplanner' run(v); helpers fvL(), fvA(1, r, y), inflation via S.infl (applyAssume, inflSet).
A4: Edge rules: When the client has chosen an inflation rate, the goal is grown to its future cost: t × (1 + inflation)^years; otherwise today's price is used. Monthly = (future cost − saved × (1+r)^y) ÷ fvA(1, r, y); 0 if nothing is left. fvA uses the monthly rate equivalent to the yearly rate, (1+r)^(1/12) − 1, and m × n at 0%.
A5: Legend: blue = input (change these) · black = formula · green = link to the Assumptions sheet · yellow fill = key assumption. Money cells show whole euros but keep full precision, as the prototype does.
A8: INPUTS
A9: Input | B9: Value | C9: Unit | D9: Default | E9: Min | F9: Max (slider) | G9: Max if typed | H9: Step | I9: Pre-filled from (if the prototype pre-fills it)
A10: Goal amount (today's prices) | B10: 15000 | C10: € | D10: 15000 | E10: 500 | F10: 500000 | G10: 5000000 | H10: 500
A11: Years until the goal | B11: 3 | C11: years | D11: 3 | E11: 1 | F11: 30 | G11: 30 | H11: 1
A12: Already saved | B12: 2000 | C12: € | D12: 2000 | E12: 0 | F12: 200000 | G12: 2000000 | H12: 500
A13: Growth / interest | B13: 0.02 | C13: % (stored as a fraction) | D13: 0.02 | E13: 0 | F13: 0.07 | G13: 0.07 | H13: 0.005
A15: CALCULATION
A16: Calculation step | B16: Value | C16: Unit | D16: JS equivalent (prototype run function)
A17: Future cost of the goal | B17: =IF(Assumptions!$C$6=1,$B$10*POWER(1+Assumptions!$C$14,$B$11),$B$10) -> 15918.12 | C17: € | D17: fut = inflSet() ? v.t * Math.pow(1 + AS.infl, v.y) : v.t
A18: Already saved, grown | B18: =$B$12*POWER(1+$B$13,$B$11) -> 2122.416 | C18: € | D18: fvL(v.s, v.r, v.y)
A19: Still to fund | B19: =$B$17-$B$18 -> 13795.704 | C19: € | D19: rest = fut - fvL(...)
A20: Monthly growth rate | B20: =POWER(1+$B$13,1/12)-1 -> 0.0016515813 | C20: rate (fraction) | D20: i = Math.pow(1 + r/100, 1/12) - 1
A21: Months | B21: =$B$11*12 -> 36 | C21: n | D21: n = y * 12
A22: Future value of €1 a month | B22: =IF($B$20<>0,(POWER(1+$B$20,$B$21)-1)/$B$20,$B$21) -> 37.06024 | C22: num | D22: fvA(1, v.r, v.y)
A23: Monthly amount | B23: =IF($B$19>0,$B$19/$B$22,0) -> 372.2508 | C23: € | D23: m = rest > 0 ? rest / fvA(1, v.r, v.y) : 0
A25: OUTPUTS
A26: Output | B26: Value | C26: As shown in the prototype | D26: Shown when / where it appears
A27: Headline label | C27: ="Monthly amount (illustrative)" -> Monthly amount (illustrative) | D27: Always
A28: Monthly amount (illustrative) | B28: =$B$23 -> 372.2508 | C28: =IF(($B$23)<0,"−€","€")&FIXED(ROUND(ABS($B$23),0),0) -> €372 | D28: Headline (also in the sentence)
A29: Goal in today's prices | B29: =$B$10 -> 15000 | C29: =IF(($B$10)<0,"−€","€")&FIXED(ROUND(ABS($B$10),0),0) -> €15,000 | D29: Row 1
A30: Will cost about (in y yrs) | B30: =IF(Assumptions!$C$6=1,$B$17,"") -> 15918.12 | C30: =IF(Assumptions!$C$6=1,IF(($B$17)<0,"−€","€")&FIXED(ROUND(ABS($B$17),0),0),"") -> €15,918 | D30: Row 2 and sentence, only when inflation is chosen
A31: Will cost about (sentence) | B31: =IF(Assumptions!$C$6=1,$B$17,"") -> 15918.12 | C31: =IF(Assumptions!$C$6=1,IF(($B$17)<0,"−€","€")&FIXED(ROUND(ABS($B$17),0),0),"") -> €15,918 | D31: Sentence, only when inflation is chosen
A32: Already saved | B32: =$B$12 -> 2000 | C32: =IF(($B$12)<0,"−€","€")&FIXED(ROUND(ABS($B$12),0),0) -> €2,000 | D32: Last row
A33: Inflation rate quoted (sentence) | B33: =IF(Assumptions!$C$6=1,Assumptions!$C$14,"") -> 0.02 | C33: =IF(Assumptions!$C$6=1,ROUND((Assumptions!$C$14)*100,2)&"%","") -> 2% | D33: Sentence, only when inflation is chosen
A34: "Add to my plan" goal amount (My goal) | B34: =$B$10 -> 15000 | C34: =$B$34&"" -> 15000 | D34: Add to my plan
A35: "Add to my plan" goal years | B35: =$B$11 -> 3 | C35: =$B$35&"" -> 3 | D35: Add to my plan

Sheet C09 Compound growth
A1: C09 · Compound growth
A2: Question shown: "What could regular saving grow into?" · Category: Savings & Goals · Prototype id: compound
A3: Replicates: CALCS 'compound' run(v); helpers fvL(), fvA(), todayM(), worthTxt(), inflRow().
A4: Edge rules: Total = p × (1+r)^y + fvA(m, r, y). Today's-money figure appears only when the client has chosen inflation. The goal amount is in today's money when inflation is chosen, otherwise the nominal total.
A5: Legend: blue = input (change these) · black = formula · green = link to the Assumptions sheet · yellow fill = key assumption. Money cells show whole euros but keep full precision, as the prototype does.
A8: INPUTS
A9: Input | B9: Value | C9: Unit | D9: Default | E9: Min | F9: Max (slider) | G9: Max if typed | H9: Step | I9: Pre-filled from (if the prototype pre-fills it)
A10: Starting amount | B10: 5000 | C10: € | D10: 5000 | E10: 0 | F10: 200000 | G10: 2000000 | H10: 500
A11: Monthly addition | B11: 200 | C11: € | D11: 200 | E11: 0 | F11: 3000 | G11: 30000 | H11: 25
A12: Growth rate | B12: 0.04 | C12: % (stored as a fraction) | D12: 0.04 | E12: 0 | F12: 0.08 | G12: 0.08 | H12: 0.005
A13: Years | B13: 20 | C13: years | D13: 20 | E13: 1 | F13: 40 | G13: 40 | H13: 1
A15: CALCULATION
A16: Calculation step | B16: Value | C16: Unit | D16: JS equivalent (prototype run function)
A17: Starting amount, grown | B17: =$B$10*POWER(1+$B$12,$B$13) -> 10955.616 | C17: € | D17: fvL(v.p, v.r, v.y)
A18: Monthly growth rate | B18: =POWER(1+$B$12,1/12)-1 -> 0.0032737398 | C18: rate (fraction) | D18: i = Math.pow(1 + r/100, 1/12) - 1
A19: Months | B19: =$B$13*12 -> 240 | C19: n | D19: n = y * 12
A20: Monthly additions, grown | B20: =IF($B$18<>0,$B$11*(POWER(1+$B$18,$B$19)-1)/$B$18,$B$11*$B$19) -> 72768.346 | C20: € | D20: fvA(v.m, v.r, v.y)
A21: Could grow to | B21: =$B$17+$B$20 -> 83723.962 | C21: € | D21: f = fvL(...) + fvA(...)
A22: Paid in | B22: =$B$10+$B$11*12*$B$13 -> 53000 | C22: € | D22: put = v.p + v.m * 12 * v.y
A23: Inflation discount factor (1 + inflation)^years | B23: =POWER(1+Assumptions!$C$14,$B$13) -> 1.4859474 | C23: num | D23: Math.pow(1 + AS.infl, y)
A24: Worth in today's money | B24: =$B$21/$B$23 -> 56343.826 | C24: € | D24: todayM(fv, y) = fv / (1 + AS.infl)^y
A26: OUTPUTS
A27: Output | B27: Value | C27: As shown in the prototype | D27: Shown when / where it appears
A28: Headline label | C28: ="Could grow to" -> Could grow to | D28: Always
A29: Could grow to | B29: =$B$21 -> 83723.962 | C29: =IF(($B$21)<0,"−€","€")&FIXED(ROUND(ABS($B$21),0),0) -> €83,724 | D29: Headline
A30: Paid in | B30: =$B$22 -> 53000 | C30: =IF(($B$22)<0,"−€","€")&FIXED(ROUND(ABS($B$22),0),0) -> €53,000 | D30: Row 1 (also in the sentence)
A31: Illustrative growth | B31: =$B$21-$B$22 -> 30723.962 | C31: =IF(($B$21-$B$22)<0,"−€","€")&FIXED(ROUND(ABS($B$21-$B$22),0),0) -> €30,724 | D31: Row 2 (also in the sentence)
A32: Worth in today's money (prices rising [inflation] a year) | B32: =IF(Assumptions!$C$6=1,$B$24,"") -> 56343.826 | C32: =IF(Assumptions!$C$6=1,IF(($B$24)<0,"−€","€")&FIXED(ROUND(ABS($B$24),0),0),"") -> €56,344 | D32: Only when the client has chosen an inflation rate (inflRow)
A33: Worth about … in today's money (sentence) | B33: =IF(Assumptions!$C$6=1,$B$24,"") -> 56343.826 | C33: =IF(Assumptions!$C$6=1,IF(($B$24)<0,"−€","€")&FIXED(ROUND(ABS($B$24),0),0),"") -> €56,344 | D33: Sentence, only when inflation is chosen
A34: "Add to my plan" goal amount (Build wealth) | B34: =INT((IF(Assumptions!$C$6=1,$B$24,$B$21))+0.5) -> 56344 | C34: =$B$34&"" -> 56344 | D34: Add to my plan: today's money if inflation chosen
A35: "Add to my plan" goal years | B35: =$B$13 -> 20 | C35: =$B$35&"" -> 20 | D35: Add to my plan

Sheet C10 Lump sum growth
A1: C10 · Lump-sum growth
A2: Question shown: "What could a one-off amount become?" · Category: Investments · Prototype id: lumpsum
A3: Replicates: CALCS 'lumpsum' run(v); helpers fvL(), todayM(), realLine(), inflRow(), adjOn('lumpsum') (the "Adjust for inflation" switch).
A4: Edge rules: Growth after fees nr = (1+r)(1−f) − 1. The "Adjust for inflation" switch (default off) shows today's money only when the client has also chosen inflation. "Start in 5 years" grows for max(0, years − 5). Fees row only when fees ≠ 0. The goal amount is in today's money whenever inflation is chosen, even with the switch off (JS behaviour).
A5: Legend: blue = input (change these) · black = formula · green = link to the Assumptions sheet · yellow fill = key assumption. Money cells show whole euros but keep full precision, as the prototype does.
A8: INPUTS
A9: Input | B9: Value | C9: Unit | D9: Default | E9: Min | F9: Max (slider) | G9: Max if typed | H9: Step | I9: Pre-filled from (if the prototype pre-fills it)
A10: Amount | B10: 10000 | C10: € | D10: 10000 | E10: 500 | F10: 500000 | G10: 5000000 | H10: 100 | I10: Your finances or investment statement: investments (if given)
A11: Growth rate | B11: 0.04 | C11: % (stored as a fraction) | D11: 0.04 | E11: 0 | F11: 0.08 | G11: 0.08 | H11: 0.005
A12: Years | B12: 15 | C12: years | D12: 15 | E12: 1 | F12: 40 | G12: 40 | H12: 1
A13: Yearly fees | B13: 0 | C13: % (stored as a fraction) | D13: 0 | E13: 0 | F13: 0.03 | G13: 0.03 | H13: 0.0005
A15: CONTEXT INPUTS (state the prototype reads besides the sliders)
A16: Input | B16: Value | C16: Unit | D16: Default | E16: Min | F16: Max (slider) | G16: Max if typed | H16: Step | I16: Pre-filled from (if the prototype pre-fills it)
A17: "Adjust for inflation" switch (1 = on) | B17: 0 | C17: flag | D17: 0 | E17: 0 | F17: 1 | G17: 1 | H17: 1 | I17: The switch on this tool; default off, remembered per tool for the session (S.adjInfl)
A19: CALCULATION
A20: Calculation step | B20: Value | C20: Unit | D20: JS equivalent (prototype run function)
A21: Growth after fees | B21: =(1+$B$11)*(1-$B$13)-1 -> 0.04 | C21: rate (fraction) | D21: nr = ((1 + v.r/100) * (1 - v.f/100) - 1) * 100
A22: Value before fees | B22: =$B$10*POWER(1+$B$11,$B$12) -> 18009.435 | C22: € | D22: gross = fvL(v.p, v.r, v.y)
A23: If you start today (after fees) | B23: =$B$10*POWER(1+$B$21,$B$12) -> 18009.435 | C23: € | D23: f = fvL(v.p, nr, v.y)
A24: If you start in 5 years | B24: =$B$10*POWER(1+$B$21,MAX(0,$B$12-Assumptions!$C$48)) -> 14802.443 | C24: € | D24: late = fvL(v.p, nr, Math.max(0, v.y - 5))
A25: Show in today's money (switch on and inflation chosen) | B25: =IF(AND($B$17=1,Assumptions!$C$6=1),1,0) -> 0 | C25: flag | D25: adjOn('lumpsum')
A26: Inflation discount factor | B26: =POWER(1+Assumptions!$C$14,$B$12) -> 1.3458683 | C26: num | D26: Math.pow(1 + AS.infl, y)
A27: In today's money | B27: =$B$23/$B$26 -> 13381.276 | C27: € | D27: todayM(f, v.y)
A28: Cost of waiting | B28: =IF($B$25=1,($B$23-$B$24)/$B$26,$B$23-$B$24) -> 3206.9922 | C28: € | D28: adj ? todayM(f - late, v.y) : f - late
A29: Real return a year | B29: =(1+$B$21)/(1+Assumptions!$C$14)-1 -> 0.019607843 | C29: rate (fraction) | D29: rr = (1 + g/100) / (1 + AS.infl) - 1
A31: OUTPUTS
A32: Output | B32: Value | C32: As shown in the prototype | D32: Shown when / where it appears
A33: Headline label | C33: =IF($B$25=1,"In today's money"&IF($B$13<>0," (after fees)",""),"Could grow to"&IF($B$13<>0," (after fees)","")) -> Could grow to | D33: Always
A34: Headline figure | B34: =IF($B$25=1,$B$27,$B$23) -> 18009.435 | C34: =IF((IF($B$25=1,$B$27,$B$23))<0,"−€","€")&FIXED(ROUND(ABS(IF($B$25=1,$B$27,$B$23)),0),0) -> €18,009 | D34: Headline: today's money when adjusted, else after fees
A35: Real return a year (sentence) | B35: =IF($B$25=1,$B$29,"") | C35: =IF($B$25=1,FIXED($B$29*100,1,TRUE())&"%","") | D35: Sentence, only when adjusted
A36: Growth after fees quoted (sentence) | B36: =IF($B$25=1,$B$21,"") | C36: =IF($B$25=1,ROUND($B$21*100,2)&"%","") | D36: Sentence, only when adjusted
A37: Cost of waiting (sentence) | B37: =$B$28 -> 3206.9922 | C37: =IF(($B$28)<0,"−€","€")&FIXED(ROUND(ABS($B$28),0),0) -> €3,207 | D37: Sentence
A38: If you start today | B38: =$B$23 -> 18009.435 | C38: =IF(($B$23)<0,"−€","€")&FIXED(ROUND(ABS($B$23),0),0) -> €18,009 | D38: Row 1
A39: If you start in 5 years | B39: =$B$24 -> 14802.443 | C39: =IF(($B$24)<0,"−€","€")&FIXED(ROUND(ABS($B$24),0),0) -> €14,802 | D39: Row 2
A40: Worth in today's money (prices rising [inflation] a year) | B40: =IF($B$25=1,$B$27,"") | C40: =IF($B$25=1,IF(($B$27)<0,"−€","€")&FIXED(ROUND(ABS($B$27),0),0),"") | D40: Row, only when adjusted
A41: Fees cost | B41: =IF($B$13<>0,$B$22-$B$23,"") | C41: =IF($B$13<>0,IF(($B$22-$B$23)<0,"−€","€")&FIXED(ROUND(ABS($B$22-$B$23),0),0),"") | D41: Row, only when fees ≠ 0
A42: "Add to my plan" goal amount (Build wealth) | B42: =INT((IF(Assumptions!$C$6=1,$B$27,$B$23))+0.5) -> 13381 | C42: =$B$42&"" -> 13381 | D42: Add to my plan: today's money whenever inflation is chosen
A43: "Add to my plan" goal years | B43: =$B$12 -> 15 | C43: =$B$43&"" -> 15 | D43: Add to my plan

Sheet C11 Emergency fund
A1: C11 · Emergency fund
A2: Question shown: "How strong is my financial cushion?" · Category: Savings & Goals · Prototype id: emergency
A3: Replicates: CALCS 'emergency' run(v).
A4: Edge rules: Months covered = savings ÷ monthly spending, shown to 1 decimal (JS toFixed(1)). No goal is offered when there is no gap.
A5: Legend: blue = input (change these) · black = formula · green = link to the Assumptions sheet · yellow fill = key assumption. Money cells show whole euros but keep full precision, as the prototype does.
A8: INPUTS
A9: Input | B9: Value | C9: Unit | D9: Default | E9: Min | F9: Max (slider) | G9: Max if typed | H9: Step | I9: Pre-filled from (if the prototype pre-fills it)
A10: Essential monthly spending | B10: 2500 | C10: € | D10: 2500 | E10: 500 | F10: 10000 | G10: 100000 | H10: 100 | I10: Your finances: monthly costs + mortgage repayment + debt repayments (if costs given)
A11: Months you want covered | B11: 6 | C11: months | D11: 6 | E11: 1 | F11: 12 | G11: 12 | H11: 1
A12: Easy-access savings | B12: 6250 | C12: € | D12: 6250 | E12: 0 | F12: 100000 | G12: 1000000 | H12: 250 | I12: Your finances: cash savings (if given)
A14: CALCULATION
A15: Calculation step | B15: Value | C15: Unit | D15: JS equivalent (prototype run function)
A16: Target cushion | B16: =$B$10*$B$11 -> 15000 | C16: € | D16: t = v.e * v.mt
A17: Months covered now | B17: =IF($B$10=0,0,$B$12/$B$10) -> 2.5 | C17: num | D17: cov = v.s / v.e [0 spending is outside the input range]
A18: Still to build | B18: =MAX(0,$B$16-$B$12) -> 8750 | C18: € | D18: gap = Math.max(0, t - v.s)
A20: OUTPUTS
A21: Output | B21: Value | C21: As shown in the prototype | D21: Shown when / where it appears
A22: Headline label | C22: ="You currently have" -> You currently have | D22: Always
A23: You currently have (months) | B23: =$B$17 -> 2.5 | C23: =FIXED($B$17,1,TRUE())&" months" -> 2.5 months | D23: Headline
A24: Your target is (sentence) | B24: =IF($B$18>0,$B$16,"") -> 15000 | C24: =IF($B$18>0,IF(($B$16)<0,"−€","€")&FIXED(ROUND(ABS($B$16),0),0),"") -> €15,000 | D24: Sentence, only when there is a gap
A25: You are … away (sentence) | B25: =IF($B$18>0,$B$18,"") -> 8750 | C25: =IF($B$18>0,IF(($B$18)<0,"−€","€")&FIXED(ROUND(ABS($B$18),0),0),"") -> €8,750 | D25: Sentence, only when there is a gap
A26: Target cushion | B26: =$B$16 -> 15000 | C26: =IF(($B$16)<0,"−€","€")&FIXED(ROUND(ABS($B$16),0),0) -> €15,000 | D26: Row 1
A27: Still to build | B27: =$B$18 -> 8750 | C27: =IF(($B$18)<0,"−€","€")&FIXED(ROUND(ABS($B$18),0),0) -> €8,750 | D27: Row 2
A28: "Add to my plan" goal amount (Emergency fund) | B28: =IF($B$18>0,INT(($B$16)+0.5),"") -> 15000 | C28: =$B$28&"" -> 15000 | D28: Add to my plan, only when there is a gap
A29: "Add to my plan" goal years | B29: =IF($B$18>0,Assumptions!$C$72,"") -> 2 | C29: =$B$29&"" -> 2 | D29: Add to my plan, only when there is a gap

Sheet C12 Retirement projection
A1: C12 · Retirement projection
A2: Question shown: "Could your current path fund the retirement you want?" · Category: Pensions & Retirement · Prototype id: retirement
A3: Replicates: CALCS 'retirement' run(v); helpers pensionAt(y, pot, monthly, g, AS.wage) (yearly loop), inflRow(), mine(); S.pdocs.retire (pension statement).
A4: Edge rules: Years = max(1, retirement age + "retire later" − age). Pot grows yearly: pot × (1+g) + monthly × 12 × (1 + pay rise)^t, t = 0…years−1; pay rise = the active growth set's wage rate. The pension statement's own projection replaces ours only if the retirement age equals the statement's, 'save more' is 0 and pot, contributions, growth and age are untouched. Target = max(0, desired − spend less − other income) × 25. Gap row says "None" when the gap ≤ 0.
A5: Legend: blue = input (change these) · black = formula · green = link to the Assumptions sheet · yellow fill = key assumption. Money cells show whole euros but keep full precision, as the prototype does. | K5: 100 rows; the inputs allow at most 60 years.
K6: pensionAt(): pot = pot × (1+g) + monthly × 12 × (1+wage)^t, for t < years
K7: t (year index) | L7: Year counted (t < years) | M7: Pot at end of year
A8: INPUTS | K8: 0 | L8: =IF(K8<$B$34,1,0) -> 1 | M8: =IF(L8=1,$B$12*(1+$B$16)+$B$35*12*POWER(1+$B$36,K8),$B$12) -> 68700
A9: Input | B9: Value | C9: Unit | D9: Default | E9: Min | F9: Max (slider) | G9: Max if typed | H9: Step | I9: Pre-filled from (if the prototype pre-fills it) | K9: =K8+1 -> 1 | L9: =IF(K9<$B$34,1,0) -> 1 | M9: =IF(L9=1,M8*(1+$B$16)+$B$35*12*POWER(1+$B$36,K9),M8) -> 77941.5
A10: Your age | B10: 40 | C10: age | D10: 40 | E10: 20 | F10: 70 | G10: 70 | H10: 1 | I10: About you: age (always) | K10: =K9+1 -> 2 | L10: =IF(K10<$B$34,1,0) -> 1 | M10: =IF(L10=1,M9*(1+$B$16)+$B$35*12*POWER(1+$B$36,K10),M9) -> 87752.617
A11: Target retirement age | B11: 65 | C11: age | D11: 65 | E11: 50 | F11: 75 | G11: 75 | H11: 1 | I11: Plan: retirement age (always) | K11: =K10+1 -> 3 | L11: =IF(K11<$B$34,1,0) -> 1 | M11: =IF(L11=1,M10*(1+$B$16)+$B$35*12*POWER(1+$B$36,K11),M10) -> 98162.829
A12: Pension value today | B12: 60000 | C12: € | D12: 60000 | E12: 0 | F12: 1500000 | G12: 15000000 | H12: 1000 | I12: Your finances or pension statement: pension value (if given) | K12: =K11+1 -> 4 | L12: =IF(K12<$B$34,1,0) -> 1 | M12: =IF(L12=1,M11*(1+$B$16)+$B$35*12*POWER(1+$B$36,K12),M11) -> 109203.03
A13: Monthly contributions | B13: 500 | C13: € | D13: 500 | E13: 0 | F13: 5000 | G13: 50000 | H13: 10 | I13: Your finances or pension statement: monthly contributions (if given) | K13: =K12+1 -> 5 | L13: =IF(K13<$B$34,1,0) -> 1 | M13: =IF(L13=1,M12*(1+$B$16)+$B$35*12*POWER(1+$B$36,K13),M12) -> 120905.62
A14: Desired yearly income | B14: 40000 | C14: € | D14: 40000 | E14: 10000 | F14: 150000 | G14: 1500000 | H14: 1000 | I14: Plan: the retirement goal's yearly income (if a retirement goal exists) | K14: =K13+1 -> 6 | L14: =IF(K14<$B$34,1,0) -> 1 | M14: =IF(L14=1,M13*(1+$B$16)+$B$35*12*POWER(1+$B$36,K14),M13) -> 133304.53
A15: Other yearly income (e.g. State Pension) | B15: 15000 | C15: € | D15: 15000 | E15: 0 | F15: 50000 | G15: 500000 | H15: 500 | I15: Always: Math.round(State Pension €15,564 × entitlement: full 1, partly 0.6, not sure 0.8) | K15: =K14+1 -> 7 | L15: =IF(K15<$B$34,1,0) -> 1 | M15: =IF(L15=1,M14*(1+$B$16)+$B$35*12*POWER(1+$B$36,K15),M14) -> 146435.35
A16: Growth after charges | B16: 0.045 | C16: % (stored as a fraction) | D16: 0.045 | E16: 0.01 | F16: 0.07 | G16: 0.07 | H16: 0.0025 | I16: Always: the plan's pension growth after charges = active set's pension rate (+1% typical charges − the statement's charges, if given), to 2 dp | K16: =K15+1 -> 8 | L16: =IF(K16<$B$34,1,0) -> 1 | M16: =IF(L16=1,M15*(1+$B$16)+$B$35*12*POWER(1+$B$36,K16),M15) -> 160335.36
K17: =K16+1 -> 9 | L17: =IF(K17<$B$34,1,0) -> 1 | M17: =IF(L17=1,M16*(1+$B$16)+$B$35*12*POWER(1+$B$36,K17),M16) -> 175043.63
A18: WHAT-IF INPUTS (the "What if…" card) | K18: =K17+1 -> 10 | L18: =IF(K18<$B$34,1,0) -> 1 | M18: =IF(L18=1,M17*(1+$B$16)+$B$35*12*POWER(1+$B$36,K18),M17) -> 190601.1
A19: Input | B19: Value | C19: Unit | D19: Default | E19: Min | F19: Max (slider) | G19: Max if typed | H19: Step | I19: Pre-filled from (if the prototype pre-fills it) | K19: =K18+1 -> 11 | L19: =IF(K19<$B$34,1,0) -> 1 | M19: =IF(L19=1,M18*(1+$B$16)+$B$35*12*POWER(1+$B$36,K19),M18) -> 207050.67
A20: Retire later by | B20: 0 | C20: years | D20: 0 | E20: 0 | F20: 5 | G20: 5 | H20: 1 | K20: =K19+1 -> 12 | L20: =IF(K20<$B$34,1,0) -> 1 | M20: =IF(L20=1,M19*(1+$B$16)+$B$35*12*POWER(1+$B$36,K20),M19) -> 224437.28
A21: Save more each month | B21: 0 | C21: € | D21: 0 | E21: 0 | F21: 1500 | G21: 15000 | H21: 50 | K21: =K20+1 -> 13 | L21: =IF(K21<$B$34,1,0) -> 1 | M21: =IF(L21=1,M20*(1+$B$16)+$B$35*12*POWER(1+$B$36,K21),M20) -> 242808.03
A22: Spend less in retirement (per year) | B22: 0 | C22: € | D22: 0 | E22: 0 | F22: 20000 | G22: 200000 | H22: 500 | K22: =K21+1 -> 14 | L22: =IF(K22<$B$34,1,0) -> 1 | M22: =IF(L22=1,M21*(1+$B$16)+$B$35*12*POWER(1+$B$36,K22),M21) -> 262212.23
K23: =K22+1 -> 15 | L23: =IF(K23<$B$34,1,0) -> 1 | M23: =IF(L23=1,M22*(1+$B$16)+$B$35*12*POWER(1+$B$36,K23),M22) -> 282701.57
A24: CONTEXT INPUTS (state the prototype reads besides the sliders) | K24: =K23+1 -> 16 | L24: =IF(K24<$B$34,1,0) -> 1 | M24: =IF(L24=1,M23*(1+$B$16)+$B$35*12*POWER(1+$B$36,K24),M23) -> 304330.17
A25: Input | B25: Value | C25: Unit | D25: Default | E25: Min | F25: Max (slider) | G25: Max if typed | H25: Step | I25: Pre-filled from (if the prototype pre-fills it) | K25: =K24+1 -> 17 | L25: =IF(K25<$B$34,1,0) -> 1 | M25: =IF(L25=1,M24*(1+$B$16)+$B$35*12*POWER(1+$B$36,K25),M24) -> 327154.74
A26: Pension statement projection available (1 = yes) | B26: 0 | C26: flag | D26: 0 | E26: 0 | F26: 1 | G26: 1 | H26: 1 | I26: Pension statement upload (S.pdocs.retire.v.proj != null) | K26: =K25+1 -> 18 | L26: =IF(K26<$B$34,1,0) -> 1 | M26: =IF(L26=1,M25*(1+$B$16)+$B$35*12*POWER(1+$B$36,K26),M25) -> 351234.66
A27: Statement's projected fund | B27: 0 | C27: € | D27: 0 | E27: 0 | F27: 100000000 | G27: 100000000 | I27: Pension statement upload | K27: =K26+1 -> 19 | L27: =IF(K27<$B$34,1,0) -> 1 | M27: =IF(L27=1,M26*(1+$B$16)+$B$35*12*POWER(1+$B$36,K27),M26) -> 376632.12
A28: Statement's retirement age | B28: 66 | C28: age | D28: 66 | E28: 18 | F28: 100 | G28: 100 | I28: Pension statement upload | K28: =K27+1 -> 20 | L28: =IF(K28<$B$34,1,0) -> 1 | M28: =IF(L28=1,M27*(1+$B$16)+$B$35*12*POWER(1+$B$36,K28),M27) -> 403412.26
A29: Customer has not moved pot, contributions, growth or age in this tool (1 = yes) | B29: 1 | C29: flag | D29: 1 | E29: 0 | F29: 1 | G29: 1 | H29: 1 | I29: mine(): 1 while the customer has not moved any of the listed sliders in this tool; 0 once they have (the stated figure then stops applying). | K29: =K28+1 -> 21 | L29: =IF(K29<$B$34,1,0) -> 1 | M29: =IF(L29=1,M28*(1+$B$16)+$B$35*12*POWER(1+$B$36,K29),M28) -> 431643.3
K30: =K29+1 -> 22 | L30: =IF(K30<$B$34,1,0) -> 1 | M30: =IF(L30=1,M29*(1+$B$16)+$B$35*12*POWER(1+$B$36,K30),M29) -> 461396.68
A31: CALCULATION | K31: =K30+1 -> 23 | L31: =IF(K31<$B$34,1,0) -> 1 | M31: =IF(L31=1,M30*(1+$B$16)+$B$35*12*POWER(1+$B$36,K31),M30) -> 492747.2
A32: Calculation step | B32: Value | C32: Unit | D32: JS equivalent (prototype run function) | K32: =K31+1 -> 24 | L32: =IF(K32<$B$34,1,0) -> 1 | M32: =IF(L32=1,M31*(1+$B$16)+$B$35*12*POWER(1+$B$36,K32),M31) -> 525773.17
A33: Retiring at | B33: =$B$11+$B$20 -> 65 | C33: age | D33: ra = v.ra + (v.later || 0) | K33: =K32+1 -> 25 | L33: =IF(K33<$B$34,1,0) -> 0 | M33: =IF(L33=1,M32*(1+$B$16)+$B$35*12*POWER(1+$B$36,K33),M32) -> 525773.17
A34: Years to retirement | B34: =MAX(1,$B$33-$B$10) -> 25 | C34: n | D34: y = Math.max(1, ra - v.age) | K34: =K33+1 -> 26 | L34: =IF(K34<$B$34,1,0) -> 0 | M34: =IF(L34=1,M33*(1+$B$16)+$B$35*12*POWER(1+$B$36,K34),M33) -> 525773.17
A35: Monthly contribution incl. save more | B35: =$B$13+$B$21 -> 500 | C35: € | D35: v.m + (v.more || 0) | K35: =K34+1 -> 27 | L35: =IF(K35<$B$34,1,0) -> 0 | M35: =IF(L35=1,M34*(1+$B$16)+$B$35*12*POWER(1+$B$36,K35),M34) -> 525773.17
A36: Pay rise a year (active growth set) | B36: =Assumptions!$E$18 -> 0.025 | C36: rate (fraction) | D36: AS.wage | K36: =K35+1 -> 28 | L36: =IF(K36<$B$34,1,0) -> 0 | M36: =IF(L36=1,M35*(1+$B$16)+$B$35*12*POWER(1+$B$36,K36),M35) -> 525773.17
A37: Projected fund on our assumptions | B37: =$M$107 -> 525773.17 | C37: € | D37: ours = pensionAt(y, v.pot, v.m + more, v.g/100, AS.wage) | K37: =K36+1 -> 29 | L37: =IF(K37<$B$34,1,0) -> 0 | M37: =IF(L37=1,M36*(1+$B$16)+$B$35*12*POWER(1+$B$36,K37),M36) -> 525773.17
A38: Use the statement's projection (1 = yes) | B38: =IF(AND($B$26=1,$B$33=$B$28,$B$21=0,$B$29=1),1,0) -> 0 | C38: flag | D38: useSt = d && d.proj != null && ra === d.nra && !v.more && mine(...) | K38: =K37+1 -> 30 | L38: =IF(K38<$B$34,1,0) -> 0 | M38: =IF(L38=1,M37*(1+$B$16)+$B$35*12*POWER(1+$B$36,K38),M37) -> 525773.17
A39: Projected fund shown | B39: =IF($B$38=1,$B$27,$B$37) -> 525773.17 | C39: € | D39: f = useSt ? d.proj : ours | K39: =K38+1 -> 31 | L39: =IF(K39<$B$34,1,0) -> 0 | M39: =IF(L39=1,M38*(1+$B$16)+$B$35*12*POWER(1+$B$36,K39),M38) -> 525773.17
A40: Illustrative target | B40: =MAX(0,$B$14-$B$22-$B$15)*Assumptions!$C$49 -> 625000 | C40: € | D40: target = Math.max(0, v.d - (v.less || 0) - v.o) * 25 | K40: =K39+1 -> 32 | L40: =IF(K40<$B$34,1,0) -> 0 | M40: =IF(L40=1,M39*(1+$B$16)+$B$35*12*POWER(1+$B$36,K40),M39) -> 525773.17
A41: Illustrative gap | B41: =$B$40-$B$39 -> 99226.825 | C41: € | D41: gap = target - f | K41: =K40+1 -> 33 | L41: =IF(K41<$B$34,1,0) -> 0 | M41: =IF(L41=1,M40*(1+$B$16)+$B$35*12*POWER(1+$B$36,K41),M40) -> 525773.17
A42: Inflation discount factor (1 + inflation)^years | B42: =POWER(1+Assumptions!$C$14,$B$34) -> 1.640606 | C42: num | D42: Math.pow(1 + AS.infl, y) | K42: =K41+1 -> 34 | L42: =IF(K42<$B$34,1,0) -> 0 | M42: =IF(L42=1,M41*(1+$B$16)+$B$35*12*POWER(1+$B$36,K42),M41) -> 525773.17
A43: Worth in today's money | B43: =$B$39/$B$42 -> 320474.98 | C43: € | D43: todayM(fv, y) = fv / (1 + AS.infl)^y | K43: =K42+1 -> 35 | L43: =IF(K43<$B$34,1,0) -> 0 | M43: =IF(L43=1,M42*(1+$B$16)+$B$35*12*POWER(1+$B$36,K43),M42) -> 525773.17
K44: =K43+1 -> 36 | L44: =IF(K44<$B$34,1,0) -> 0 | M44: =IF(L44=1,M43*(1+$B$16)+$B$35*12*POWER(1+$B$36,K44),M43) -> 525773.17
A45: OUTPUTS | K45: =K44+1 -> 37 | L45: =IF(K45<$B$34,1,0) -> 0 | M45: =IF(L45=1,M44*(1+$B$16)+$B$35*12*POWER(1+$B$36,K45),M44) -> 525773.17
A46: Output | B46: Value | C46: As shown in the prototype | D46: Shown when / where it appears | K46: =K45+1 -> 38 | L46: =IF(K46<$B$34,1,0) -> 0 | M46: =IF(L46=1,M45*(1+$B$16)+$B$35*12*POWER(1+$B$36,K46),M45) -> 525773.17
A47: Headline label | C47: =IF($B$38=1,"Projected fund (from your statement)","Projected fund") -> Projected fund | D47: Always | K47: =K46+1 -> 39 | L47: =IF(K47<$B$34,1,0) -> 0 | M47: =IF(L47=1,M46*(1+$B$16)+$B$35*12*POWER(1+$B$36,K47),M46) -> 525773.17
A48: Projected fund | B48: =$B$39 -> 525773.17 | C48: =IF(($B$39)<0,"−€","€")&FIXED(ROUND(ABS($B$39),0),0) -> €525,773 | D48: Headline | K48: =K47+1 -> 40 | L48: =IF(K48<$B$34,1,0) -> 0 | M48: =IF(L48=1,M47*(1+$B$16)+$B$35*12*POWER(1+$B$36,K48),M47) -> 525773.17
A49: Illustrative gap of (sentence) | B49: =IF($B$41>0,$B$41,"") -> 99226.825 | C49: =IF($B$41>0,IF(($B$41)<0,"−€","€")&FIXED(ROUND(ABS($B$41),0),0),"") -> €99,227 | D49: Sentence, only when there is a gap | K49: =K48+1 -> 41 | L49: =IF(K49<$B$34,1,0) -> 0 | M49: =IF(L49=1,M48*(1+$B$16)+$B$35*12*POWER(1+$B$36,K49),M48) -> 525773.17
A50: Pay rise quoted (sentence) | B50: =$B$36 -> 0.025 | C50: =ROUND(($B$36)*100,2)&"%" -> 2.5% | D50: Sentence | K50: =K49+1 -> 42 | L50: =IF(K50<$B$34,1,0) -> 0 | M50: =IF(L50=1,M49*(1+$B$16)+$B$35*12*POWER(1+$B$36,K50),M49) -> 525773.17
A51: Illustrative target (25 × the income you need) | B51: =$B$40 -> 625000 | C51: =IF(($B$40)<0,"−€","€")&FIXED(ROUND(ABS($B$40),0),0) -> €625,000 | D51: Row 1 | K51: =K50+1 -> 43 | L51: =IF(K51<$B$34,1,0) -> 0 | M51: =IF(L51=1,M50*(1+$B$16)+$B$35*12*POWER(1+$B$36,K51),M50) -> 525773.17
A52: Illustrative gap | B52: =IF($B$41>0,$B$41,"None") -> 99226.825 | C52: =IF($B$41>0,IF(($B$41)<0,"−€","€")&FIXED(ROUND(ABS($B$41),0),0),"None") -> €99,227 | D52: Row 2 | K52: =K51+1 -> 44 | L52: =IF(K52<$B$34,1,0) -> 0 | M52: =IF(L52=1,M51*(1+$B$16)+$B$35*12*POWER(1+$B$36,K52),M51) -> 525773.17
A53: Retiring at | B53: =$B$33 -> 65 | C53: =$B$33&"" -> 65 | D53: Row 3 | K53: =K52+1 -> 45 | L53: =IF(K53<$B$34,1,0) -> 0 | M53: =IF(L53=1,M52*(1+$B$16)+$B$35*12*POWER(1+$B$36,K53),M52) -> 525773.17
A54: Worth in today's money (prices rising [inflation] a year) | B54: =IF(Assumptions!$C$6=1,$B$43,"") -> 320474.98 | C54: =IF(Assumptions!$C$6=1,IF(($B$43)<0,"−€","€")&FIXED(ROUND(ABS($B$43),0),0),"") -> €320,475 | D54: Only when the client has chosen an inflation rate (inflRow) | K54: =K53+1 -> 46 | L54: =IF(K54<$B$34,1,0) -> 0 | M54: =IF(L54=1,M53*(1+$B$16)+$B$35*12*POWER(1+$B$36,K54),M53) -> 525773.17
A55: Your statement projects (age nra) | B55: =IF($B$26=1,$B$27,"") | C55: =IF($B$26=1,IF(($B$27)<0,"−€","€")&FIXED(ROUND(ABS($B$27),0),0),"") | D55: Row, only with a statement projection | K55: =K54+1 -> 47 | L55: =IF(K55<$B$34,1,0) -> 0 | M55: =IF(L55=1,M54*(1+$B$16)+$B$35*12*POWER(1+$B$36,K55),M54) -> 525773.17
A56: On our assumptions (age ra) | B56: =IF($B$26=1,$B$37,"") | C56: =IF($B$26=1,IF(($B$37)<0,"−€","€")&FIXED(ROUND(ABS($B$37),0),0),"") | D56: Row, only with a statement projection | K56: =K55+1 -> 48 | L56: =IF(K56<$B$34,1,0) -> 0 | M56: =IF(L56=1,M55*(1+$B$16)+$B$35*12*POWER(1+$B$36,K56),M55) -> 525773.17
A57: "Add to my plan" goal amount (Comfortable retirement) | B57: =INT(($B$40)+0.5) -> 625000 | C57: =$B$57&"" -> 625000 | D57: Add to my plan | K57: =K56+1 -> 49 | L57: =IF(K57<$B$34,1,0) -> 0 | M57: =IF(L57=1,M56*(1+$B$16)+$B$35*12*POWER(1+$B$36,K57),M56) -> 525773.17
A58: "Add to my plan" goal years | B58: =$B$34 -> 25 | C58: =$B$58&"" -> 25 | D58: Add to my plan | K58: =K57+1 -> 50 | L58: =IF(K58<$B$34,1,0) -> 0 | M58: =IF(L58=1,M57*(1+$B$16)+$B$35*12*POWER(1+$B$36,K58),M57) -> 525773.17
K59: =K58+1 -> 51 | L59: =IF(K59<$B$34,1,0) -> 0 | M59: =IF(L59=1,M58*(1+$B$16)+$B$35*12*POWER(1+$B$36,K59),M58) -> 525773.17
K60: =K59+1 -> 52 | L60: =IF(K60<$B$34,1,0) -> 0 | M60: =IF(L60=1,M59*(1+$B$16)+$B$35*12*POWER(1+$B$36,K60),M59) -> 525773.17
K61: =K60+1 -> 53 | L61: =IF(K61<$B$34,1,0) -> 0 | M61: =IF(L61=1,M60*(1+$B$16)+$B$35*12*POWER(1+$B$36,K61),M60) -> 525773.17
K62: =K61+1 -> 54 | L62: =IF(K62<$B$34,1,0) -> 0 | M62: =IF(L62=1,M61*(1+$B$16)+$B$35*12*POWER(1+$B$36,K62),M61) -> 525773.17
K63: =K62+1 -> 55 | L63: =IF(K63<$B$34,1,0) -> 0 | M63: =IF(L63=1,M62*(1+$B$16)+$B$35*12*POWER(1+$B$36,K63),M62) -> 525773.17
K64: =K63+1 -> 56 | L64: =IF(K64<$B$34,1,0) -> 0 | M64: =IF(L64=1,M63*(1+$B$16)+$B$35*12*POWER(1+$B$36,K64),M63) -> 525773.17
K65: =K64+1 -> 57 | L65: =IF(K65<$B$34,1,0) -> 0 | M65: =IF(L65=1,M64*(1+$B$16)+$B$35*12*POWER(1+$B$36,K65),M64) -> 525773.17
K66: =K65+1 -> 58 | L66: =IF(K66<$B$34,1,0) -> 0 | M66: =IF(L66=1,M65*(1+$B$16)+$B$35*12*POWER(1+$B$36,K66),M65) -> 525773.17
K67: =K66+1 -> 59 | L67: =IF(K67<$B$34,1,0) -> 0 | M67: =IF(L67=1,M66*(1+$B$16)+$B$35*12*POWER(1+$B$36,K67),M66) -> 525773.17
K68: =K67+1 -> 60 | L68: =IF(K68<$B$34,1,0) -> 0 | M68: =IF(L68=1,M67*(1+$B$16)+$B$35*12*POWER(1+$B$36,K68),M67) -> 525773.17
K69: =K68+1 -> 61 | L69: =IF(K69<$B$34,1,0) -> 0 | M69: =IF(L69=1,M68*(1+$B$16)+$B$35*12*POWER(1+$B$36,K69),M68) -> 525773.17
K70: =K69+1 -> 62 | L70: =IF(K70<$B$34,1,0) -> 0 | M70: =IF(L70=1,M69*(1+$B$16)+$B$35*12*POWER(1+$B$36,K70),M69) -> 525773.17
... K107: =K106+1 -> 99 | L107: =IF(K107<$B$34,1,0) -> 0 | M107: =IF(L107=1,M106*(1+$B$16)+$B$35*12*POWER(1+$B$36,K107),M106) -> 525773.17

Sheet C13 Contribution impact
A1: C13 · Contribution impact
A2: Question shown: "What difference would a small increase make?" · Category: Pensions & Retirement · Prototype id: contrib
A3: Replicates: CALCS 'contrib' run(v); helpers fvA(), inflRow().
A4: Edge rules: Extra a month = salary × increase ÷ 12; cost after relief = extra × (1 − tax rate). No limits on relief are applied (the text says "limits apply").
A5: Legend: blue = input (change these) · black = formula · green = link to the Assumptions sheet · yellow fill = key assumption. Money cells show whole euros but keep full precision, as the prototype does.
A8: INPUTS
A9: Input | B9: Value | C9: Unit | D9: Default | E9: Min | F9: Max (slider) | G9: Max if typed | H9: Step | I9: Pre-filled from (if the prototype pre-fills it)
A10: Salary | B10: 60000 | C10: € | D10: 60000 | E10: 15000 | F10: 250000 | G10: 2500000 | H10: 1000 | I10: Your finances: income (if given)
A11: Increase contributions by | B11: 0.02 | C11: % (stored as a fraction) | D11: 0.02 | E11: 0.005 | F11: 0.1 | G11: 0.1 | H11: 0.005
A12: Years to retirement | B12: 25 | C12: years | D12: 25 | E12: 1 | F12: 45 | G12: 45 | H12: 1 | I12: Always: plan retirement age − age (min 1)
A13: Growth assumption | B13: 0.045 | C13: % (stored as a fraction) | D13: 0.045 | E13: 0.01 | F13: 0.07 | G13: 0.07 | H13: 0.005 | I13: Always: the plan's pension growth after charges, to 2 dp
A14: Your tax rate | B14: 0.4 | C14: % (stored as a fraction) | D14: 0.4 | E14: 0.2 | F14: 0.4 | G14: 0.4 | H14: 0.2 | I14: If income given: 40% if income > €44,000, else 20%
A16: CALCULATION
A17: Calculation step | B17: Value | C17: Unit | D17: JS equivalent (prototype run function)
A18: Extra per month | B18: =$B$10*$B$11/12 -> 100 | C18: € | D18: m = v.sal * v.inc / 100 / 12
A19: Monthly growth rate | B19: =POWER(1+$B$13,1/12)-1 -> 0.0036748094 | C19: rate (fraction) | D19: fvA: i = Math.pow(1 + r/100, 1/12) - 1
A20: Months | B20: =$B$12*12 -> 300 | C20: n | D20: n = y * 12
A21: Could add to your pension | B21: =IF($B$19<>0,$B$18*(POWER(1+$B$19,$B$20)-1)/$B$19,$B$18*$B$20) -> 54572.475 | C21: € | D21: f = fvA(m, v.g, v.y)
A22: Cost after tax relief | B22: =$B$18*(1-$B$14) -> 60 | C22: € | D22: net = m * (1 - v.tr/100)
A23: Inflation discount factor (1 + inflation)^years | B23: =POWER(1+Assumptions!$C$14,$B$12) -> 1.640606 | C23: num | D23: Math.pow(1 + AS.infl, y)
A24: Worth in today's money | B24: =$B$21/$B$23 -> 33263.608 | C24: € | D24: todayM(fv, y) = fv / (1 + AS.infl)^y
A26: OUTPUTS
A27: Output | B27: Value | C27: As shown in the prototype | D27: Shown when / where it appears
A28: Headline label | C28: ="Could add to your pension" -> Could add to your pension | D28: Always
A29: Could add to your pension | B29: =$B$21 -> 54572.475 | C29: =IF(($B$21)<0,"−€","€")&FIXED(ROUND(ABS($B$21),0),0) -> €54,572 | D29: Headline
A30: Extra per month | B30: =$B$18 -> 100 | C30: =IF(($B$18)<0,"−€","€")&FIXED(ROUND(ABS($B$18),0),0) -> €100 | D30: Row 1 (also in the sentence)
A31: Cost after tax relief | B31: =$B$22 -> 60 | C31: =IF(($B$22)<0,"−€","€")&FIXED(ROUND(ABS($B$22),0),0) -> €60 | D31: Row 2 (also in the sentence)
A32: Worth in today's money (prices rising [inflation] a year) | B32: =IF(Assumptions!$C$6=1,$B$24,"") -> 33263.608 | C32: =IF(Assumptions!$C$6=1,IF(($B$24)<0,"−€","€")&FIXED(ROUND(ABS($B$24),0),0),"") -> €33,264 | D32: Only when the client has chosen an inflation rate (inflRow)
A33: "Add to my plan" goal amount (Boost my pension) | B33: =INT(($B$21)+0.5) -> 54572 | C33: =$B$33&"" -> 54572 | D33: Add to my plan
A34: "Add to my plan" goal years | B34: =$B$12 -> 25 | C34: =$B$34&"" -> 25 | D34: Add to my plan

Sheet C14 AVC impact
A1: C14 · AVC impact
A2: Question shown: "What could extra voluntary contributions add?" · Category: Pensions & Retirement · Prototype id: avc
A3: Replicates: CALCS 'avc' run(v); helpers fvA(), inflRow().
A4: Edge rules: Net cost = AVC × (1 − tax rate) each month, × 12 × years in total. Age-related relief limits are not applied (the text says they apply).
A5: Legend: blue = input (change these) · black = formula · green = link to the Assumptions sheet · yellow fill = key assumption. Money cells show whole euros but keep full precision, as the prototype does.
A8: INPUTS
A9: Input | B9: Value | C9: Unit | D9: Default | E9: Min | F9: Max (slider) | G9: Max if typed | H9: Step | I9: Pre-filled from (if the prototype pre-fills it)
A10: AVC per month | B10: 200 | C10: € | D10: 200 | E10: 25 | F10: 2000 | G10: 20000 | H10: 25
A11: Years to retirement | B11: 15 | C11: years | D11: 15 | E11: 1 | F11: 40 | G11: 40 | H11: 1 | I11: Always: plan retirement age − age (min 1)
A12: Growth assumption | B12: 0.045 | C12: % (stored as a fraction) | D12: 0.045 | E12: 0.01 | F12: 0.07 | G12: 0.07 | H12: 0.005 | I12: Always: the plan's pension growth after charges, to 2 dp
A13: Your tax rate | B13: 0.4 | C13: % (stored as a fraction) | D13: 0.4 | E13: 0.2 | F13: 0.4 | G13: 0.4 | H13: 0.2 | I13: If income given: 40% if income > €44,000, else 20%
A15: CALCULATION
A16: Calculation step | B16: Value | C16: Unit | D16: JS equivalent (prototype run function)
A17: Monthly growth rate | B17: =POWER(1+$B$12,1/12)-1 -> 0.0036748094 | C17: rate (fraction) | D17: fvA: i = Math.pow(1 + r/100, 1/12) - 1
A18: Months | B18: =$B$11*12 -> 180 | C18: n | D18: n = y * 12
A19: Could add | B19: =IF($B$17<>0,$B$10*(POWER(1+$B$17,$B$18)-1)/$B$17,$B$10*$B$18) -> 50902.365 | C19: € | D19: f = fvA(v.m, v.g, v.y)
A20: Net cost of each monthly AVC | B20: =$B$10*(1-$B$13) -> 120 | C20: € | D20: v.m * (1 - v.tr/100)
A21: Paid in | B21: =$B$10*12*$B$11 -> 36000 | C21: € | D21: v.m * 12 * v.y
A22: Net cost to you | B22: =$B$10*(1-$B$13)*12*$B$11 -> 21600 | C22: € | D22: v.m * (1 - v.tr/100) * 12 * v.y
A23: Inflation discount factor (1 + inflation)^years | B23: =POWER(1+Assumptions!$C$14,$B$11) -> 1.3458683 | C23: num | D23: Math.pow(1 + AS.infl, y)
A24: Worth in today's money | B24: =$B$19/$B$23 -> 37821.207 | C24: € | D24: todayM(fv, y) = fv / (1 + AS.infl)^y
A26: OUTPUTS
A27: Output | B27: Value | C27: As shown in the prototype | D27: Shown when / where it appears
A28: Headline label | C28: ="Could add" -> Could add | D28: Always
A29: Could add | B29: =$B$19 -> 50902.365 | C29: =IF(($B$19)<0,"−€","€")&FIXED(ROUND(ABS($B$19),0),0) -> €50,902 | D29: Headline
A30: Each AVC could cost about (sentence) | B30: =$B$20 -> 120 | C30: =IF(($B$20)<0,"−€","€")&FIXED(ROUND(ABS($B$20),0),0) -> €120 | D30: Sentence
A31: Paid in | B31: =$B$21 -> 36000 | C31: =IF(($B$21)<0,"−€","€")&FIXED(ROUND(ABS($B$21),0),0) -> €36,000 | D31: Row 1
A32: Net cost to you | B32: =$B$22 -> 21600 | C32: =IF(($B$22)<0,"−€","€")&FIXED(ROUND(ABS($B$22),0),0) -> €21,600 | D32: Row 2
A33: Worth in today's money (prices rising [inflation] a year) | B33: =IF(Assumptions!$C$6=1,$B$24,"") -> 37821.207 | C33: =IF(Assumptions!$C$6=1,IF(($B$24)<0,"−€","€")&FIXED(ROUND(ABS($B$24),0),0),"") -> €37,821 | D33: Only when the client has chosen an inflation rate (inflRow)
A34: "Add to my plan" goal amount (Boost my pension) | B34: =INT(($B$19)+0.5) -> 50902 | C34: =$B$34&"" -> 50902 | D34: Add to my plan
A35: "Add to my plan" goal years | B35: =$B$11 -> 15 | C35: =$B$35&"" -> 15 | D35: Add to my plan

Sheet C15 Will my money last
A1: C15 · Will my money last?
A2: Question shown: "How long could my retirement savings last?" · Category: Pensions & Retirement · Prototype id: lastmoney
A3: Replicates: CALCS 'lastmoney' run(v); helper lasts(pot, w, g, inflation) (yearly loop, cap 60).
A4: Edge rules: Each year: pot = pot × (1+g) − withdrawal; stop when the pot goes below 0 (a pot of exactly 0 still counts the year); then the withdrawal rises with inflation. Counts full years paid only, capped at 60 ("60+ years"). Withdrawals stay flat (0% rise) until the client has chosen an inflation rate.
A5: Legend: blue = input (change these) · black = formula · green = link to the Assumptions sheet · yellow fill = key assumption. Money cells show whole euros but keep full precision, as the prototype does. | K5: One row per year, capped at 60 years like the JS loop.
K6: lasts(v.pot, v.w, v.g, inflation)
K7: Year | L7: Loop runs this year | M7: Withdrawal this year | N7: Pot after growth and withdrawal | O7: Full year paid (pot ≥ 0)
A8: INPUTS | K8: 1 | L8: =IF(K8<=Assumptions!$C$44,1,0) -> 1 | M8: =$B$11 -> 24000 | N8: =IF(L8=1,$B$10*(1+$B$12)-M8,$B$10) -> 388000 | O8: =IF(AND(L8=1,N8>=0),1,0) -> 1
A9: Input | B9: Value | C9: Unit | D9: Default | E9: Min | F9: Max (slider) | G9: Max if typed | H9: Step | I9: Pre-filled from (if the prototype pre-fills it) | K9: =K8+1 -> 2 | L9: =IF(AND(K9<=Assumptions!$C$44,O8=1),1,0) -> 1 | M9: =IF(L9=1,M8*(1+$B$16),M8) -> 24480 | N9: =IF(L9=1,N8*(1+$B$12)-M9,N8) -> 375160 | O9: =IF(AND(L9=1,N9>=0),1,0) -> 1
A10: Retirement savings | B10: 400000 | C10: € | D10: 400000 | E10: 10000 | F10: 3000000 | G10: 30000000 | H10: 10000 | I10: If pension or contributions given: the pension pot projected to retirement age (pensionAt, rounded) | K10: =K9+1 -> 3 | L10: =IF(AND(K10<=Assumptions!$C$44,O9=1),1,0) -> 1 | M10: =IF(L10=1,M9*(1+$B$16),M9) -> 24969.6 | N10: =IF(L10=1,N9*(1+$B$12)-M10,N9) -> 361445.2 | O10: =IF(AND(L10=1,N10>=0),1,0) -> 1
A11: Yearly withdrawal | B11: 24000 | C11: € | D11: 24000 | E11: 1000 | F11: 200000 | G11: 2000000 | H11: 1000 | K11: =K10+1 -> 4 | L11: =IF(AND(K11<=Assumptions!$C$44,O10=1),1,0) -> 1 | M11: =IF(L11=1,M10*(1+$B$16),M10) -> 25468.992 | N11: =IF(L11=1,N10*(1+$B$12)-M11,N10) -> 346819.56 | O11: =IF(AND(L11=1,N11>=0),1,0) -> 1
A12: Growth assumption | B12: 0.03 | C12: % (stored as a fraction) | D12: 0.03 | E12: 0 | F12: 0.07 | G12: 0.07 | H12: 0.005 | I12: Always: the active growth set's pension growth once retired (3.15% Standard / 2.8% Cautious) | K12: =K11+1 -> 5 | L12: =IF(AND(K12<=Assumptions!$C$44,O11=1),1,0) -> 1 | M12: =IF(L12=1,M11*(1+$B$16),M11) -> 25978.372 | N12: =IF(L12=1,N11*(1+$B$12)-M12,N11) -> 331245.78 | O12: =IF(AND(L12=1,N12>=0),1,0) -> 1
K13: =K12+1 -> 6 | L13: =IF(AND(K13<=Assumptions!$C$44,O12=1),1,0) -> 1 | M13: =IF(L13=1,M12*(1+$B$16),M12) -> 26497.939 | N13: =IF(L13=1,N12*(1+$B$12)-M13,N12) -> 314685.21 | O13: =IF(AND(L13=1,N13>=0),1,0) -> 1
A14: CALCULATION | K14: =K13+1 -> 7 | L14: =IF(AND(K14<=Assumptions!$C$44,O13=1),1,0) -> 1 | M14: =IF(L14=1,M13*(1+$B$16),M13) -> 27027.898 | N14: =IF(L14=1,N13*(1+$B$12)-M14,N13) -> 297097.87 | O14: =IF(AND(L14=1,N14>=0),1,0) -> 1
A15: Calculation step | B15: Value | C15: Unit | D15: JS equivalent (prototype run function) | K15: =K14+1 -> 8 | L15: =IF(AND(K15<=Assumptions!$C$44,O14=1),1,0) -> 1 | M15: =IF(L15=1,M14*(1+$B$16),M14) -> 27568.456 | N15: =IF(L15=1,N14*(1+$B$12)-M15,N14) -> 278442.35 | O15: =IF(AND(L15=1,N15>=0),1,0) -> 1
A16: Withdrawals rise by (inflation if chosen, else 0) | B16: =IF(Assumptions!$C$6=1,Assumptions!$C$14,0) -> 0.02 | C16: rate (fraction) | D16: inflSet() ? AS.infl * 100 : 0 | K16: =K15+1 -> 9 | L16: =IF(AND(K16<=Assumptions!$C$44,O15=1),1,0) -> 1 | M16: =IF(L16=1,M15*(1+$B$16),M15) -> 28119.825 | N16: =IF(L16=1,N15*(1+$B$12)-M16,N15) -> 258675.8 | O16: =IF(AND(L16=1,N16>=0),1,0) -> 1
A17: Years the money lasts | B17: =SUM($O$8:$O$67) -> 18 | C17: n | D17: y = lasts(v.pot, v.w, v.g, inf) | K17: =K16+1 -> 10 | L17: =IF(AND(K17<=Assumptions!$C$44,O16=1),1,0) -> 1 | M17: =IF(L17=1,M16*(1+$B$16),M16) -> 28682.222 | N17: =IF(L17=1,N16*(1+$B$12)-M17,N16) -> 237753.85 | O17: =IF(AND(L17=1,N17>=0),1,0) -> 1
A18: Withdrawal rate | B18: =IF($B$10=0,0,$B$11/$B$10) -> 0.06 | C18: rate (fraction) | D18: v.w / v.pot | K18: =K17+1 -> 11 | L18: =IF(AND(K18<=Assumptions!$C$44,O17=1),1,0) -> 1 | M18: =IF(L18=1,M17*(1+$B$16),M17) -> 29255.866 | N18: =IF(L18=1,N17*(1+$B$12)-M18,N17) -> 215630.6 | O18: =IF(AND(L18=1,N18>=0),1,0) -> 1
K19: =K18+1 -> 12 | L19: =IF(AND(K19<=Assumptions!$C$44,O18=1),1,0) -> 1 | M19: =IF(L19=1,M18*(1+$B$16),M18) -> 29840.983 | N19: =IF(L19=1,N18*(1+$B$12)-M19,N18) -> 192258.53 | O19: =IF(AND(L19=1,N19>=0),1,0) -> 1
A20: OUTPUTS | K20: =K19+1 -> 13 | L20: =IF(AND(K20<=Assumptions!$C$44,O19=1),1,0) -> 1 | M20: =IF(L20=1,M19*(1+$B$16),M19) -> 30437.803 | N20: =IF(L20=1,N19*(1+$B$12)-M20,N19) -> 167588.49 | O20: =IF(AND(L20=1,N20>=0),1,0) -> 1
A21: Output | B21: Value | C21: As shown in the prototype | D21: Shown when / where it appears | K21: =K20+1 -> 14 | L21: =IF(AND(K21<=Assumptions!$C$44,O20=1),1,0) -> 1 | M21: =IF(L21=1,M20*(1+$B$16),M20) -> 31046.559 | N21: =IF(L21=1,N20*(1+$B$12)-M21,N20) -> 141569.58 | O21: =IF(AND(L21=1,N21>=0),1,0) -> 1
A22: Headline label | C22: ="Could last about" -> Could last about | D22: Always | K22: =K21+1 -> 15 | L22: =IF(AND(K22<=Assumptions!$C$44,O21=1),1,0) -> 1 | M22: =IF(L22=1,M21*(1+$B$16),M21) -> 31667.49 | N22: =IF(L22=1,N21*(1+$B$12)-M22,N21) -> 114149.18 | O22: =IF(AND(L22=1,N22>=0),1,0) -> 1
A23: Could last about (years) | B23: =$B$17 -> 18 | C23: =IF($B$17>=Assumptions!$C$44,Assumptions!$C$44&"+ years",$B$17&" years") -> 18 years | D23: Headline | K23: =K22+1 -> 16 | L23: =IF(AND(K23<=Assumptions!$C$44,O22=1),1,0) -> 1 | M23: =IF(L23=1,M22*(1+$B$16),M22) -> 32300.84 | N23: =IF(L23=1,N22*(1+$B$12)-M23,N22) -> 85272.814 | O23: =IF(AND(L23=1,N23>=0),1,0) -> 1
A24: Withdrawing a year (sentence) | B24: =$B$11 -> 24000 | C24: =IF(($B$11)<0,"−€","€")&FIXED(ROUND(ABS($B$11),0),0) -> €24,000 | D24: Sentence | K24: =K23+1 -> 17 | L24: =IF(AND(K24<=Assumptions!$C$44,O23=1),1,0) -> 1 | M24: =IF(L24=1,M23*(1+$B$16),M23) -> 32946.857 | N24: =IF(L24=1,N23*(1+$B$12)-M24,N23) -> 54884.142 | O24: =IF(AND(L24=1,N24>=0),1,0) -> 1
A25: Withdrawals rise with prices at (sentence) | B25: =IF(Assumptions!$C$6=1,Assumptions!$C$14,"") -> 0.02 | C25: =IF(Assumptions!$C$6=1,ROUND((Assumptions!$C$14)*100,2)&"%","") -> 2% | D25: Sentence, only when inflation is chosen | K25: =K24+1 -> 18 | L25: =IF(AND(K25<=Assumptions!$C$44,O24=1),1,0) -> 1 | M25: =IF(L25=1,M24*(1+$B$16),M24) -> 33605.794 | N25: =IF(L25=1,N24*(1+$B$12)-M25,N24) -> 22924.872 | O25: =IF(AND(L25=1,N25>=0),1,0) -> 1
A26: Withdrawal rate | B26: =$B$18 -> 0.06 | C26: =FIXED($B$18*100,1,TRUE())&"%" -> 6.0% | D26: Row 1 | K26: =K25+1 -> 19 | L26: =IF(AND(K26<=Assumptions!$C$44,O25=1),1,0) -> 1 | M26: =IF(L26=1,M25*(1+$B$16),M25) -> 34277.91 | N26: =IF(L26=1,N25*(1+$B$12)-M26,N25) -> -10665.292 | O26: =IF(AND(L26=1,N26>=0),1,0) -> 0
K27: =K26+1 -> 20 | L27: =IF(AND(K27<=Assumptions!$C$44,O26=1),1,0) -> 0 | M27: =IF(L27=1,M26*(1+$B$16),M26) -> 34277.91 | N27: =IF(L27=1,N26*(1+$B$12)-M27,N26) -> -10665.292 | O27: =IF(AND(L27=1,N27>=0),1,0) -> 0
K28: =K27+1 -> 21 | L28: =IF(AND(K28<=Assumptions!$C$44,O27=1),1,0) -> 0 | M28: =IF(L28=1,M27*(1+$B$16),M27) -> 34277.91 | N28: =IF(L28=1,N27*(1+$B$12)-M28,N27) -> -10665.292 | O28: =IF(AND(L28=1,N28>=0),1,0) -> 0
K29: =K28+1 -> 22 | L29: =IF(AND(K29<=Assumptions!$C$44,O28=1),1,0) -> 0 | M29: =IF(L29=1,M28*(1+$B$16),M28) -> 34277.91 | N29: =IF(L29=1,N28*(1+$B$12)-M29,N28) -> -10665.292 | O29: =IF(AND(L29=1,N29>=0),1,0) -> 0
K30: =K29+1 -> 23 | L30: =IF(AND(K30<=Assumptions!$C$44,O29=1),1,0) -> 0 | M30: =IF(L30=1,M29*(1+$B$16),M29) -> 34277.91 | N30: =IF(L30=1,N29*(1+$B$12)-M30,N29) -> -10665.292 | O30: =IF(AND(L30=1,N30>=0),1,0) -> 0
K31: =K30+1 -> 24 | L31: =IF(AND(K31<=Assumptions!$C$44,O30=1),1,0) -> 0 | M31: =IF(L31=1,M30*(1+$B$16),M30) -> 34277.91 | N31: =IF(L31=1,N30*(1+$B$12)-M31,N30) -> -10665.292 | O31: =IF(AND(L31=1,N31>=0),1,0) -> 0
K32: =K31+1 -> 25 | L32: =IF(AND(K32<=Assumptions!$C$44,O31=1),1,0) -> 0 | M32: =IF(L32=1,M31*(1+$B$16),M31) -> 34277.91 | N32: =IF(L32=1,N31*(1+$B$12)-M32,N31) -> -10665.292 | O32: =IF(AND(L32=1,N32>=0),1,0) -> 0
K33: =K32+1 -> 26 | L33: =IF(AND(K33<=Assumptions!$C$44,O32=1),1,0) -> 0 | M33: =IF(L33=1,M32*(1+$B$16),M32) -> 34277.91 | N33: =IF(L33=1,N32*(1+$B$12)-M33,N32) -> -10665.292 | O33: =IF(AND(L33=1,N33>=0),1,0) -> 0
K34: =K33+1 -> 27 | L34: =IF(AND(K34<=Assumptions!$C$44,O33=1),1,0) -> 0 | M34: =IF(L34=1,M33*(1+$B$16),M33) -> 34277.91 | N34: =IF(L34=1,N33*(1+$B$12)-M34,N33) -> -10665.292 | O34: =IF(AND(L34=1,N34>=0),1,0) -> 0
K35: =K34+1 -> 28 | L35: =IF(AND(K35<=Assumptions!$C$44,O34=1),1,0) -> 0 | M35: =IF(L35=1,M34*(1+$B$16),M34) -> 34277.91 | N35: =IF(L35=1,N34*(1+$B$12)-M35,N34) -> -10665.292 | O35: =IF(AND(L35=1,N35>=0),1,0) -> 0
K36: =K35+1 -> 29 | L36: =IF(AND(K36<=Assumptions!$C$44,O35=1),1,0) -> 0 | M36: =IF(L36=1,M35*(1+$B$16),M35) -> 34277.91 | N36: =IF(L36=1,N35*(1+$B$12)-M36,N35) -> -10665.292 | O36: =IF(AND(L36=1,N36>=0),1,0) -> 0
K37: =K36+1 -> 30 | L37: =IF(AND(K37<=Assumptions!$C$44,O36=1),1,0) -> 0 | M37: =IF(L37=1,M36*(1+$B$16),M36) -> 34277.91 | N37: =IF(L37=1,N36*(1+$B$12)-M37,N36) -> -10665.292 | O37: =IF(AND(L37=1,N37>=0),1,0) -> 0
K38: =K37+1 -> 31 | L38: =IF(AND(K38<=Assumptions!$C$44,O37=1),1,0) -> 0 | M38: =IF(L38=1,M37*(1+$B$16),M37) -> 34277.91 | N38: =IF(L38=1,N37*(1+$B$12)-M38,N37) -> -10665.292 | O38: =IF(AND(L38=1,N38>=0),1,0) -> 0
... K67: =K66+1 -> 60 | L67: =IF(AND(K67<=Assumptions!$C$44,O66=1),1,0) -> 0 | M67: =IF(L67=1,M66*(1+$B$16),M66) -> 34277.91 | N67: =IF(L67=1,N66*(1+$B$12)-M67,N66) -> -10665.292 | O67: =IF(AND(L67=1,N67>=0),1,0) -> 0

Sheet C16 Drawdown scenarios
A1: C16 · Retirement drawdown scenarios
A2: Question shown: "How do different growth rates change things?" · Category: Pensions & Retirement · Prototype id: drawdown
A3: Replicates: CALCS 'drawdown' run(v); helper lasts() at 2%, 4% and 6% growth.
A4: Edge rules: Three lasts() loops (cap 60). Headline shows "60+" for the Balanced case and the Growth row shows "60+ yrs", but the Cautious and Balanced rows show the plain number (e.g. "60 yrs") (JS behaviour, replicated). Withdrawals rise with inflation only when it is chosen.
A5: Legend: blue = input (change these) · black = formula · green = link to the Assumptions sheet · yellow fill = key assumption. Money cells show whole euros but keep full precision, as the prototype does. | K5: One row per year, capped at 60 years like the JS loop. | Q5: One row per year, capped at 60 years like the JS loop. | W5: One row per year, capped at 60 years like the JS loop.
K6: lasts(pot, w, 2%, inflation) | Q6: lasts(pot, w, 4%, inflation) | W6: lasts(pot, w, 6%, inflation)
K7: Year | L7: Loop runs this year | M7: Withdrawal this year | N7: Pot after growth and withdrawal | O7: Full year paid (pot ≥ 0) | Q7: Year | R7: Loop runs this year | S7: Withdrawal this year | T7: Pot after growth and withdrawal | U7: Full year paid (pot ≥ 0) | W7: Year | X7: Loop runs this year | Y7: Withdrawal this year | Z7: Pot after growth and withdrawal | AA7: Full year paid (pot ≥ 0)
A8: INPUTS | K8: 1 | L8: =IF(K8<=Assumptions!$C$44,1,0) -> 1 | M8: =$B$11 -> 20000 | N8: =IF(L8=1,$B$10*(1+$B$16)-M8,$B$10) -> 388000 | O8: =IF(AND(L8=1,N8>=0),1,0) -> 1 | Q8: 1 | R8: =IF(Q8<=Assumptions!$C$44,1,0) -> 1 | S8: =$B$11 -> 20000 | T8: =IF(R8=1,$B$10*(1+$B$17)-S8,$B$10) -> 396000 | U8: =IF(AND(R8=1,T8>=0),1,0) -> 1 | W8: 1 | X8: =IF(W8<=Assumptions!$C$44,1,0) -> 1 | Y8: =$B$11 -> 20000 | Z8: =IF(X8=1,$B$10*(1+$B$18)-Y8,$B$10) -> 404000 | AA8: =IF(AND(X8=1,Z8>=0),1,0) -> 1
A9: Input | B9: Value | C9: Unit | D9: Default | E9: Min | F9: Max (slider) | G9: Max if typed | H9: Step | I9: Pre-filled from (if the prototype pre-fills it) | K9: =K8+1 -> 2 | L9: =IF(AND(K9<=Assumptions!$C$44,O8=1),1,0) -> 1 | M9: =IF(L9=1,M8*(1+$B$15),M8) -> 20400 | N9: =IF(L9=1,N8*(1+$B$16)-M9,N8) -> 375360 | O9: =IF(AND(L9=1,N9>=0),1,0) -> 1 | Q9: =Q8+1 -> 2 | R9: =IF(AND(Q9<=Assumptions!$C$44,U8=1),1,0) -> 1 | S9: =IF(R9=1,S8*(1+$B$15),S8) -> 20400 | T9: =IF(R9=1,T8*(1+$B$17)-S9,T8) -> 391440 | U9: =IF(AND(R9=1,T9>=0),1,0) -> 1 | W9: =W8+1 -> 2 | X9: =IF(AND(W9<=Assumptions!$C$44,AA8=1),1,0) -> 1 | Y9: =IF(X9=1,Y8*(1+$B$15),Y8) -> 20400 | Z9: =IF(X9=1,Z8*(1+$B$18)-Y9,Z8) -> 407840 | AA9: =IF(AND(X9=1,Z9>=0),1,0) -> 1
A10: Retirement savings | B10: 400000 | C10: € | D10: 400000 | E10: 10000 | F10: 3000000 | G10: 30000000 | H10: 10000 | I10: If pension or contributions given: the pension pot projected to retirement age (pensionAt, rounded) | K10: =K9+1 -> 3 | L10: =IF(AND(K10<=Assumptions!$C$44,O9=1),1,0) -> 1 | M10: =IF(L10=1,M9*(1+$B$15),M9) -> 20808 | N10: =IF(L10=1,N9*(1+$B$16)-M10,N9) -> 362059.2 | O10: =IF(AND(L10=1,N10>=0),1,0) -> 1 | Q10: =Q9+1 -> 3 | R10: =IF(AND(Q10<=Assumptions!$C$44,U9=1),1,0) -> 1 | S10: =IF(R10=1,S9*(1+$B$15),S9) -> 20808 | T10: =IF(R10=1,T9*(1+$B$17)-S10,T9) -> 386289.6 | U10: =IF(AND(R10=1,T10>=0),1,0) -> 1 | W10: =W9+1 -> 3 | X10: =IF(AND(W10<=Assumptions!$C$44,AA9=1),1,0) -> 1 | Y10: =IF(X10=1,Y9*(1+$B$15),Y9) -> 20808 | Z10: =IF(X10=1,Z9*(1+$B$18)-Y10,Z9) -> 411502.4 | AA10: =IF(AND(X10=1,Z10>=0),1,0) -> 1
A11: Yearly withdrawal | B11: 20000 | C11: € | D11: 20000 | E11: 1000 | F11: 200000 | G11: 2000000 | H11: 1000 | K11: =K10+1 -> 4 | L11: =IF(AND(K11<=Assumptions!$C$44,O10=1),1,0) -> 1 | M11: =IF(L11=1,M10*(1+$B$15),M10) -> 21224.16 | N11: =IF(L11=1,N10*(1+$B$16)-M11,N10) -> 348076.22 | O11: =IF(AND(L11=1,N11>=0),1,0) -> 1 | Q11: =Q10+1 -> 4 | R11: =IF(AND(Q11<=Assumptions!$C$44,U10=1),1,0) -> 1 | S11: =IF(R11=1,S10*(1+$B$15),S10) -> 21224.16 | T11: =IF(R11=1,T10*(1+$B$17)-S11,T10) -> 380517.02 | U11: =IF(AND(R11=1,T11>=0),1,0) -> 1 | W11: =W10+1 -> 4 | X11: =IF(AND(W11<=Assumptions!$C$44,AA10=1),1,0) -> 1 | Y11: =IF(X11=1,Y10*(1+$B$15),Y10) -> 21224.16 | Z11: =IF(X11=1,Z10*(1+$B$18)-Y11,Z10) -> 414968.38 | AA11: =IF(AND(X11=1,Z11>=0),1,0) -> 1
K12: =K11+1 -> 5 | L12: =IF(AND(K12<=Assumptions!$C$44,O11=1),1,0) -> 1 | M12: =IF(L12=1,M11*(1+$B$15),M11) -> 21648.643 | N12: =IF(L12=1,N11*(1+$B$16)-M12,N11) -> 333389.11 | O12: =IF(AND(L12=1,N12>=0),1,0) -> 1 | Q12: =Q11+1 -> 5 | R12: =IF(AND(Q12<=Assumptions!$C$44,U11=1),1,0) -> 1 | S12: =IF(R12=1,S11*(1+$B$15),S11) -> 21648.643 | T12: =IF(R12=1,T11*(1+$B$17)-S12,T11) -> 374089.06 | U12: =IF(AND(R12=1,T12>=0),1,0) -> 1 | W12: =W11+1 -> 5 | X12: =IF(AND(W12<=Assumptions!$C$44,AA11=1),1,0) -> 1 | Y12: =IF(X12=1,Y11*(1+$B$15),Y11) -> 21648.643 | Z12: =IF(X12=1,Z11*(1+$B$18)-Y12,Z11) -> 418217.84 | AA12: =IF(AND(X12=1,Z12>=0),1,0) -> 1
A13: CALCULATION | K13: =K12+1 -> 6 | L13: =IF(AND(K13<=Assumptions!$C$44,O12=1),1,0) -> 1 | M13: =IF(L13=1,M12*(1+$B$15),M12) -> 22081.616 | N13: =IF(L13=1,N12*(1+$B$16)-M13,N12) -> 317975.27 | O13: =IF(AND(L13=1,N13>=0),1,0) -> 1 | Q13: =Q12+1 -> 6 | R13: =IF(AND(Q13<=Assumptions!$C$44,U12=1),1,0) -> 1 | S13: =IF(R13=1,S12*(1+$B$15),S12) -> 22081.616 | T13: =IF(R13=1,T12*(1+$B$17)-S13,T12) -> 366971.01 | U13: =IF(AND(R13=1,T13>=0),1,0) -> 1 | W13: =W12+1 -> 6 | X13: =IF(AND(W13<=Assumptions!$C$44,AA12=1),1,0) -> 1 | Y13: =IF(X13=1,Y12*(1+$B$15),Y12) -> 22081.616 | Z13: =IF(X13=1,Z12*(1+$B$18)-Y13,Z12) -> 421229.3 | AA13: =IF(AND(X13=1,Z13>=0),1,0) -> 1
A14: Calculation step | B14: Value | C14: Unit | D14: JS equivalent (prototype run function) | K14: =K13+1 -> 7 | L14: =IF(AND(K14<=Assumptions!$C$44,O13=1),1,0) -> 1 | M14: =IF(L14=1,M13*(1+$B$15),M13) -> 22523.248 | N14: =IF(L14=1,N13*(1+$B$16)-M14,N13) -> 301811.53 | O14: =IF(AND(L14=1,N14>=0),1,0) -> 1 | Q14: =Q13+1 -> 7 | R14: =IF(AND(Q14<=Assumptions!$C$44,U13=1),1,0) -> 1 | S14: =IF(R14=1,S13*(1+$B$15),S13) -> 22523.248 | T14: =IF(R14=1,T13*(1+$B$17)-S14,T13) -> 359126.6 | U14: =IF(AND(R14=1,T14>=0),1,0) -> 1 | W14: =W13+1 -> 7 | X14: =IF(AND(W14<=Assumptions!$C$44,AA13=1),1,0) -> 1 | Y14: =IF(X14=1,Y13*(1+$B$15),Y13) -> 22523.248 | Z14: =IF(X14=1,Z13*(1+$B$18)-Y14,Z13) -> 423979.81 | AA14: =IF(AND(X14=1,Z14>=0),1,0) -> 1
A15: Withdrawals rise by (inflation if chosen, else 0) | B15: =IF(Assumptions!$C$6=1,Assumptions!$C$14,0) -> 0.02 | C15: rate (fraction) | D15: inflSet() ? AS.infl * 100 : 0 | K15: =K14+1 -> 8 | L15: =IF(AND(K15<=Assumptions!$C$44,O14=1),1,0) -> 1 | M15: =IF(L15=1,M14*(1+$B$15),M14) -> 22973.713 | N15: =IF(L15=1,N14*(1+$B$16)-M15,N14) -> 284874.05 | O15: =IF(AND(L15=1,N15>=0),1,0) -> 1 | Q15: =Q14+1 -> 8 | R15: =IF(AND(Q15<=Assumptions!$C$44,U14=1),1,0) -> 1 | S15: =IF(R15=1,S14*(1+$B$15),S14) -> 22973.713 | T15: =IF(R15=1,T14*(1+$B$17)-S15,T14) -> 350517.95 | U15: =IF(AND(R15=1,T15>=0),1,0) -> 1 | W15: =W14+1 -> 8 | X15: =IF(AND(W15<=Assumptions!$C$44,AA14=1),1,0) -> 1 | Y15: =IF(X15=1,Y14*(1+$B$15),Y14) -> 22973.713 | Z15: =IF(X15=1,Z14*(1+$B$18)-Y15,Z14) -> 426444.88 | AA15: =IF(AND(X15=1,Z15>=0),1,0) -> 1
A16: Cautious growth | B16: =Assumptions!$C$51 -> 0.02 | C16: rate (fraction) | D16: 2 | K16: =K15+1 -> 9 | L16: =IF(AND(K16<=Assumptions!$C$44,O15=1),1,0) -> 1 | M16: =IF(L16=1,M15*(1+$B$15),M15) -> 23433.188 | N16: =IF(L16=1,N15*(1+$B$16)-M16,N15) -> 267138.34 | O16: =IF(AND(L16=1,N16>=0),1,0) -> 1 | Q16: =Q15+1 -> 9 | R16: =IF(AND(Q16<=Assumptions!$C$44,U15=1),1,0) -> 1 | S16: =IF(R16=1,S15*(1+$B$15),S15) -> 23433.188 | T16: =IF(R16=1,T15*(1+$B$17)-S16,T15) -> 341105.48 | U16: =IF(AND(R16=1,T16>=0),1,0) -> 1 | W16: =W15+1 -> 9 | X16: =IF(AND(W16<=Assumptions!$C$44,AA15=1),1,0) -> 1 | Y16: =IF(X16=1,Y15*(1+$B$15),Y15) -> 23433.188 | Z16: =IF(X16=1,Z15*(1+$B$18)-Y16,Z15) -> 428598.39 | AA16: =IF(AND(X16=1,Z16>=0),1,0) -> 1
A17: Balanced growth | B17: =Assumptions!$C$52 -> 0.04 | C17: rate (fraction) | D17: 4 | K17: =K16+1 -> 10 | L17: =IF(AND(K17<=Assumptions!$C$44,O16=1),1,0) -> 1 | M17: =IF(L17=1,M16*(1+$B$15),M16) -> 23901.851 | N17: =IF(L17=1,N16*(1+$B$16)-M17,N16) -> 248579.25 | O17: =IF(AND(L17=1,N17>=0),1,0) -> 1 | Q17: =Q16+1 -> 10 | R17: =IF(AND(Q17<=Assumptions!$C$44,U16=1),1,0) -> 1 | S17: =IF(R17=1,S16*(1+$B$15),S16) -> 23901.851 | T17: =IF(R17=1,T16*(1+$B$17)-S17,T16) -> 330847.85 | U17: =IF(AND(R17=1,T17>=0),1,0) -> 1 | W17: =W16+1 -> 10 | X17: =IF(AND(W17<=Assumptions!$C$44,AA16=1),1,0) -> 1 | Y17: =IF(X17=1,Y16*(1+$B$15),Y16) -> 23901.851 | Z17: =IF(X17=1,Z16*(1+$B$18)-Y17,Z16) -> 430412.44 | AA17: =IF(AND(X17=1,Z17>=0),1,0) -> 1
A18: Growth growth | B18: =Assumptions!$C$53 -> 0.06 | C18: rate (fraction) | D18: 6 | K18: =K17+1 -> 11 | L18: =IF(AND(K18<=Assumptions!$C$44,O17=1),1,0) -> 1 | M18: =IF(L18=1,M17*(1+$B$15),M17) -> 24379.888 | N18: =IF(L18=1,N17*(1+$B$16)-M18,N17) -> 229170.95 | O18: =IF(AND(L18=1,N18>=0),1,0) -> 1 | Q18: =Q17+1 -> 11 | R18: =IF(AND(Q18<=Assumptions!$C$44,U17=1),1,0) -> 1 | S18: =IF(R18=1,S17*(1+$B$15),S17) -> 24379.888 | T18: =IF(R18=1,T17*(1+$B$17)-S18,T17) -> 319701.87 | U18: =IF(AND(R18=1,T18>=0),1,0) -> 1 | W18: =W17+1 -> 11 | X18: =IF(AND(W18<=Assumptions!$C$44,AA17=1),1,0) -> 1 | Y18: =IF(X18=1,Y17*(1+$B$15),Y17) -> 24379.888 | Z18: =IF(X18=1,Z17*(1+$B$18)-Y18,Z17) -> 431857.3 | AA18: =IF(AND(X18=1,Z18>=0),1,0) -> 1
A19: Cautious: years | B19: =SUM($O$8:$O$67) -> 20 | C19: n | D19: s[0] = lasts(v.pot, v.w, 2, inf) | K19: =K18+1 -> 12 | L19: =IF(AND(K19<=Assumptions!$C$44,O18=1),1,0) -> 1 | M19: =IF(L19=1,M18*(1+$B$15),M18) -> 24867.486 | N19: =IF(L19=1,N18*(1+$B$16)-M19,N18) -> 208886.88 | O19: =IF(AND(L19=1,N19>=0),1,0) -> 1 | Q19: =Q18+1 -> 12 | R19: =IF(AND(Q19<=Assumptions!$C$44,U18=1),1,0) -> 1 | S19: =IF(R19=1,S18*(1+$B$15),S18) -> 24867.486 | T19: =IF(R19=1,T18*(1+$B$17)-S19,T18) -> 307622.46 | U19: =IF(AND(R19=1,T19>=0),1,0) -> 1 | W19: =W18+1 -> 12 | X19: =IF(AND(W19<=Assumptions!$C$44,AA18=1),1,0) -> 1 | Y19: =IF(X19=1,Y18*(1+$B$15),Y18) -> 24867.486 | Z19: =IF(X19=1,Z18*(1+$B$18)-Y19,Z18) -> 432901.25 | AA19: =IF(AND(X19=1,Z19>=0),1,0) -> 1
A20: Balanced: years | B20: =SUM($U$8:$U$67) -> 26 | C20: n | D20: s[1] = lasts(v.pot, v.w, 4, inf) | K20: =K19+1 -> 13 | L20: =IF(AND(K20<=Assumptions!$C$44,O19=1),1,0) -> 1 | M20: =IF(L20=1,M19*(1+$B$15),M19) -> 25364.836 | N20: =IF(L20=1,N19*(1+$B$16)-M20,N19) -> 187699.79 | O20: =IF(AND(L20=1,N20>=0),1,0) -> 1 | Q20: =Q19+1 -> 13 | R20: =IF(AND(Q20<=Assumptions!$C$44,U19=1),1,0) -> 1 | S20: =IF(R20=1,S19*(1+$B$15),S19) -> 25364.836 | T20: =IF(R20=1,T19*(1+$B$17)-S20,T19) -> 294562.53 | U20: =IF(AND(R20=1,T20>=0),1,0) -> 1 | W20: =W19+1 -> 13 | X20: =IF(AND(W20<=Assumptions!$C$44,AA19=1),1,0) -> 1 | Y20: =IF(X20=1,Y19*(1+$B$15),Y19) -> 25364.836 | Z20: =IF(X20=1,Z19*(1+$B$18)-Y20,Z19) -> 433510.49 | AA20: =IF(AND(X20=1,Z20>=0),1,0) -> 1
A21: Growth: years | B21: =SUM($AA$8:$AA$67) -> 41 | C21: n | D21: s[2] = lasts(v.pot, v.w, 6, inf) | K21: =K20+1 -> 14 | L21: =IF(AND(K21<=Assumptions!$C$44,O20=1),1,0) -> 1 | M21: =IF(L21=1,M20*(1+$B$15),M20) -> 25872.133 | N21: =IF(L21=1,N20*(1+$B$16)-M21,N20) -> 165581.65 | O21: =IF(AND(L21=1,N21>=0),1,0) -> 1 | Q21: =Q20+1 -> 14 | R21: =IF(AND(Q21<=Assumptions!$C$44,U20=1),1,0) -> 1 | S21: =IF(R21=1,S20*(1+$B$15),S20) -> 25872.133 | T21: =IF(R21=1,T20*(1+$B$17)-S21,T20) -> 280472.89 | U21: =IF(AND(R21=1,T21>=0),1,0) -> 1 | W21: =W20+1 -> 14 | X21: =IF(AND(W21<=Assumptions!$C$44,AA20=1),1,0) -> 1 | Y21: =IF(X21=1,Y20*(1+$B$15),Y20) -> 25872.133 | Z21: =IF(X21=1,Z20*(1+$B$18)-Y21,Z20) -> 433648.99 | AA21: =IF(AND(X21=1,Z21>=0),1,0) -> 1
K22: =K21+1 -> 15 | L22: =IF(AND(K22<=Assumptions!$C$44,O21=1),1,0) -> 1 | M22: =IF(L22=1,M21*(1+$B$15),M21) -> 26389.575 | N22: =IF(L22=1,N21*(1+$B$16)-M22,N21) -> 142503.71 | O22: =IF(AND(L22=1,N22>=0),1,0) -> 1 | Q22: =Q21+1 -> 15 | R22: =IF(AND(Q22<=Assumptions!$C$44,U21=1),1,0) -> 1 | S22: =IF(R22=1,S21*(1+$B$15),S21) -> 26389.575 | T22: =IF(R22=1,T21*(1+$B$17)-S22,T21) -> 265302.24 | U22: =IF(AND(R22=1,T22>=0),1,0) -> 1 | W22: =W21+1 -> 15 | X22: =IF(AND(W22<=Assumptions!$C$44,AA21=1),1,0) -> 1 | Y22: =IF(X22=1,Y21*(1+$B$15),Y21) -> 26389.575 | Z22: =IF(X22=1,Z21*(1+$B$18)-Y22,Z21) -> 433278.35 | AA22: =IF(AND(X22=1,Z22>=0),1,0) -> 1
A23: OUTPUTS | K23: =K22+1 -> 16 | L23: =IF(AND(K23<=Assumptions!$C$44,O22=1),1,0) -> 1 | M23: =IF(L23=1,M22*(1+$B$15),M22) -> 26917.367 | N23: =IF(L23=1,N22*(1+$B$16)-M23,N22) -> 118436.41 | O23: =IF(AND(L23=1,N23>=0),1,0) -> 1 | Q23: =Q22+1 -> 16 | R23: =IF(AND(Q23<=Assumptions!$C$44,U22=1),1,0) -> 1 | S23: =IF(R23=1,S22*(1+$B$15),S22) -> 26917.367 | T23: =IF(R23=1,T22*(1+$B$17)-S23,T22) -> 248996.96 | U23: =IF(AND(R23=1,T23>=0),1,0) -> 1 | W23: =W22+1 -> 16 | X23: =IF(AND(W23<=Assumptions!$C$44,AA22=1),1,0) -> 1 | Y23: =IF(X23=1,Y22*(1+$B$15),Y22) -> 26917.367 | Z23: =IF(X23=1,Z22*(1+$B$18)-Y23,Z22) -> 432357.68 | AA23: =IF(AND(X23=1,Z23>=0),1,0) -> 1
A24: Output | B24: Value | C24: As shown in the prototype | D24: Shown when / where it appears | K24: =K23+1 -> 17 | L24: =IF(AND(K24<=Assumptions!$C$44,O23=1),1,0) -> 1 | M24: =IF(L24=1,M23*(1+$B$15),M23) -> 27455.714 | N24: =IF(L24=1,N23*(1+$B$16)-M24,N23) -> 93349.428 | O24: =IF(AND(L24=1,N24>=0),1,0) -> 1 | Q24: =Q23+1 -> 17 | R24: =IF(AND(Q24<=Assumptions!$C$44,U23=1),1,0) -> 1 | S24: =IF(R24=1,S23*(1+$B$15),S23) -> 27455.714 | T24: =IF(R24=1,T23*(1+$B$17)-S24,T23) -> 231501.12 | U24: =IF(AND(R24=1,T24>=0),1,0) -> 1 | W24: =W23+1 -> 17 | X24: =IF(AND(W24<=Assumptions!$C$44,AA23=1),1,0) -> 1 | Y24: =IF(X24=1,Y23*(1+$B$15),Y23) -> 27455.714 | Z24: =IF(X24=1,Z23*(1+$B$18)-Y24,Z23) -> 430843.43 | AA24: =IF(AND(X24=1,Z24>=0),1,0) -> 1
A25: Headline label | C25: ="Balanced scenario lasts" -> Balanced scenario lasts | D25: Always | K25: =K24+1 -> 18 | L25: =IF(AND(K25<=Assumptions!$C$44,O24=1),1,0) -> 1 | M25: =IF(L25=1,M24*(1+$B$15),M24) -> 28004.828 | N25: =IF(L25=1,N24*(1+$B$16)-M25,N24) -> 67211.588 | O25: =IF(AND(L25=1,N25>=0),1,0) -> 1 | Q25: =Q24+1 -> 18 | R25: =IF(AND(Q25<=Assumptions!$C$44,U24=1),1,0) -> 1 | S25: =IF(R25=1,S24*(1+$B$15),S24) -> 28004.828 | T25: =IF(R25=1,T24*(1+$B$17)-S25,T24) -> 212756.34 | U25: =IF(AND(R25=1,T25>=0),1,0) -> 1 | W25: =W24+1 -> 18 | X25: =IF(AND(W25<=Assumptions!$C$44,AA24=1),1,0) -> 1 | Y25: =IF(X25=1,Y24*(1+$B$15),Y24) -> 28004.828 | Z25: =IF(X25=1,Z24*(1+$B$18)-Y25,Z24) -> 428689.21 | AA25: =IF(AND(X25=1,Z25>=0),1,0) -> 1
A26: Balanced scenario lasts (years) | B26: =$B$20 -> 26 | C26: =IF($B$20>=Assumptions!$C$44,Assumptions!$C$44&"+",$B$20)&" years" -> 26 years | D26: Headline | K26: =K25+1 -> 19 | L26: =IF(AND(K26<=Assumptions!$C$44,O25=1),1,0) -> 1 | M26: =IF(L26=1,M25*(1+$B$15),M25) -> 28564.925 | N26: =IF(L26=1,N25*(1+$B$16)-M26,N25) -> 39990.895 | O26: =IF(AND(L26=1,N26>=0),1,0) -> 1 | Q26: =Q25+1 -> 19 | R26: =IF(AND(Q26<=Assumptions!$C$44,U25=1),1,0) -> 1 | S26: =IF(R26=1,S25*(1+$B$15),S25) -> 28564.925 | T26: =IF(R26=1,T25*(1+$B$17)-S26,T25) -> 192701.67 | U26: =IF(AND(R26=1,T26>=0),1,0) -> 1 | W26: =W25+1 -> 19 | X26: =IF(AND(W26<=Assumptions!$C$44,AA25=1),1,0) -> 1 | Y26: =IF(X26=1,Y25*(1+$B$15),Y25) -> 28564.925 | Z26: =IF(X26=1,Z25*(1+$B$18)-Y26,Z25) -> 425845.64 | AA26: =IF(AND(X26=1,Z26>=0),1,0) -> 1
A27: Cautious (2%) | B27: =$B$19 -> 20 | C27: =$B$19&" yrs" -> 20 yrs | D27: Row 1 (no "60+" form) | K27: =K26+1 -> 20 | L27: =IF(AND(K27<=Assumptions!$C$44,O26=1),1,0) -> 1 | M27: =IF(L27=1,M26*(1+$B$15),M26) -> 29136.223 | N27: =IF(L27=1,N26*(1+$B$16)-M27,N26) -> 11654.489 | O27: =IF(AND(L27=1,N27>=0),1,0) -> 1 | Q27: =Q26+1 -> 20 | R27: =IF(AND(Q27<=Assumptions!$C$44,U26=1),1,0) -> 1 | S27: =IF(R27=1,S26*(1+$B$15),S26) -> 29136.223 | T27: =IF(R27=1,T26*(1+$B$17)-S27,T26) -> 171273.51 | U27: =IF(AND(R27=1,T27>=0),1,0) -> 1 | W27: =W26+1 -> 20 | X27: =IF(AND(W27<=Assumptions!$C$44,AA26=1),1,0) -> 1 | Y27: =IF(X27=1,Y26*(1+$B$15),Y26) -> 29136.223 | Z27: =IF(X27=1,Z26*(1+$B$18)-Y27,Z26) -> 422260.15 | AA27: =IF(AND(X27=1,Z27>=0),1,0) -> 1
A28: Balanced (4%) | B28: =$B$20 -> 26 | C28: =$B$20&" yrs" -> 26 yrs | D28: Row 2 (no "60+" form) | K28: =K27+1 -> 21 | L28: =IF(AND(K28<=Assumptions!$C$44,O27=1),1,0) -> 1 | M28: =IF(L28=1,M27*(1+$B$15),M27) -> 29718.948 | N28: =IF(L28=1,N27*(1+$B$16)-M28,N27) -> -17831.369 | O28: =IF(AND(L28=1,N28>=0),1,0) -> 0 | Q28: =Q27+1 -> 21 | R28: =IF(AND(Q28<=Assumptions!$C$44,U27=1),1,0) -> 1 | S28: =IF(R28=1,S27*(1+$B$15),S27) -> 29718.948 | T28: =IF(R28=1,T27*(1+$B$17)-S28,T27) -> 148405.5 | U28: =IF(AND(R28=1,T28>=0),1,0) -> 1 | W28: =W27+1 -> 21 | X28: =IF(AND(W28<=Assumptions!$C$44,AA27=1),1,0) -> 1 | Y28: =IF(X28=1,Y27*(1+$B$15),Y27) -> 29718.948 | Z28: =IF(X28=1,Z27*(1+$B$18)-Y28,Z27) -> 417876.81 | AA28: =IF(AND(X28=1,Z28>=0),1,0) -> 1
A29: Growth (6%) | B29: =$B$21 -> 41 | C29: =IF($B$21>=Assumptions!$C$44,Assumptions!$C$44&"+",$B$21)&" yrs" -> 41 yrs | D29: Row 3 | K29: =K28+1 -> 22 | L29: =IF(AND(K29<=Assumptions!$C$44,O28=1),1,0) -> 0 | M29: =IF(L29=1,M28*(1+$B$15),M28) -> 29718.948 | N29: =IF(L29=1,N28*(1+$B$16)-M29,N28) -> -17831.369 | O29: =IF(AND(L29=1,N29>=0),1,0) -> 0 | Q29: =Q28+1 -> 22 | R29: =IF(AND(Q29<=Assumptions!$C$44,U28=1),1,0) -> 1 | S29: =IF(R29=1,S28*(1+$B$15),S28) -> 30313.327 | T29: =IF(R29=1,T28*(1+$B$17)-S29,T28) -> 124028.4 | U29: =IF(AND(R29=1,T29>=0),1,0) -> 1 | W29: =W28+1 -> 22 | X29: =IF(AND(W29<=Assumptions!$C$44,AA28=1),1,0) -> 1 | Y29: =IF(X29=1,Y28*(1+$B$15),Y28) -> 30313.327 | Z29: =IF(X29=1,Z28*(1+$B$18)-Y29,Z28) -> 412636.09 | AA29: =IF(AND(X29=1,Z29>=0),1,0) -> 1
A30: Withdrawals rise with prices at (sentence) | B30: =IF(Assumptions!$C$6=1,Assumptions!$C$14,"") -> 0.02 | C30: =IF(Assumptions!$C$6=1,ROUND((Assumptions!$C$14)*100,2)&"%","") -> 2% | D30: Sentence, only when inflation is chosen | K30: =K29+1 -> 23 | L30: =IF(AND(K30<=Assumptions!$C$44,O29=1),1,0) -> 0 | M30: =IF(L30=1,M29*(1+$B$15),M29) -> 29718.948 | N30: =IF(L30=1,N29*(1+$B$16)-M30,N29) -> -17831.369 | O30: =IF(AND(L30=1,N30>=0),1,0) -> 0 | Q30: =Q29+1 -> 23 | R30: =IF(AND(Q30<=Assumptions!$C$44,U29=1),1,0) -> 1 | S30: =IF(R30=1,S29*(1+$B$15),S29) -> 30919.593 | T30: =IF(R30=1,T29*(1+$B$17)-S30,T29) -> 98069.938 | U30: =IF(AND(R30=1,T30>=0),1,0) -> 1 | W30: =W29+1 -> 23 | X30: =IF(AND(W30<=Assumptions!$C$44,AA29=1),1,0) -> 1 | Y30: =IF(X30=1,Y29*(1+$B$15),Y29) -> 30919.593 | Z30: =IF(X30=1,Z29*(1+$B$18)-Y30,Z29) -> 406474.67 | AA30: =IF(AND(X30=1,Z30>=0),1,0) -> 1
K31: =K30+1 -> 24 | L31: =IF(AND(K31<=Assumptions!$C$44,O30=1),1,0) -> 0 | M31: =IF(L31=1,M30*(1+$B$15),M30) -> 29718.948 | N31: =IF(L31=1,N30*(1+$B$16)-M31,N30) -> -17831.369 | O31: =IF(AND(L31=1,N31>=0),1,0) -> 0 | Q31: =Q30+1 -> 24 | R31: =IF(AND(Q31<=Assumptions!$C$44,U30=1),1,0) -> 1 | S31: =IF(R31=1,S30*(1+$B$15),S30) -> 31537.985 | T31: =IF(R31=1,T30*(1+$B$17)-S31,T30) -> 70454.751 | U31: =IF(AND(R31=1,T31>=0),1,0) -> 1 | W31: =W30+1 -> 24 | X31: =IF(AND(W31<=Assumptions!$C$44,AA30=1),1,0) -> 1 | Y31: =IF(X31=1,Y30*(1+$B$15),Y30) -> 31537.985 | Z31: =IF(X31=1,Z30*(1+$B$18)-Y31,Z30) -> 399325.16 | AA31: =IF(AND(X31=1,Z31>=0),1,0) -> 1
K32: =K31+1 -> 25 | L32: =IF(AND(K32<=Assumptions!$C$44,O31=1),1,0) -> 0 | M32: =IF(L32=1,M31*(1+$B$15),M31) -> 29718.948 | N32: =IF(L32=1,N31*(1+$B$16)-M32,N31) -> -17831.369 | O32: =IF(AND(L32=1,N32>=0),1,0) -> 0 | Q32: =Q31+1 -> 25 | R32: =IF(AND(Q32<=Assumptions!$C$44,U31=1),1,0) -> 1 | S32: =IF(R32=1,S31*(1+$B$15),S31) -> 32168.745 | T32: =IF(R32=1,T31*(1+$B$17)-S32,T31) -> 41104.196 | U32: =IF(AND(R32=1,T32>=0),1,0) -> 1 | W32: =W31+1 -> 25 | X32: =IF(AND(W32<=Assumptions!$C$44,AA31=1),1,0) -> 1 | Y32: =IF(X32=1,Y31*(1+$B$15),Y31) -> 32168.745 | Z32: =IF(X32=1,Z31*(1+$B$18)-Y32,Z31) -> 391115.93 | AA32: =IF(AND(X32=1,Z32>=0),1,0) -> 1
K33: =K32+1 -> 26 | L33: =IF(AND(K33<=Assumptions!$C$44,O32=1),1,0) -> 0 | M33: =IF(L33=1,M32*(1+$B$15),M32) -> 29718.948 | N33: =IF(L33=1,N32*(1+$B$16)-M33,N32) -> -17831.369 | O33: =IF(AND(L33=1,N33>=0),1,0) -> 0 | Q33: =Q32+1 -> 26 | R33: =IF(AND(Q33<=Assumptions!$C$44,U32=1),1,0) -> 1 | S33: =IF(R33=1,S32*(1+$B$15),S32) -> 32812.12 | T33: =IF(R33=1,T32*(1+$B$17)-S33,T32) -> 9936.2435 | U33: =IF(AND(R33=1,T33>=0),1,0) -> 1 | W33: =W32+1 -> 26 | X33: =IF(AND(W33<=Assumptions!$C$44,AA32=1),1,0) -> 1 | Y33: =IF(X33=1,Y32*(1+$B$15),Y32) -> 32812.12 | Z33: =IF(X33=1,Z32*(1+$B$18)-Y33,Z32) -> 381770.76 | AA33: =IF(AND(X33=1,Z33>=0),1,0) -> 1
K34: =K33+1 -> 27 | L34: =IF(AND(K34<=Assumptions!$C$44,O33=1),1,0) -> 0 | M34: =IF(L34=1,M33*(1+$B$15),M33) -> 29718.948 | N34: =IF(L34=1,N33*(1+$B$16)-M34,N33) -> -17831.369 | O34: =IF(AND(L34=1,N34>=0),1,0) -> 0 | Q34: =Q33+1 -> 27 | R34: =IF(AND(Q34<=Assumptions!$C$44,U33=1),1,0) -> 1 | S34: =IF(R34=1,S33*(1+$B$15),S33) -> 33468.362 | T34: =IF(R34=1,T33*(1+$B$17)-S34,T33) -> -23134.669 | U34: =IF(AND(R34=1,T34>=0),1,0) -> 0 | W34: =W33+1 -> 27 | X34: =IF(AND(W34<=Assumptions!$C$44,AA33=1),1,0) -> 1 | Y34: =IF(X34=1,Y33*(1+$B$15),Y33) -> 33468.362 | Z34: =IF(X34=1,Z33*(1+$B$18)-Y34,Z33) -> 371208.64 | AA34: =IF(AND(X34=1,Z34>=0),1,0) -> 1
K35: =K34+1 -> 28 | L35: =IF(AND(K35<=Assumptions!$C$44,O34=1),1,0) -> 0 | M35: =IF(L35=1,M34*(1+$B$15),M34) -> 29718.948 | N35: =IF(L35=1,N34*(1+$B$16)-M35,N34) -> -17831.369 | O35: =IF(AND(L35=1,N35>=0),1,0) -> 0 | Q35: =Q34+1 -> 28 | R35: =IF(AND(Q35<=Assumptions!$C$44,U34=1),1,0) -> 0 | S35: =IF(R35=1,S34*(1+$B$15),S34) -> 33468.362 | T35: =IF(R35=1,T34*(1+$B$17)-S35,T34) -> -23134.669 | U35: =IF(AND(R35=1,T35>=0),1,0) -> 0 | W35: =W34+1 -> 28 | X35: =IF(AND(W35<=Assumptions!$C$44,AA34=1),1,0) -> 1 | Y35: =IF(X35=1,Y34*(1+$B$15),Y34) -> 34137.73 | Z35: =IF(X35=1,Z34*(1+$B$18)-Y35,Z34) -> 359343.43 | AA35: =IF(AND(X35=1,Z35>=0),1,0) -> 1
K36: =K35+1 -> 29 | L36: =IF(AND(K36<=Assumptions!$C$44,O35=1),1,0) -> 0 | M36: =IF(L36=1,M35*(1+$B$15),M35) -> 29718.948 | N36: =IF(L36=1,N35*(1+$B$16)-M36,N35) -> -17831.369 | O36: =IF(AND(L36=1,N36>=0),1,0) -> 0 | Q36: =Q35+1 -> 29 | R36: =IF(AND(Q36<=Assumptions!$C$44,U35=1),1,0) -> 0 | S36: =IF(R36=1,S35*(1+$B$15),S35) -> 33468.362 | T36: =IF(R36=1,T35*(1+$B$17)-S36,T35) -> -23134.669 | U36: =IF(AND(R36=1,T36>=0),1,0) -> 0 | W36: =W35+1 -> 29 | X36: =IF(AND(W36<=Assumptions!$C$44,AA35=1),1,0) -> 1 | Y36: =IF(X36=1,Y35*(1+$B$15),Y35) -> 34820.484 | Z36: =IF(X36=1,Z35*(1+$B$18)-Y36,Z35) -> 346083.56 | AA36: =IF(AND(X36=1,Z36>=0),1,0) -> 1
K37: =K36+1 -> 30 | L37: =IF(AND(K37<=Assumptions!$C$44,O36=1),1,0) -> 0 | M37: =IF(L37=1,M36*(1+$B$15),M36) -> 29718.948 | N37: =IF(L37=1,N36*(1+$B$16)-M37,N36) -> -17831.369 | O37: =IF(AND(L37=1,N37>=0),1,0) -> 0 | Q37: =Q36+1 -> 30 | R37: =IF(AND(Q37<=Assumptions!$C$44,U36=1),1,0) -> 0 | S37: =IF(R37=1,S36*(1+$B$15),S36) -> 33468.362 | T37: =IF(R37=1,T36*(1+$B$17)-S37,T36) -> -23134.669 | U37: =IF(AND(R37=1,T37>=0),1,0) -> 0 | W37: =W36+1 -> 30 | X37: =IF(AND(W37<=Assumptions!$C$44,AA36=1),1,0) -> 1 | Y37: =IF(X37=1,Y36*(1+$B$15),Y36) -> 35516.894 | Z37: =IF(X37=1,Z36*(1+$B$18)-Y37,Z36) -> 331331.67 | AA37: =IF(AND(X37=1,Z37>=0),1,0) -> 1
K38: =K37+1 -> 31 | L38: =IF(AND(K38<=Assumptions!$C$44,O37=1),1,0) -> 0 | M38: =IF(L38=1,M37*(1+$B$15),M37) -> 29718.948 | N38: =IF(L38=1,N37*(1+$B$16)-M38,N37) -> -17831.369 | O38: =IF(AND(L38=1,N38>=0),1,0) -> 0 | Q38: =Q37+1 -> 31 | R38: =IF(AND(Q38<=Assumptions!$C$44,U37=1),1,0) -> 0 | S38: =IF(R38=1,S37*(1+$B$15),S37) -> 33468.362 | T38: =IF(R38=1,T37*(1+$B$17)-S38,T37) -> -23134.669 | U38: =IF(AND(R38=1,T38>=0),1,0) -> 0 | W38: =W37+1 -> 31 | X38: =IF(AND(W38<=Assumptions!$C$44,AA37=1),1,0) -> 1 | Y38: =IF(X38=1,Y37*(1+$B$15),Y37) -> 36227.232 | Z38: =IF(X38=1,Z37*(1+$B$18)-Y38,Z37) -> 314984.34 | AA38: =IF(AND(X38=1,Z38>=0),1,0) -> 1
K39: =K38+1 -> 32 | L39: =IF(AND(K39<=Assumptions!$C$44,O38=1),1,0) -> 0 | M39: =IF(L39=1,M38*(1+$B$15),M38) -> 29718.948 | N39: =IF(L39=1,N38*(1+$B$16)-M39,N38) -> -17831.369 | O39: =IF(AND(L39=1,N39>=0),1,0) -> 0 | Q39: =Q38+1 -> 32 | R39: =IF(AND(Q39<=Assumptions!$C$44,U38=1),1,0) -> 0 | S39: =IF(R39=1,S38*(1+$B$15),S38) -> 33468.362 | T39: =IF(R39=1,T38*(1+$B$17)-S39,T38) -> -23134.669 | U39: =IF(AND(R39=1,T39>=0),1,0) -> 0 | W39: =W38+1 -> 32 | X39: =IF(AND(W39<=Assumptions!$C$44,AA38=1),1,0) -> 1 | Y39: =IF(X39=1,Y38*(1+$B$15),Y38) -> 36951.776 | Z39: =IF(X39=1,Z38*(1+$B$18)-Y39,Z38) -> 296931.63 | AA39: =IF(AND(X39=1,Z39>=0),1,0) -> 1
K40: =K39+1 -> 33 | L40: =IF(AND(K40<=Assumptions!$C$44,O39=1),1,0) -> 0 | M40: =IF(L40=1,M39*(1+$B$15),M39) -> 29718.948 | N40: =IF(L40=1,N39*(1+$B$16)-M40,N39) -> -17831.369 | O40: =IF(AND(L40=1,N40>=0),1,0) -> 0 | Q40: =Q39+1 -> 33 | R40: =IF(AND(Q40<=Assumptions!$C$44,U39=1),1,0) -> 0 | S40: =IF(R40=1,S39*(1+$B$15),S39) -> 33468.362 | T40: =IF(R40=1,T39*(1+$B$17)-S40,T39) -> -23134.669 | U40: =IF(AND(R40=1,T40>=0),1,0) -> 0 | W40: =W39+1 -> 33 | X40: =IF(AND(W40<=Assumptions!$C$44,AA39=1),1,0) -> 1 | Y40: =IF(X40=1,Y39*(1+$B$15),Y39) -> 37690.812 | Z40: =IF(X40=1,Z39*(1+$B$18)-Y40,Z39) -> 277056.71 | AA40: =IF(AND(X40=1,Z40>=0),1,0) -> 1
K41: =K40+1 -> 34 | L41: =IF(AND(K41<=Assumptions!$C$44,O40=1),1,0) -> 0 | M41: =IF(L41=1,M40*(1+$B$15),M40) -> 29718.948 | N41: =IF(L41=1,N40*(1+$B$16)-M41,N40) -> -17831.369 | O41: =IF(AND(L41=1,N41>=0),1,0) -> 0 | Q41: =Q40+1 -> 34 | R41: =IF(AND(Q41<=Assumptions!$C$44,U40=1),1,0) -> 0 | S41: =IF(R41=1,S40*(1+$B$15),S40) -> 33468.362 | T41: =IF(R41=1,T40*(1+$B$17)-S41,T40) -> -23134.669 | U41: =IF(AND(R41=1,T41>=0),1,0) -> 0 | W41: =W40+1 -> 34 | X41: =IF(AND(W41<=Assumptions!$C$44,AA40=1),1,0) -> 1 | Y41: =IF(X41=1,Y40*(1+$B$15),Y40) -> 38444.628 | Z41: =IF(X41=1,Z40*(1+$B$18)-Y41,Z40) -> 255235.49 | AA41: =IF(AND(X41=1,Z41>=0),1,0) -> 1
K42: =K41+1 -> 35 | L42: =IF(AND(K42<=Assumptions!$C$44,O41=1),1,0) -> 0 | M42: =IF(L42=1,M41*(1+$B$15),M41) -> 29718.948 | N42: =IF(L42=1,N41*(1+$B$16)-M42,N41) -> -17831.369 | O42: =IF(AND(L42=1,N42>=0),1,0) -> 0 | Q42: =Q41+1 -> 35 | R42: =IF(AND(Q42<=Assumptions!$C$44,U41=1),1,0) -> 0 | S42: =IF(R42=1,S41*(1+$B$15),S41) -> 33468.362 | T42: =IF(R42=1,T41*(1+$B$17)-S42,T41) -> -23134.669 | U42: =IF(AND(R42=1,T42>=0),1,0) -> 0 | W42: =W41+1 -> 35 | X42: =IF(AND(W42<=Assumptions!$C$44,AA41=1),1,0) -> 1 | Y42: =IF(X42=1,Y41*(1+$B$15),Y41) -> 39213.521 | Z42: =IF(X42=1,Z41*(1+$B$18)-Y42,Z41) -> 231336.1 | AA42: =IF(AND(X42=1,Z42>=0),1,0) -> 1
... K67: =K66+1 -> 60 | L67: =IF(AND(K67<=Assumptions!$C$44,O66=1),1,0) -> 0 | M67: =IF(L67=1,M66*(1+$B$15),M66) -> 29718.948 | N67: =IF(L67=1,N66*(1+$B$16)-M67,N66) -> -17831.369 | O67: =IF(AND(L67=1,N67>=0),1,0) -> 0 | Q67: =Q66+1 -> 60 | R67: =IF(AND(Q67<=Assumptions!$C$44,U66=1),1,0) -> 0 | S67: =IF(R67=1,S66*(1+$B$15),S66) -> 33468.362 | T67: =IF(R67=1,T66*(1+$B$17)-S67,T66) -> -23134.669 | U67: =IF(AND(R67=1,T67>=0),1,0) -> 0 | W67: =W66+1 -> 60 | X67: =IF(AND(W67<=Assumptions!$C$44,AA66=1),1,0) -> 0 | Y67: =IF(X67=1,Y66*(1+$B$15),Y66) -> 45044.009 | Z67: =IF(X67=1,Z66*(1+$B$18)-Y67,Z66) -> -7081.0344 | AA67: =IF(AND(X67=1,Z67>=0),1,0) -> 0

Sheet C17 Inflation adjusted return
A1: C17 · Inflation-adjusted return
A2: Question shown: "What is my money really worth in future?" · Category: Investments · Prototype id: realreturn
A3: Replicates: CALCS 'realreturn' run(v); helpers fvL(), inflation via S.infl.
A4: Edge rules: Without a chosen inflation rate only the future value is shown. With one: exact real return (1+r)/(1+inflation) − 1 (not r − inflation) and value ÷ (1+inflation)^years.
A5: Legend: blue = input (change these) · black = formula · green = link to the Assumptions sheet · yellow fill = key assumption. Money cells show whole euros but keep full precision, as the prototype does.
A8: INPUTS
A9: Input | B9: Value | C9: Unit | D9: Default | E9: Min | F9: Max (slider) | G9: Max if typed | H9: Step | I9: Pre-filled from (if the prototype pre-fills it)
A10: Amount | B10: 20000 | C10: € | D10: 20000 | E10: 500 | F10: 500000 | G10: 5000000 | H10: 100 | I10: Your finances or investment statement: investments (if given)
A11: Nominal return | B11: 0.05 | C11: % (stored as a fraction) | D11: 0.05 | E11: 0 | F11: 0.1 | G11: 0.1 | H11: 0.0025
A12: Years | B12: 15 | C12: years | D12: 15 | E12: 1 | F12: 40 | G12: 40 | H12: 1
A14: CALCULATION
A15: Calculation step | B15: Value | C15: Unit | D15: JS equivalent (prototype run function)
A16: Future value | B16: =$B$10*POWER(1+$B$11,$B$12) -> 41578.564 | C16: € | D16: n = fvL(v.p, v.r, v.y)
A17: Real return a year | B17: =(1+$B$11)/(1+Assumptions!$C$14)-1 -> 0.029411765 | C17: rate (fraction) | D17: rr = (1 + v.r/100) / (1 + i) - 1
A18: Value in today's money | B18: =$B$16/POWER(1+Assumptions!$C$14,$B$12) -> 30893.485 | C18: € | D18: real = n / Math.pow(1 + i, v.y)
A20: OUTPUTS
A21: Output | B21: Value | C21: As shown in the prototype | D21: Shown when / where it appears
A22: Headline label | C22: =IF(Assumptions!$C$6=1,"In today's money","Future value") -> In today's money | D22: Always
A23: Headline figure | B23: =IF(Assumptions!$C$6=1,$B$18,$B$16) -> 30893.485 | C23: =IF((IF(Assumptions!$C$6=1,$B$18,$B$16))<0,"−€","€")&FIXED(ROUND(ABS(IF(Assumptions!$C$6=1,$B$18,$B$16)),0),0) -> €30,893 | D23: Headline: today's money if inflation chosen, else future value
A24: Future value | B24: =$B$16 -> 41578.564 | C24: =IF(($B$16)<0,"−€","€")&FIXED(ROUND(ABS($B$16),0),0) -> €41,579 | D24: Row 1
A25: Real return a year | B25: =IF(Assumptions!$C$6=1,$B$17,"") -> 0.029411765 | C25: =IF(Assumptions!$C$6=1,ROUND($B$17*100,2)&"%","") -> 2.94% | D25: Row 2, only when inflation is chosen
A26: Value in today's money | B26: =IF(Assumptions!$C$6=1,$B$18,"") -> 30893.485 | C26: =IF(Assumptions!$C$6=1,IF(($B$18)<0,"−€","€")&FIXED(ROUND(ABS($B$18),0),0),"") -> €30,893 | D26: Row 3, only when inflation is chosen
A27: Real return (sentence, 1 dp) | B27: =IF(Assumptions!$C$6=1,$B$17,"") -> 0.029411765 | C27: =IF(Assumptions!$C$6=1,FIXED($B$17*100,1,TRUE())&"%","") -> 2.9% | D27: Sentence, only when inflation is chosen

Sheet C18 Regular investing
A1: C18 · Regular investing
A2: Question shown: "What could investing monthly build?" · Category: Investments · Prototype id: regularinvest
A3: Replicates: CALCS 'regularinvest' run(v); helpers fvA(), todayM(), realLine(), inflRow(), adjOn('regularinvest').
A4: Edge rules: Growth after fees nr = (1+g)(1−f) − 1; both before-fee and after-fee values use fvA. "Adjust for inflation" (default off) shows today's money only when the client has also chosen inflation. The goal amount is the nominal after-fee value (unlike Lump-sum growth).
A5: Legend: blue = input (change these) · black = formula · green = link to the Assumptions sheet · yellow fill = key assumption. Money cells show whole euros but keep full precision, as the prototype does.
A8: INPUTS
A9: Input | B9: Value | C9: Unit | D9: Default | E9: Min | F9: Max (slider) | G9: Max if typed | H9: Step | I9: Pre-filled from (if the prototype pre-fills it)
A10: Monthly amount | B10: 300 | C10: € | D10: 300 | E10: 25 | F10: 5000 | G10: 50000 | H10: 25
A11: Years | B11: 15 | C11: years | D11: 15 | E11: 1 | F11: 40 | G11: 40 | H11: 1
A12: Growth assumption | B12: 0.05 | C12: % (stored as a fraction) | D12: 0.05 | E12: 0 | F12: 0.08 | G12: 0.08 | H12: 0.005
A13: Yearly fees | B13: 0.01 | C13: % (stored as a fraction) | D13: 0.01 | E13: 0 | F13: 0.03 | G13: 0.03 | H13: 0.0005
A15: CONTEXT INPUTS (state the prototype reads besides the sliders)
A16: Input | B16: Value | C16: Unit | D16: Default | E16: Min | F16: Max (slider) | G16: Max if typed | H16: Step | I16: Pre-filled from (if the prototype pre-fills it)
A17: "Adjust for inflation" switch (1 = on) | B17: 0 | C17: flag | D17: 0 | E17: 0 | F17: 1 | G17: 1 | H17: 1 | I17: The switch on this tool; default off, remembered per tool for the session (S.adjInfl)
A19: CALCULATION
A20: Calculation step | B20: Value | C20: Unit | D20: JS equivalent (prototype run function)
A21: Growth after fees | B21: =(1+$B$12)*(1-$B$13)-1 -> 0.0395 | C21: rate (fraction) | D21: nr = ((1 + v.g/100) * (1 - v.f/100) - 1) * 100
A22: Months | B22: =$B$11*12 -> 180 | C22: n | D22: n = y * 12
A23: Monthly growth before fees | B23: =POWER(1+$B$12,1/12)-1 -> 0.0040741238 | C23: rate (fraction) | D23: fvA: i = Math.pow(1 + g/100, 1/12) - 1
A24: Before fees | B24: =IF($B$23<>0,$B$10*(POWER(1+$B$23,$B$22)-1)/$B$23,$B$10*$B$22) -> 79447.378 | C24: € | D24: gross = fvA(v.m, v.g, v.y)
A25: Monthly growth after fees | B25: =POWER(1+$B$21,1/12)-1 -> 0.0032335357 | C25: rate (fraction) | D25: fvA: i = Math.pow(1 + nr/100, 1/12) - 1
A26: After fees | B26: =IF($B$25<>0,$B$10*(POWER(1+$B$25,$B$22)-1)/$B$25,$B$10*$B$22) -> 73108.785 | C26: € | D26: net = fvA(v.m, nr, v.y)
A27: Show in today's money (switch on and inflation chosen) | B27: =IF(AND($B$17=1,Assumptions!$C$6=1),1,0) -> 0 | C27: flag | D27: adjOn('regularinvest')
A28: In today's money | B28: =$B$26/POWER(1+Assumptions!$C$14,$B$11) -> 54320.904 | C28: € | D28: todayM(net, v.y)
